Workbook

Sheet README
A1: Retirement plan
A2: A year-by-year retirement model for a couple, with a Monte Carlo test against history. See the project README for how to use it with Claude.
A4: Tabs
A5: Model - ...: a scenario. Yellow cells are its inputs (when you stop working, pensions, property sales, one-off events). Duplicate the tab to try another scenario.
A6: household: names, birth years, CPP and OAS, kids.
A7: budget: 12 months of spending by category (the statement pipeline fills it). The retirement_budget column is what the model spends.
A8: kids_budget: one line per kid and cost (support, college, help after college), each with its own years and amount.
A9: other_budget: renovations, cars and other big irregular costs, per year.
A10: properties: your home and any other properties.
A11: healthcare: private health/dental plan, out-of-pocket and long-term care costs.
A12: assets: every account, its balance and which bucket it feeds.
A13: tax_tables: the tax law the model uses (federal + your province). Edit to change state/province or update the law.
... A24: Not financial advice. Tax rules are simplified; check important decisions with a professional.

Sheet Model - Example
A1: Retirement model - Example
A2: Yellow cells are this scenario's inputs. To try another scenario: right-click this tab > Duplicate, rename it 'Model - <name>', change its yellow cells. Shared facts (budgets, properties, accounts, healthcare, tax law) are on the other tabs. Don't insert or delete rows on this tab.
A4: WORK | E4: RESULTS (today's dollars)
A5: =household!$B$5&"'s first year without a paycheck" | B5: 2030 | C5: The year after the last working year | E5: ="Net worth when "&household!$B$5&" is 70" | G5: =IFERROR(INDEX($J$81:$J$123,MATCH(household!$B$6+70,$A$81:$A$123,0)),"")
A6: =household!$B$8&"'s first year without a paycheck" | B6: 2031 | E6: ... at 80 | G6: =IFERROR(INDEX($J$81:$J$123,MATCH(household!$B$6+80,$A$81:$A$123,0)),"")
A7: =household!$B$5&"'s pay per year while working (today's $)" | B7: 165000 | C7: Salary + bonus + stock vesting | E7: ... at 85 | G7: =IFERROR(INDEX($J$81:$J$123,MATCH(household!$B$6+85,$A$81:$A$123,0)),"")
A8: =household!$B$8&"'s pay per year while working" | B8: 112000 | E8: ... at 90 | G8: =IFERROR(INDEX($J$81:$J$123,MATCH(household!$B$6+90,$A$81:$A$123,0)),"")
A9: =household!$B$5&"'s RRSP / pension contributions" | B9: 16000 | C9: While working | E9: ... at 95 | G9: =IFERROR(INDEX($J$81:$J$123,MATCH(household!$B$6+95,$A$81:$A$123,0)),"")
A10: =household!$B$8&"'s RRSP / pension contributions" | B10: 11000 | E10: ="Investments when "&household!$B$5&" is 90" | G10: =IFERROR(MAX(0,INDEX($I$81:$I$123,MATCH(household!$B$6+90,$A$81:$A$123,0))),"")
A11: ="Employer match / pension contributions for "&household!$B$5 | B11: 8000 | E11: First year investments can't cover costs | G11: =IF(COUNTIF($K$81:$K$123,">1")=0,"never",SUMPRODUCT(MIN($A$81:$A$123+($K$81:$K$123<=1)*10000)))
A12: ="Employer match / pension contributions for "&household!$B$8 | B12: 5500 | E12: First year's living costs | G12: =INDEX($D$81:$D$123,1)
A13: Income tax withheld from pay | B13: 0.27 | C13: Share of taxable pay; the difference is settled next April | E13: First year's withdrawal rate | G13: =INDEX($H$81:$H$123,1)
A14: Tax owed for last year, paid in April of the first year | B14: 0 | C14: Negative = a refund | E14: Lifetime income tax (today's $) | G14: =SUMPRODUCT($EC$81:$EC$123/$O$81:$O$123)
A16: ECONOMY
A17: Inflation | B17: 0.025 | C17: Living costs, pay, pensions, tax brackets
A18: Investment return (per year, before inflation) | B18: 0.05 | C18: Override any year in the yellow 'Return override' column below
A19: Dividend yield on non-registered accounts | B19: 0.025 | C19: Paid out as cash each year
A20: Share of those dividends that are eligible Canadian dividends | B20: 0.5 | C20: The rest (foreign, interest) is taxed as ordinary income
A21: Healthcare cost growth | B21: =healthcare!$B$5 | C21: From the healthcare tab
A22: College cost growth | B22: 0.035
A23: Long-term care cost growth | B23: =healthcare!$B$7 | C23: From the healthcare tab
A25: CPP AND OAS
A26: =household!$B$5&" starts CPP at age" | B26: 70 | C26: 60-70: -0.6%/month before 65, +0.7%/month after
A27: =household!$B$8&" starts CPP at age" | B27: 65
A28: =household!$B$5&" starts OAS at age" | B28: 67 | C28: 65-70: +0.6%/month deferred
A29: =household!$B$8&" starts OAS at age" | B29: 65
A30: =household!$B$5&"'s CPP vs age 65" | B30: =IF(ROUND(($B$26-65)*12,0)>=0,1+0.007*MIN(ROUND(($B$26-65)*12,0),60),1+0.006*MAX(ROUND(($B$26-65)*12,0),-60))
A31: =household!$B$8&"'s CPP vs age 65" | B31: =IF(ROUND(($B$27-65)*12,0)>=0,1+0.007*MIN(ROUND(($B$27-65)*12,0),60),1+0.006*MAX(ROUND(($B$27-65)*12,0),-60))
A32: =household!$B$5&"'s OAS deferral increase" | B32: =1+0.006*MIN(60,MAX(0,ROUND(($B$28-65)*12,0)))
A33: =household!$B$8&"'s OAS deferral increase" | B33: =1+0.006*MIN(60,MAX(0,ROUND(($B$29-65)*12,0)))
A35: WORKPLACE PENSIONS
A36: =household!$B$5&"'s defined-benefit pension per year (today's $)" | B36: 0 | C36: 0 = none. Your pension statement's estimate
A37: ... starts at age | B37: 65
A38: =household!$B$8&"'s defined-benefit pension per year (today's $)" | B38: 30000
A39: ... starts at age | B39: 65
A40: Pension increases, as a share of inflation | B40: 0.8 | C40: 0% = fixed dollar amount, 100% = fully indexed
A41: Share that continues to the survivor | B41: 0.6 | C41: Joint-and-survivor option; used in the Monte Carlo's lifetime runs
A43: HEALTHCARE AND LONG-TERM CARE
A44: =household!$B$5&" needs long-term care from age" | B44: 85 | C44: Paid from savings
A45: ... for this many years | B45: 2 | C45: Averages: men ~2 years, women ~3.5
A46: =household!$B$8&" needs long-term care from age" | B46: 89 | C46: Overlapping years double the cost
A47: ... for this many years | B47: 3
A48: Long-term care cost per person-year (today's $) | B48: =healthcare!$B$6 | C48: From the healthcare tab
A50: TAX MOVES
A51: Extra RRSP/RRIF withdrawal per year (today's $) | B51: 40000 | C51: An 'RRSP meltdown': taxed now, the cash fills the TFSA or pays the bills
A52: ... from year | B52: 2031 | C52: Blank = none
A53: ... through year | B53: 2036
A55: STARTING POINT (1 January of the first year) - from the assets tab; type over to freeze
A56: Non-registered investments + cash | B56: =SUMIF(assets!$B$2:$B$150,"non_registered",assets!$C$2:$C$150)
A57: ... their adjusted cost base | B57: =assets!$J$2
A58: =household!$B$5&"'s RRSP/RRIF" | B58: =SUMIF(assets!$B$2:$B$150,"rrsp_p1",assets!$C$2:$C$150)
A59: =household!$B$8&"'s RRSP/RRIF" | B59: =SUMIF(assets!$B$2:$B$150,"rrsp_p2",assets!$C$2:$C$150)
A60: TFSAs | B60: =SUMIF(assets!$B$2:$B$150,"tfsa",assets!$C$2:$C$150)
A61: RESPs | B61: =SUMIF(assets!$B$2:$B$150,"resp",assets!$C$2:$C$150)
A63: Property | B63: Sell in year | C63: Change use from year | D63: New rent / yr (today's $) | E63: New costs / yr (today's $) | F63: Sale price | G63: Net proceeds | H63: Taxable gain | I63: CCA recapture
A64: =IF(properties!$A$2="","",properties!$A$2) | F64: =IF($B64="",0,properties!$C$2*(1+properties!$D$2)^($B64-household!$B$4+1)) | G64: =IF($B64="",0,F64*(1-properties!$E$2)-IFERROR(INDEX($AO$81:$AO$123,MATCH($B64,$A$81:$A$123,0)),0)) | H64: 0 | I64: 0
A65: =IF(properties!$A$3="","",properties!$A$3) | B65: 2040 | F65: =IF($B65="",0,properties!$C$3*(1+properties!$D$3)^($B65-household!$B$4+1)) | G65: =IF($B65="",0,F65*(1-properties!$E$3)) | H65: =IF($B65="",0,MAX(0,G65-properties!$F$3)) | I65: =IF($B65="",0,MIN((properties!$P$3+properties!$N$3*MAX(0,MIN($B65,properties!$O$3)-household!$B$4+1)),MAX(0,G65-(properties!$F$3-(properties!$P$3+properties!$N$3*MAX(0,MIN($B65,properties!$O$3)-household!$B$4+1))))))
A66: =IF(properties!$A$4="","",properties!$A$4) | F66: =IF($B66="",0,properties!$C$4*(1+properties!$D$4)^($B66-household!$B$4+1)) | G66: =IF($B66="",0,F66*(1-properties!$E$4)) | H66: =IF($B66="",0,MAX(0,G66-properties!$F$4)) | I66: =IF($B66="",0,MIN((properties!$P$4+properties!$N$4*MAX(0,MIN($B66,properties!$O$4)-household!$B$4+1)),MAX(0,G66-(properties!$F$4-(properties!$P$4+properties!$N$4*MAX(0,MIN($B66,properties!$O$4)-household!$B$4+1))))))
A67: =IF(properties!$A$5="","",properties!$A$5) | F67: =IF($B67="",0,properties!$C$5*(1+properties!$D$5)^($B67-household!$B$4+1)) | G67: =IF($B67="",0,F67*(1-properties!$E$5)) | H67: =IF($B67="",0,MAX(0,G67-properties!$F$5)) | I67: =IF($B67="",0,MIN((properties!$P$5+properties!$N$5*MAX(0,MIN($B67,properties!$O$5)-household!$B$4+1)),MAX(0,G67-(properties!$F$5-(properties!$P$5+properties!$N$5*MAX(0,MIN($B67,properties!$O$5)-household!$B$4+1))))))
A68: =IF(properties!$A$6="","",properties!$A$6) | F68: =IF($B68="",0,properties!$C$6*(1+properties!$D$6)^($B68-household!$B$4+1)) | G68: =IF($B68="",0,F68*(1-properties!$E$6)) | H68: =IF($B68="",0,MAX(0,G68-properties!$F$6)) | I68: =IF($B68="",0,MIN((properties!$P$6+properties!$N$6*MAX(0,MIN($B68,properties!$O$6)-household!$B$4+1)),MAX(0,G68-(properties!$F$6-(properties!$P$6+properties!$N$6*MAX(0,MIN($B68,properties!$O$6)-household!$B$4+1))))))
A69: Home: 'New costs' = what housing costs per year after you sell it (rent, or a new place's carrying costs; if you buy one, its price goes in one-off Expenses below and its value isn't counted in net worth). Other properties: 'Change use' switches to the new rent/costs from that year (e.g. move into the cottage: rent 0, costs = its upkeep). Sale price is a formula; type over it to use your own estimate.
A71: One-off money in or out | B71: Year | C71: Amount (today's $) | D71: Type
A72: Severance (one year's pay) | B72: 2030 | C72: 80000 | D72: Wages: person 1 | F72: Severance, an inheritance, a wedding, a new car, buying a smaller home. Wages get payroll tax; 'Other taxable income' is taxed as ordinary income; 'Tax-free money in' isn't taxed; 'Expense' is spent that year.
A79: SUMMARY | L79: ASSUMPTIONS BY YEAR | U79: WORK | AN79: HOUSING | AV79: LIVING | BD79: HEALTHCARE | BK79: PROPERTIES | BS79: CPP AND OAS | BW79: PENSIONS | BY79: INVESTMENTS | DE79: INCOME TAX | ED79: TOTALS
A80: Year | B80: =household!$B$5&"'s age" | C80: =household!$B$8&"'s age" | D80: Living costs (all spending except income tax) | E80: Income + payroll tax paid this year | F80: CPP + OAS | G80: Taken out of investments (net) | H80: Withdrawal rate | I80: Investments at year end (today's $) | J80: Net worth at year end (today's $) | K80: Shortfall (costs your accounts couldn't cover) | L80: Return override (blank = default) | M80: Return used | N80: Household spending multiplier (blank = 100%) | O80: Price level vs today | P80: Tax-law index | Q80: Provincial index | R80: Healthcare price level | S80: College price level | T80: Long-term care price level | U80: =household!$B$5&" working?" | V80: =household!$B$8&" working?" | W80: Either working? | X80: =household!$B$5&"'s pay" | Y80: =household!$B$8&"'s pay" | Z80: =household!$B$5&"'s retirement contributions" | AA80: =household!$B$8&"'s retirement contributions" | AB80: ="Employer contributions for "&household!$B$5 | AC80: ="Employer contributions for "&household!$B$8 | AD80: Total pay | AE80: Taxable pay | AF80: =household!$B$5&"'s CPP + EI contributions" | AG80: =household!$B$8&"'s CPP + EI contributions" | AH80: CPP + EI contributions | AI80: Income tax withheld from pay | AJ80: Take-home pay | AK80: One-off: other taxable income | AL80: One-off: tax-free money in | AM80: One-off: expenses | AN80: Own your home? | AO80: Mortgage balance, start | AP80: Mortgage interest | AQ80: Mortgage payments | AR80: Mortgage balance, end | AS80: Home carrying costs | AT80: Housing after selling your home | AU80: Housing total | AV80: Household living (budget tab) | AW80: Renovations, cars, other (other_budget tab) | AX80: Kids: costs you pay | AY80: Kids: costs paid from college funds | AZ80: College funds, start | BA80: Paid by college funds | BB80: College costs paid by you | BC80: College funds, end | BD80: Employer health plan (while working) | BE80: Adults on a retiree health plan | BF80: Extended health + dental premiums | BG80: Out-of-pocket (drugs, dental, vision) | BH80: People in long-term care | BI80: Long-term care | BJ80: Healthcare total | BK80: Property income after costs | BL80: Capital cost allowance | BM80: Taxable property income | BN80: Property sale proceeds | BO80: Capital gains on sales | BP80: CCA recapture | BQ80: Home value, end | BR80: Other property values, end | BS80: =household!$B$5&"'s CPP" | BT80: =household!$B$8&"'s CPP" | BU80: =household!$B$5&"'s OAS" | BV80: =household!$B$8&"'s OAS" | BW80: =household!$B$5&"'s workplace pension" | BX80: =household!$B$8&"'s workplace pension" | BY80: Non-registered, start | BZ80: Adjusted cost base, start | CA80: Dividends | CB80: =household!$B$5&" RRSP/RRIF, start" | CC80: =household!$B$8&" RRSP/RRIF, start" | CD80: =household!$B$5&"'s RRIF minimum" | CE80: =household!$B$8&"'s RRIF minimum" | CF80: TFSA, start | CG80: Extra RRSP/RRIF withdrawal planned | CH80: =household!$B$5&" RRSP/RRIF available" | CI80: =household!$B$8&" RRSP/RRIF available" | CJ80: Extra RRSP/RRIF withdrawal | CK80: ="... from "&household!$B$5&"'s" | CL80: ="... from "&household!$B$8&"'s" | CM80: TFSA room, start | CN80: Last year's income tax still owed | CO80: Cash coming in | CP80: Still needed (+) or surplus (-) | CQ80: Sold from non-registered | CR80: Withdrawn from RRSP/RRIF | CS80: ="... from "&household!$B$5&"'s" | CT80: ="... from "&household!$B$8&"'s" | CU80: Withdrawn from TFSA | CV80: Surplus reinvested | CW80: Surplus into TFSAs | CX80: Gain share of sales | CY80: Capital gains realized | CZ80: Non-registered, end | DA80: Adjusted cost base, end | DB80: =household!$B$5&" RRSP/RRIF, end" | DC80: =household!$B$8&" RRSP/RRIF, end" | DD80: TFSA, end | DE80: =household!$B$5&"'s RRSP/RRIF income" | DF80: =household!$B$5&"'s grossed-up eligible dividends" | DG80: =household!$B$5&"'s net income before pension splitting" | DH80: =household!$B$8&"'s RRSP/RRIF income" | DI80: =household!$B$8&"'s grossed-up eligible dividends" | DJ80: =household!$B$8&"'s net income before pension splitting" | DK80: Pension income moved to the lower-income spouse | DL80: =household!$B$5&"'s net income" | DM80: =household!$B$5&"'s eligible pension income" | DN80: =household!$B$5&"'s OAS clawback" | DO80: =household!$B$5&"'s taxable income" | DP80: =household!$B$8&"'s net income" | DQ80: =household!$B$8&"'s eligible pension income" | DR80: =household!$B$8&"'s OAS clawback" | DS80: =household!$B$8&"'s taxable income" | DT80: Medical expenses for the credit | DU80: =household!$B$5&"'s federal credit amounts" | DV80: =household!$B$5&"'s federal tax" | DW80: =household!$B$5&"'s provincial credit amounts" | DX80: =household!$B$5&"'s provincial tax" | DY80: =household!$B$8&"'s federal credit amounts" | DZ80: =household!$B$8&"'s federal tax" | EA80: =household!$B$8&"'s provincial credit amounts" | EB80: =household!$B$8&"'s provincial tax" | EC80: Income tax for the year (incl. OAS clawback) | ED80: Investments, end | EE80: Net worth, end
A81: =household!$B$4+0 | B81: =A81-household!$B$6 | C81: =A81-household!$B$9 | D81: =AU81+AV81+AW81+AX81+BB81+BJ81+AM81 | E81: =CN81+AI81+AH81 | F81: =BS81+BT81+BU81+BV81 | G81: =CQ81+CR81+CU81+CD81+CE81+CA81-CV81+CJ81+CW81 | H81: =IF(BY81+CB81+CC81+CF81<=0,"",G81/(BY81+CB81+CC81+CF81)) | I81: =ED81/O81 | J81: =EE81/O81 | K81: =MAX(0,CP81-CQ81-CR81-CU81) | M81: =IF(L81="",$B$18,L81) | O81: =(1+$B$17)^(A81-household!$B$4+1) | P81: =(1+$B$17)^(A81-tax_tables!$B$4) | Q81: =(1+$B$17)^(A81-tax_tables!$B$4-MAX(0,MIN(A81,tax_tables!$B$45)-tax_tables!$B$44+1)) | R81: =(1+$B$21)^(A81-household!$B$4+1) | S81: =(1+$B$22)^(A81-household!$B$4+1) | T81: =(1+$B$23)^(A81-household!$B$4+1) | U81: =IF(A81<$B$5,1,0) | V81: =IF(A81<$B$6,1,0) | W81: =IF(U81+V81>0,1,0) | X81: =U81*$B$7*O81+SUMPRODUCT(($B$72:$B$77=A81)*($D$72:$D$77="Wages: person 1")*$C$72:$C$77)*O81 | Y81: =V81*$B$8*O81+SUMPRODUCT(($B$72:$B$77=A81)*($D$72:$D$77="Wages: person 2")*$C$72:$C$77)*O81 | Z81: =U81*$B$9*O81 | AA81: =V81*$B$10*O81 | AB81: =U81*$B$11*O81 | AC81: =V81*$B$12*O81 | AD81: =X81+Y81 | AE81: =AD81-Z81-AA81 | AF81: =tax_tables!$B$25*MAX(0,MIN(X81,tax_tables!$B$27*P81)-tax_tables!$B$26)+tax_tables!$B$28*MAX(0,MIN(X81,tax_tables!$B$29*P81)-tax_tables!$B$27*P81)+tax_tables!$B$30*MIN(X81,tax_tables!$B$31*P81) | AG81: =tax_tables!$B$25*MAX(0,MIN(Y81,tax_tables!$B$27*P81)-tax_tables!$B$26)+tax_tables!$B$28*MAX(0,MIN(Y81,tax_tables!$B$29*P81)-tax_tables!$B$27*P81)+tax_tables!$B$30*MIN(Y81,tax_tables!$B$31*P81) | AH81: =AF81+AG81 | AI81: =$B$13*AE81 | AJ81: =AD81-Z81-AA81-AH81-AI81 | AK81: =SUMPRODUCT(($B$72:$B$77=A81)*($D$72:$D$77="Other taxable income")*$C$72:$C$77)*O81 | AL81: =SUMPRODUCT(($B$72:$B$77=A81)*($D$72:$D$77="Tax-free money in")*$C$72:$C$77)*O81 | AM81: =SUMPRODUCT(($B$72:$B$77=A81)*($D$72:$D$77="Expense")*$C$72:$C$77)*O81 | AN81: =IF(OR($B$64="",A81<$B$64),1,0) | AO81: =properties!$I$2 | AP81: =AN81*AO81*properties!$J$2 | AQ81: =AN81*MIN(properties!$K$2,AO81+AP81) | AR81: =AN81*(AO81+AP81-AQ81) | AS81: =AN81*properties!$G$2*O81 | AT81: =(1-AN81)*$E$64*O81 | AU81: =AQ81+AS81+AT81 | AV81: =SUMIF(budget!$A$2:$A$300,"household",budget!$F$2:$F$300)*O81*IF(N81="",1,N81) | AW81: =SUMPRODUCT((other_budget!$C$2:$C$30<=A81)*(other_budget!$D$2:$D$30>=A81)*other_budget!$B$2:$B$30)*O81 | AX81: =SUMPRODUCT((kids_budget!$D$2:$D$40<=A81)*(kids_budget!$E$2:$E$40>=A81)*(kids_budget!$G$2:$G$40<>"college_funds")*kids_budget!$C$2:$C$40*((kids_budget!$F$2:$F$40="college")*S81+(kids_budget!$F$2:$F$40<>"college")*O81)) | AY81: =SUMPRODUCT((kids_budget!$D$2:$D$40<=A81)*(kids_budget!$E$2:$E$40>=A81)*(kids_budget!$G$2:$G$40="college_funds")*kids_budget!$C$2:$C$40*((kids_budget!$F$2:$F$40="college")*S81+(kids_budget!$F$2:$F$40<>"college")*O81)) | AZ81: =$B$61 | BA81: =MIN(AY81,AZ81*(1+M81)) | BB81: =AY81-BA81 | BC81: =AZ81*(1+M81)-BA81 | BD81: =W81*healthcare!$B$2*R81 | BE81: =(1-W81)*2 | BF81: =BE81*healthcare!$B$3*12*R81 | BG81: =BE81*healthcare!$B$4*R81 | BH81: =AND(B81>=$B$44,B81<$B$44+$B$45)*1+AND(C81>=$B$46,C81<$B$46+$B$47)*1 | BI81: =BH81*$B$48*T81 | BJ81: =BD81+BF81+BG81+BI81 | BK81: =SUMPRODUCT((1-($B$65:$B$68>0)*(A81>=$B$65:$B$68))*(1-(($C$65:$C$68>0)*(A81>=$C$65:$C$68)))*(properties!$L$3:$L$6-properties!$M$3:$M$6))*O81+SUMPRODUCT((1-($B$65:$B$68>0)*(A81>=$B$65:$B$68))*(($C$65:$C$68>0)*(A81>=$C$65:$C$68))*($D$65:$D$68-$E$65:$E$68))*O81 | BL81: =SUMPRODUCT((1-($B$65:$B$68>0)*(A81>=$B$65:$B$68))*properties!$N$3:$N$6*(A81<=properties!$O$3:$O$6)) | BM81: =MAX(0,BK81-BL81) | BN81: =SUMPRODUCT(($B$64:$B$68=A81)*$G$64:$G$68) | BO81: =SUMPRODUCT(($B$64:$B$68=A81)*$H$64:$H$68) | BP81: =SUMPRODUCT(($B$64:$B$68=A81)*$I$64:$I$68) | BQ81: =AN81*properties!$C$2*(1+properties!$D$2)^(A81-household!$B$4+1) | BR81: =SUMPRODUCT((1-($B$65:$B$68>0)*(A81>=$B$65:$B$68))*properties!$C$3:$C$6*(1+properties!$D$3:$D$6)^(A81-household!$B$4+1)) | BS81: =IF(A81>=household!$B$6+$B$26,household!$B$11*12*$B$30*O81,0) | BT81: =IF(A81>=household!$B$9+$B$27,household!$B$12*12*$B$31*O81,0) | BU81: =IF(A81>=household!$B$6+$B$28,tax_tables!$B$19*12*P81*MIN(1,household!$B$13/40)*$B$32*(1+tax_tables!$B$20*(B81>=75)),0) | BV81: =IF(A81>=household!$B$9+$B$29,tax_tables!$B$19*12*P81*MIN(1,household!$B$14/40)*$B$33*(1+tax_tables!$B$20*(C81>=75)),0) | BW81: =IF(AND($B$36<>0,A81>=household!$B$6+$B$37),$B$36*(1+$B$17)^(MAX(household!$B$6+$B$37,household!$B$4-1)-household!$B$4+1)*(1+$B$40*$B$17)^(A81-MAX(household!$B$6+$B$37,household!$B$4-1)),0) | BX81: =IF(AND($B$38<>0,A81>=household!$B$9+$B$39),$B$38*(1+$B$17)^(MAX(household!$B$9+$B$39,household!$B$4-1)-household!$B$4+1)*(1+$B$40*$B$17)^(A81-MAX(household!$B$9+$B$39,household!$B$4-1)),0) | BY81: =$B$56 | BZ81: =$B$57 | CA81: =$B$19*BY81 | CB81: =$B$58 | CC81: =$B$59 | CD81: =IF(B81>=tax_tables!$B$46,MAX(0,CB81)*INDEX(tax_tables!$N$5:$N$54,MATCH(MIN(B81-1,120),tax_tables!$M$5:$M$54,0)),0) | CE81: =IF(C81>=tax_tables!$B$46,MAX(0,CC81)*INDEX(tax_tables!$N$5:$N$54,MATCH(MIN(C81-1,120),tax_tables!$M$5:$M$54,0)),0) | CF81: =$B$60 | CG81: =IF(OR($B$52="",$B$53=""),0,IF(AND(A81>=$B$52,A81<=$B$53),$B$51*O81,0)) | CH81: =MAX(0,CB81*(1+M81)-CD81) | CI81: =MAX(0,CC81*(1+M81)-CE81) | CJ81: =MIN(CG81,CH81+CI81) | CK81: =IF(CH81+CI81>1,CJ81*CH81/(CH81+CI81),0) | CL81: =CJ81-CK81 | CM81: =household!$B$16 | CN81: =$B$14 | CO81: =AJ81+F81+BW81+BX81+BK81+CA81+CD81+CE81+BN81+AK81+AL81+CJ81 | CP81: =D81+CN81-CO81 | CQ81: =MAX(0,MIN(CP81,BY81*(1+M81-$B$19))) | CR81: =MAX(0,MIN(CP81-CQ81,(CH81-CK81)+(CI81-CL81))) | CS81: =IF((CH81-CK81)+(CI81-CL81)>1,CR81*(CH81-CK81)/((CH81-CK81)+(CI81-CL81)),0) | CT81: =CR81-CS81 | CU81: =MAX(0,MIN(CP81-CQ81-CR81,CF81*(1+M81))) | CV81: =MAX(0,-CP81) | CW81: =MIN(CV81,MAX(0,CM81)) | CX81: =IF(BY81>0,MAX(0,1-BZ81/BY81),0) | CY81: =CQ81*CX81 | CZ81: =BY81*(1+M81-$B$19)-CQ81+(CV81-CW81) | DA81: =BZ81-(CQ81-CY81)+(CV81-CW81) | DB81: =CB81*(1+M81)-CD81-CS81-CK81+Z81+AB81 | DC81: =CC81*(1+M81)-CE81-CT81-CL81+AA81+AC81 | DD81: =CF81*(1+M81)-CU81+CW81 | DE81: =CD81+CK81+CS81 | DF81: =CA81*household!$B$15*$B$20*(1+tax_tables!$B$17) | DG81: =X81+BS81+BU81+BW81+DE81+DF81+CA81*household!$B$15*(1-$B$20)+(CY81+BO81)*household!$B$15*tax_tables!$B$18+(BP81+BM81+AK81)*household!$B$15-Z81 | DH81: =CE81+CL81+CT81 | DI81: =CA81*(1-household!$B$15)*$B$20*(1+tax_tables!$B$17) | DJ81: =Y81+BT81+BV81+BX81+DH81+DI81+CA81*(1-household!$B$15)*(1-$B$20)+(CY81+BO81)*(1-household!$B$15)*tax_tables!$B$18+(BP81+BM81+AK81)*(1-household!$B$15)-AA81 | DK81: =IF((DG81>=DJ81),MIN(0.5*(BW81+IF(B81>=65,DE81,0)),MAX(0,(DG81-DJ81)/2)),MIN(0.5*(BX81+IF(C81>=65,DH81,0)),MAX(0,(DJ81-DG81)/2))) | DL81: =DG81+IF((DG81>=DJ81),-DK81,DK81) | DM81: =BW81+IF(B81>=65,DE81,0)+IF((DG81>=DJ81),-DK81,DK81) | DN81: =MIN(BU81,tax_tables!$B$22*MAX(0,DL81-tax_tables!$B$21*P81)) | DO81: =MAX(0,DL81-DN81) | DP81: =DJ81+IF((DG81>=DJ81),DK81,-DK81) | DQ81: =BX81+IF(C81>=65,DH81,0)+IF((DG81>=DJ81),DK81,-DK81) | DR81: =MIN(BV81,tax_tables!$B$22*MAX(0,DP81-tax_tables!$B$21*P81)) | DS81: =MAX(0,DP81-DR81) | DT81: =BJ81-BD81 | DU81: =(tax_tables!$B$6-(tax_tables!$B$6-tax_tables!$B$7)*MIN(1,MAX(0,(DL81-tax_tables!$B$8*P81)/((tax_tables!$B$9-tax_tables!$B$8)*P81))))*P81+(B81>=65)*MAX(0,tax_tables!$B$10*P81-tax_tables!$B$12*MAX(0,DL81-tax_tables!$B$11*P81))+MIN(tax_tables!$B$13,DM81)+MIN(tax_tables!$B$14*P81,X81)+AF81+(DL81<=DP81)*MAX(0,DT81-MIN(0.03*DL81,tax_tables!$B$15*P81)) | DV81: =MAX(0,SUMPRODUCT((DO81>tax_tables!$E$5:$E$16*P81)*(DO81-tax_tables!$E$5:$E$16*P81)*tax_tables!$G$5:$G$16)-tax_tables!$B$5*DU81-tax_tables!$B$16*DF81) | DW81: =tax_tables!$B$35*Q81+(B81>=65)*MAX(0,tax_tables!$B$36*Q81-tax_tables!$B$12*MAX(0,DL81-tax_tables!$B$37*Q81))+MIN(tax_tables!$B$38,DM81)+AF81+(DL81<=DP81)*MAX(0,DT81-MIN(0.03*DL81,tax_tables!$B$39*Q81)) | DX81: =MAX(0,SUMPRODUCT((DO81>tax_tables!$I$5:$I$16*Q81)*(DO81-tax_tables!$I$5:$I$16*Q81)*tax_tables!$K$5:$K$16)-tax_tables!$B$34*DW81-tax_tables!$B$40*DF81-MAX(0,tax_tables!$B$41*Q81-tax_tables!$B$43*MAX(0,DL81-tax_tables!$B$42*Q81))) | DY81: =(tax_tables!$B$6-(tax_tables!$B$6-tax_tables!$B$7)*MIN(1,MAX(0,(DP81-tax_tables!$B$8*P81)/((tax_tables!$B$9-tax_tables!$B$8)*P81))))*P81+(C81>=65)*MAX(0,tax_tables!$B$10*P81-tax_tables!$B$12*MAX(0,DP81-tax_tables!$B$11*P81))+MIN(tax_tables!$B$13,DQ81)+MIN(tax_tables!$B$14*P81,Y81)+AG81+(DL81>DP81)*MAX(0,DT81-MIN(0.03*DP81,tax_tables!$B$15*P81)) | DZ81: =MAX(0,SUMPRODUCT((DS81>tax_tables!$E$5:$E$16*P81)*(DS81-tax_tables!$E$5:$E$16*P81)*tax_tables!$G$5:$G$16)-tax_tables!$B$5*DY81-tax_tables!$B$16*DI81) | EA81: =tax_tables!$B$35*Q81+(C81>=65)*MAX(0,tax_tables!$B$36*Q81-tax_tables!$B$12*MAX(0,DP81-tax_tables!$B$37*Q81))+MIN(tax_tables!$B$38,DQ81)+AG81+(DL81>DP81)*MAX(0,DT81-MIN(0.03*DP81,tax_tables!$B$39*Q81)) | EB81: =MAX(0,SUMPRODUCT((DS81>tax_tables!$I$5:$I$16*Q81)*(DS81-tax_tables!$I$5:$I$16*Q81)*tax_tables!$K$5:$K$16)-tax_tables!$B$34*EA81-tax_tables!$B$40*DI81-MAX(0,tax_tables!$B$41*Q81-tax_tables!$B$43*MAX(0,DP81-tax_tables!$B$42*Q81))) | EC81: =DV81+DZ81+DX81+EB81+DN81+DR81 | ED81: =CZ81+DB81+DC81+DD81 | EE81: =ED81+BQ81-AR81+BR81
A82: =A81+1 | B82: =A82-household!$B$6 | C82: =A82-household!$B$9 | D82: =AU82+AV82+AW82+AX82+BB82+BJ82+AM82 | E82: =CN82+AI82+AH82 | F82: =BS82+BT82+BU82+BV82 | G82: =CQ82+CR82+CU82+CD82+CE82+CA82-CV82+CJ82+CW82 | H82: =IF(BY82+CB82+CC82+CF82<=0,"",G82/(BY82+CB82+CC82+CF82)) | I82: =ED82/O82 | J82: =EE82/O82 | K82: =MAX(0,CP82-CQ82-CR82-CU82) | M82: =IF(L82="",$B$18,L82) | O82: =(1+$B$17)^(A82-household!$B$4+1) | P82: =(1+$B$17)^(A82-tax_tables!$B$4) | Q82: =(1+$B$17)^(A82-tax_tables!$B$4-MAX(0,MIN(A82,tax_tables!$B$45)-tax_tables!$B$44+1)) | R82: =(1+$B$21)^(A82-household!$B$4+1) | S82: =(1+$B$22)^(A82-household!$B$4+1) | T82: =(1+$B$23)^(A82-household!$B$4+1) | U82: =IF(A82<$B$5,1,0) | V82: =IF(A82<$B$6,1,0) | W82: =IF(U82+V82>0,1,0) | X82: =U82*$B$7*O82+SUMPRODUCT(($B$72:$B$77=A82)*($D$72:$D$77="Wages: person 1")*$C$72:$C$77)*O82 | Y82: =V82*$B$8*O82+SUMPRODUCT(($B$72:$B$77=A82)*($D$72:$D$77="Wages: person 2")*$C$72:$C$77)*O82 | Z82: =U82*$B$9*O82 | AA82: =V82*$B$10*O82 | AB82: =U82*$B$11*O82 | AC82: =V82*$B$12*O82 | AD82: =X82+Y82 | AE82: =AD82-Z82-AA82 | AF82: =tax_tables!$B$25*MAX(0,MIN(X82,tax_tables!$B$27*P82)-tax_tables!$B$26)+tax_tables!$B$28*MAX(0,MIN(X82,tax_tables!$B$29*P82)-tax_tables!$B$27*P82)+tax_tables!$B$30*MIN(X82,tax_tables!$B$31*P82) | AG82: =tax_tables!$B$25*MAX(0,MIN(Y82,tax_tables!$B$27*P82)-tax_tables!$B$26)+tax_tables!$B$28*MAX(0,MIN(Y82,tax_tables!$B$29*P82)-tax_tables!$B$27*P82)+tax_tables!$B$30*MIN(Y82,tax_tables!$B$31*P82) | AH82: =AF82+AG82 | AI82: =$B$13*AE82 | AJ82: =AD82-Z82-AA82-AH82-AI82 | AK82: =SUMPRODUCT(($B$72:$B$77=A82)*($D$72:$D$77="Other taxable income")*$C$72:$C$77)*O82 | AL82: =SUMPRODUCT(($B$72:$B$77=A82)*($D$72:$D$77="Tax-free money in")*$C$72:$C$77)*O82 | AM82: =SUMPRODUCT(($B$72:$B$77=A82)*($D$72:$D$77="Expense")*$C$72:$C$77)*O82 | AN82: =IF(OR($B$64="",A82<$B$64),1,0) | AO82: =AR81 | AP82: =AN82*AO82*properties!$J$2 | AQ82: =AN82*MIN(properties!$K$2,AO82+AP82) | AR82: =AN82*(AO82+AP82-AQ82) | AS82: =AN82*properties!$G$2*O82 | AT82: =(1-AN82)*$E$64*O82 | AU82: =AQ82+AS82+AT82 | AV82: =SUMIF(budget!$A$2:$A$300,"household",budget!$F$2:$F$300)*O82*IF(N82="",1,N82) | AW82: =SUMPRODUCT((other_budget!$C$2:$C$30<=A82)*(other_budget!$D$2:$D$30>=A82)*other_budget!$B$2:$B$30)*O82 | AX82: =SUMPRODUCT((kids_budget!$D$2:$D$40<=A82)*(kids_budget!$E$2:$E$40>=A82)*(kids_budget!$G$2:$G$40<>"college_funds")*kids_budget!$C$2:$C$40*((kids_budget!$F$2:$F$40="college")*S82+(kids_budget!$F$2:$F$40<>"college")*O82)) | AY82: =SUMPRODUCT((kids_budget!$D$2:$D$40<=A82)*(kids_budget!$E$2:$E$40>=A82)*(kids_budget!$G$2:$G$40="college_funds")*kids_budget!$C$2:$C$40*((kids_budget!$F$2:$F$40="college")*S82+(kids_budget!$F$2:$F$40<>"college")*O82)) | AZ82: =BC81 | BA82: =MIN(AY82,AZ82*(1+M82)) | BB82: =AY82-BA82 | BC82: =AZ82*(1+M82)-BA82 | BD82: =W82*healthcare!$B$2*R82 | BE82: =(1-W82)*2 | BF82: =BE82*healthcare!$B$3*12*R82 | BG82: =BE82*healthcare!$B$4*R82 | BH82: =AND(B82>=$B$44,B82<$B$44+$B$45)*1+AND(C82>=$B$46,C82<$B$46+$B$47)*1 | BI82: =BH82*$B$48*T82 | BJ82: =BD82+BF82+BG82+BI82 | BK82: =SUMPRODUCT((1-($B$65:$B$68>0)*(A82>=$B$65:$B$68))*(1-(($C$65:$C$68>0)*(A82>=$C$65:$C$68)))*(properties!$L$3:$L$6-properties!$M$3:$M$6))*O82+SUMPRODUCT((1-($B$65:$B$68>0)*(A82>=$B$65:$B$68))*(($C$65:$C$68>0)*(A82>=$C$65:$C$68))*($D$65:$D$68-$E$65:$E$68))*O82 | BL82: =SUMPRODUCT((1-($B$65:$B$68>0)*(A82>=$B$65:$B$68))*properties!$N$3:$N$6*(A82<=properties!$O$3:$O$6)) | BM82: =MAX(0,BK82-BL82) | BN82: =SUMPRODUCT(($B$64:$B$68=A82)*$G$64:$G$68) | BO82: =SUMPRODUCT(($B$64:$B$68=A82)*$H$64:$H$68) | BP82: =SUMPRODUCT(($B$64:$B$68=A82)*$I$64:$I$68) | BQ82: =AN82*properties!$C$2*(1+properties!$D$2)^(A82-household!$B$4+1) | BR82: =SUMPRODUCT((1-($B$65:$B$68>0)*(A82>=$B$65:$B$68))*properties!$C$3:$C$6*(1+properties!$D$3:$D$6)^(A82-household!$B$4+1)) | BS82: =IF(A82>=household!$B$6+$B$26,household!$B$11*12*$B$30*O82,0) | BT82: =IF(A82>=household!$B$9+$B$27,household!$B$12*12*$B$31*O82,0) | BU82: =IF(A82>=household!$B$6+$B$28,tax_tables!$B$19*12*P82*MIN(1,household!$B$13/40)*$B$32*(1+tax_tables!$B$20*(B82>=75)),0) | BV82: =IF(A82>=household!$B$9+$B$29,tax_tables!$B$19*12*P82*MIN(1,household!$B$14/40)*$B$33*(1+tax_tables!$B$20*(C82>=75)),0) | BW82: =IF(AND($B$36<>0,A82>=household!$B$6+$B$37),$B$36*(1+$B$17)^(MAX(household!$B$6+$B$37,household!$B$4-1)-household!$B$4+1)*(1+$B$40*$B$17)^(A82-MAX(household!$B$6+$B$37,household!$B$4-1)),0) | BX82: =IF(AND($B$38<>0,A82>=household!$B$9+$B$39),$B$38*(1+$B$17)^(MAX(household!$B$9+$B$39,household!$B$4-1)-household!$B$4+1)*(1+$B$40*$B$17)^(A82-MAX(household!$B$9+$B$39,household!$B$4-1)),0) | BY82: =CZ81 | BZ82: =DA81 | CA82: =$B$19*BY82 | CB82: =DB81 | CC82: =DC81 | CD82: =IF(B82>=tax_tables!$B$46,MAX(0,CB82)*INDEX(tax_tables!$N$5:$N$54,MATCH(MIN(B82-1,120),tax_tables!$M$5:$M$54,0)),0) | CE82: =IF(C82>=tax_tables!$B$46,MAX(0,CC82)*INDEX(tax_tables!$N$5:$N$54,MATCH(MIN(C82-1,120),tax_tables!$M$5:$M$54,0)),0) | CF82: =DD81 | CG82: =IF(OR($B$52="",$B$53=""),0,IF(AND(A82>=$B$52,A82<=$B$53),$B$51*O82,0)) | CH82: =MAX(0,CB82*(1+M82)-CD82) | CI82: =MAX(0,CC82*(1+M82)-CE82) | CJ82: =MIN(CG82,CH82+CI82) | CK82: =IF(CH82+CI82>1,CJ82*CH82/(CH82+CI82),0) | CL82: =CJ82-CK82 | CM82: =CM81-CW81+CU81+tax_tables!$B$32*P82*2 | CN82: =EC81-AI81 | CO82: =AJ82+F82+BW82+BX82+BK82+CA82+CD82+CE82+BN82+AK82+AL82+CJ82 | CP82: =D82+CN82-CO82 | CQ82: =MAX(0,MIN(CP82,BY82*(1+M82-$B$19))) | CR82: =MAX(0,MIN(CP82-CQ82,(CH82-CK82)+(CI82-CL82))) | CS82: =IF((CH82-CK82)+(CI82-CL82)>1,CR82*(CH82-CK82)/((CH82-CK82)+(CI82-CL82)),0) | CT82: =CR82-CS82 | CU82: =MAX(0,MIN(CP82-CQ82-CR82,CF82*(1+M82))) | CV82: =MAX(0,-CP82) | CW82: =MIN(CV82,MAX(0,CM82)) | CX82: =IF(BY82>0,MAX(0,1-BZ82/BY82),0) | CY82: =CQ82*CX82 | CZ82: =BY82*(1+M82-$B$19)-CQ82+(CV82-CW82) | DA82: =BZ82-(CQ82-CY82)+(CV82-CW82) | DB82: =CB82*(1+M82)-CD82-CS82-CK82+Z82+AB82 | DC82: =CC82*(1+M82)-CE82-CT82-CL82+AA82+AC82 | DD82: =CF82*(1+M82)-CU82+CW82 | DE82: =CD82+CK82+CS82 | DF82: =CA82*household!$B$15*$B$20*(1+tax_tables!$B$17) | DG82: =X82+BS82+BU82+BW82+DE82+DF82+CA82*household!$B$15*(1-$B$20)+(CY82+BO82)*household!$B$15*tax_tables!$B$18+(BP82+BM82+AK82)*household!$B$15-Z82 | DH82: =CE82+CL82+CT82 | DI82: =CA82*(1-household!$B$15)*$B$20*(1+tax_tables!$B$17) | DJ82: =Y82+BT82+BV82+BX82+DH82+DI82+CA82*(1-household!$B$15)*(1-$B$20)+(CY82+BO82)*(1-household!$B$15)*tax_tables!$B$18+(BP82+BM82+AK82)*(1-household!$B$15)-AA82 | DK82: =IF((DG82>=DJ82),MIN(0.5*(BW82+IF(B82>=65,DE82,0)),MAX(0,(DG82-DJ82)/2)),MIN(0.5*(BX82+IF(C82>=65,DH82,0)),MAX(0,(DJ82-DG82)/2))) | DL82: =DG82+IF((DG82>=DJ82),-DK82,DK82) | DM82: =BW82+IF(B82>=65,DE82,0)+IF((DG82>=DJ82),-DK82,DK82) | DN82: =MIN(BU82,tax_tables!$B$22*MAX(0,DL82-tax_tables!$B$21*P82)) | DO82: =MAX(0,DL82-DN82) | DP82: =DJ82+IF((DG82>=DJ82),DK82,-DK82) | DQ82: =BX82+IF(C82>=65,DH82,0)+IF((DG82>=DJ82),DK82,-DK82) | DR82: =MIN(BV82,tax_tables!$B$22*MAX(0,DP82-tax_tables!$B$21*P82)) | DS82: =MAX(0,DP82-DR82) | DT82: =BJ82-BD82 | DU82: =(tax_tables!$B$6-(tax_tables!$B$6-tax_tables!$B$7)*MIN(1,MAX(0,(DL82-tax_tables!$B$8*P82)/((tax_tables!$B$9-tax_tables!$B$8)*P82))))*P82+(B82>=65)*MAX(0,tax_tables!$B$10*P82-tax_tables!$B$12*MAX(0,DL82-tax_tables!$B$11*P82))+MIN(tax_tables!$B$13,DM82)+MIN(tax_tables!$B$14*P82,X82)+AF82+(DL82<=DP82)*MAX(0,DT82-MIN(0.03*DL82,tax_tables!$B$15*P82)) | DV82: =MAX(0,SUMPRODUCT((DO82>tax_tables!$E$5:$E$16*P82)*(DO82-tax_tables!$E$5:$E$16*P82)*tax_tables!$G$5:$G$16)-tax_tables!$B$5*DU82-tax_tables!$B$16*DF82) | DW82: =tax_tables!$B$35*Q82+(B82>=65)*MAX(0,tax_tables!$B$36*Q82-tax_tables!$B$12*MAX(0,DL82-tax_tables!$B$37*Q82))+MIN(tax_tables!$B$38,DM82)+AF82+(DL82<=DP82)*MAX(0,DT82-MIN(0.03*DL82,tax_tables!$B$39*Q82)) | DX82: =MAX(0,SUMPRODUCT((DO82>tax_tables!$I$5:$I$16*Q82)*(DO82-tax_tables!$I$5:$I$16*Q82)*tax_tables!$K$5:$K$16)-tax_tables!$B$34*DW82-tax_tables!$B$40*DF82-MAX(0,tax_tables!$B$41*Q82-tax_tables!$B$43*MAX(0,DL82-tax_tables!$B$42*Q82))) | DY82: =(tax_tables!$B$6-(tax_tables!$B$6-tax_tables!$B$7)*MIN(1,MAX(0,(DP82-tax_tables!$B$8*P82)/((tax_tables!$B$9-tax_tables!$B$8)*P82))))*P82+(C82>=65)*MAX(0,tax_tables!$B$10*P82-tax_tables!$B$12*MAX(0,DP82-tax_tables!$B$11*P82))+MIN(tax_tables!$B$13,DQ82)+MIN(tax_tables!$B$14*P82,Y82)+AG82+(DL82>DP82)*MAX(0,DT82-MIN(0.03*DP82,tax_tables!$B$15*P82)) | DZ82: =MAX(0,SUMPRODUCT((DS82>tax_tables!$E$5:$E$16*P82)*(DS82-tax_tables!$E$5:$E$16*P82)*tax_tables!$G$5:$G$16)-tax_tables!$B$5*DY82-tax_tables!$B$16*DI82) | EA82: =tax_tables!$B$35*Q82+(C82>=65)*MAX(0,tax_tables!$B$36*Q82-tax_tables!$B$12*MAX(0,DP82-tax_tables!$B$37*Q82))+MIN(tax_tables!$B$38,DQ82)+AG82+(DL82>DP82)*MAX(0,DT82-MIN(0.03*DP82,tax_tables!$B$39*Q82)) | EB82: =MAX(0,SUMPRODUCT((DS82>tax_tables!$I$5:$I$16*Q82)*(DS82-tax_tables!$I$5:$I$16*Q82)*tax_tables!$K$5:$K$16)-tax_tables!$B$34*EA82-tax_tables!$B$40*DI82-MAX(0,tax_tables!$B$41*Q82-tax_tables!$B$43*MAX(0,DP82-tax_tables!$B$42*Q82))) | EC82: =DV82+DZ82+DX82+EB82+DN82+DR82 | ED82: =CZ82+DB82+DC82+DD82 | EE82: =ED82+BQ82-AR82+BR82
A83: =A82+1 | B83: =A83-household!$B$6 | C83: =A83-household!$B$9 | D83: =AU83+AV83+AW83+AX83+BB83+BJ83+AM83 | E83: =CN83+AI83+AH83 | F83: =BS83+BT83+BU83+BV83 | G83: =CQ83+CR83+CU83+CD83+CE83+CA83-CV83+CJ83+CW83 | H83: =IF(BY83+CB83+CC83+CF83<=0,"",G83/(BY83+CB83+CC83+CF83)) | I83: =ED83/O83 | J83: =EE83/O83 | K83: =MAX(0,CP83-CQ83-CR83-CU83) | M83: =IF(L83="",$B$18,L83) | O83: =(1+$B$17)^(A83-household!$B$4+1) | P83: =(1+$B$17)^(A83-tax_tables!$B$4) | Q83: =(1+$B$17)^(A83-tax_tables!$B$4-MAX(0,MIN(A83,tax_tables!$B$45)-tax_tables!$B$44+1)) | R83: =(1+$B$21)^(A83-household!$B$4+1) | S83: =(1+$B$22)^(A83-household!$B$4+1) | T83: =(1+$B$23)^(A83-household!$B$4+1) | U83: =IF(A83<$B$5,1,0) | V83: =IF(A83<$B$6,1,0) | W83: =IF(U83+V83>0,1,0) | X83: =U83*$B$7*O83+SUMPRODUCT(($B$72:$B$77=A83)*($D$72:$D$77="Wages: person 1")*$C$72:$C$77)*O83 | Y83: =V83*$B$8*O83+SUMPRODUCT(($B$72:$B$77=A83)*($D$72:$D$77="Wages: person 2")*$C$72:$C$77)*O83 | Z83: =U83*$B$9*O83 | AA83: =V83*$B$10*O83 | AB83: =U83*$B$11*O83 | AC83: =V83*$B$12*O83 | AD83: =X83+Y83 | AE83: =AD83-Z83-AA83 | AF83: =tax_tables!$B$25*MAX(0,MIN(X83,tax_tables!$B$27*P83)-tax_tables!$B$26)+tax_tables!$B$28*MAX(0,MIN(X83,tax_tables!$B$29*P83)-tax_tables!$B$27*P83)+tax_tables!$B$30*MIN(X83,tax_tables!$B$31*P83) | AG83: =tax_tables!$B$25*MAX(0,MIN(Y83,tax_tables!$B$27*P83)-tax_tables!$B$26)+tax_tables!$B$28*MAX(0,MIN(Y83,tax_tables!$B$29*P83)-tax_tables!$B$27*P83)+tax_tables!$B$30*MIN(Y83,tax_tables!$B$31*P83) | AH83: =AF83+AG83 | AI83: =$B$13*AE83 | AJ83: =AD83-Z83-AA83-AH83-AI83 | AK83: =SUMPRODUCT(($B$72:$B$77=A83)*($D$72:$D$77="Other taxable income")*$C$72:$C$77)*O83 | AL83: =SUMPRODUCT(($B$72:$B$77=A83)*($D$72:$D$77="Tax-free money in")*$C$72:$C$77)*O83 | AM83: =SUMPRODUCT(($B$72:$B$77=A83)*($D$72:$D$77="Expense")*$C$72:$C$77)*O83 | AN83: =IF(OR($B$64="",A83<$B$64),1,0) | AO83: =AR82 | AP83: =AN83*AO83*properties!$J$2 | AQ83: =AN83*MIN(properties!$K$2,AO83+AP83) | AR83: =AN83*(AO83+AP83-AQ83) | AS83: =AN83*properties!$G$2*O83 | AT83: =(1-AN83)*$E$64*O83 | AU83: =AQ83+AS83+AT83 | AV83: =SUMIF(budget!$A$2:$A$300,"household",budget!$F$2:$F$300)*O83*IF(N83="",1,N83) | AW83: =SUMPRODUCT((other_budget!$C$2:$C$30<=A83)*(other_budget!$D$2:$D$30>=A83)*other_budget!$B$2:$B$30)*O83 | AX83: =SUMPRODUCT((kids_budget!$D$2:$D$40<=A83)*(kids_budget!$E$2:$E$40>=A83)*(kids_budget!$G$2:$G$40<>"college_funds")*kids_budget!$C$2:$C$40*((kids_budget!$F$2:$F$40="college")*S83+(kids_budget!$F$2:$F$40<>"college")*O83)) | AY83: =SUMPRODUCT((kids_budget!$D$2:$D$40<=A83)*(kids_budget!$E$2:$E$40>=A83)*(kids_budget!$G$2:$G$40="college_funds")*kids_budget!$C$2:$C$40*((kids_budget!$F$2:$F$40="college")*S83+(kids_budget!$F$2:$F$40<>"college")*O83)) | AZ83: =BC82 | BA83: =MIN(AY83,AZ83*(1+M83)) | BB83: =AY83-BA83 | BC83: =AZ83*(1+M83)-BA83 | BD83: =W83*healthcare!$B$2*R83 | BE83: =(1-W83)*2 | BF83: =BE83*healthcare!$B$3*12*R83 | BG83: =BE83*healthcare!$B$4*R83 | BH83: =AND(B83>=$B$44,B83<$B$44+$B$45)*1+AND(C83>=$B$46,C83<$B$46+$B$47)*1 | BI83: =BH83*$B$48*T83 | BJ83: =BD83+BF83+BG83+BI83 | BK83: =SUMPRODUCT((1-($B$65:$B$68>0)*(A83>=$B$65:$B$68))*(1-(($C$65:$C$68>0)*(A83>=$C$65:$C$68)))*(properties!$L$3:$L$6-properties!$M$3:$M$6))*O83+SUMPRODUCT((1-($B$65:$B$68>0)*(A83>=$B$65:$B$68))*(($C$65:$C$68>0)*(A83>=$C$65:$C$68))*($D$65:$D$68-$E$65:$E$68))*O83 | BL83: =SUMPRODUCT((1-($B$65:$B$68>0)*(A83>=$B$65:$B$68))*properties!$N$3:$N$6*(A83<=properties!$O$3:$O$6)) | BM83: =MAX(0,BK83-BL83) | BN83: =SUMPRODUCT(($B$64:$B$68=A83)*$G$64:$G$68) | BO83: =SUMPRODUCT(($B$64:$B$68=A83)*$H$64:$H$68) | BP83: =SUMPRODUCT(($B$64:$B$68=A83)*$I$64:$I$68) | BQ83: =AN83*properties!$C$2*(1+properties!$D$2)^(A83-household!$B$4+1) | BR83: =SUMPRODUCT((1-($B$65:$B$68>0)*(A83>=$B$65:$B$68))*properties!$C$3:$C$6*(1+properties!$D$3:$D$6)^(A83-household!$B$4+1)) | BS83: =IF(A83>=household!$B$6+$B$26,household!$B$11*12*$B$30*O83,0) | BT83: =IF(A83>=household!$B$9+$B$27,household!$B$12*12*$B$31*O83,0) | BU83: =IF(A83>=household!$B$6+$B$28,tax_tables!$B$19*12*P83*MIN(1,household!$B$13/40)*$B$32*(1+tax_tables!$B$20*(B83>=75)),0) | BV83: =IF(A83>=household!$B$9+$B$29,tax_tables!$B$19*12*P83*MIN(1,household!$B$14/40)*$B$33*(1+tax_tables!$B$20*(C83>=75)),0) | BW83: =IF(AND($B$36<>0,A83>=household!$B$6+$B$37),$B$36*(1+$B$17)^(MAX(household!$B$6+$B$37,household!$B$4-1)-household!$B$4+1)*(1+$B$40*$B$17)^(A83-MAX(household!$B$6+$B$37,household!$B$4-1)),0) | BX83: =IF(AND($B$38<>0,A83>=household!$B$9+$B$39),$B$38*(1+$B$17)^(MAX(household!$B$9+$B$39,household!$B$4-1)-household!$B$4+1)*(1+$B$40*$B$17)^(A83-MAX(household!$B$9+$B$39,household!$B$4-1)),0) | BY83: =CZ82 | BZ83: =DA82 | CA83: =$B$19*BY83 | CB83: =DB82 | CC83: =DC82 | CD83: =IF(B83>=tax_tables!$B$46,MAX(0,CB83)*INDEX(tax_tables!$N$5:$N$54,MATCH(MIN(B83-1,120),tax_tables!$M$5:$M$54,0)),0) | CE83: =IF(C83>=tax_tables!$B$46,MAX(0,CC83)*INDEX(tax_tables!$N$5:$N$54,MATCH(MIN(C83-1,120),tax_tables!$M$5:$M$54,0)),0) | CF83: =DD82 | CG83: =IF(OR($B$52="",$B$53=""),0,IF(AND(A83>=$B$52,A83<=$B$53),$B$51*O83,0)) | CH83: =MAX(0,CB83*(1+M83)-CD83) | CI83: =MAX(0,CC83*(1+M83)-CE83) | CJ83: =MIN(CG83,CH83+CI83) | CK83: =IF(CH83+CI83>1,CJ83*CH83/(CH83+CI83),0) | CL83: =CJ83-CK83 | CM83: =CM82-CW82+CU82+tax_tables!$B$32*P83*2 | CN83: =EC82-AI82 | CO83: =AJ83+F83+BW83+BX83+BK83+CA83+CD83+CE83+BN83+AK83+AL83+CJ83 | CP83: =D83+CN83-CO83 | CQ83: =MAX(0,MIN(CP83,BY83*(1+M83-$B$19))) | CR83: =MAX(0,MIN(CP83-CQ83,(CH83-CK83)+(CI83-CL83))) | CS83: =IF((CH83-CK83)+(CI83-CL83)>1,CR83*(CH83-CK83)/((CH83-CK83)+(CI83-CL83)),0) | CT83: =CR83-CS83 | CU83: =MAX(0,MIN(CP83-CQ83-CR83,CF83*(1+M83))) | CV83: =MAX(0,-CP83) | CW83: =MIN(CV83,MAX(0,CM83)) | CX83: =IF(BY83>0,MAX(0,1-BZ83/BY83),0) | CY83: =CQ83*CX83 | CZ83: =BY83*(1+M83-$B$19)-CQ83+(CV83-CW83) | DA83: =BZ83-(CQ83-CY83)+(CV83-CW83) | DB83: =CB83*(1+M83)-CD83-CS83-CK83+Z83+AB83 | DC83: =CC83*(1+M83)-CE83-CT83-CL83+AA83+AC83 | DD83: =CF83*(1+M83)-CU83+CW83 | DE83: =CD83+CK83+CS83 | DF83: =CA83*household!$B$15*$B$20*(1+tax_tables!$B$17) | DG83: =X83+BS83+BU83+BW83+DE83+DF83+CA83*household!$B$15*(1-$B$20)+(CY83+BO83)*household!$B$15*tax_tables!$B$18+(BP83+BM83+AK83)*household!$B$15-Z83 | DH83: =CE83+CL83+CT83 | DI83: =CA83*(1-household!$B$15)*$B$20*(1+tax_tables!$B$17) | DJ83: =Y83+BT83+BV83+BX83+DH83+DI83+CA83*(1-household!$B$15)*(1-$B$20)+(CY83+BO83)*(1-household!$B$15)*tax_tables!$B$18+(BP83+BM83+AK83)*(1-household!$B$15)-AA83 | DK83: =IF((DG83>=DJ83),MIN(0.5*(BW83+IF(B83>=65,DE83,0)),MAX(0,(DG83-DJ83)/2)),MIN(0.5*(BX83+IF(C83>=65,DH83,0)),MAX(0,(DJ83-DG83)/2))) | DL83: =DG83+IF((DG83>=DJ83),-DK83,DK83) | DM83: =BW83+IF(B83>=65,DE83,0)+IF((DG83>=DJ83),-DK83,DK83) | DN83: =MIN(BU83,tax_tables!$B$22*MAX(0,DL83-tax_tables!$B$21*P83)) | DO83: =MAX(0,DL83-DN83) | DP83: =DJ83+IF((DG83>=DJ83),DK83,-DK83) | DQ83: =BX83+IF(C83>=65,DH83,0)+IF((DG83>=DJ83),DK83,-DK83) | DR83: =MIN(BV83,tax_tables!$B$22*MAX(0,DP83-tax_tables!$B$21*P83)) | DS83: =MAX(0,DP83-DR83) | DT83: =BJ83-BD83 | DU83: =(tax_tables!$B$6-(tax_tables!$B$6-tax_tables!$B$7)*MIN(1,MAX(0,(DL83-tax_tables!$B$8*P83)/((tax_tables!$B$9-tax_tables!$B$8)*P83))))*P83+(B83>=65)*MAX(0,tax_tables!$B$10*P83-tax_tables!$B$12*MAX(0,DL83-tax_tables!$B$11*P83))+MIN(tax_tables!$B$13,DM83)+MIN(tax_tables!$B$14*P83,X83)+AF83+(DL83<=DP83)*MAX(0,DT83-MIN(0.03*DL83,tax_tables!$B$15*P83)) | DV83: =MAX(0,SUMPRODUCT((DO83>tax_tables!$E$5:$E$16*P83)*(DO83-tax_tables!$E$5:$E$16*P83)*tax_tables!$G$5:$G$16)-tax_tables!$B$5*DU83-tax_tables!$B$16*DF83) | DW83: =tax_tables!$B$35*Q83+(B83>=65)*MAX(0,tax_tables!$B$36*Q83-tax_tables!$B$12*MAX(0,DL83-tax_tables!$B$37*Q83))+MIN(tax_tables!$B$38,DM83)+AF83+(DL83<=DP83)*MAX(0,DT83-MIN(0.03*DL83,tax_tables!$B$39*Q83)) | DX83: =MAX(0,SUMPRODUCT((DO83>tax_tables!$I$5:$I$16*Q83)*(DO83-tax_tables!$I$5:$I$16*Q83)*tax_tables!$K$5:$K$16)-tax_tables!$B$34*DW83-tax_tables!$B$40*DF83-MAX(0,tax_tables!$B$41*Q83-tax_tables!$B$43*MAX(0,DL83-tax_tables!$B$42*Q83))) | DY83: =(tax_tables!$B$6-(tax_tables!$B$6-tax_tables!$B$7)*MIN(1,MAX(0,(DP83-tax_tables!$B$8*P83)/((tax_tables!$B$9-tax_tables!$B$8)*P83))))*P83+(C83>=65)*MAX(0,tax_tables!$B$10*P83-tax_tables!$B$12*MAX(0,DP83-tax_tables!$B$11*P83))+MIN(tax_tables!$B$13,DQ83)+MIN(tax_tables!$B$14*P83,Y83)+AG83+(DL83>DP83)*MAX(0,DT83-MIN(0.03*DP83,tax_tables!$B$15*P83)) | DZ83: =MAX(0,SUMPRODUCT((DS83>tax_tables!$E$5:$E$16*P83)*(DS83-tax_tables!$E$5:$E$16*P83)*tax_tables!$G$5:$G$16)-tax_tables!$B$5*DY83-tax_tables!$B$16*DI83) | EA83: =tax_tables!$B$35*Q83+(C83>=65)*MAX(0,tax_tables!$B$36*Q83-tax_tables!$B$12*MAX(0,DP83-tax_tables!$B$37*Q83))+MIN(tax_tables!$B$38,DQ83)+AG83+(DL83>DP83)*MAX(0,DT83-MIN(0.03*DP83,tax_tables!$B$39*Q83)) | EB83: =MAX(0,SUMPRODUCT((DS83>tax_tables!$I$5:$I$16*Q83)*(DS83-tax_tables!$I$5:$I$16*Q83)*tax_tables!$K$5:$K$16)-tax_tables!$B$34*EA83-tax_tables!$B$40*DI83-MAX(0,tax_tables!$B$41*Q83-tax_tables!$B$43*MAX(0,DP83-tax_tables!$B$42*Q83))) | EC83: =DV83+DZ83+DX83+EB83+DN83+DR83 | ED83: =CZ83+DB83+DC83+DD83 | EE83: =ED83+BQ83-AR83+BR83
A84: =A83+1 | B84: =A84-household!$B$6 | C84: =A84-household!$B$9 | D84: =AU84+AV84+AW84+AX84+BB84+BJ84+AM84 | E84: =CN84+AI84+AH84 | F84: =BS84+BT84+BU84+BV84 | G84: =CQ84+CR84+CU84+CD84+CE84+CA84-CV84+CJ84+CW84 | H84: =IF(BY84+CB84+CC84+CF84<=0,"",G84/(BY84+CB84+CC84+CF84)) | I84: =ED84/O84 | J84: =EE84/O84 | K84: =MAX(0,CP84-CQ84-CR84-CU84) | M84: =IF(L84="",$B$18,L84) | O84: =(1+$B$17)^(A84-household!$B$4+1) | P84: =(1+$B$17)^(A84-tax_tables!$B$4) | Q84: =(1+$B$17)^(A84-tax_tables!$B$4-MAX(0,MIN(A84,tax_tables!$B$45)-tax_tables!$B$44+1)) | R84: =(1+$B$21)^(A84-household!$B$4+1) | S84: =(1+$B$22)^(A84-household!$B$4+1) | T84: =(1+$B$23)^(A84-household!$B$4+1) | U84: =IF(A84<$B$5,1,0) | V84: =IF(A84<$B$6,1,0) | W84: =IF(U84+V84>0,1,0) | X84: =U84*$B$7*O84+SUMPRODUCT(($B$72:$B$77=A84)*($D$72:$D$77="Wages: person 1")*$C$72:$C$77)*O84 | Y84: =V84*$B$8*O84+SUMPRODUCT(($B$72:$B$77=A84)*($D$72:$D$77="Wages: person 2")*$C$72:$C$77)*O84 | Z84: =U84*$B$9*O84 | AA84: =V84*$B$10*O84 | AB84: =U84*$B$11*O84 | AC84: =V84*$B$12*O84 | AD84: =X84+Y84 | AE84: =AD84-Z84-AA84 | AF84: =tax_tables!$B$25*MAX(0,MIN(X84,tax_tables!$B$27*P84)-tax_tables!$B$26)+tax_tables!$B$28*MAX(0,MIN(X84,tax_tables!$B$29*P84)-tax_tables!$B$27*P84)+tax_tables!$B$30*MIN(X84,tax_tables!$B$31*P84) | AG84: =tax_tables!$B$25*MAX(0,MIN(Y84,tax_tables!$B$27*P84)-tax_tables!$B$26)+tax_tables!$B$28*MAX(0,MIN(Y84,tax_tables!$B$29*P84)-tax_tables!$B$27*P84)+tax_tables!$B$30*MIN(Y84,tax_tables!$B$31*P84) | AH84: =AF84+AG84 | AI84: =$B$13*AE84 | AJ84: =AD84-Z84-AA84-AH84-AI84 | AK84: =SUMPRODUCT(($B$72:$B$77=A84)*($D$72:$D$77="Other taxable income")*$C$72:$C$77)*O84 | AL84: =SUMPRODUCT(($B$72:$B$77=A84)*($D$72:$D$77="Tax-free money in")*$C$72:$C$77)*O84 | AM84: =SUMPRODUCT(($B$72:$B$77=A84)*($D$72:$D$77="Expense")*$C$72:$C$77)*O84 | AN84: =IF(OR($B$64="",A84<$B$64),1,0) | AO84: =AR83 | AP84: =AN84*AO84*properties!$J$2 | AQ84: =AN84*MIN(properties!$K$2,AO84+AP84) | AR84: =AN84*(AO84+AP84-AQ84) | AS84: =AN84*properties!$G$2*O84 | AT84: =(1-AN84)*$E$64*O84 | AU84: =AQ84+AS84+AT84 | AV84: =SUMIF(budget!$A$2:$A$300,"household",budget!$F$2:$F$300)*O84*IF(N84="",1,N84) | AW84: =SUMPRODUCT((other_budget!$C$2:$C$30<=A84)*(other_budget!$D$2:$D$30>=A84)*other_budget!$B$2:$B$30)*O84 | AX84: =SUMPRODUCT((kids_budget!$D$2:$D$40<=A84)*(kids_budget!$E$2:$E$40>=A84)*(kids_budget!$G$2:$G$40<>"college_funds")*kids_budget!$C$2:$C$40*((kids_budget!$F$2:$F$40="college")*S84+(kids_budget!$F$2:$F$40<>"college")*O84)) | AY84: =SUMPRODUCT((kids_budget!$D$2:$D$40<=A84)*(kids_budget!$E$2:$E$40>=A84)*(kids_budget!$G$2:$G$40="college_funds")*kids_budget!$C$2:$C$40*((kids_budget!$F$2:$F$40="college")*S84+(kids_budget!$F$2:$F$40<>"college")*O84)) | AZ84: =BC83 | BA84: =MIN(AY84,AZ84*(1+M84)) | BB84: =AY84-BA84 | BC84: =AZ84*(1+M84)-BA84 | BD84: =W84*healthcare!$B$2*R84 | BE84: =(1-W84)*2 | BF84: =BE84*healthcare!$B$3*12*R84 | BG84: =BE84*healthcare!$B$4*R84 | BH84: =AND(B84>=$B$44,B84<$B$44+$B$45)*1+AND(C84>=$B$46,C84<$B$46+$B$47)*1 | BI84: =BH84*$B$48*T84 | BJ84: =BD84+BF84+BG84+BI84 | BK84: =SUMPRODUCT((1-($B$65:$B$68>0)*(A84>=$B$65:$B$68))*(1-(($C$65:$C$68>0)*(A84>=$C$65:$C$68)))*(properties!$L$3:$L$6-properties!$M$3:$M$6))*O84+SUMPRODUCT((1-($B$65:$B$68>0)*(A84>=$B$65:$B$68))*(($C$65:$C$68>0)*(A84>=$C$65:$C$68))*($D$65:$D$68-$E$65:$E$68))*O84 | BL84: =SUMPRODUCT((1-($B$65:$B$68>0)*(A84>=$B$65:$B$68))*properties!$N$3:$N$6*(A84<=properties!$O$3:$O$6)) | BM84: =MAX(0,BK84-BL84) | BN84: =SUMPRODUCT(($B$64:$B$68=A84)*$G$64:$G$68) | BO84: =SUMPRODUCT(($B$64:$B$68=A84)*$H$64:$H$68) | BP84: =SUMPRODUCT(($B$64:$B$68=A84)*$I$64:$I$68) | BQ84: =AN84*properties!$C$2*(1+properties!$D$2)^(A84-household!$B$4+1) | BR84: =SUMPRODUCT((1-($B$65:$B$68>0)*(A84>=$B$65:$B$68))*properties!$C$3:$C$6*(1+properties!$D$3:$D$6)^(A84-household!$B$4+1)) | BS84: =IF(A84>=household!$B$6+$B$26,household!$B$11*12*$B$30*O84,0) | BT84: =IF(A84>=household!$B$9+$B$27,household!$B$12*12*$B$31*O84,0) | BU84: =IF(A84>=household!$B$6+$B$28,tax_tables!$B$19*12*P84*MIN(1,household!$B$13/40)*$B$32*(1+tax_tables!$B$20*(B84>=75)),0) | BV84: =IF(A84>=household!$B$9+$B$29,tax_tables!$B$19*12*P84*MIN(1,household!$B$14/40)*$B$33*(1+tax_tables!$B$20*(C84>=75)),0) | BW84: =IF(AND($B$36<>0,A84>=household!$B$6+$B$37),$B$36*(1+$B$17)^(MAX(household!$B$6+$B$37,household!$B$4-1)-household!$B$4+1)*(1+$B$40*$B$17)^(A84-MAX(household!$B$6+$B$37,household!$B$4-1)),0) | BX84: =IF(AND($B$38<>0,A84>=household!$B$9+$B$39),$B$38*(1+$B$17)^(MAX(household!$B$9+$B$39,household!$B$4-1)-household!$B$4+1)*(1+$B$40*$B$17)^(A84-MAX(household!$B$9+$B$39,household!$B$4-1)),0) | BY84: =CZ83 | BZ84: =DA83 | CA84: =$B$19*BY84 | CB84: =DB83 | CC84: =DC83 | CD84: =IF(B84>=tax_tables!$B$46,MAX(0,CB84)*INDEX(tax_tables!$N$5:$N$54,MATCH(MIN(B84-1,120),tax_tables!$M$5:$M$54,0)),0) | CE84: =IF(C84>=tax_tables!$B$46,MAX(0,CC84)*INDEX(tax_tables!$N$5:$N$54,MATCH(MIN(C84-1,120),tax_tables!$M$5:$M$54,0)),0) | CF84: =DD83 | CG84: =IF(OR($B$52="",$B$53=""),0,IF(AND(A84>=$B$52,A84<=$B$53),$B$51*O84,0)) | CH84: =MAX(0,CB84*(1+M84)-CD84) | CI84: =MAX(0,CC84*(1+M84)-CE84) | CJ84: =MIN(CG84,CH84+CI84) | CK84: =IF(CH84+CI84>1,CJ84*CH84/(CH84+CI84),0) | CL84: =CJ84-CK84 | CM84: =CM83-CW83+CU83+tax_tables!$B$32*P84*2 | CN84: =EC83-AI83 | CO84: =AJ84+F84+BW84+BX84+BK84+CA84+CD84+CE84+BN84+AK84+AL84+CJ84 | CP84: =D84+CN84-CO84 | CQ84: =MAX(0,MIN(CP84,BY84*(1+M84-$B$19))) | CR84: =MAX(0,MIN(CP84-CQ84,(CH84-CK84)+(CI84-CL84))) | CS84: =IF((CH84-CK84)+(CI84-CL84)>1,CR84*(CH84-CK84)/((CH84-CK84)+(CI84-CL84)),0) | CT84: =CR84-CS84 | CU84: =MAX(0,MIN(CP84-CQ84-CR84,CF84*(1+M84))) | CV84: =MAX(0,-CP84) | CW84: =MIN(CV84,MAX(0,CM84)) | CX84: =IF(BY84>0,MAX(0,1-BZ84/BY84),0) | CY84: =CQ84*CX84 | CZ84: =BY84*(1+M84-$B$19)-CQ84+(CV84-CW84) | DA84: =BZ84-(CQ84-CY84)+(CV84-CW84) | DB84: =CB84*(1+M84)-CD84-CS84-CK84+Z84+AB84 | DC84: =CC84*(1+M84)-CE84-CT84-CL84+AA84+AC84 | DD84: =CF84*(1+M84)-CU84+CW84 | DE84: =CD84+CK84+CS84 | DF84: =CA84*household!$B$15*$B$20*(1+tax_tables!$B$17) | DG84: =X84+BS84+BU84+BW84+DE84+DF84+CA84*household!$B$15*(1-$B$20)+(CY84+BO84)*household!$B$15*tax_tables!$B$18+(BP84+BM84+AK84)*household!$B$15-Z84 | DH84: =CE84+CL84+CT84 | DI84: =CA84*(1-household!$B$15)*$B$20*(1+tax_tables!$B$17) | DJ84: =Y84+BT84+BV84+BX84+DH84+DI84+CA84*(1-household!$B$15)*(1-$B$20)+(CY84+BO84)*(1-household!$B$15)*tax_tables!$B$18+(BP84+BM84+AK84)*(1-household!$B$15)-AA84 | DK84: =IF((DG84>=DJ84),MIN(0.5*(BW84+IF(B84>=65,DE84,0)),MAX(0,(DG84-DJ84)/2)),MIN(0.5*(BX84+IF(C84>=65,DH84,0)),MAX(0,(DJ84-DG84)/2))) | DL84: =DG84+IF((DG84>=DJ84),-DK84,DK84) | DM84: =BW84+IF(B84>=65,DE84,0)+IF((DG84>=DJ84),-DK84,DK84) | DN84: =MIN(BU84,tax_tables!$B$22*MAX(0,DL84-tax_tables!$B$21*P84)) | DO84: =MAX(0,DL84-DN84) | DP84: =DJ84+IF((DG84>=DJ84),DK84,-DK84) | DQ84: =BX84+IF(C84>=65,DH84,0)+IF((DG84>=DJ84),DK84,-DK84) | DR84: =MIN(BV84,tax_tables!$B$22*MAX(0,DP84-tax_tables!$B$21*P84)) | DS84: =MAX(0,DP84-DR84) | DT84: =BJ84-BD84 | DU84: =(tax_tables!$B$6-(tax_tables!$B$6-tax_tables!$B$7)*MIN(1,MAX(0,(DL84-tax_tables!$B$8*P84)/((tax_tables!$B$9-tax_tables!$B$8)*P84))))*P84+(B84>=65)*MAX(0,tax_tables!$B$10*P84-tax_tables!$B$12*MAX(0,DL84-tax_tables!$B$11*P84))+MIN(tax_tables!$B$13,DM84)+MIN(tax_tables!$B$14*P84,X84)+AF84+(DL84<=DP84)*MAX(0,DT84-MIN(0.03*DL84,tax_tables!$B$15*P84)) | DV84: =MAX(0,SUMPRODUCT((DO84>tax_tables!$E$5:$E$16*P84)*(DO84-tax_tables!$E$5:$E$16*P84)*tax_tables!$G$5:$G$16)-tax_tables!$B$5*DU84-tax_tables!$B$16*DF84) | DW84: =tax_tables!$B$35*Q84+(B84>=65)*MAX(0,tax_tables!$B$36*Q84-tax_tables!$B$12*MAX(0,DL84-tax_tables!$B$37*Q84))+MIN(tax_tables!$B$38,DM84)+AF84+(DL84<=DP84)*MAX(0,DT84-MIN(0.03*DL84,tax_tables!$B$39*Q84)) | DX84: =MAX(0,SUMPRODUCT((DO84>tax_tables!$I$5:$I$16*Q84)*(DO84-tax_tables!$I$5:$I$16*Q84)*tax_tables!$K$5:$K$16)-tax_tables!$B$34*DW84-tax_tables!$B$40*DF84-MAX(0,tax_tables!$B$41*Q84-tax_tables!$B$43*MAX(0,DL84-tax_tables!$B$42*Q84))) | DY84: =(tax_tables!$B$6-(tax_tables!$B$6-tax_tables!$B$7)*MIN(1,MAX(0,(DP84-tax_tables!$B$8*P84)/((tax_tables!$B$9-tax_tables!$B$8)*P84))))*P84+(C84>=65)*MAX(0,tax_tables!$B$10*P84-tax_tables!$B$12*MAX(0,DP84-tax_tables!$B$11*P84))+MIN(tax_tables!$B$13,DQ84)+MIN(tax_tables!$B$14*P84,Y84)+AG84+(DL84>DP84)*MAX(0,DT84-MIN(0.03*DP84,tax_tables!$B$15*P84)) | DZ84: =MAX(0,SUMPRODUCT((DS84>tax_tables!$E$5:$E$16*P84)*(DS84-tax_tables!$E$5:$E$16*P84)*tax_tables!$G$5:$G$16)-tax_tables!$B$5*DY84-tax_tables!$B$16*DI84) | EA84: =tax_tables!$B$35*Q84+(C84>=65)*MAX(0,tax_tables!$B$36*Q84-tax_tables!$B$12*MAX(0,DP84-tax_tables!$B$37*Q84))+MIN(tax_tables!$B$38,DQ84)+AG84+(DL84>DP84)*MAX(0,DT84-MIN(0.03*DP84,tax_tables!$B$39*Q84)) | EB84: =MAX(0,SUMPRODUCT((DS84>tax_tables!$I$5:$I$16*Q84)*(DS84-tax_tables!$I$5:$I$16*Q84)*tax_tables!$K$5:$K$16)-tax_tables!$B$34*EA84-tax_tables!$B$40*DI84-MAX(0,tax_tables!$B$41*Q84-tax_tables!$B$43*MAX(0,DP84-tax_tables!$B$42*Q84))) | EC84: =DV84+DZ84+DX84+EB84+DN84+DR84 | ED84: =CZ84+DB84+DC84+DD84 | EE84: =ED84+BQ84-AR84+BR84
A85: =A84+1 | B85: =A85-household!$B$6 | C85: =A85-household!$B$9 | D85: =AU85+AV85+AW85+AX85+BB85+BJ85+AM85 | E85: =CN85+AI85+AH85 | F85: =BS85+BT85+BU85+BV85 | G85: =CQ85+CR85+CU85+CD85+CE85+CA85-CV85+CJ85+CW85 | H85: =IF(BY85+CB85+CC85+CF85<=0,"",G85/(BY85+CB85+CC85+CF85)) | I85: =ED85/O85 | J85: =EE85/O85 | K85: =MAX(0,CP85-CQ85-CR85-CU85) | M85: =IF(L85="",$B$18,L85) | O85: =(1+$B$17)^(A85-household!$B$4+1) | P85: =(1+$B$17)^(A85-tax_tables!$B$4) | Q85: =(1+$B$17)^(A85-tax_tables!$B$4-MAX(0,MIN(A85,tax_tables!$B$45)-tax_tables!$B$44+1)) | R85: =(1+$B$21)^(A85-household!$B$4+1) | S85: =(1+$B$22)^(A85-household!$B$4+1) | T85: =(1+$B$23)^(A85-household!$B$4+1) | U85: =IF(A85<$B$5,1,0) | V85: =IF(A85<$B$6,1,0) | W85: =IF(U85+V85>0,1,0) | X85: =U85*$B$7*O85+SUMPRODUCT(($B$72:$B$77=A85)*($D$72:$D$77="Wages: person 1")*$C$72:$C$77)*O85 | Y85: =V85*$B$8*O85+SUMPRODUCT(($B$72:$B$77=A85)*($D$72:$D$77="Wages: person 2")*$C$72:$C$77)*O85 | Z85: =U85*$B$9*O85 | AA85: =V85*$B$10*O85 | AB85: =U85*$B$11*O85 | AC85: =V85*$B$12*O85 | AD85: =X85+Y85 | AE85: =AD85-Z85-AA85 | AF85: =tax_tables!$B$25*MAX(0,MIN(X85,tax_tables!$B$27*P85)-tax_tables!$B$26)+tax_tables!$B$28*MAX(0,MIN(X85,tax_tables!$B$29*P85)-tax_tables!$B$27*P85)+tax_tables!$B$30*MIN(X85,tax_tables!$B$31*P85) | AG85: =tax_tables!$B$25*MAX(0,MIN(Y85,tax_tables!$B$27*P85)-tax_tables!$B$26)+tax_tables!$B$28*MAX(0,MIN(Y85,tax_tables!$B$29*P85)-tax_tables!$B$27*P85)+tax_tables!$B$30*MIN(Y85,tax_tables!$B$31*P85) | AH85: =AF85+AG85 | AI85: =$B$13*AE85 | AJ85: =AD85-Z85-AA85-AH85-AI85 | AK85: =SUMPRODUCT(($B$72:$B$77=A85)*($D$72:$D$77="Other taxable income")*$C$72:$C$77)*O85 | AL85: =SUMPRODUCT(($B$72:$B$77=A85)*($D$72:$D$77="Tax-free money in")*$C$72:$C$77)*O85 | AM85: =SUMPRODUCT(($B$72:$B$77=A85)*($D$72:$D$77="Expense")*$C$72:$C$77)*O85 | AN85: =IF(OR($B$64="",A85<$B$64),1,0) | AO85: =AR84 | AP85: =AN85*AO85*properties!$J$2 | AQ85: =AN85*MIN(properties!$K$2,AO85+AP85) | AR85: =AN85*(AO85+AP85-AQ85) | AS85: =AN85*properties!$G$2*O85 | AT85: =(1-AN85)*$E$64*O85 | AU85: =AQ85+AS85+AT85 | AV85: =SUMIF(budget!$A$2:$A$300,"household",budget!$F$2:$F$300)*O85*IF(N85="",1,N85) | AW85: =SUMPRODUCT((other_budget!$C$2:$C$30<=A85)*(other_budget!$D$2:$D$30>=A85)*other_budget!$B$2:$B$30)*O85 | AX85: =SUMPRODUCT((kids_budget!$D$2:$D$40<=A85)*(kids_budget!$E$2:$E$40>=A85)*(kids_budget!$G$2:$G$40<>"college_funds")*kids_budget!$C$2:$C$40*((kids_budget!$F$2:$F$40="college")*S85+(kids_budget!$F$2:$F$40<>"college")*O85)) | AY85: =SUMPRODUCT((kids_budget!$D$2:$D$40<=A85)*(kids_budget!$E$2:$E$40>=A85)*(kids_budget!$G$2:$G$40="college_funds")*kids_budget!$C$2:$C$40*((kids_budget!$F$2:$F$40="college")*S85+(kids_budget!$F$2:$F$40<>"college")*O85)) | AZ85: =BC84 | BA85: =MIN(AY85,AZ85*(1+M85)) | BB85: =AY85-BA85 | BC85: =AZ85*(1+M85)-BA85 | BD85: =W85*healthcare!$B$2*R85 | BE85: =(1-W85)*2 | BF85: =BE85*healthcare!$B$3*12*R85 | BG85: =BE85*healthcare!$B$4*R85 | BH85: =AND(B85>=$B$44,B85<$B$44+$B$45)*1+AND(C85>=$B$46,C85<$B$46+$B$47)*1 | BI85: =BH85*$B$48*T85 | BJ85: =BD85+BF85+BG85+BI85 | BK85: =SUMPRODUCT((1-($B$65:$B$68>0)*(A85>=$B$65:$B$68))*(1-(($C$65:$C$68>0)*(A85>=$C$65:$C$68)))*(properties!$L$3:$L$6-properties!$M$3:$M$6))*O85+SUMPRODUCT((1-($B$65:$B$68>0)*(A85>=$B$65:$B$68))*(($C$65:$C$68>0)*(A85>=$C$65:$C$68))*($D$65:$D$68-$E$65:$E$68))*O85 | BL85: =SUMPRODUCT((1-($B$65:$B$68>0)*(A85>=$B$65:$B$68))*properties!$N$3:$N$6*(A85<=properties!$O$3:$O$6)) | BM85: =MAX(0,BK85-BL85) | BN85: =SUMPRODUCT(($B$64:$B$68=A85)*$G$64:$G$68) | BO85: =SUMPRODUCT(($B$64:$B$68=A85)*$H$64:$H$68) | BP85: =SUMPRODUCT(($B$64:$B$68=A85)*$I$64:$I$68) | BQ85: =AN85*properties!$C$2*(1+properties!$D$2)^(A85-household!$B$4+1) | BR85: =SUMPRODUCT((1-($B$65:$B$68>0)*(A85>=$B$65:$B$68))*properties!$C$3:$C$6*(1+properties!$D$3:$D$6)^(A85-household!$B$4+1)) | BS85: =IF(A85>=household!$B$6+$B$26,household!$B$11*12*$B$30*O85,0) | BT85: =IF(A85>=household!$B$9+$B$27,household!$B$12*12*$B$31*O85,0) | BU85: =IF(A85>=household!$B$6+$B$28,tax_tables!$B$19*12*P85*MIN(1,household!$B$13/40)*$B$32*(1+tax_tables!$B$20*(B85>=75)),0) | BV85: =IF(A85>=household!$B$9+$B$29,tax_tables!$B$19*12*P85*MIN(1,household!$B$14/40)*$B$33*(1+tax_tables!$B$20*(C85>=75)),0) | BW85: =IF(AND($B$36<>0,A85>=household!$B$6+$B$37),$B$36*(1+$B$17)^(MAX(household!$B$6+$B$37,household!$B$4-1)-household!$B$4+1)*(1+$B$40*$B$17)^(A85-MAX(household!$B$6+$B$37,household!$B$4-1)),0) | BX85: =IF(AND($B$38<>0,A85>=household!$B$9+$B$39),$B$38*(1+$B$17)^(MAX(household!$B$9+$B$39,household!$B$4-1)-household!$B$4+1)*(1+$B$40*$B$17)^(A85-MAX(household!$B$9+$B$39,household!$B$4-1)),0) | BY85: =CZ84 | BZ85: =DA84 | CA85: =$B$19*BY85 | CB85: =DB84 | CC85: =DC84 | CD85: =IF(B85>=tax_tables!$B$46,MAX(0,CB85)*INDEX(tax_tables!$N$5:$N$54,MATCH(MIN(B85-1,120),tax_tables!$M$5:$M$54,0)),0) | CE85: =IF(C85>=tax_tables!$B$46,MAX(0,CC85)*INDEX(tax_tables!$N$5:$N$54,MATCH(MIN(C85-1,120),tax_tables!$M$5:$M$54,0)),0) | CF85: =DD84 | CG85: =IF(OR($B$52="",$B$53=""),0,IF(AND(A85>=$B$52,A85<=$B$53),$B$51*O85,0)) | CH85: =MAX(0,CB85*(1+M85)-CD85) | CI85: =MAX(0,CC85*(1+M85)-CE85) | CJ85: =MIN(CG85,CH85+CI85) | CK85: =IF(CH85+CI85>1,CJ85*CH85/(CH85+CI85),0) | CL85: =CJ85-CK85 | CM85: =CM84-CW84+CU84+tax_tables!$B$32*P85*2 | CN85: =EC84-AI84 | CO85: =AJ85+F85+BW85+BX85+BK85+CA85+CD85+CE85+BN85+AK85+AL85+CJ85 | CP85: =D85+CN85-CO85 | CQ85: =MAX(0,MIN(CP85,BY85*(1+M85-$B$19))) | CR85: =MAX(0,MIN(CP85-CQ85,(CH85-CK85)+(CI85-CL85))) | CS85: =IF((CH85-CK85)+(CI85-CL85)>1,CR85*(CH85-CK85)/((CH85-CK85)+(CI85-CL85)),0) | CT85: =CR85-CS85 | CU85: =MAX(0,MIN(CP85-CQ85-CR85,CF85*(1+M85))) | CV85: =MAX(0,-CP85) | CW85: =MIN(CV85,MAX(0,CM85)) | CX85: =IF(BY85>0,MAX(0,1-BZ85/BY85),0) | CY85: =CQ85*CX85 | CZ85: =BY85*(1+M85-$B$19)-CQ85+(CV85-CW85) | DA85: =BZ85-(CQ85-CY85)+(CV85-CW85) | DB85: =CB85*(1+M85)-CD85-CS85-CK85+Z85+AB85 | DC85: =CC85*(1+M85)-CE85-CT85-CL85+AA85+AC85 | DD85: =CF85*(1+M85)-CU85+CW85 | DE85: =CD85+CK85+CS85 | DF85: =CA85*household!$B$15*$B$20*(1+tax_tables!$B$17) | DG85: =X85+BS85+BU85+BW85+DE85+DF85+CA85*household!$B$15*(1-$B$20)+(CY85+BO85)*household!$B$15*tax_tables!$B$18+(BP85+BM85+AK85)*household!$B$15-Z85 | DH85: =CE85+CL85+CT85 | DI85: =CA85*(1-household!$B$15)*$B$20*(1+tax_tables!$B$17) | DJ85: =Y85+BT85+BV85+BX85+DH85+DI85+CA85*(1-household!$B$15)*(1-$B$20)+(CY85+BO85)*(1-household!$B$15)*tax_tables!$B$18+(BP85+BM85+AK85)*(1-household!$B$15)-AA85 | DK85: =IF((DG85>=DJ85),MIN(0.5*(BW85+IF(B85>=65,DE85,0)),MAX(0,(DG85-DJ85)/2)),MIN(0.5*(BX85+IF(C85>=65,DH85,0)),MAX(0,(DJ85-DG85)/2))) | DL85: =DG85+IF((DG85>=DJ85),-DK85,DK85) | DM85: =BW85+IF(B85>=65,DE85,0)+IF((DG85>=DJ85),-DK85,DK85) | DN85: =MIN(BU85,tax_tables!$B$22*MAX(0,DL85-tax_tables!$B$21*P85)) | DO85: =MAX(0,DL85-DN85) | DP85: =DJ85+IF((DG85>=DJ85),DK85,-DK85) | DQ85: =BX85+IF(C85>=65,DH85,0)+IF((DG85>=DJ85),DK85,-DK85) | DR85: =MIN(BV85,tax_tables!$B$22*MAX(0,DP85-tax_tables!$B$21*P85)) | DS85: =MAX(0,DP85-DR85) | DT85: =BJ85-BD85 | DU85: =(tax_tables!$B$6-(tax_tables!$B$6-tax_tables!$B$7)*MIN(1,MAX(0,(DL85-tax_tables!$B$8*P85)/((tax_tables!$B$9-tax_tables!$B$8)*P85))))*P85+(B85>=65)*MAX(0,tax_tables!$B$10*P85-tax_tables!$B$12*MAX(0,DL85-tax_tables!$B$11*P85))+MIN(tax_tables!$B$13,DM85)+MIN(tax_tables!$B$14*P85,X85)+AF85+(DL85<=DP85)*MAX(0,DT85-MIN(0.03*DL85,tax_tables!$B$15*P85)) | DV85: =MAX(0,SUMPRODUCT((DO85>tax_tables!$E$5:$E$16*P85)*(DO85-tax_tables!$E$5:$E$16*P85)*tax_tables!$G$5:$G$16)-tax_tables!$B$5*DU85-tax_tables!$B$16*DF85) | DW85: =tax_tables!$B$35*Q85+(B85>=65)*MAX(0,tax_tables!$B$36*Q85-tax_tables!$B$12*MAX(0,DL85-tax_tables!$B$37*Q85))+MIN(tax_tables!$B$38,DM85)+AF85+(DL85<=DP85)*MAX(0,DT85-MIN(0.03*DL85,tax_tables!$B$39*Q85)) | DX85: =MAX(0,SUMPRODUCT((DO85>tax_tables!$I$5:$I$16*Q85)*(DO85-tax_tables!$I$5:$I$16*Q85)*tax_tables!$K$5:$K$16)-tax_tables!$B$34*DW85-tax_tables!$B$40*DF85-MAX(0,tax_tables!$B$41*Q85-tax_tables!$B$43*MAX(0,DL85-tax_tables!$B$42*Q85))) | DY85: =(tax_tables!$B$6-(tax_tables!$B$6-tax_tables!$B$7)*MIN(1,MAX(0,(DP85-tax_tables!$B$8*P85)/((tax_tables!$B$9-tax_tables!$B$8)*P85))))*P85+(C85>=65)*MAX(0,tax_tables!$B$10*P85-tax_tables!$B$12*MAX(0,DP85-tax_tables!$B$11*P85))+MIN(tax_tables!$B$13,DQ85)+MIN(tax_tables!$B$14*P85,Y85)+AG85+(DL85>DP85)*MAX(0,DT85-MIN(0.03*DP85,tax_tables!$B$15*P85)) | DZ85: =MAX(0,SUMPRODUCT((DS85>tax_tables!$E$5:$E$16*P85)*(DS85-tax_tables!$E$5:$E$16*P85)*tax_tables!$G$5:$G$16)-tax_tables!$B$5*DY85-tax_tables!$B$16*DI85) | EA85: =tax_tables!$B$35*Q85+(C85>=65)*MAX(0,tax_tables!$B$36*Q85-tax_tables!$B$12*MAX(0,DP85-tax_tables!$B$37*Q85))+MIN(tax_tables!$B$38,DQ85)+AG85+(DL85>DP85)*MAX(0,DT85-MIN(0.03*DP85,tax_tables!$B$39*Q85)) | EB85: =MAX(0,SUMPRODUCT((DS85>tax_tables!$I$5:$I$16*Q85)*(DS85-tax_tables!$I$5:$I$16*Q85)*tax_tables!$K$5:$K$16)-tax_tables!$B$34*EA85-tax_tables!$B$40*DI85-MAX(0,tax_tables!$B$41*Q85-tax_tables!$B$43*MAX(0,DP85-tax_tables!$B$42*Q85))) | EC85: =DV85+DZ85+DX85+EB85+DN85+DR85 | ED85: =CZ85+DB85+DC85+DD85 | EE85: =ED85+BQ85-AR85+BR85
A86: =A85+1 | B86: =A86-household!$B$6 | C86: =A86-household!$B$9 | D86: =AU86+AV86+AW86+AX86+BB86+BJ86+AM86 | E86: =CN86+AI86+AH86 | F86: =BS86+BT86+BU86+BV86 | G86: =CQ86+CR86+CU86+CD86+CE86+CA86-CV86+CJ86+CW86 | H86: =IF(BY86+CB86+CC86+CF86<=0,"",G86/(BY86+CB86+CC86+CF86)) | I86: =ED86/O86 | J86: =EE86/O86 | K86: =MAX(0,CP86-CQ86-CR86-CU86) | M86: =IF(L86="",$B$18,L86) | O86: =(1+$B$17)^(A86-household!$B$4+1) | P86: =(1+$B$17)^(A86-tax_tables!$B$4) | Q86: =(1+$B$17)^(A86-tax_tables!$B$4-MAX(0,MIN(A86,tax_tables!$B$45)-tax_tables!$B$44+1)) | R86: =(1+$B$21)^(A86-household!$B$4+1) | S86: =(1+$B$22)^(A86-household!$B$4+1) | T86: =(1+$B$23)^(A86-household!$B$4+1) | U86: =IF(A86<$B$5,1,0) | V86: =IF(A86<$B$6,1,0) | W86: =IF(U86+V86>0,1,0) | X86: =U86*$B$7*O86+SUMPRODUCT(($B$72:$B$77=A86)*($D$72:$D$77="Wages: person 1")*$C$72:$C$77)*O86 | Y86: =V86*$B$8*O86+SUMPRODUCT(($B$72:$B$77=A86)*($D$72:$D$77="Wages: person 2")*$C$72:$C$77)*O86 | Z86: =U86*$B$9*O86 | AA86: =V86*$B$10*O86 | AB86: =U86*$B$11*O86 | AC86: =V86*$B$12*O86 | AD86: =X86+Y86 | AE86: =AD86-Z86-AA86 | AF86: =tax_tables!$B$25*MAX(0,MIN(X86,tax_tables!$B$27*P86)-tax_tables!$B$26)+tax_tables!$B$28*MAX(0,MIN(X86,tax_tables!$B$29*P86)-tax_tables!$B$27*P86)+tax_tables!$B$30*MIN(X86,tax_tables!$B$31*P86) | AG86: =tax_tables!$B$25*MAX(0,MIN(Y86,tax_tables!$B$27*P86)-tax_tables!$B$26)+tax_tables!$B$28*MAX(0,MIN(Y86,tax_tables!$B$29*P86)-tax_tables!$B$27*P86)+tax_tables!$B$30*MIN(Y86,tax_tables!$B$31*P86) | AH86: =AF86+AG86 | AI86: =$B$13*AE86 | AJ86: =AD86-Z86-AA86-AH86-AI86 | AK86: =SUMPRODUCT(($B$72:$B$77=A86)*($D$72:$D$77="Other taxable income")*$C$72:$C$77)*O86 | AL86: =SUMPRODUCT(($B$72:$B$77=A86)*($D$72:$D$77="Tax-free money in")*$C$72:$C$77)*O86 | AM86: =SUMPRODUCT(($B$72:$B$77=A86)*($D$72:$D$77="Expense")*$C$72:$C$77)*O86 | AN86: =IF(OR($B$64="",A86<$B$64),1,0) | AO86: =AR85 | AP86: =AN86*AO86*properties!$J$2 | AQ86: =AN86*MIN(properties!$K$2,AO86+AP86) | AR86: =AN86*(AO86+AP86-AQ86) | AS86: =AN86*properties!$G$2*O86 | AT86: =(1-AN86)*$E$64*O86 | AU86: =AQ86+AS86+AT86 | AV86: =SUMIF(budget!$A$2:$A$300,"household",budget!$F$2:$F$300)*O86*IF(N86="",1,N86) | AW86: =SUMPRODUCT((other_budget!$C$2:$C$30<=A86)*(other_budget!$D$2:$D$30>=A86)*other_budget!$B$2:$B$30)*O86 | AX86: =SUMPRODUCT((kids_budget!$D$2:$D$40<=A86)*(kids_budget!$E$2:$E$40>=A86)*(kids_budget!$G$2:$G$40<>"college_funds")*kids_budget!$C$2:$C$40*((kids_budget!$F$2:$F$40="college")*S86+(kids_budget!$F$2:$F$40<>"college")*O86)) | AY86: =SUMPRODUCT((kids_budget!$D$2:$D$40<=A86)*(kids_budget!$E$2:$E$40>=A86)*(kids_budget!$G$2:$G$40="college_funds")*kids_budget!$C$2:$C$40*((kids_budget!$F$2:$F$40="college")*S86+(kids_budget!$F$2:$F$40<>"college")*O86)) | AZ86: =BC85 | BA86: =MIN(AY86,AZ86*(1+M86)) | BB86: =AY86-BA86 | BC86: =AZ86*(1+M86)-BA86 | BD86: =W86*healthcare!$B$2*R86 | BE86: =(1-W86)*2 | BF86: =BE86*healthcare!$B$3*12*R86 | BG86: =BE86*healthcare!$B$4*R86 | BH86: =AND(B86>=$B$44,B86<$B$44+$B$45)*1+AND(C86>=$B$46,C86<$B$46+$B$47)*1 | BI86: =BH86*$B$48*T86 | BJ86: =BD86+BF86+BG86+BI86 | BK86: =SUMPRODUCT((1-($B$65:$B$68>0)*(A86>=$B$65:$B$68))*(1-(($C$65:$C$68>0)*(A86>=$C$65:$C$68)))*(properties!$L$3:$L$6-properties!$M$3:$M$6))*O86+SUMPRODUCT((1-($B$65:$B$68>0)*(A86>=$B$65:$B$68))*(($C$65:$C$68>0)*(A86>=$C$65:$C$68))*($D$65:$D$68-$E$65:$E$68))*O86 | BL86: =SUMPRODUCT((1-($B$65:$B$68>0)*(A86>=$B$65:$B$68))*properties!$N$3:$N$6*(A86<=properties!$O$3:$O$6)) | BM86: =MAX(0,BK86-BL86) | BN86: =SUMPRODUCT(($B$64:$B$68=A86)*$G$64:$G$68) | BO86: =SUMPRODUCT(($B$64:$B$68=A86)*$H$64:$H$68) | BP86: =SUMPRODUCT(($B$64:$B$68=A86)*$I$64:$I$68) | BQ86: =AN86*properties!$C$2*(1+properties!$D$2)^(A86-household!$B$4+1) | BR86: =SUMPRODUCT((1-($B$65:$B$68>0)*(A86>=$B$65:$B$68))*properties!$C$3:$C$6*(1+properties!$D$3:$D$6)^(A86-household!$B$4+1)) | BS86: =IF(A86>=household!$B$6+$B$26,household!$B$11*12*$B$30*O86,0) | BT86: =IF(A86>=household!$B$9+$B$27,household!$B$12*12*$B$31*O86,0) | BU86: =IF(A86>=household!$B$6+$B$28,tax_tables!$B$19*12*P86*MIN(1,household!$B$13/40)*$B$32*(1+tax_tables!$B$20*(B86>=75)),0) | BV86: =IF(A86>=household!$B$9+$B$29,tax_tables!$B$19*12*P86*MIN(1,household!$B$14/40)*$B$33*(1+tax_tables!$B$20*(C86>=75)),0) | BW86: =IF(AND($B$36<>0,A86>=household!$B$6+$B$37),$B$36*(1+$B$17)^(MAX(household!$B$6+$B$37,household!$B$4-1)-household!$B$4+1)*(1+$B$40*$B$17)^(A86-MAX(household!$B$6+$B$37,household!$B$4-1)),0) | BX86: =IF(AND($B$38<>0,A86>=household!$B$9+$B$39),$B$38*(1+$B$17)^(MAX(household!$B$9+$B$39,household!$B$4-1)-household!$B$4+1)*(1+$B$40*$B$17)^(A86-MAX(household!$B$9+$B$39,household!$B$4-1)),0) | BY86: =CZ85 | BZ86: =DA85 | CA86: =$B$19*BY86 | CB86: =DB85 | CC86: =DC85 | CD86: =IF(B86>=tax_tables!$B$46,MAX(0,CB86)*INDEX(tax_tables!$N$5:$N$54,MATCH(MIN(B86-1,120),tax_tables!$M$5:$M$54,0)),0) | CE86: =IF(C86>=tax_tables!$B$46,MAX(0,CC86)*INDEX(tax_tables!$N$5:$N$54,MATCH(MIN(C86-1,120),tax_tables!$M$5:$M$54,0)),0) | CF86: =DD85 | CG86: =IF(OR($B$52="",$B$53=""),0,IF(AND(A86>=$B$52,A86<=$B$53),$B$51*O86,0)) | CH86: =MAX(0,CB86*(1+M86)-CD86) | CI86: =MAX(0,CC86*(1+M86)-CE86) | CJ86: =MIN(CG86,CH86+CI86) | CK86: =IF(CH86+CI86>1,CJ86*CH86/(CH86+CI86),0) | CL86: =CJ86-CK86 | CM86: =CM85-CW85+CU85+tax_tables!$B$32*P86*2 | CN86: =EC85-AI85 | CO86: =AJ86+F86+BW86+BX86+BK86+CA86+CD86+CE86+BN86+AK86+AL86+CJ86 | CP86: =D86+CN86-CO86 | CQ86: =MAX(0,MIN(CP86,BY86*(1+M86-$B$19))) | CR86: =MAX(0,MIN(CP86-CQ86,(CH86-CK86)+(CI86-CL86))) | CS86: =IF((CH86-CK86)+(CI86-CL86)>1,CR86*(CH86-CK86)/((CH86-CK86)+(CI86-CL86)),0) | CT86: =CR86-CS86 | CU86: =MAX(0,MIN(CP86-CQ86-CR86,CF86*(1+M86))) | CV86: =MAX(0,-CP86) | CW86: =MIN(CV86,MAX(0,CM86)) | CX86: =IF(BY86>0,MAX(0,1-BZ86/BY86),0) | CY86: =CQ86*CX86 | CZ86: =BY86*(1+M86-$B$19)-CQ86+(CV86-CW86) | DA86: =BZ86-(CQ86-CY86)+(CV86-CW86) | DB86: =CB86*(1+M86)-CD86-CS86-CK86+Z86+AB86 | DC86: =CC86*(1+M86)-CE86-CT86-CL86+AA86+AC86 | DD86: =CF86*(1+M86)-CU86+CW86 | DE86: =CD86+CK86+CS86 | DF86: =CA86*household!$B$15*$B$20*(1+tax_tables!$B$17) | DG86: =X86+BS86+BU86+BW86+DE86+DF86+CA86*household!$B$15*(1-$B$20)+(CY86+BO86)*household!$B$15*tax_tables!$B$18+(BP86+BM86+AK86)*household!$B$15-Z86 | DH86: =CE86+CL86+CT86 | DI86: =CA86*(1-household!$B$15)*$B$20*(1+tax_tables!$B$17) | DJ86: =Y86+BT86+BV86+BX86+DH86+DI86+CA86*(1-household!$B$15)*(1-$B$20)+(CY86+BO86)*(1-household!$B$15)*tax_tables!$B$18+(BP86+BM86+AK86)*(1-household!$B$15)-AA86 | DK86: =IF((DG86>=DJ86),MIN(0.5*(BW86+IF(B86>=65,DE86,0)),MAX(0,(DG86-DJ86)/2)),MIN(0.5*(BX86+IF(C86>=65,DH86,0)),MAX(0,(DJ86-DG86)/2))) | DL86: =DG86+IF((DG86>=DJ86),-DK86,DK86) | DM86: =BW86+IF(B86>=65,DE86,0)+IF((DG86>=DJ86),-DK86,DK86) | DN86: =MIN(BU86,tax_tables!$B$22*MAX(0,DL86-tax_tables!$B$21*P86)) | DO86: =MAX(0,DL86-DN86) | DP86: =DJ86+IF((DG86>=DJ86),DK86,-DK86) | DQ86: =BX86+IF(C86>=65,DH86,0)+IF((DG86>=DJ86),DK86,-DK86) | DR86: =MIN(BV86,tax_tables!$B$22*MAX(0,DP86-tax_tables!$B$21*P86)) | DS86: =MAX(0,DP86-DR86) | DT86: =BJ86-BD86 | DU86: =(tax_tables!$B$6-(tax_tables!$B$6-tax_tables!$B$7)*MIN(1,MAX(0,(DL86-tax_tables!$B$8*P86)/((tax_tables!$B$9-tax_tables!$B$8)*P86))))*P86+(B86>=65)*MAX(0,tax_tables!$B$10*P86-tax_tables!$B$12*MAX(0,DL86-tax_tables!$B$11*P86))+MIN(tax_tables!$B$13,DM86)+MIN(tax_tables!$B$14*P86,X86)+AF86+(DL86<=DP86)*MAX(0,DT86-MIN(0.03*DL86,tax_tables!$B$15*P86)) | DV86: =MAX(0,SUMPRODUCT((DO86>tax_tables!$E$5:$E$16*P86)*(DO86-tax_tables!$E$5:$E$16*P86)*tax_tables!$G$5:$G$16)-tax_tables!$B$5*DU86-tax_tables!$B$16*DF86) | DW86: =tax_tables!$B$35*Q86+(B86>=65)*MAX(0,tax_tables!$B$36*Q86-tax_tables!$B$12*MAX(0,DL86-tax_tables!$B$37*Q86))+MIN(tax_tables!$B$38,DM86)+AF86+(DL86<=DP86)*MAX(0,DT86-MIN(0.03*DL86,tax_tables!$B$39*Q86)) | DX86: =MAX(0,SUMPRODUCT((DO86>tax_tables!$I$5:$I$16*Q86)*(DO86-tax_tables!$I$5:$I$16*Q86)*tax_tables!$K$5:$K$16)-tax_tables!$B$34*DW86-tax_tables!$B$40*DF86-MAX(0,tax_tables!$B$41*Q86-tax_tables!$B$43*MAX(0,DL86-tax_tables!$B$42*Q86))) | DY86: =(tax_tables!$B$6-(tax_tables!$B$6-tax_tables!$B$7)*MIN(1,MAX(0,(DP86-tax_tables!$B$8*P86)/((tax_tables!$B$9-tax_tables!$B$8)*P86))))*P86+(C86>=65)*MAX(0,tax_tables!$B$10*P86-tax_tables!$B$12*MAX(0,DP86-tax_tables!$B$11*P86))+MIN(tax_tables!$B$13,DQ86)+MIN(tax_tables!$B$14*P86,Y86)+AG86+(DL86>DP86)*MAX(0,DT86-MIN(0.03*DP86,tax_tables!$B$15*P86)) | DZ86: =MAX(0,SUMPRODUCT((DS86>tax_tables!$E$5:$E$16*P86)*(DS86-tax_tables!$E$5:$E$16*P86)*tax_tables!$G$5:$G$16)-tax_tables!$B$5*DY86-tax_tables!$B$16*DI86) | EA86: =tax_tables!$B$35*Q86+(C86>=65)*MAX(0,tax_tables!$B$36*Q86-tax_tables!$B$12*MAX(0,DP86-tax_tables!$B$37*Q86))+MIN(tax_tables!$B$38,DQ86)+AG86+(DL86>DP86)*MAX(0,DT86-MIN(0.03*DP86,tax_tables!$B$39*Q86)) | EB86: =MAX(0,SUMPRODUCT((DS86>tax_tables!$I$5:$I$16*Q86)*(DS86-tax_tables!$I$5:$I$16*Q86)*tax_tables!$K$5:$K$16)-tax_tables!$B$34*EA86-tax_tables!$B$40*DI86-MAX(0,tax_tables!$B$41*Q86-tax_tables!$B$43*MAX(0,DP86-tax_tables!$B$42*Q86))) | EC86: =DV86+DZ86+DX86+EB86+DN86+DR86 | ED86: =CZ86+DB86+DC86+DD86 | EE86: =ED86+BQ86-AR86+BR86
A87: =A86+1 | B87: =A87-household!$B$6 | C87: =A87-household!$B$9 | D87: =AU87+AV87+AW87+AX87+BB87+BJ87+AM87 | E87: =CN87+AI87+AH87 | F87: =BS87+BT87+BU87+BV87 | G87: =CQ87+CR87+CU87+CD87+CE87+CA87-CV87+CJ87+CW87 | H87: =IF(BY87+CB87+CC87+CF87<=0,"",G87/(BY87+CB87+CC87+CF87)) | I87: =ED87/O87 | J87: =EE87/O87 | K87: =MAX(0,CP87-CQ87-CR87-CU87) | M87: =IF(L87="",$B$18,L87) | O87: =(1+$B$17)^(A87-household!$B$4+1) | P87: =(1+$B$17)^(A87-tax_tables!$B$4) | Q87: =(1+$B$17)^(A87-tax_tables!$B$4-MAX(0,MIN(A87,tax_tables!$B$45)-tax_tables!$B$44+1)) | R87: =(1+$B$21)^(A87-household!$B$4+1) | S87: =(1+$B$22)^(A87-household!$B$4+1) | T87: =(1+$B$23)^(A87-household!$B$4+1) | U87: =IF(A87<$B$5,1,0) | V87: =IF(A87<$B$6,1,0) | W87: =IF(U87+V87>0,1,0) | X87: =U87*$B$7*O87+SUMPRODUCT(($B$72:$B$77=A87)*($D$72:$D$77="Wages: person 1")*$C$72:$C$77)*O87 | Y87: =V87*$B$8*O87+SUMPRODUCT(($B$72:$B$77=A87)*($D$72:$D$77="Wages: person 2")*$C$72:$C$77)*O87 | Z87: =U87*$B$9*O87 | AA87: =V87*$B$10*O87 | AB87: =U87*$B$11*O87 | AC87: =V87*$B$12*O87 | AD87: =X87+Y87 | AE87: =AD87-Z87-AA87 | AF87: =tax_tables!$B$25*MAX(0,MIN(X87,tax_tables!$B$27*P87)-tax_tables!$B$26)+tax_tables!$B$28*MAX(0,MIN(X87,tax_tables!$B$29*P87)-tax_tables!$B$27*P87)+tax_tables!$B$30*MIN(X87,tax_tables!$B$31*P87) | AG87: =tax_tables!$B$25*MAX(0,MIN(Y87,tax_tables!$B$27*P87)-tax_tables!$B$26)+tax_tables!$B$28*MAX(0,MIN(Y87,tax_tables!$B$29*P87)-tax_tables!$B$27*P87)+tax_tables!$B$30*MIN(Y87,tax_tables!$B$31*P87) | AH87: =AF87+AG87 | AI87: =$B$13*AE87 | AJ87: =AD87-Z87-AA87-AH87-AI87 | AK87: =SUMPRODUCT(($B$72:$B$77=A87)*($D$72:$D$77="Other taxable income")*$C$72:$C$77)*O87 | AL87: =SUMPRODUCT(($B$72:$B$77=A87)*($D$72:$D$77="Tax-free money in")*$C$72:$C$77)*O87 | AM87: =SUMPRODUCT(($B$72:$B$77=A87)*($D$72:$D$77="Expense")*$C$72:$C$77)*O87 | AN87: =IF(OR($B$64="",A87<$B$64),1,0) | AO87: =AR86 | AP87: =AN87*AO87*properties!$J$2 | AQ87: =AN87*MIN(properties!$K$2,AO87+AP87) | AR87: =AN87*(AO87+AP87-AQ87) | AS87: =AN87*properties!$G$2*O87 | AT87: =(1-AN87)*$E$64*O87 | AU87: =AQ87+AS87+AT87 | AV87: =SUMIF(budget!$A$2:$A$300,"household",budget!$F$2:$F$300)*O87*IF(N87="",1,N87) | AW87: =SUMPRODUCT((other_budget!$C$2:$C$30<=A87)*(other_budget!$D$2:$D$30>=A87)*other_budget!$B$2:$B$30)*O87 | AX87: =SUMPRODUCT((kids_budget!$D$2:$D$40<=A87)*(kids_budget!$E$2:$E$40>=A87)*(kids_budget!$G$2:$G$40<>"college_funds")*kids_budget!$C$2:$C$40*((kids_budget!$F$2:$F$40="college")*S87+(kids_budget!$F$2:$F$40<>"college")*O87)) | AY87: =SUMPRODUCT((kids_budget!$D$2:$D$40<=A87)*(kids_budget!$E$2:$E$40>=A87)*(kids_budget!$G$2:$G$40="college_funds")*kids_budget!$C$2:$C$40*((kids_budget!$F$2:$F$40="college")*S87+(kids_budget!$F$2:$F$40<>"college")*O87)) | AZ87: =BC86 | BA87: =MIN(AY87,AZ87*(1+M87)) | BB87: =AY87-BA87 | BC87: =AZ87*(1+M87)-BA87 | BD87: =W87*healthcare!$B$2*R87 | BE87: =(1-W87)*2 | BF87: =BE87*healthcare!$B$3*12*R87 | BG87: =BE87*healthcare!$B$4*R87 | BH87: =AND(B87>=$B$44,B87<$B$44+$B$45)*1+AND(C87>=$B$46,C87<$B$46+$B$47)*1 | BI87: =BH87*$B$48*T87 | BJ87: =BD87+BF87+BG87+BI87 | BK87: =SUMPRODUCT((1-($B$65:$B$68>0)*(A87>=$B$65:$B$68))*(1-(($C$65:$C$68>0)*(A87>=$C$65:$C$68)))*(properties!$L$3:$L$6-properties!$M$3:$M$6))*O87+SUMPRODUCT((1-($B$65:$B$68>0)*(A87>=$B$65:$B$68))*(($C$65:$C$68>0)*(A87>=$C$65:$C$68))*($D$65:$D$68-$E$65:$E$68))*O87 | BL87: =SUMPRODUCT((1-($B$65:$B$68>0)*(A87>=$B$65:$B$68))*properties!$N$3:$N$6*(A87<=properties!$O$3:$O$6)) | BM87: =MAX(0,BK87-BL87) | BN87: =SUMPRODUCT(($B$64:$B$68=A87)*$G$64:$G$68) | BO87: =SUMPRODUCT(($B$64:$B$68=A87)*$H$64:$H$68) | BP87: =SUMPRODUCT(($B$64:$B$68=A87)*$I$64:$I$68) | BQ87: =AN87*properties!$C$2*(1+properties!$D$2)^(A87-household!$B$4+1) | BR87: =SUMPRODUCT((1-($B$65:$B$68>0)*(A87>=$B$65:$B$68))*properties!$C$3:$C$6*(1+properties!$D$3:$D$6)^(A87-household!$B$4+1)) | BS87: =IF(A87>=household!$B$6+$B$26,household!$B$11*12*$B$30*O87,0) | BT87: =IF(A87>=household!$B$9+$B$27,household!$B$12*12*$B$31*O87,0) | BU87: =IF(A87>=household!$B$6+$B$28,tax_tables!$B$19*12*P87*MIN(1,household!$B$13/40)*$B$32*(1+tax_tables!$B$20*(B87>=75)),0) | BV87: =IF(A87>=household!$B$9+$B$29,tax_tables!$B$19*12*P87*MIN(1,household!$B$14/40)*$B$33*(1+tax_tables!$B$20*(C87>=75)),0) | BW87: =IF(AND($B$36<>0,A87>=household!$B$6+$B$37),$B$36*(1+$B$17)^(MAX(household!$B$6+$B$37,household!$B$4-1)-household!$B$4+1)*(1+$B$40*$B$17)^(A87-MAX(household!$B$6+$B$37,household!$B$4-1)),0) | BX87: =IF(AND($B$38<>0,A87>=household!$B$9+$B$39),$B$38*(1+$B$17)^(MAX(household!$B$9+$B$39,household!$B$4-1)-household!$B$4+1)*(1+$B$40*$B$17)^(A87-MAX(household!$B$9+$B$39,household!$B$4-1)),0) | BY87: =CZ86 | BZ87: =DA86 | CA87: =$B$19*BY87 | CB87: =DB86 | CC87: =DC86 | CD87: =IF(B87>=tax_tables!$B$46,MAX(0,CB87)*INDEX(tax_tables!$N$5:$N$54,MATCH(MIN(B87-1,120),tax_tables!$M$5:$M$54,0)),0) | CE87: =IF(C87>=tax_tables!$B$46,MAX(0,CC87)*INDEX(tax_tables!$N$5:$N$54,MATCH(MIN(C87-1,120),tax_tables!$M$5:$M$54,0)),0) | CF87: =DD86 | CG87: =IF(OR($B$52="",$B$53=""),0,IF(AND(A87>=$B$52,A87<=$B$53),$B$51*O87,0)) | CH87: =MAX(0,CB87*(1+M87)-CD87) | CI87: =MAX(0,CC87*(1+M87)-CE87) | CJ87: =MIN(CG87,CH87+CI87) | CK87: =IF(CH87+CI87>1,CJ87*CH87/(CH87+CI87),0) | CL87: =CJ87-CK87 | CM87: =CM86-CW86+CU86+tax_tables!$B$32*P87*2 | CN87: =EC86-AI86 | CO87: =AJ87+F87+BW87+BX87+BK87+CA87+CD87+CE87+BN87+AK87+AL87+CJ87 | CP87: =D87+CN87-CO87 | CQ87: =MAX(0,MIN(CP87,BY87*(1+M87-$B$19))) | CR87: =MAX(0,MIN(CP87-CQ87,(CH87-CK87)+(CI87-CL87))) | CS87: =IF((CH87-CK87)+(CI87-CL87)>1,CR87*(CH87-CK87)/((CH87-CK87)+(CI87-CL87)),0) | CT87: =CR87-CS87 | CU87: =MAX(0,MIN(CP87-CQ87-CR87,CF87*(1+M87))) | CV87: =MAX(0,-CP87) | CW87: =MIN(CV87,MAX(0,CM87)) | CX87: =IF(BY87>0,MAX(0,1-BZ87/BY87),0) | CY87: =CQ87*CX87 | CZ87: =BY87*(1+M87-$B$19)-CQ87+(CV87-CW87) | DA87: =BZ87-(CQ87-CY87)+(CV87-CW87) | DB87: =CB87*(1+M87)-CD87-CS87-CK87+Z87+AB87 | DC87: =CC87*(1+M87)-CE87-CT87-CL87+AA87+AC87 | DD87: =CF87*(1+M87)-CU87+CW87 | DE87: =CD87+CK87+CS87 | DF87: =CA87*household!$B$15*$B$20*(1+tax_tables!$B$17) | DG87: =X87+BS87+BU87+BW87+DE87+DF87+CA87*household!$B$15*(1-$B$20)+(CY87+BO87)*household!$B$15*tax_tables!$B$18+(BP87+BM87+AK87)*household!$B$15-Z87 | DH87: =CE87+CL87+CT87 | DI87: =CA87*(1-household!$B$15)*$B$20*(1+tax_tables!$B$17) | DJ87: =Y87+BT87+BV87+BX87+DH87+DI87+CA87*(1-household!$B$15)*(1-$B$20)+(CY87+BO87)*(1-household!$B$15)*tax_tables!$B$18+(BP87+BM87+AK87)*(1-household!$B$15)-AA87 | DK87: =IF((DG87>=DJ87),MIN(0.5*(BW87+IF(B87>=65,DE87,0)),MAX(0,(DG87-DJ87)/2)),MIN(0.5*(BX87+IF(C87>=65,DH87,0)),MAX(0,(DJ87-DG87)/2))) | DL87: =DG87+IF((DG87>=DJ87),-DK87,DK87) | DM87: =BW87+IF(B87>=65,DE87,0)+IF((DG87>=DJ87),-DK87,DK87) | DN87: =MIN(BU87,tax_tables!$B$22*MAX(0,DL87-tax_tables!$B$21*P87)) | DO87: =MAX(0,DL87-DN87) | DP87: =DJ87+IF((DG87>=DJ87),DK87,-DK87) | DQ87: =BX87+IF(C87>=65,DH87,0)+IF((DG87>=DJ87),DK87,-DK87) | DR87: =MIN(BV87,tax_tables!$B$22*MAX(0,DP87-tax_tables!$B$21*P87)) | DS87: =MAX(0,DP87-DR87) | DT87: =BJ87-BD87 | DU87: =(tax_tables!$B$6-(tax_tables!$B$6-tax_tables!$B$7)*MIN(1,MAX(0,(DL87-tax_tables!$B$8*P87)/((tax_tables!$B$9-tax_tables!$B$8)*P87))))*P87+(B87>=65)*MAX(0,tax_tables!$B$10*P87-tax_tables!$B$12*MAX(0,DL87-tax_tables!$B$11*P87))+MIN(tax_tables!$B$13,DM87)+MIN(tax_tables!$B$14*P87,X87)+AF87+(DL87<=DP87)*MAX(0,DT87-MIN(0.03*DL87,tax_tables!$B$15*P87)) | DV87: =MAX(0,SUMPRODUCT((DO87>tax_tables!$E$5:$E$16*P87)*(DO87-tax_tables!$E$5:$E$16*P87)*tax_tables!$G$5:$G$16)-tax_tables!$B$5*DU87-tax_tables!$B$16*DF87) | DW87: =tax_tables!$B$35*Q87+(B87>=65)*MAX(0,tax_tables!$B$36*Q87-tax_tables!$B$12*MAX(0,DL87-tax_tables!$B$37*Q87))+MIN(tax_tables!$B$38,DM87)+AF87+(DL87<=DP87)*MAX(0,DT87-MIN(0.03*DL87,tax_tables!$B$39*Q87)) | DX87: =MAX(0,SUMPRODUCT((DO87>tax_tables!$I$5:$I$16*Q87)*(DO87-tax_tables!$I$5:$I$16*Q87)*tax_tables!$K$5:$K$16)-tax_tables!$B$34*DW87-tax_tables!$B$40*DF87-MAX(0,tax_tables!$B$41*Q87-tax_tables!$B$43*MAX(0,DL87-tax_tables!$B$42*Q87))) | DY87: =(tax_tables!$B$6-(tax_tables!$B$6-tax_tables!$B$7)*MIN(1,MAX(0,(DP87-tax_tables!$B$8*P87)/((tax_tables!$B$9-tax_tables!$B$8)*P87))))*P87+(C87>=65)*MAX(0,tax_tables!$B$10*P87-tax_tables!$B$12*MAX(0,DP87-tax_tables!$B$11*P87))+MIN(tax_tables!$B$13,DQ87)+MIN(tax_tables!$B$14*P87,Y87)+AG87+(DL87>DP87)*MAX(0,DT87-MIN(0.03*DP87,tax_tables!$B$15*P87)) | DZ87: =MAX(0,SUMPRODUCT((DS87>tax_tables!$E$5:$E$16*P87)*(DS87-tax_tables!$E$5:$E$16*P87)*tax_tables!$G$5:$G$16)-tax_tables!$B$5*DY87-tax_tables!$B$16*DI87) | EA87: =tax_tables!$B$35*Q87+(C87>=65)*MAX(0,tax_tables!$B$36*Q87-tax_tables!$B$12*MAX(0,DP87-tax_tables!$B$37*Q87))+MIN(tax_tables!$B$38,DQ87)+AG87+(DL87>DP87)*MAX(0,DT87-MIN(0.03*DP87,tax_tables!$B$39*Q87)) | EB87: =MAX(0,SUMPRODUCT((DS87>tax_tables!$I$5:$I$16*Q87)*(DS87-tax_tables!$I$5:$I$16*Q87)*tax_tables!$K$5:$K$16)-tax_tables!$B$34*EA87-tax_tables!$B$40*DI87-MAX(0,tax_tables!$B$41*Q87-tax_tables!$B$43*MAX(0,DP87-tax_tables!$B$42*Q87))) | EC87: =DV87+DZ87+DX87+EB87+DN87+DR87 | ED87: =CZ87+DB87+DC87+DD87 | EE87: =ED87+BQ87-AR87+BR87
A88: =A87+1 | B88: =A88-household!$B$6 | C88: =A88-household!$B$9 | D88: =AU88+AV88+AW88+AX88+BB88+BJ88+AM88 | E88: =CN88+AI88+AH88 | F88: =BS88+BT88+BU88+BV88 | G88: =CQ88+CR88+CU88+CD88+CE88+CA88-CV88+CJ88+CW88 | H88: =IF(BY88+CB88+CC88+CF88<=0,"",G88/(BY88+CB88+CC88+CF88)) | I88: =ED88/O88 | J88: =EE88/O88 | K88: =MAX(0,CP88-CQ88-CR88-CU88) | M88: =IF(L88="",$B$18,L88) | O88: =(1+$B$17)^(A88-household!$B$4+1) | P88: =(1+$B$17)^(A88-tax_tables!$B$4) | Q88: =(1+$B$17)^(A88-tax_tables!$B$4-MAX(0,MIN(A88,tax_tables!$B$45)-tax_tables!$B$44+1)) | R88: =(1+$B$21)^(A88-household!$B$4+1) | S88: =(1+$B$22)^(A88-household!$B$4+1) | T88: =(1+$B$23)^(A88-household!$B$4+1) | U88: =IF(A88<$B$5,1,0) | V88: =IF(A88<$B$6,1,0) | W88: =IF(U88+V88>0,1,0) | X88: =U88*$B$7*O88+SUMPRODUCT(($B$72:$B$77=A88)*($D$72:$D$77="Wages: person 1")*$C$72:$C$77)*O88 | Y88: =V88*$B$8*O88+SUMPRODUCT(($B$72:$B$77=A88)*($D$72:$D$77="Wages: person 2")*$C$72:$C$77)*O88 | Z88: =U88*$B$9*O88 | AA88: =V88*$B$10*O88 | AB88: =U88*$B$11*O88 | AC88: =V88*$B$12*O88 | AD88: =X88+Y88 | AE88: =AD88-Z88-AA88 | AF88: =tax_tables!$B$25*MAX(0,MIN(X88,tax_tables!$B$27*P88)-tax_tables!$B$26)+tax_tables!$B$28*MAX(0,MIN(X88,tax_tables!$B$29*P88)-tax_tables!$B$27*P88)+tax_tables!$B$30*MIN(X88,tax_tables!$B$31*P88) | AG88: =tax_tables!$B$25*MAX(0,MIN(Y88,tax_tables!$B$27*P88)-tax_tables!$B$26)+tax_tables!$B$28*MAX(0,MIN(Y88,tax_tables!$B$29*P88)-tax_tables!$B$27*P88)+tax_tables!$B$30*MIN(Y88,tax_tables!$B$31*P88) | AH88: =AF88+AG88 | AI88: =$B$13*AE88 | AJ88: =AD88-Z88-AA88-AH88-AI88 | AK88: =SUMPRODUCT(($B$72:$B$77=A88)*($D$72:$D$77="Other taxable income")*$C$72:$C$77)*O88 | AL88: =SUMPRODUCT(($B$72:$B$77=A88)*($D$72:$D$77="Tax-free money in")*$C$72:$C$77)*O88 | AM88: =SUMPRODUCT(($B$72:$B$77=A88)*($D$72:$D$77="Expense")*$C$72:$C$77)*O88 | AN88: =IF(OR($B$64="",A88<$B$64),1,0) | AO88: =AR87 | AP88: =AN88*AO88*properties!$J$2 | AQ88: =AN88*MIN(properties!$K$2,AO88+AP88) | AR88: =AN88*(AO88+AP88-AQ88) | AS88: =AN88*properties!$G$2*O88 | AT88: =(1-AN88)*$E$64*O88 | AU88: =AQ88+AS88+AT88 | AV88: =SUMIF(budget!$A$2:$A$300,"household",budget!$F$2:$F$300)*O88*IF(N88="",1,N88) | AW88: =SUMPRODUCT((other_budget!$C$2:$C$30<=A88)*(other_budget!$D$2:$D$30>=A88)*other_budget!$B$2:$B$30)*O88 | AX88: =SUMPRODUCT((kids_budget!$D$2:$D$40<=A88)*(kids_budget!$E$2:$E$40>=A88)*(kids_budget!$G$2:$G$40<>"college_funds")*kids_budget!$C$2:$C$40*((kids_budget!$F$2:$F$40="college")*S88+(kids_budget!$F$2:$F$40<>"college")*O88)) | AY88: =SUMPRODUCT((kids_budget!$D$2:$D$40<=A88)*(kids_budget!$E$2:$E$40>=A88)*(kids_budget!$G$2:$G$40="college_funds")*kids_budget!$C$2:$C$40*((kids_budget!$F$2:$F$40="college")*S88+(kids_budget!$F$2:$F$40<>"college")*O88)) | AZ88: =BC87 | BA88: =MIN(AY88,AZ88*(1+M88)) | BB88: =AY88-BA88 | BC88: =AZ88*(1+M88)-BA88 | BD88: =W88*healthcare!$B$2*R88 | BE88: =(1-W88)*2 | BF88: =BE88*healthcare!$B$3*12*R88 | BG88: =BE88*healthcare!$B$4*R88 | BH88: =AND(B88>=$B$44,B88<$B$44+$B$45)*1+AND(C88>=$B$46,C88<$B$46+$B$47)*1 | BI88: =BH88*$B$48*T88 | BJ88: =BD88+BF88+BG88+BI88 | BK88: =SUMPRODUCT((1-($B$65:$B$68>0)*(A88>=$B$65:$B$68))*(1-(($C$65:$C$68>0)*(A88>=$C$65:$C$68)))*(properties!$L$3:$L$6-properties!$M$3:$M$6))*O88+SUMPRODUCT((1-($B$65:$B$68>0)*(A88>=$B$65:$B$68))*(($C$65:$C$68>0)*(A88>=$C$65:$C$68))*($D$65:$D$68-$E$65:$E$68))*O88 | BL88: =SUMPRODUCT((1-($B$65:$B$68>0)*(A88>=$B$65:$B$68))*properties!$N$3:$N$6*(A88<=properties!$O$3:$O$6)) | BM88: =MAX(0,BK88-BL88) | BN88: =SUMPRODUCT(($B$64:$B$68=A88)*$G$64:$G$68) | BO88: =SUMPRODUCT(($B$64:$B$68=A88)*$H$64:$H$68) | BP88: =SUMPRODUCT(($B$64:$B$68=A88)*$I$64:$I$68) | BQ88: =AN88*properties!$C$2*(1+properties!$D$2)^(A88-household!$B$4+1) | BR88: =SUMPRODUCT((1-($B$65:$B$68>0)*(A88>=$B$65:$B$68))*properties!$C$3:$C$6*(1+properties!$D$3:$D$6)^(A88-household!$B$4+1)) | BS88: =IF(A88>=household!$B$6+$B$26,household!$B$11*12*$B$30*O88,0) | BT88: =IF(A88>=household!$B$9+$B$27,household!$B$12*12*$B$31*O88,0) | BU88: =IF(A88>=household!$B$6+$B$28,tax_tables!$B$19*12*P88*MIN(1,household!$B$13/40)*$B$32*(1+tax_tables!$B$20*(B88>=75)),0) | BV88: =IF(A88>=household!$B$9+$B$29,tax_tables!$B$19*12*P88*MIN(1,household!$B$14/40)*$B$33*(1+tax_tables!$B$20*(C88>=75)),0) | BW88: =IF(AND($B$36<>0,A88>=household!$B$6+$B$37),$B$36*(1+$B$17)^(MAX(household!$B$6+$B$37,household!$B$4-1)-household!$B$4+1)*(1+$B$40*$B$17)^(A88-MAX(household!$B$6+$B$37,household!$B$4-1)),0) | BX88: =IF(AND($B$38<>0,A88>=household!$B$9+$B$39),$B$38*(1+$B$17)^(MAX(household!$B$9+$B$39,household!$B$4-1)-household!$B$4+1)*(1+$B$40*$B$17)^(A88-MAX(household!$B$9+$B$39,household!$B$4-1)),0) | BY88: =CZ87 | BZ88: =DA87 | CA88: =$B$19*BY88 | CB88: =DB87 | CC88: =DC87 | CD88: =IF(B88>=tax_tables!$B$46,MAX(0,CB88)*INDEX(tax_tables!$N$5:$N$54,MATCH(MIN(B88-1,120),tax_tables!$M$5:$M$54,0)),0) | CE88: =IF(C88>=tax_tables!$B$46,MAX(0,CC88)*INDEX(tax_tables!$N$5:$N$54,MATCH(MIN(C88-1,120),tax_tables!$M$5:$M$54,0)),0) | CF88: =DD87 | CG88: =IF(OR($B$52="",$B$53=""),0,IF(AND(A88>=$B$52,A88<=$B$53),$B$51*O88,0)) | CH88: =MAX(0,CB88*(1+M88)-CD88) | CI88: =MAX(0,CC88*(1+M88)-CE88) | CJ88: =MIN(CG88,CH88+CI88) | CK88: =IF(CH88+CI88>1,CJ88*CH88/(CH88+CI88),0) | CL88: =CJ88-CK88 | CM88: =CM87-CW87+CU87+tax_tables!$B$32*P88*2 | CN88: =EC87-AI87 | CO88: =AJ88+F88+BW88+BX88+BK88+CA88+CD88+CE88+BN88+AK88+AL88+CJ88 | CP88: =D88+CN88-CO88 | CQ88: =MAX(0,MIN(CP88,BY88*(1+M88-$B$19))) | CR88: =MAX(0,MIN(CP88-CQ88,(CH88-CK88)+(CI88-CL88))) | CS88: =IF((CH88-CK88)+(CI88-CL88)>1,CR88*(CH88-CK88)/((CH88-CK88)+(CI88-CL88)),0) | CT88: =CR88-CS88 | CU88: =MAX(0,MIN(CP88-CQ88-CR88,CF88*(1+M88))) | CV88: =MAX(0,-CP88) | CW88: =MIN(CV88,MAX(0,CM88)) | CX88: =IF(BY88>0,MAX(0,1-BZ88/BY88),0) | CY88: =CQ88*CX88 | CZ88: =BY88*(1+M88-$B$19)-CQ88+(CV88-CW88) | DA88: =BZ88-(CQ88-CY88)+(CV88-CW88) | DB88: =CB88*(1+M88)-CD88-CS88-CK88+Z88+AB88 | DC88: =CC88*(1+M88)-CE88-CT88-CL88+AA88+AC88 | DD88: =CF88*(1+M88)-CU88+CW88 | DE88: =CD88+CK88+CS88 | DF88: =CA88*household!$B$15*$B$20*(1+tax_tables!$B$17) | DG88: =X88+BS88+BU88+BW88+DE88+DF88+CA88*household!$B$15*(1-$B$20)+(CY88+BO88)*household!$B$15*tax_tables!$B$18+(BP88+BM88+AK88)*household!$B$15-Z88 | DH88: =CE88+CL88+CT88 | DI88: =CA88*(1-household!$B$15)*$B$20*(1+tax_tables!$B$17) | DJ88: =Y88+BT88+BV88+BX88+DH88+DI88+CA88*(1-household!$B$15)*(1-$B$20)+(CY88+BO88)*(1-household!$B$15)*tax_tables!$B$18+(BP88+BM88+AK88)*(1-household!$B$15)-AA88 | DK88: =IF((DG88>=DJ88),MIN(0.5*(BW88+IF(B88>=65,DE88,0)),MAX(0,(DG88-DJ88)/2)),MIN(0.5*(BX88+IF(C88>=65,DH88,0)),MAX(0,(DJ88-DG88)/2))) | DL88: =DG88+IF((DG88>=DJ88),-DK88,DK88) | DM88: =BW88+IF(B88>=65,DE88,0)+IF((DG88>=DJ88),-DK88,DK88) | DN88: =MIN(BU88,tax_tables!$B$22*MAX(0,DL88-tax_tables!$B$21*P88)) | DO88: =MAX(0,DL88-DN88) | DP88: =DJ88+IF((DG88>=DJ88),DK88,-DK88) | DQ88: =BX88+IF(C88>=65,DH88,0)+IF((DG88>=DJ88),DK88,-DK88) | DR88: =MIN(BV88,tax_tables!$B$22*MAX(0,DP88-tax_tables!$B$21*P88)) | DS88: =MAX(0,DP88-DR88) | DT88: =BJ88-BD88 | DU88: =(tax_tables!$B$6-(tax_tables!$B$6-tax_tables!$B$7)*MIN(1,MAX(0,(DL88-tax_tables!$B$8*P88)/((tax_tables!$B$9-tax_tables!$B$8)*P88))))*P88+(B88>=65)*MAX(0,tax_tables!$B$10*P88-tax_tables!$B$12*MAX(0,DL88-tax_tables!$B$11*P88))+MIN(tax_tables!$B$13,DM88)+MIN(tax_tables!$B$14*P88,X88)+AF88+(DL88<=DP88)*MAX(0,DT88-MIN(0.03*DL88,tax_tables!$B$15*P88)) | DV88: =MAX(0,SUMPRODUCT((DO88>tax_tables!$E$5:$E$16*P88)*(DO88-tax_tables!$E$5:$E$16*P88)*tax_tables!$G$5:$G$16)-tax_tables!$B$5*DU88-tax_tables!$B$16*DF88) | DW88: =tax_tables!$B$35*Q88+(B88>=65)*MAX(0,tax_tables!$B$36*Q88-tax_tables!$B$12*MAX(0,DL88-tax_tables!$B$37*Q88))+MIN(tax_tables!$B$38,DM88)+AF88+(DL88<=DP88)*MAX(0,DT88-MIN(0.03*DL88,tax_tables!$B$39*Q88)) | DX88: =MAX(0,SUMPRODUCT((DO88>tax_tables!$I$5:$I$16*Q88)*(DO88-tax_tables!$I$5:$I$16*Q88)*tax_tables!$K$5:$K$16)-tax_tables!$B$34*DW88-tax_tables!$B$40*DF88-MAX(0,tax_tables!$B$41*Q88-tax_tables!$B$43*MAX(0,DL88-tax_tables!$B$42*Q88))) | DY88: =(tax_tables!$B$6-(tax_tables!$B$6-tax_tables!$B$7)*MIN(1,MAX(0,(DP88-tax_tables!$B$8*P88)/((tax_tables!$B$9-tax_tables!$B$8)*P88))))*P88+(C88>=65)*MAX(0,tax_tables!$B$10*P88-tax_tables!$B$12*MAX(0,DP88-tax_tables!$B$11*P88))+MIN(tax_tables!$B$13,DQ88)+MIN(tax_tables!$B$14*P88,Y88)+AG88+(DL88>DP88)*MAX(0,DT88-MIN(0.03*DP88,tax_tables!$B$15*P88)) | DZ88: =MAX(0,SUMPRODUCT((DS88>tax_tables!$E$5:$E$16*P88)*(DS88-tax_tables!$E$5:$E$16*P88)*tax_tables!$G$5:$G$16)-tax_tables!$B$5*DY88-tax_tables!$B$16*DI88) | EA88: =tax_tables!$B$35*Q88+(C88>=65)*MAX(0,tax_tables!$B$36*Q88-tax_tables!$B$12*MAX(0,DP88-tax_tables!$B$37*Q88))+MIN(tax_tables!$B$38,DQ88)+AG88+(DL88>DP88)*MAX(0,DT88-MIN(0.03*DP88,tax_tables!$B$39*Q88)) | EB88: =MAX(0,SUMPRODUCT((DS88>tax_tables!$I$5:$I$16*Q88)*(DS88-tax_tables!$I$5:$I$16*Q88)*tax_tables!$K$5:$K$16)-tax_tables!$B$34*EA88-tax_tables!$B$40*DI88-MAX(0,tax_tables!$B$41*Q88-tax_tables!$B$43*MAX(0,DP88-tax_tables!$B$42*Q88))) | EC88: =DV88+DZ88+DX88+EB88+DN88+DR88 | ED88: =CZ88+DB88+DC88+DD88 | EE88: =ED88+BQ88-AR88+BR88
A89: =A88+1 | B89: =A89-household!$B$6 | C89: =A89-household!$B$9 | D89: =AU89+AV89+AW89+AX89+BB89+BJ89+AM89 | E89: =CN89+AI89+AH89 | F89: =BS89+BT89+BU89+BV89 | G89: =CQ89+CR89+CU89+CD89+CE89+CA89-CV89+CJ89+CW89 | H89: =IF(BY89+CB89+CC89+CF89<=0,"",G89/(BY89+CB89+CC89+CF89)) | I89: =ED89/O89 | J89: =EE89/O89 | K89: =MAX(0,CP89-CQ89-CR89-CU89) | M89: =IF(L89="",$B$18,L89) | O89: =(1+$B$17)^(A89-household!$B$4+1) | P89: =(1+$B$17)^(A89-tax_tables!$B$4) | Q89: =(1+$B$17)^(A89-tax_tables!$B$4-MAX(0,MIN(A89,tax_tables!$B$45)-tax_tables!$B$44+1)) | R89: =(1+$B$21)^(A89-household!$B$4+1) | S89: =(1+$B$22)^(A89-household!$B$4+1) | T89: =(1+$B$23)^(A89-household!$B$4+1) | U89: =IF(A89<$B$5,1,0) | V89: =IF(A89<$B$6,1,0) | W89: =IF(U89+V89>0,1,0) | X89: =U89*$B$7*O89+SUMPRODUCT(($B$72:$B$77=A89)*($D$72:$D$77="Wages: person 1")*$C$72:$C$77)*O89 | Y89: =V89*$B$8*O89+SUMPRODUCT(($B$72:$B$77=A89)*($D$72:$D$77="Wages: person 2")*$C$72:$C$77)*O89 | Z89: =U89*$B$9*O89 | AA89: =V89*$B$10*O89 | AB89: =U89*$B$11*O89 | AC89: =V89*$B$12*O89 | AD89: =X89+Y89 | AE89: =AD89-Z89-AA89 | AF89: =tax_tables!$B$25*MAX(0,MIN(X89,tax_tables!$B$27*P89)-tax_tables!$B$26)+tax_tables!$B$28*MAX(0,MIN(X89,tax_tables!$B$29*P89)-tax_tables!$B$27*P89)+tax_tables!$B$30*MIN(X89,tax_tables!$B$31*P89) | AG89: =tax_tables!$B$25*MAX(0,MIN(Y89,tax_tables!$B$27*P89)-tax_tables!$B$26)+tax_tables!$B$28*MAX(0,MIN(Y89,tax_tables!$B$29*P89)-tax_tables!$B$27*P89)+tax_tables!$B$30*MIN(Y89,tax_tables!$B$31*P89) | AH89: =AF89+AG89 | AI89: =$B$13*AE89 | AJ89: =AD89-Z89-AA89-AH89-AI89 | AK89: =SUMPRODUCT(($B$72:$B$77=A89)*($D$72:$D$77="Other taxable income")*$C$72:$C$77)*O89 | AL89: =SUMPRODUCT(($B$72:$B$77=A89)*($D$72:$D$77="Tax-free money in")*$C$72:$C$77)*O89 | AM89: =SUMPRODUCT(($B$72:$B$77=A89)*($D$72:$D$77="Expense")*$C$72:$C$77)*O89 | AN89: =IF(OR($B$64="",A89<$B$64),1,0) | AO89: =AR88 | AP89: =AN89*AO89*properties!$J$2 | AQ89: =AN89*MIN(properties!$K$2,AO89+AP89) | AR89: =AN89*(AO89+AP89-AQ89) | AS89: =AN89*properties!$G$2*O89 | AT89: =(1-AN89)*$E$64*O89 | AU89: =AQ89+AS89+AT89 | AV89: =SUMIF(budget!$A$2:$A$300,"household",budget!$F$2:$F$300)*O89*IF(N89="",1,N89) | AW89: =SUMPRODUCT((other_budget!$C$2:$C$30<=A89)*(other_budget!$D$2:$D$30>=A89)*other_budget!$B$2:$B$30)*O89 | AX89: =SUMPRODUCT((kids_budget!$D$2:$D$40<=A89)*(kids_budget!$E$2:$E$40>=A89)*(kids_budget!$G$2:$G$40<>"college_funds")*kids_budget!$C$2:$C$40*((kids_budget!$F$2:$F$40="college")*S89+(kids_budget!$F$2:$F$40<>"college")*O89)) | AY89: =SUMPRODUCT((kids_budget!$D$2:$D$40<=A89)*(kids_budget!$E$2:$E$40>=A89)*(kids_budget!$G$2:$G$40="college_funds")*kids_budget!$C$2:$C$40*((kids_budget!$F$2:$F$40="college")*S89+(kids_budget!$F$2:$F$40<>"college")*O89)) | AZ89: =BC88 | BA89: =MIN(AY89,AZ89*(1+M89)) | BB89: =AY89-BA89 | BC89: =AZ89*(1+M89)-BA89 | BD89: =W89*healthcare!$B$2*R89 | BE89: =(1-W89)*2 | BF89: =BE89*healthcare!$B$3*12*R89 | BG89: =BE89*healthcare!$B$4*R89 | BH89: =AND(B89>=$B$44,B89<$B$44+$B$45)*1+AND(C89>=$B$46,C89<$B$46+$B$47)*1 | BI89: =BH89*$B$48*T89 | BJ89: =BD89+BF89+BG89+BI89 | BK89: =SUMPRODUCT((1-($B$65:$B$68>0)*(A89>=$B$65:$B$68))*(1-(($C$65:$C$68>0)*(A89>=$C$65:$C$68)))*(properties!$L$3:$L$6-properties!$M$3:$M$6))*O89+SUMPRODUCT((1-($B$65:$B$68>0)*(A89>=$B$65:$B$68))*(($C$65:$C$68>0)*(A89>=$C$65:$C$68))*($D$65:$D$68-$E$65:$E$68))*O89 | BL89: =SUMPRODUCT((1-($B$65:$B$68>0)*(A89>=$B$65:$B$68))*properties!$N$3:$N$6*(A89<=properties!$O$3:$O$6)) | BM89: =MAX(0,BK89-BL89) | BN89: =SUMPRODUCT(($B$64:$B$68=A89)*$G$64:$G$68) | BO89: =SUMPRODUCT(($B$64:$B$68=A89)*$H$64:$H$68) | BP89: =SUMPRODUCT(($B$64:$B$68=A89)*$I$64:$I$68) | BQ89: =AN89*properties!$C$2*(1+properties!$D$2)^(A89-household!$B$4+1) | BR89: =SUMPRODUCT((1-($B$65:$B$68>0)*(A89>=$B$65:$B$68))*properties!$C$3:$C$6*(1+properties!$D$3:$D$6)^(A89-household!$B$4+1)) | BS89: =IF(A89>=household!$B$6+$B$26,household!$B$11*12*$B$30*O89,0) | BT89: =IF(A89>=household!$B$9+$B$27,household!$B$12*12*$B$31*O89,0) | BU89: =IF(A89>=household!$B$6+$B$28,tax_tables!$B$19*12*P89*MIN(1,household!$B$13/40)*$B$32*(1+tax_tables!$B$20*(B89>=75)),0) | BV89: =IF(A89>=household!$B$9+$B$29,tax_tables!$B$19*12*P89*MIN(1,household!$B$14/40)*$B$33*(1+tax_tables!$B$20*(C89>=75)),0) | BW89: =IF(AND($B$36<>0,A89>=household!$B$6+$B$37),$B$36*(1+$B$17)^(MAX(household!$B$6+$B$37,household!$B$4-1)-household!$B$4+1)*(1+$B$40*$B$17)^(A89-MAX(household!$B$6+$B$37,household!$B$4-1)),0) | BX89: =IF(AND($B$38<>0,A89>=household!$B$9+$B$39),$B$38*(1+$B$17)^(MAX(household!$B$9+$B$39,household!$B$4-1)-household!$B$4+1)*(1+$B$40*$B$17)^(A89-MAX(household!$B$9+$B$39,household!$B$4-1)),0) | BY89: =CZ88 | BZ89: =DA88 | CA89: =$B$19*BY89 | CB89: =DB88 | CC89: =DC88 | CD89: =IF(B89>=tax_tables!$B$46,MAX(0,CB89)*INDEX(tax_tables!$N$5:$N$54,MATCH(MIN(B89-1,120),tax_tables!$M$5:$M$54,0)),0) | CE89: =IF(C89>=tax_tables!$B$46,MAX(0,CC89)*INDEX(tax_tables!$N$5:$N$54,MATCH(MIN(C89-1,120),tax_tables!$M$5:$M$54,0)),0) | CF89: =DD88 | CG89: =IF(OR($B$52="",$B$53=""),0,IF(AND(A89>=$B$52,A89<=$B$53),$B$51*O89,0)) | CH89: =MAX(0,CB89*(1+M89)-CD89) | CI89: =MAX(0,CC89*(1+M89)-CE89) | CJ89: =MIN(CG89,CH89+CI89) | CK89: =IF(CH89+CI89>1,CJ89*CH89/(CH89+CI89),0) | CL89: =CJ89-CK89 | CM89: =CM88-CW88+CU88+tax_tables!$B$32*P89*2 | CN89: =EC88-AI88 | CO89: =AJ89+F89+BW89+BX89+BK89+CA89+CD89+CE89+BN89+AK89+AL89+CJ89 | CP89: =D89+CN89-CO89 | CQ89: =MAX(0,MIN(CP89,BY89*(1+M89-$B$19))) | CR89: =MAX(0,MIN(CP89-CQ89,(CH89-CK89)+(CI89-CL89))) | CS89: =IF((CH89-CK89)+(CI89-CL89)>1,CR89*(CH89-CK89)/((CH89-CK89)+(CI89-CL89)),0) | CT89: =CR89-CS89 | CU89: =MAX(0,MIN(CP89-CQ89-CR89,CF89*(1+M89))) | CV89: =MAX(0,-CP89) | CW89: =MIN(CV89,MAX(0,CM89)) | CX89: =IF(BY89>0,MAX(0,1-BZ89/BY89),0) | CY89: =CQ89*CX89 | CZ89: =BY89*(1+M89-$B$19)-CQ89+(CV89-CW89) | DA89: =BZ89-(CQ89-CY89)+(CV89-CW89) | DB89: =CB89*(1+M89)-CD89-CS89-CK89+Z89+AB89 | DC89: =CC89*(1+M89)-CE89-CT89-CL89+AA89+AC89 | DD89: =CF89*(1+M89)-CU89+CW89 | DE89: =CD89+CK89+CS89 | DF89: =CA89*household!$B$15*$B$20*(1+tax_tables!$B$17) | DG89: =X89+BS89+BU89+BW89+DE89+DF89+CA89*household!$B$15*(1-$B$20)+(CY89+BO89)*household!$B$15*tax_tables!$B$18+(BP89+BM89+AK89)*household!$B$15-Z89 | DH89: =CE89+CL89+CT89 | DI89: =CA89*(1-household!$B$15)*$B$20*(1+tax_tables!$B$17) | DJ89: =Y89+BT89+BV89+BX89+DH89+DI89+CA89*(1-household!$B$15)*(1-$B$20)+(CY89+BO89)*(1-household!$B$15)*tax_tables!$B$18+(BP89+BM89+AK89)*(1-household!$B$15)-AA89 | DK89: =IF((DG89>=DJ89),MIN(0.5*(BW89+IF(B89>=65,DE89,0)),MAX(0,(DG89-DJ89)/2)),MIN(0.5*(BX89+IF(C89>=65,DH89,0)),MAX(0,(DJ89-DG89)/2))) | DL89: =DG89+IF((DG89>=DJ89),-DK89,DK89) | DM89: =BW89+IF(B89>=65,DE89,0)+IF((DG89>=DJ89),-DK89,DK89) | DN89: =MIN(BU89,tax_tables!$B$22*MAX(0,DL89-tax_tables!$B$21*P89)) | DO89: =MAX(0,DL89-DN89) | DP89: =DJ89+IF((DG89>=DJ89),DK89,-DK89) | DQ89: =BX89+IF(C89>=65,DH89,0)+IF((DG89>=DJ89),DK89,-DK89) | DR89: =MIN(BV89,tax_tables!$B$22*MAX(0,DP89-tax_tables!$B$21*P89)) | DS89: =MAX(0,DP89-DR89) | DT89: =BJ89-BD89 | DU89: =(tax_tables!$B$6-(tax_tables!$B$6-tax_tables!$B$7)*MIN(1,MAX(0,(DL89-tax_tables!$B$8*P89)/((tax_tables!$B$9-tax_tables!$B$8)*P89))))*P89+(B89>=65)*MAX(0,tax_tables!$B$10*P89-tax_tables!$B$12*MAX(0,DL89-tax_tables!$B$11*P89))+MIN(tax_tables!$B$13,DM89)+MIN(tax_tables!$B$14*P89,X89)+AF89+(DL89<=DP89)*MAX(0,DT89-MIN(0.03*DL89,tax_tables!$B$15*P89)) | DV89: =MAX(0,SUMPRODUCT((DO89>tax_tables!$E$5:$E$16*P89)*(DO89-tax_tables!$E$5:$E$16*P89)*tax_tables!$G$5:$G$16)-tax_tables!$B$5*DU89-tax_tables!$B$16*DF89) | DW89: =tax_tables!$B$35*Q89+(B89>=65)*MAX(0,tax_tables!$B$36*Q89-tax_tables!$B$12*MAX(0,DL89-tax_tables!$B$37*Q89))+MIN(tax_tables!$B$38,DM89)+AF89+(DL89<=DP89)*MAX(0,DT89-MIN(0.03*DL89,tax_tables!$B$39*Q89)) | DX89: =MAX(0,SUMPRODUCT((DO89>tax_tables!$I$5:$I$16*Q89)*(DO89-tax_tables!$I$5:$I$16*Q89)*tax_tables!$K$5:$K$16)-tax_tables!$B$34*DW89-tax_tables!$B$40*DF89-MAX(0,tax_tables!$B$41*Q89-tax_tables!$B$43*MAX(0,DL89-tax_tables!$B$42*Q89))) | DY89: =(tax_tables!$B$6-(tax_tables!$B$6-tax_tables!$B$7)*MIN(1,MAX(0,(DP89-tax_tables!$B$8*P89)/((tax_tables!$B$9-tax_tables!$B$8)*P89))))*P89+(C89>=65)*MAX(0,tax_tables!$B$10*P89-tax_tables!$B$12*MAX(0,DP89-tax_tables!$B$11*P89))+MIN(tax_tables!$B$13,DQ89)+MIN(tax_tables!$B$14*P89,Y89)+AG89+(DL89>DP89)*MAX(0,DT89-MIN(0.03*DP89,tax_tables!$B$15*P89)) | DZ89: =MAX(0,SUMPRODUCT((DS89>tax_tables!$E$5:$E$16*P89)*(DS89-tax_tables!$E$5:$E$16*P89)*tax_tables!$G$5:$G$16)-tax_tables!$B$5*DY89-tax_tables!$B$16*DI89) | EA89: =tax_tables!$B$35*Q89+(C89>=65)*MAX(0,tax_tables!$B$36*Q89-tax_tables!$B$12*MAX(0,DP89-tax_tables!$B$37*Q89))+MIN(tax_tables!$B$38,DQ89)+AG89+(DL89>DP89)*MAX(0,DT89-MIN(0.03*DP89,tax_tables!$B$39*Q89)) | EB89: =MAX(0,SUMPRODUCT((DS89>tax_tables!$I$5:$I$16*Q89)*(DS89-tax_tables!$I$5:$I$16*Q89)*tax_tables!$K$5:$K$16)-tax_tables!$B$34*EA89-tax_tables!$B$40*DI89-MAX(0,tax_tables!$B$41*Q89-tax_tables!$B$43*MAX(0,DP89-tax_tables!$B$42*Q89))) | EC89: =DV89+DZ89+DX89+EB89+DN89+DR89 | ED89: =CZ89+DB89+DC89+DD89 | EE89: =ED89+BQ89-AR89+BR89
A90: =A89+1 | B90: =A90-household!$B$6 | C90: =A90-household!$B$9 | D90: =AU90+AV90+AW90+AX90+BB90+BJ90+AM90 | E90: =CN90+AI90+AH90 | F90: =BS90+BT90+BU90+BV90 | G90: =CQ90+CR90+CU90+CD90+CE90+CA90-CV90+CJ90+CW90 | H90: =IF(BY90+CB90+CC90+CF90<=0,"",G90/(BY90+CB90+CC90+CF90)) | I90: =ED90/O90 | J90: =EE90/O90 | K90: =MAX(0,CP90-CQ90-CR90-CU90) | M90: =IF(L90="",$B$18,L90) | O90: =(1+$B$17)^(A90-household!$B$4+1) | P90: =(1+$B$17)^(A90-tax_tables!$B$4) | Q90: =(1+$B$17)^(A90-tax_tables!$B$4-MAX(0,MIN(A90,tax_tables!$B$45)-tax_tables!$B$44+1)) | R90: =(1+$B$21)^(A90-household!$B$4+1) | S90: =(1+$B$22)^(A90-household!$B$4+1) | T90: =(1+$B$23)^(A90-household!$B$4+1) | U90: =IF(A90<$B$5,1,0) | V90: =IF(A90<$B$6,1,0) | W90: =IF(U90+V90>0,1,0) | X90: =U90*$B$7*O90+SUMPRODUCT(($B$72:$B$77=A90)*($D$72:$D$77="Wages: person 1")*$C$72:$C$77)*O90 | Y90: =V90*$B$8*O90+SUMPRODUCT(($B$72:$B$77=A90)*($D$72:$D$77="Wages: person 2")*$C$72:$C$77)*O90 | Z90: =U90*$B$9*O90 | AA90: =V90*$B$10*O90 | AB90: =U90*$B$11*O90 | AC90: =V90*$B$12*O90 | AD90: =X90+Y90 | AE90: =AD90-Z90-AA90 | AF90: =tax_tables!$B$25*MAX(0,MIN(X90,tax_tables!$B$27*P90)-tax_tables!$B$26)+tax_tables!$B$28*MAX(0,MIN(X90,tax_tables!$B$29*P90)-tax_tables!$B$27*P90)+tax_tables!$B$30*MIN(X90,tax_tables!$B$31*P90) | AG90: =tax_tables!$B$25*MAX(0,MIN(Y90,tax_tables!$B$27*P90)-tax_tables!$B$26)+tax_tables!$B$28*MAX(0,MIN(Y90,tax_tables!$B$29*P90)-tax_tables!$B$27*P90)+tax_tables!$B$30*MIN(Y90,tax_tables!$B$31*P90) | AH90: =AF90+AG90 | AI90: =$B$13*AE90 | AJ90: =AD90-Z90-AA90-AH90-AI90 | AK90: =SUMPRODUCT(($B$72:$B$77=A90)*($D$72:$D$77="Other taxable income")*$C$72:$C$77)*O90 | AL90: =SUMPRODUCT(($B$72:$B$77=A90)*($D$72:$D$77="Tax-free money in")*$C$72:$C$77)*O90 | AM90: =SUMPRODUCT(($B$72:$B$77=A90)*($D$72:$D$77="Expense")*$C$72:$C$77)*O90 | AN90: =IF(OR($B$64="",A90<$B$64),1,0) | AO90: =AR89 | AP90: =AN90*AO90*properties!$J$2 | AQ90: =AN90*MIN(properties!$K$2,AO90+AP90) | AR90: =AN90*(AO90+AP90-AQ90) | AS90: =AN90*properties!$G$2*O90 | AT90: =(1-AN90)*$E$64*O90 | AU90: =AQ90+AS90+AT90 | AV90: =SUMIF(budget!$A$2:$A$300,"household",budget!$F$2:$F$300)*O90*IF(N90="",1,N90) | AW90: =SUMPRODUCT((other_budget!$C$2:$C$30<=A90)*(other_budget!$D$2:$D$30>=A90)*other_budget!$B$2:$B$30)*O90 | AX90: =SUMPRODUCT((kids_budget!$D$2:$D$40<=A90)*(kids_budget!$E$2:$E$40>=A90)*(kids_budget!$G$2:$G$40<>"college_funds")*kids_budget!$C$2:$C$40*((kids_budget!$F$2:$F$40="college")*S90+(kids_budget!$F$2:$F$40<>"college")*O90)) | AY90: =SUMPRODUCT((kids_budget!$D$2:$D$40<=A90)*(kids_budget!$E$2:$E$40>=A90)*(kids_budget!$G$2:$G$40="college_funds")*kids_budget!$C$2:$C$40*((kids_budget!$F$2:$F$40="college")*S90+(kids_budget!$F$2:$F$40<>"college")*O90)) | AZ90: =BC89 | BA90: =MIN(AY90,AZ90*(1+M90)) | BB90: =AY90-BA90 | BC90: =AZ90*(1+M90)-BA90 | BD90: =W90*healthcare!$B$2*R90 | BE90: =(1-W90)*2 | BF90: =BE90*healthcare!$B$3*12*R90 | BG90: =BE90*healthcare!$B$4*R90 | BH90: =AND(B90>=$B$44,B90<$B$44+$B$45)*1+AND(C90>=$B$46,C90<$B$46+$B$47)*1 | BI90: =BH90*$B$48*T90 | BJ90: =BD90+BF90+BG90+BI90 | BK90: =SUMPRODUCT((1-($B$65:$B$68>0)*(A90>=$B$65:$B$68))*(1-(($C$65:$C$68>0)*(A90>=$C$65:$C$68)))*(properties!$L$3:$L$6-properties!$M$3:$M$6))*O90+SUMPRODUCT((1-($B$65:$B$68>0)*(A90>=$B$65:$B$68))*(($C$65:$C$68>0)*(A90>=$C$65:$C$68))*($D$65:$D$68-$E$65:$E$68))*O90 | BL90: =SUMPRODUCT((1-($B$65:$B$68>0)*(A90>=$B$65:$B$68))*properties!$N$3:$N$6*(A90<=properties!$O$3:$O$6)) | BM90: =MAX(0,BK90-BL90) | BN90: =SUMPRODUCT(($B$64:$B$68=A90)*$G$64:$G$68) | BO90: =SUMPRODUCT(($B$64:$B$68=A90)*$H$64:$H$68) | BP90: =SUMPRODUCT(($B$64:$B$68=A90)*$I$64:$I$68) | BQ90: =AN90*properties!$C$2*(1+properties!$D$2)^(A90-household!$B$4+1) | BR90: =SUMPRODUCT((1-($B$65:$B$68>0)*(A90>=$B$65:$B$68))*properties!$C$3:$C$6*(1+properties!$D$3:$D$6)^(A90-household!$B$4+1)) | BS90: =IF(A90>=household!$B$6+$B$26,household!$B$11*12*$B$30*O90,0) | BT90: =IF(A90>=household!$B$9+$B$27,household!$B$12*12*$B$31*O90,0) | BU90: =IF(A90>=household!$B$6+$B$28,tax_tables!$B$19*12*P90*MIN(1,household!$B$13/40)*$B$32*(1+tax_tables!$B$20*(B90>=75)),0) | BV90: =IF(A90>=household!$B$9+$B$29,tax_tables!$B$19*12*P90*MIN(1,household!$B$14/40)*$B$33*(1+tax_tables!$B$20*(C90>=75)),0) | BW90: =IF(AND($B$36<>0,A90>=household!$B$6+$B$37),$B$36*(1+$B$17)^(MAX(household!$B$6+$B$37,household!$B$4-1)-household!$B$4+1)*(1+$B$40*$B$17)^(A90-MAX(household!$B$6+$B$37,household!$B$4-1)),0) | BX90: =IF(AND($B$38<>0,A90>=household!$B$9+$B$39),$B$38*(1+$B$17)^(MAX(household!$B$9+$B$39,household!$B$4-1)-household!$B$4+1)*(1+$B$40*$B$17)^(A90-MAX(household!$B$9+$B$39,household!$B$4-1)),0) | BY90: =CZ89 | BZ90: =DA89 | CA90: =$B$19*BY90 | CB90: =DB89 | CC90: =DC89 | CD90: =IF(B90>=tax_tables!$B$46,MAX(0,CB90)*INDEX(tax_tables!$N$5:$N$54,MATCH(MIN(B90-1,120),tax_tables!$M$5:$M$54,0)),0) | CE90: =IF(C90>=tax_tables!$B$46,MAX(0,CC90)*INDEX(tax_tables!$N$5:$N$54,MATCH(MIN(C90-1,120),tax_tables!$M$5:$M$54,0)),0) | CF90: =DD89 | CG90: =IF(OR($B$52="",$B$53=""),0,IF(AND(A90>=$B$52,A90<=$B$53),$B$51*O90,0)) | CH90: =MAX(0,CB90*(1+M90)-CD90) | CI90: =MAX(0,CC90*(1+M90)-CE90) | CJ90: =MIN(CG90,CH90+CI90) | CK90: =IF(CH90+CI90>1,CJ90*CH90/(CH90+CI90),0) | CL90: =CJ90-CK90 | CM90: =CM89-CW89+CU89+tax_tables!$B$32*P90*2 | CN90: =EC89-AI89 | CO90: =AJ90+F90+BW90+BX90+BK90+CA90+CD90+CE90+BN90+AK90+AL90+CJ90 | CP90: =D90+CN90-CO90 | CQ90: =MAX(0,MIN(CP90,BY90*(1+M90-$B$19))) | CR90: =MAX(0,MIN(CP90-CQ90,(CH90-CK90)+(CI90-CL90))) | CS90: =IF((CH90-CK90)+(CI90-CL90)>1,CR90*(CH90-CK90)/((CH90-CK90)+(CI90-CL90)),0) | CT90: =CR90-CS90 | CU90: =MAX(0,MIN(CP90-CQ90-CR90,CF90*(1+M90))) | CV90: =MAX(0,-CP90) | CW90: =MIN(CV90,MAX(0,CM90)) | CX90: =IF(BY90>0,MAX(0,1-BZ90/BY90),0) | CY90: =CQ90*CX90 | CZ90: =BY90*(1+M90-$B$19)-CQ90+(CV90-CW90) | DA90: =BZ90-(CQ90-CY90)+(CV90-CW90) | DB90: =CB90*(1+M90)-CD90-CS90-CK90+Z90+AB90 | DC90: =CC90*(1+M90)-CE90-CT90-CL90+AA90+AC90 | DD90: =CF90*(1+M90)-CU90+CW90 | DE90: =CD90+CK90+CS90 | DF90: =CA90*household!$B$15*$B$20*(1+tax_tables!$B$17) | DG90: =X90+BS90+BU90+BW90+DE90+DF90+CA90*household!$B$15*(1-$B$20)+(CY90+BO90)*household!$B$15*tax_tables!$B$18+(BP90+BM90+AK90)*household!$B$15-Z90 | DH90: =CE90+CL90+CT90 | DI90: =CA90*(1-household!$B$15)*$B$20*(1+tax_tables!$B$17) | DJ90: =Y90+BT90+BV90+BX90+DH90+DI90+CA90*(1-household!$B$15)*(1-$B$20)+(CY90+BO90)*(1-household!$B$15)*tax_tables!$B$18+(BP90+BM90+AK90)*(1-household!$B$15)-AA90 | DK90: =IF((DG90>=DJ90),MIN(0.5*(BW90+IF(B90>=65,DE90,0)),MAX(0,(DG90-DJ90)/2)),MIN(0.5*(BX90+IF(C90>=65,DH90,0)),MAX(0,(DJ90-DG90)/2))) | DL90: =DG90+IF((DG90>=DJ90),-DK90,DK90) | DM90: =BW90+IF(B90>=65,DE90,0)+IF((DG90>=DJ90),-DK90,DK90) | DN90: =MIN(BU90,tax_tables!$B$22*MAX(0,DL90-tax_tables!$B$21*P90)) | DO90: =MAX(0,DL90-DN90) | DP90: =DJ90+IF((DG90>=DJ90),DK90,-DK90) | DQ90: =BX90+IF(C90>=65,DH90,0)+IF((DG90>=DJ90),DK90,-DK90) | DR90: =MIN(BV90,tax_tables!$B$22*MAX(0,DP90-tax_tables!$B$21*P90)) | DS90: =MAX(0,DP90-DR90) | DT90: =BJ90-BD90 | DU90: =(tax_tables!$B$6-(tax_tables!$B$6-tax_tables!$B$7)*MIN(1,MAX(0,(DL90-tax_tables!$B$8*P90)/((tax_tables!$B$9-tax_tables!$B$8)*P90))))*P90+(B90>=65)*MAX(0,tax_tables!$B$10*P90-tax_tables!$B$12*MAX(0,DL90-tax_tables!$B$11*P90))+MIN(tax_tables!$B$13,DM90)+MIN(tax_tables!$B$14*P90,X90)+AF90+(DL90<=DP90)*MAX(0,DT90-MIN(0.03*DL90,tax_tables!$B$15*P90)) | DV90: =MAX(0,SUMPRODUCT((DO90>tax_tables!$E$5:$E$16*P90)*(DO90-tax_tables!$E$5:$E$16*P90)*tax_tables!$G$5:$G$16)-tax_tables!$B$5*DU90-tax_tables!$B$16*DF90) | DW90: =tax_tables!$B$35*Q90+(B90>=65)*MAX(0,tax_tables!$B$36*Q90-tax_tables!$B$12*MAX(0,DL90-tax_tables!$B$37*Q90))+MIN(tax_tables!$B$38,DM90)+AF90+(DL90<=DP90)*MAX(0,DT90-MIN(0.03*DL90,tax_tables!$B$39*Q90)) | DX90: =MAX(0,SUMPRODUCT((DO90>tax_tables!$I$5:$I$16*Q90)*(DO90-tax_tables!$I$5:$I$16*Q90)*tax_tables!$K$5:$K$16)-tax_tables!$B$34*DW90-tax_tables!$B$40*DF90-MAX(0,tax_tables!$B$41*Q90-tax_tables!$B$43*MAX(0,DL90-tax_tables!$B$42*Q90))) | DY90: =(tax_tables!$B$6-(tax_tables!$B$6-tax_tables!$B$7)*MIN(1,MAX(0,(DP90-tax_tables!$B$8*P90)/((tax_tables!$B$9-tax_tables!$B$8)*P90))))*P90+(C90>=65)*MAX(0,tax_tables!$B$10*P90-tax_tables!$B$12*MAX(0,DP90-tax_tables!$B$11*P90))+MIN(tax_tables!$B$13,DQ90)+MIN(tax_tables!$B$14*P90,Y90)+AG90+(DL90>DP90)*MAX(0,DT90-MIN(0.03*DP90,tax_tables!$B$15*P90)) | DZ90: =MAX(0,SUMPRODUCT((DS90>tax_tables!$E$5:$E$16*P90)*(DS90-tax_tables!$E$5:$E$16*P90)*tax_tables!$G$5:$G$16)-tax_tables!$B$5*DY90-tax_tables!$B$16*DI90) | EA90: =tax_tables!$B$35*Q90+(C90>=65)*MAX(0,tax_tables!$B$36*Q90-tax_tables!$B$12*MAX(0,DP90-tax_tables!$B$37*Q90))+MIN(tax_tables!$B$38,DQ90)+AG90+(DL90>DP90)*MAX(0,DT90-MIN(0.03*DP90,tax_tables!$B$39*Q90)) | EB90: =MAX(0,SUMPRODUCT((DS90>tax_tables!$I$5:$I$16*Q90)*(DS90-tax_tables!$I$5:$I$16*Q90)*tax_tables!$K$5:$K$16)-tax_tables!$B$34*EA90-tax_tables!$B$40*DI90-MAX(0,tax_tables!$B$41*Q90-tax_tables!$B$43*MAX(0,DP90-tax_tables!$B$42*Q90))) | EC90: =DV90+DZ90+DX90+EB90+DN90+DR90 | ED90: =CZ90+DB90+DC90+DD90 | EE90: =ED90+BQ90-AR90+BR90
A91: =A90+1 | B91: =A91-household!$B$6 | C91: =A91-household!$B$9 | D91: =AU91+AV91+AW91+AX91+BB91+BJ91+AM91 | E91: =CN91+AI91+AH91 | F91: =BS91+BT91+BU91+BV91 | G91: =CQ91+CR91+CU91+CD91+CE91+CA91-CV91+CJ91+CW91 | H91: =IF(BY91+CB91+CC91+CF91<=0,"",G91/(BY91+CB91+CC91+CF91)) | I91: =ED91/O91 | J91: =EE91/O91 | K91: =MAX(0,CP91-CQ91-CR91-CU91) | M91: =IF(L91="",$B$18,L91) | O91: =(1+$B$17)^(A91-household!$B$4+1) | P91: =(1+$B$17)^(A91-tax_tables!$B$4) | Q91: =(1+$B$17)^(A91-tax_tables!$B$4-MAX(0,MIN(A91,tax_tables!$B$45)-tax_tables!$B$44+1)) | R91: =(1+$B$21)^(A91-household!$B$4+1) | S91: =(1+$B$22)^(A91-household!$B$4+1) | T91: =(1+$B$23)^(A91-household!$B$4+1) | U91: =IF(A91<$B$5,1,0) | V91: =IF(A91<$B$6,1,0) | W91: =IF(U91+V91>0,1,0) | X91: =U91*$B$7*O91+SUMPRODUCT(($B$72:$B$77=A91)*($D$72:$D$77="Wages: person 1")*$C$72:$C$77)*O91 | Y91: =V91*$B$8*O91+SUMPRODUCT(($B$72:$B$77=A91)*($D$72:$D$77="Wages: person 2")*$C$72:$C$77)*O91 | Z91: =U91*$B$9*O91 | AA91: =V91*$B$10*O91 | AB91: =U91*$B$11*O91 | AC91: =V91*$B$12*O91 | AD91: =X91+Y91 | AE91: =AD91-Z91-AA91 | AF91: =tax_tables!$B$25*MAX(0,MIN(X91,tax_tables!$B$27*P91)-tax_tables!$B$26)+tax_tables!$B$28*MAX(0,MIN(X91,tax_tables!$B$29*P91)-tax_tables!$B$27*P91)+tax_tables!$B$30*MIN(X91,tax_tables!$B$31*P91) | AG91: =tax_tables!$B$25*MAX(0,MIN(Y91,tax_tables!$B$27*P91)-tax_tables!$B$26)+tax_tables!$B$28*MAX(0,MIN(Y91,tax_tables!$B$29*P91)-tax_tables!$B$27*P91)+tax_tables!$B$30*MIN(Y91,tax_tables!$B$31*P91) | AH91: =AF91+AG91 | AI91: =$B$13*AE91 | AJ91: =AD91-Z91-AA91-AH91-AI91 | AK91: =SUMPRODUCT(($B$72:$B$77=A91)*($D$72:$D$77="Other taxable income")*$C$72:$C$77)*O91 | AL91: =SUMPRODUCT(($B$72:$B$77=A91)*($D$72:$D$77="Tax-free money in")*$C$72:$C$77)*O91 | AM91: =SUMPRODUCT(($B$72:$B$77=A91)*($D$72:$D$77="Expense")*$C$72:$C$77)*O91 | AN91: =IF(OR($B$64="",A91<$B$64),1,0) | AO91: =AR90 | AP91: =AN91*AO91*properties!$J$2 | AQ91: =AN91*MIN(properties!$K$2,AO91+AP91) | AR91: =AN91*(AO91+AP91-AQ91) | AS91: =AN91*properties!$G$2*O91 | AT91: =(1-AN91)*$E$64*O91 | AU91: =AQ91+AS91+AT91 | AV91: =SUMIF(budget!$A$2:$A$300,"household",budget!$F$2:$F$300)*O91*IF(N91="",1,N91) | AW91: =SUMPRODUCT((other_budget!$C$2:$C$30<=A91)*(other_budget!$D$2:$D$30>=A91)*other_budget!$B$2:$B$30)*O91 | AX91: =SUMPRODUCT((kids_budget!$D$2:$D$40<=A91)*(kids_budget!$E$2:$E$40>=A91)*(kids_budget!$G$2:$G$40<>"college_funds")*kids_budget!$C$2:$C$40*((kids_budget!$F$2:$F$40="college")*S91+(kids_budget!$F$2:$F$40<>"college")*O91)) | AY91: =SUMPRODUCT((kids_budget!$D$2:$D$40<=A91)*(kids_budget!$E$2:$E$40>=A91)*(kids_budget!$G$2:$G$40="college_funds")*kids_budget!$C$2:$C$40*((kids_budget!$F$2:$F$40="college")*S91+(kids_budget!$F$2:$F$40<>"college")*O91)) | AZ91: =BC90 | BA91: =MIN(AY91,AZ91*(1+M91)) | BB91: =AY91-BA91 | BC91: =AZ91*(1+M91)-BA91 | BD91: =W91*healthcare!$B$2*R91 | BE91: =(1-W91)*2 | BF91: =BE91*healthcare!$B$3*12*R91 | BG91: =BE91*healthcare!$B$4*R91 | BH91: =AND(B91>=$B$44,B91<$B$44+$B$45)*1+AND(C91>=$B$46,C91<$B$46+$B$47)*1 | BI91: =BH91*$B$48*T91 | BJ91: =BD91+BF91+BG91+BI91 | BK91: =SUMPRODUCT((1-($B$65:$B$68>0)*(A91>=$B$65:$B$68))*(1-(($C$65:$C$68>0)*(A91>=$C$65:$C$68)))*(properties!$L$3:$L$6-properties!$M$3:$M$6))*O91+SUMPRODUCT((1-($B$65:$B$68>0)*(A91>=$B$65:$B$68))*(($C$65:$C$68>0)*(A91>=$C$65:$C$68))*($D$65:$D$68-$E$65:$E$68))*O91 | BL91: =SUMPRODUCT((1-($B$65:$B$68>0)*(A91>=$B$65:$B$68))*properties!$N$3:$N$6*(A91<=properties!$O$3:$O$6)) | BM91: =MAX(0,BK91-BL91) | BN91: =SUMPRODUCT(($B$64:$B$68=A91)*$G$64:$G$68) | BO91: =SUMPRODUCT(($B$64:$B$68=A91)*$H$64:$H$68) | BP91: =SUMPRODUCT(($B$64:$B$68=A91)*$I$64:$I$68) | BQ91: =AN91*properties!$C$2*(1+properties!$D$2)^(A91-household!$B$4+1) | BR91: =SUMPRODUCT((1-($B$65:$B$68>0)*(A91>=$B$65:$B$68))*properties!$C$3:$C$6*(1+properties!$D$3:$D$6)^(A91-household!$B$4+1)) | BS91: =IF(A91>=household!$B$6+$B$26,household!$B$11*12*$B$30*O91,0) | BT91: =IF(A91>=household!$B$9+$B$27,household!$B$12*12*$B$31*O91,0) | BU91: =IF(A91>=household!$B$6+$B$28,tax_tables!$B$19*12*P91*MIN(1,household!$B$13/40)*$B$32*(1+tax_tables!$B$20*(B91>=75)),0) | BV91: =IF(A91>=household!$B$9+$B$29,tax_tables!$B$19*12*P91*MIN(1,household!$B$14/40)*$B$33*(1+tax_tables!$B$20*(C91>=75)),0) | BW91: =IF(AND($B$36<>0,A91>=household!$B$6+$B$37),$B$36*(1+$B$17)^(MAX(household!$B$6+$B$37,household!$B$4-1)-household!$B$4+1)*(1+$B$40*$B$17)^(A91-MAX(household!$B$6+$B$37,household!$B$4-1)),0) | BX91: =IF(AND($B$38<>0,A91>=household!$B$9+$B$39),$B$38*(1+$B$17)^(MAX(household!$B$9+$B$39,household!$B$4-1)-household!$B$4+1)*(1+$B$40*$B$17)^(A91-MAX(household!$B$9+$B$39,household!$B$4-1)),0) | BY91: =CZ90 | BZ91: =DA90 | CA91: =$B$19*BY91 | CB91: =DB90 | CC91: =DC90 | CD91: =IF(B91>=tax_tables!$B$46,MAX(0,CB91)*INDEX(tax_tables!$N$5:$N$54,MATCH(MIN(B91-1,120),tax_tables!$M$5:$M$54,0)),0) | CE91: =IF(C91>=tax_tables!$B$46,MAX(0,CC91)*INDEX(tax_tables!$N$5:$N$54,MATCH(MIN(C91-1,120),tax_tables!$M$5:$M$54,0)),0) | CF91: =DD90 | CG91: =IF(OR($B$52="",$B$53=""),0,IF(AND(A91>=$B$52,A91<=$B$53),$B$51*O91,0)) | CH91: =MAX(0,CB91*(1+M91)-CD91) | CI91: =MAX(0,CC91*(1+M91)-CE91) | CJ91: =MIN(CG91,CH91+CI91) | CK91: =IF(CH91+CI91>1,CJ91*CH91/(CH91+CI91),0) | CL91: =CJ91-CK91 | CM91: =CM90-CW90+CU90+tax_tables!$B$32*P91*2 | CN91: =EC90-AI90 | CO91: =AJ91+F91+BW91+BX91+BK91+CA91+CD91+CE91+BN91+AK91+AL91+CJ91 | CP91: =D91+CN91-CO91 | CQ91: =MAX(0,MIN(CP91,BY91*(1+M91-$B$19))) | CR91: =MAX(0,MIN(CP91-CQ91,(CH91-CK91)+(CI91-CL91))) | CS91: =IF((CH91-CK91)+(CI91-CL91)>1,CR91*(CH91-CK91)/((CH91-CK91)+(CI91-CL91)),0) | CT91: =CR91-CS91 | CU91: =MAX(0,MIN(CP91-CQ91-CR91,CF91*(1+M91))) | CV91: =MAX(0,-CP91) | CW91: =MIN(CV91,MAX(0,CM91)) | CX91: =IF(BY91>0,MAX(0,1-BZ91/BY91),0) | CY91: =CQ91*CX91 | CZ91: =BY91*(1+M91-$B$19)-CQ91+(CV91-CW91) | DA91: =BZ91-(CQ91-CY91)+(CV91-CW91) | DB91: =CB91*(1+M91)-CD91-CS91-CK91+Z91+AB91 | DC91: =CC91*(1+M91)-CE91-CT91-CL91+AA91+AC91 | DD91: =CF91*(1+M91)-CU91+CW91 | DE91: =CD91+CK91+CS91 | DF91: =CA91*household!$B$15*$B$20*(1+tax_tables!$B$17) | DG91: =X91+BS91+BU91+BW91+DE91+DF91+CA91*household!$B$15*(1-$B$20)+(CY91+BO91)*household!$B$15*tax_tables!$B$18+(BP91+BM91+AK91)*household!$B$15-Z91 | DH91: =CE91+CL91+CT91 | DI91: =CA91*(1-household!$B$15)*$B$20*(1+tax_tables!$B$17) | DJ91: =Y91+BT91+BV91+BX91+DH91+DI91+CA91*(1-household!$B$15)*(1-$B$20)+(CY91+BO91)*(1-household!$B$15)*tax_tables!$B$18+(BP91+BM91+AK91)*(1-household!$B$15)-AA91 | DK91: =IF((DG91>=DJ91),MIN(0.5*(BW91+IF(B91>=65,DE91,0)),MAX(0,(DG91-DJ91)/2)),MIN(0.5*(BX91+IF(C91>=65,DH91,0)),MAX(0,(DJ91-DG91)/2))) | DL91: =DG91+IF((DG91>=DJ91),-DK91,DK91) | DM91: =BW91+IF(B91>=65,DE91,0)+IF((DG91>=DJ91),-DK91,DK91) | DN91: =MIN(BU91,tax_tables!$B$22*MAX(0,DL91-tax_tables!$B$21*P91)) | DO91: =MAX(0,DL91-DN91) | DP91: =DJ91+IF((DG91>=DJ91),DK91,-DK91) | DQ91: =BX91+IF(C91>=65,DH91,0)+IF((DG91>=DJ91),DK91,-DK91) | DR91: =MIN(BV91,tax_tables!$B$22*MAX(0,DP91-tax_tables!$B$21*P91)) | DS91: =MAX(0,DP91-DR91) | DT91: =BJ91-BD91 | DU91: =(tax_tables!$B$6-(tax_tables!$B$6-tax_tables!$B$7)*MIN(1,MAX(0,(DL91-tax_tables!$B$8*P91)/((tax_tables!$B$9-tax_tables!$B$8)*P91))))*P91+(B91>=65)*MAX(0,tax_tables!$B$10*P91-tax_tables!$B$12*MAX(0,DL91-tax_tables!$B$11*P91))+MIN(tax_tables!$B$13,DM91)+MIN(tax_tables!$B$14*P91,X91)+AF91+(DL91<=DP91)*MAX(0,DT91-MIN(0.03*DL91,tax_tables!$B$15*P91)) | DV91: =MAX(0,SUMPRODUCT((DO91>tax_tables!$E$5:$E$16*P91)*(DO91-tax_tables!$E$5:$E$16*P91)*tax_tables!$G$5:$G$16)-tax_tables!$B$5*DU91-tax_tables!$B$16*DF91) | DW91: =tax_tables!$B$35*Q91+(B91>=65)*MAX(0,tax_tables!$B$36*Q91-tax_tables!$B$12*MAX(0,DL91-tax_tables!$B$37*Q91))+MIN(tax_tables!$B$38,DM91)+AF91+(DL91<=DP91)*MAX(0,DT91-MIN(0.03*DL91,tax_tables!$B$39*Q91)) | DX91: =MAX(0,SUMPRODUCT((DO91>tax_tables!$I$5:$I$16*Q91)*(DO91-tax_tables!$I$5:$I$16*Q91)*tax_tables!$K$5:$K$16)-tax_tables!$B$34*DW91-tax_tables!$B$40*DF91-MAX(0,tax_tables!$B$41*Q91-tax_tables!$B$43*MAX(0,DL91-tax_tables!$B$42*Q91))) | DY91: =(tax_tables!$B$6-(tax_tables!$B$6-tax_tables!$B$7)*MIN(1,MAX(0,(DP91-tax_tables!$B$8*P91)/((tax_tables!$B$9-tax_tables!$B$8)*P91))))*P91+(C91>=65)*MAX(0,tax_tables!$B$10*P91-tax_tables!$B$12*MAX(0,DP91-tax_tables!$B$11*P91))+MIN(tax_tables!$B$13,DQ91)+MIN(tax_tables!$B$14*P91,Y91)+AG91+(DL91>DP91)*MAX(0,DT91-MIN(0.03*DP91,tax_tables!$B$15*P91)) | DZ91: =MAX(0,SUMPRODUCT((DS91>tax_tables!$E$5:$E$16*P91)*(DS91-tax_tables!$E$5:$E$16*P91)*tax_tables!$G$5:$G$16)-tax_tables!$B$5*DY91-tax_tables!$B$16*DI91) | EA91: =tax_tables!$B$35*Q91+(C91>=65)*MAX(0,tax_tables!$B$36*Q91-tax_tables!$B$12*MAX(0,DP91-tax_tables!$B$37*Q91))+MIN(tax_tables!$B$38,DQ91)+AG91+(DL91>DP91)*MAX(0,DT91-MIN(0.03*DP91,tax_tables!$B$39*Q91)) | EB91: =MAX(0,SUMPRODUCT((DS91>tax_tables!$I$5:$I$16*Q91)*(DS91-tax_tables!$I$5:$I$16*Q91)*tax_tables!$K$5:$K$16)-tax_tables!$B$34*EA91-tax_tables!$B$40*DI91-MAX(0,tax_tables!$B$41*Q91-tax_tables!$B$43*MAX(0,DP91-tax_tables!$B$42*Q91))) | EC91: =DV91+DZ91+DX91+EB91+DN91+DR91 | ED91: =CZ91+DB91+DC91+DD91 | EE91: =ED91+BQ91-AR91+BR91
A92: =A91+1 | B92: =A92-household!$B$6 | C92: =A92-household!$B$9 | D92: =AU92+AV92+AW92+AX92+BB92+BJ92+AM92 | E92: =CN92+AI92+AH92 | F92: =BS92+BT92+BU92+BV92 | G92: =CQ92+CR92+CU92+CD92+CE92+CA92-CV92+CJ92+CW92 | H92: =IF(BY92+CB92+CC92+CF92<=0,"",G92/(BY92+CB92+CC92+CF92)) | I92: =ED92/O92 | J92: =EE92/O92 | K92: =MAX(0,CP92-CQ92-CR92-CU92) | M92: =IF(L92="",$B$18,L92) | O92: =(1+$B$17)^(A92-household!$B$4+1) | P92: =(1+$B$17)^(A92-tax_tables!$B$4) | Q92: =(1+$B$17)^(A92-tax_tables!$B$4-MAX(0,MIN(A92,tax_tables!$B$45)-tax_tables!$B$44+1)) | R92: =(1+$B$21)^(A92-household!$B$4+1) | S92: =(1+$B$22)^(A92-household!$B$4+1) | T92: =(1+$B$23)^(A92-household!$B$4+1) | U92: =IF(A92<$B$5,1,0) | V92: =IF(A92<$B$6,1,0) | W92: =IF(U92+V92>0,1,0) | X92: =U92*$B$7*O92+SUMPRODUCT(($B$72:$B$77=A92)*($D$72:$D$77="Wages: person 1")*$C$72:$C$77)*O92 | Y92: =V92*$B$8*O92+SUMPRODUCT(($B$72:$B$77=A92)*($D$72:$D$77="Wages: person 2")*$C$72:$C$77)*O92 | Z92: =U92*$B$9*O92 | AA92: =V92*$B$10*O92 | AB92: =U92*$B$11*O92 | AC92: =V92*$B$12*O92 | AD92: =X92+Y92 | AE92: =AD92-Z92-AA92 | AF92: =tax_tables!$B$25*MAX(0,MIN(X92,tax_tables!$B$27*P92)-tax_tables!$B$26)+tax_tables!$B$28*MAX(0,MIN(X92,tax_tables!$B$29*P92)-tax_tables!$B$27*P92)+tax_tables!$B$30*MIN(X92,tax_tables!$B$31*P92) | AG92: =tax_tables!$B$25*MAX(0,MIN(Y92,tax_tables!$B$27*P92)-tax_tables!$B$26)+tax_tables!$B$28*MAX(0,MIN(Y92,tax_tables!$B$29*P92)-tax_tables!$B$27*P92)+tax_tables!$B$30*MIN(Y92,tax_tables!$B$31*P92) | AH92: =AF92+AG92 | AI92: =$B$13*AE92 | AJ92: =AD92-Z92-AA92-AH92-AI92 | AK92: =SUMPRODUCT(($B$72:$B$77=A92)*($D$72:$D$77="Other taxable income")*$C$72:$C$77)*O92 | AL92: =SUMPRODUCT(($B$72:$B$77=A92)*($D$72:$D$77="Tax-free money in")*$C$72:$C$77)*O92 | AM92: =SUMPRODUCT(($B$72:$B$77=A92)*($D$72:$D$77="Expense")*$C$72:$C$77)*O92 | AN92: =IF(OR($B$64="",A92<$B$64),1,0) | AO92: =AR91 | AP92: =AN92*AO92*properties!$J$2 | AQ92: =AN92*MIN(properties!$K$2,AO92+AP92) | AR92: =AN92*(AO92+AP92-AQ92) | AS92: =AN92*properties!$G$2*O92 | AT92: =(1-AN92)*$E$64*O92 | AU92: =AQ92+AS92+AT92 | AV92: =SUMIF(budget!$A$2:$A$300,"household",budget!$F$2:$F$300)*O92*IF(N92="",1,N92) | AW92: =SUMPRODUCT((other_budget!$C$2:$C$30<=A92)*(other_budget!$D$2:$D$30>=A92)*other_budget!$B$2:$B$30)*O92 | AX92: =SUMPRODUCT((kids_budget!$D$2:$D$40<=A92)*(kids_budget!$E$2:$E$40>=A92)*(kids_budget!$G$2:$G$40<>"college_funds")*kids_budget!$C$2:$C$40*((kids_budget!$F$2:$F$40="college")*S92+(kids_budget!$F$2:$F$40<>"college")*O92)) | AY92: =SUMPRODUCT((kids_budget!$D$2:$D$40<=A92)*(kids_budget!$E$2:$E$40>=A92)*(kids_budget!$G$2:$G$40="college_funds")*kids_budget!$C$2:$C$40*((kids_budget!$F$2:$F$40="college")*S92+(kids_budget!$F$2:$F$40<>"college")*O92)) | AZ92: =BC91 | BA92: =MIN(AY92,AZ92*(1+M92)) | BB92: =AY92-BA92 | BC92: =AZ92*(1+M92)-BA92 | BD92: =W92*healthcare!$B$2*R92 | BE92: =(1-W92)*2 | BF92: =BE92*healthcare!$B$3*12*R92 | BG92: =BE92*healthcare!$B$4*R92 | BH92: =AND(B92>=$B$44,B92<$B$44+$B$45)*1+AND(C92>=$B$46,C92<$B$46+$B$47)*1 | BI92: =BH92*$B$48*T92 | BJ92: =BD92+BF92+BG92+BI92 | BK92: =SUMPRODUCT((1-($B$65:$B$68>0)*(A92>=$B$65:$B$68))*(1-(($C$65:$C$68>0)*(A92>=$C$65:$C$68)))*(properties!$L$3:$L$6-properties!$M$3:$M$6))*O92+SUMPRODUCT((1-($B$65:$B$68>0)*(A92>=$B$65:$B$68))*(($C$65:$C$68>0)*(A92>=$C$65:$C$68))*($D$65:$D$68-$E$65:$E$68))*O92 | BL92: =SUMPRODUCT((1-($B$65:$B$68>0)*(A92>=$B$65:$B$68))*properties!$N$3:$N$6*(A92<=properties!$O$3:$O$6)) | BM92: =MAX(0,BK92-BL92) | BN92: =SUMPRODUCT(($B$64:$B$68=A92)*$G$64:$G$68) | BO92: =SUMPRODUCT(($B$64:$B$68=A92)*$H$64:$H$68) | BP92: =SUMPRODUCT(($B$64:$B$68=A92)*$I$64:$I$68) | BQ92: =AN92*properties!$C$2*(1+properties!$D$2)^(A92-household!$B$4+1) | BR92: =SUMPRODUCT((1-($B$65:$B$68>0)*(A92>=$B$65:$B$68))*properties!$C$3:$C$6*(1+properties!$D$3:$D$6)^(A92-household!$B$4+1)) | BS92: =IF(A92>=household!$B$6+$B$26,household!$B$11*12*$B$30*O92,0) | BT92: =IF(A92>=household!$B$9+$B$27,household!$B$12*12*$B$31*O92,0) | BU92: =IF(A92>=household!$B$6+$B$28,tax_tables!$B$19*12*P92*MIN(1,household!$B$13/40)*$B$32*(1+tax_tables!$B$20*(B92>=75)),0) | BV92: =IF(A92>=household!$B$9+$B$29,tax_tables!$B$19*12*P92*MIN(1,household!$B$14/40)*$B$33*(1+tax_tables!$B$20*(C92>=75)),0) | BW92: =IF(AND($B$36<>0,A92>=household!$B$6+$B$37),$B$36*(1+$B$17)^(MAX(household!$B$6+$B$37,household!$B$4-1)-household!$B$4+1)*(1+$B$40*$B$17)^(A92-MAX(household!$B$6+$B$37,household!$B$4-1)),0) | BX92: =IF(AND($B$38<>0,A92>=household!$B$9+$B$39),$B$38*(1+$B$17)^(MAX(household!$B$9+$B$39,household!$B$4-1)-household!$B$4+1)*(1+$B$40*$B$17)^(A92-MAX(household!$B$9+$B$39,household!$B$4-1)),0) | BY92: =CZ91 | BZ92: =DA91 | CA92: =$B$19*BY92 | CB92: =DB91 | CC92: =DC91 | CD92: =IF(B92>=tax_tables!$B$46,MAX(0,CB92)*INDEX(tax_tables!$N$5:$N$54,MATCH(MIN(B92-1,120),tax_tables!$M$5:$M$54,0)),0) | CE92: =IF(C92>=tax_tables!$B$46,MAX(0,CC92)*INDEX(tax_tables!$N$5:$N$54,MATCH(MIN(C92-1,120),tax_tables!$M$5:$M$54,0)),0) | CF92: =DD91 | CG92: =IF(OR($B$52="",$B$53=""),0,IF(AND(A92>=$B$52,A92<=$B$53),$B$51*O92,0)) | CH92: =MAX(0,CB92*(1+M92)-CD92) | CI92: =MAX(0,CC92*(1+M92)-CE92) | CJ92: =MIN(CG92,CH92+CI92) | CK92: =IF(CH92+CI92>1,CJ92*CH92/(CH92+CI92),0) | CL92: =CJ92-CK92 | CM92: =CM91-CW91+CU91+tax_tables!$B$32*P92*2 | CN92: =EC91-AI91 | CO92: =AJ92+F92+BW92+BX92+BK92+CA92+CD92+CE92+BN92+AK92+AL92+CJ92 | CP92: =D92+CN92-CO92 | CQ92: =MAX(0,MIN(CP92,BY92*(1+M92-$B$19))) | CR92: =MAX(0,MIN(CP92-CQ92,(CH92-CK92)+(CI92-CL92))) | CS92: =IF((CH92-CK92)+(CI92-CL92)>1,CR92*(CH92-CK92)/((CH92-CK92)+(CI92-CL92)),0) | CT92: =CR92-CS92 | CU92: =MAX(0,MIN(CP92-CQ92-CR92,CF92*(1+M92))) | CV92: =MAX(0,-CP92) | CW92: =MIN(CV92,MAX(0,CM92)) | CX92: =IF(BY92>0,MAX(0,1-BZ92/BY92),0) | CY92: =CQ92*CX92 | CZ92: =BY92*(1+M92-$B$19)-CQ92+(CV92-CW92) | DA92: =BZ92-(CQ92-CY92)+(CV92-CW92) | DB92: =CB92*(1+M92)-CD92-CS92-CK92+Z92+AB92 | DC92: =CC92*(1+M92)-CE92-CT92-CL92+AA92+AC92 | DD92: =CF92*(1+M92)-CU92+CW92 | DE92: =CD92+CK92+CS92 | DF92: =CA92*household!$B$15*$B$20*(1+tax_tables!$B$17) | DG92: =X92+BS92+BU92+BW92+DE92+DF92+CA92*household!$B$15*(1-$B$20)+(CY92+BO92)*household!$B$15*tax_tables!$B$18+(BP92+BM92+AK92)*household!$B$15-Z92 | DH92: =CE92+CL92+CT92 | DI92: =CA92*(1-household!$B$15)*$B$20*(1+tax_tables!$B$17) | DJ92: =Y92+BT92+BV92+BX92+DH92+DI92+CA92*(1-household!$B$15)*(1-$B$20)+(CY92+BO92)*(1-household!$B$15)*tax_tables!$B$18+(BP92+BM92+AK92)*(1-household!$B$15)-AA92 | DK92: =IF((DG92>=DJ92),MIN(0.5*(BW92+IF(B92>=65,DE92,0)),MAX(0,(DG92-DJ92)/2)),MIN(0.5*(BX92+IF(C92>=65,DH92,0)),MAX(0,(DJ92-DG92)/2))) | DL92: =DG92+IF((DG92>=DJ92),-DK92,DK92) | DM92: =BW92+IF(B92>=65,DE92,0)+IF((DG92>=DJ92),-DK92,DK92) | DN92: =MIN(BU92,tax_tables!$B$22*MAX(0,DL92-tax_tables!$B$21*P92)) | DO92: =MAX(0,DL92-DN92) | DP92: =DJ92+IF((DG92>=DJ92),DK92,-DK92) | DQ92: =BX92+IF(C92>=65,DH92,0)+IF((DG92>=DJ92),DK92,-DK92) | DR92: =MIN(BV92,tax_tables!$B$22*MAX(0,DP92-tax_tables!$B$21*P92)) | DS92: =MAX(0,DP92-DR92) | DT92: =BJ92-BD92 | DU92: =(tax_tables!$B$6-(tax_tables!$B$6-tax_tables!$B$7)*MIN(1,MAX(0,(DL92-tax_tables!$B$8*P92)/((tax_tables!$B$9-tax_tables!$B$8)*P92))))*P92+(B92>=65)*MAX(0,tax_tables!$B$10*P92-tax_tables!$B$12*MAX(0,DL92-tax_tables!$B$11*P92))+MIN(tax_tables!$B$13,DM92)+MIN(tax_tables!$B$14*P92,X92)+AF92+(DL92<=DP92)*MAX(0,DT92-MIN(0.03*DL92,tax_tables!$B$15*P92)) | DV92: =MAX(0,SUMPRODUCT((DO92>tax_tables!$E$5:$E$16*P92)*(DO92-tax_tables!$E$5:$E$16*P92)*tax_tables!$G$5:$G$16)-tax_tables!$B$5*DU92-tax_tables!$B$16*DF92) | DW92: =tax_tables!$B$35*Q92+(B92>=65)*MAX(0,tax_tables!$B$36*Q92-tax_tables!$B$12*MAX(0,DL92-tax_tables!$B$37*Q92))+MIN(tax_tables!$B$38,DM92)+AF92+(DL92<=DP92)*MAX(0,DT92-MIN(0.03*DL92,tax_tables!$B$39*Q92)) | DX92: =MAX(0,SUMPRODUCT((DO92>tax_tables!$I$5:$I$16*Q92)*(DO92-tax_tables!$I$5:$I$16*Q92)*tax_tables!$K$5:$K$16)-tax_tables!$B$34*DW92-tax_tables!$B$40*DF92-MAX(0,tax_tables!$B$41*Q92-tax_tables!$B$43*MAX(0,DL92-tax_tables!$B$42*Q92))) | DY92: =(tax_tables!$B$6-(tax_tables!$B$6-tax_tables!$B$7)*MIN(1,MAX(0,(DP92-tax_tables!$B$8*P92)/((tax_tables!$B$9-tax_tables!$B$8)*P92))))*P92+(C92>=65)*MAX(0,tax_tables!$B$10*P92-tax_tables!$B$12*MAX(0,DP92-tax_tables!$B$11*P92))+MIN(tax_tables!$B$13,DQ92)+MIN(tax_tables!$B$14*P92,Y92)+AG92+(DL92>DP92)*MAX(0,DT92-MIN(0.03*DP92,tax_tables!$B$15*P92)) | DZ92: =MAX(0,SUMPRODUCT((DS92>tax_tables!$E$5:$E$16*P92)*(DS92-tax_tables!$E$5:$E$16*P92)*tax_tables!$G$5:$G$16)-tax_tables!$B$5*DY92-tax_tables!$B$16*DI92) | EA92: =tax_tables!$B$35*Q92+(C92>=65)*MAX(0,tax_tables!$B$36*Q92-tax_tables!$B$12*MAX(0,DP92-tax_tables!$B$37*Q92))+MIN(tax_tables!$B$38,DQ92)+AG92+(DL92>DP92)*MAX(0,DT92-MIN(0.03*DP92,tax_tables!$B$39*Q92)) | EB92: =MAX(0,SUMPRODUCT((DS92>tax_tables!$I$5:$I$16*Q92)*(DS92-tax_tables!$I$5:$I$16*Q92)*tax_tables!$K$5:$K$16)-tax_tables!$B$34*EA92-tax_tables!$B$40*DI92-MAX(0,tax_tables!$B$41*Q92-tax_tables!$B$43*MAX(0,DP92-tax_tables!$B$42*Q92))) | EC92: =DV92+DZ92+DX92+EB92+DN92+DR92 | ED92: =CZ92+DB92+DC92+DD92 | EE92: =ED92+BQ92-AR92+BR92
A93: =A92+1 | B93: =A93-household!$B$6 | C93: =A93-household!$B$9 | D93: =AU93+AV93+AW93+AX93+BB93+BJ93+AM93 | E93: =CN93+AI93+AH93 | F93: =BS93+BT93+BU93+BV93 | G93: =CQ93+CR93+CU93+CD93+CE93+CA93-CV93+CJ93+CW93 | H93: =IF(BY93+CB93+CC93+CF93<=0,"",G93/(BY93+CB93+CC93+CF93)) | I93: =ED93/O93 | J93: =EE93/O93 | K93: =MAX(0,CP93-CQ93-CR93-CU93) | M93: =IF(L93="",$B$18,L93) | O93: =(1+$B$17)^(A93-household!$B$4+1) | P93: =(1+$B$17)^(A93-tax_tables!$B$4) | Q93: =(1+$B$17)^(A93-tax_tables!$B$4-MAX(0,MIN(A93,tax_tables!$B$45)-tax_tables!$B$44+1)) | R93: =(1+$B$21)^(A93-household!$B$4+1) | S93: =(1+$B$22)^(A93-household!$B$4+1) | T93: =(1+$B$23)^(A93-household!$B$4+1) | U93: =IF(A93<$B$5,1,0) | V93: =IF(A93<$B$6,1,0) | W93: =IF(U93+V93>0,1,0) | X93: =U93*$B$7*O93+SUMPRODUCT(($B$72:$B$77=A93)*($D$72:$D$77="Wages: person 1")*$C$72:$C$77)*O93 | Y93: =V93*$B$8*O93+SUMPRODUCT(($B$72:$B$77=A93)*($D$72:$D$77="Wages: person 2")*$C$72:$C$77)*O93 | Z93: =U93*$B$9*O93 | AA93: =V93*$B$10*O93 | AB93: =U93*$B$11*O93 | AC93: =V93*$B$12*O93 | AD93: =X93+Y93 | AE93: =AD93-Z93-AA93 | AF93: =tax_tables!$B$25*MAX(0,MIN(X93,tax_tables!$B$27*P93)-tax_tables!$B$26)+tax_tables!$B$28*MAX(0,MIN(X93,tax_tables!$B$29*P93)-tax_tables!$B$27*P93)+tax_tables!$B$30*MIN(X93,tax_tables!$B$31*P93) | AG93: =tax_tables!$B$25*MAX(0,MIN(Y93,tax_tables!$B$27*P93)-tax_tables!$B$26)+tax_tables!$B$28*MAX(0,MIN(Y93,tax_tables!$B$29*P93)-tax_tables!$B$27*P93)+tax_tables!$B$30*MIN(Y93,tax_tables!$B$31*P93) | AH93: =AF93+AG93 | AI93: =$B$13*AE93 | AJ93: =AD93-Z93-AA93-AH93-AI93 | AK93: =SUMPRODUCT(($B$72:$B$77=A93)*($D$72:$D$77="Other taxable income")*$C$72:$C$77)*O93 | AL93: =SUMPRODUCT(($B$72:$B$77=A93)*($D$72:$D$77="Tax-free money in")*$C$72:$C$77)*O93 | AM93: =SUMPRODUCT(($B$72:$B$77=A93)*($D$72:$D$77="Expense")*$C$72:$C$77)*O93 | AN93: =IF(OR($B$64="",A93<$B$64),1,0) | AO93: =AR92 | AP93: =AN93*AO93*properties!$J$2 | AQ93: =AN93*MIN(properties!$K$2,AO93+AP93) | AR93: =AN93*(AO93+AP93-AQ93) | AS93: =AN93*properties!$G$2*O93 | AT93: =(1-AN93)*$E$64*O93 | AU93: =AQ93+AS93+AT93 | AV93: =SUMIF(budget!$A$2:$A$300,"household",budget!$F$2:$F$300)*O93*IF(N93="",1,N93) | AW93: =SUMPRODUCT((other_budget!$C$2:$C$30<=A93)*(other_budget!$D$2:$D$30>=A93)*other_budget!$B$2:$B$30)*O93 | AX93: =SUMPRODUCT((kids_budget!$D$2:$D$40<=A93)*(kids_budget!$E$2:$E$40>=A93)*(kids_budget!$G$2:$G$40<>"college_funds")*kids_budget!$C$2:$C$40*((kids_budget!$F$2:$F$40="college")*S93+(kids_budget!$F$2:$F$40<>"college")*O93)) | AY93: =SUMPRODUCT((kids_budget!$D$2:$D$40<=A93)*(kids_budget!$E$2:$E$40>=A93)*(kids_budget!$G$2:$G$40="college_funds")*kids_budget!$C$2:$C$40*((kids_budget!$F$2:$F$40="college")*S93+(kids_budget!$F$2:$F$40<>"college")*O93)) | AZ93: =BC92 | BA93: =MIN(AY93,AZ93*(1+M93)) | BB93: =AY93-BA93 | BC93: =AZ93*(1+M93)-BA93 | BD93: =W93*healthcare!$B$2*R93 | BE93: =(1-W93)*2 | BF93: =BE93*healthcare!$B$3*12*R93 | BG93: =BE93*healthcare!$B$4*R93 | BH93: =AND(B93>=$B$44,B93<$B$44+$B$45)*1+AND(C93>=$B$46,C93<$B$46+$B$47)*1 | BI93: =BH93*$B$48*T93 | BJ93: =BD93+BF93+BG93+BI93 | BK93: =SUMPRODUCT((1-($B$65:$B$68>0)*(A93>=$B$65:$B$68))*(1-(($C$65:$C$68>0)*(A93>=$C$65:$C$68)))*(properties!$L$3:$L$6-properties!$M$3:$M$6))*O93+SUMPRODUCT((1-($B$65:$B$68>0)*(A93>=$B$65:$B$68))*(($C$65:$C$68>0)*(A93>=$C$65:$C$68))*($D$65:$D$68-$E$65:$E$68))*O93 | BL93: =SUMPRODUCT((1-($B$65:$B$68>0)*(A93>=$B$65:$B$68))*properties!$N$3:$N$6*(A93<=properties!$O$3:$O$6)) | BM93: =MAX(0,BK93-BL93) | BN93: =SUMPRODUCT(($B$64:$B$68=A93)*$G$64:$G$68) | BO93: =SUMPRODUCT(($B$64:$B$68=A93)*$H$64:$H$68) | BP93: =SUMPRODUCT(($B$64:$B$68=A93)*$I$64:$I$68) | BQ93: =AN93*properties!$C$2*(1+properties!$D$2)^(A93-household!$B$4+1) | BR93: =SUMPRODUCT((1-($B$65:$B$68>0)*(A93>=$B$65:$B$68))*properties!$C$3:$C$6*(1+properties!$D$3:$D$6)^(A93-household!$B$4+1)) | BS93: =IF(A93>=household!$B$6+$B$26,household!$B$11*12*$B$30*O93,0) | BT93: =IF(A93>=household!$B$9+$B$27,household!$B$12*12*$B$31*O93,0) | BU93: =IF(A93>=household!$B$6+$B$28,tax_tables!$B$19*12*P93*MIN(1,household!$B$13/40)*$B$32*(1+tax_tables!$B$20*(B93>=75)),0) | BV93: =IF(A93>=household!$B$9+$B$29,tax_tables!$B$19*12*P93*MIN(1,household!$B$14/40)*$B$33*(1+tax_tables!$B$20*(C93>=75)),0) | BW93: =IF(AND($B$36<>0,A93>=household!$B$6+$B$37),$B$36*(1+$B$17)^(MAX(household!$B$6+$B$37,household!$B$4-1)-household!$B$4+1)*(1+$B$40*$B$17)^(A93-MAX(household!$B$6+$B$37,household!$B$4-1)),0) | BX93: =IF(AND($B$38<>0,A93>=household!$B$9+$B$39),$B$38*(1+$B$17)^(MAX(household!$B$9+$B$39,household!$B$4-1)-household!$B$4+1)*(1+$B$40*$B$17)^(A93-MAX(household!$B$9+$B$39,household!$B$4-1)),0) | BY93: =CZ92 | BZ93: =DA92 | CA93: =$B$19*BY93 | CB93: =DB92 | CC93: =DC92 | CD93: =IF(B93>=tax_tables!$B$46,MAX(0,CB93)*INDEX(tax_tables!$N$5:$N$54,MATCH(MIN(B93-1,120),tax_tables!$M$5:$M$54,0)),0) | CE93: =IF(C93>=tax_tables!$B$46,MAX(0,CC93)*INDEX(tax_tables!$N$5:$N$54,MATCH(MIN(C93-1,120),tax_tables!$M$5:$M$54,0)),0) | CF93: =DD92 | CG93: =IF(OR($B$52="",$B$53=""),0,IF(AND(A93>=$B$52,A93<=$B$53),$B$51*O93,0)) | CH93: =MAX(0,CB93*(1+M93)-CD93) | CI93: =MAX(0,CC93*(1+M93)-CE93) | CJ93: =MIN(CG93,CH93+CI93) | CK93: =IF(CH93+CI93>1,CJ93*CH93/(CH93+CI93),0) | CL93: =CJ93-CK93 | CM93: =CM92-CW92+CU92+tax_tables!$B$32*P93*2 | CN93: =EC92-AI92 | CO93: =AJ93+F93+BW93+BX93+BK93+CA93+CD93+CE93+BN93+AK93+AL93+CJ93 | CP93: =D93+CN93-CO93 | CQ93: =MAX(0,MIN(CP93,BY93*(1+M93-$B$19))) | CR93: =MAX(0,MIN(CP93-CQ93,(CH93-CK93)+(CI93-CL93))) | CS93: =IF((CH93-CK93)+(CI93-CL93)>1,CR93*(CH93-CK93)/((CH93-CK93)+(CI93-CL93)),0) | CT93: =CR93-CS93 | CU93: =MAX(0,MIN(CP93-CQ93-CR93,CF93*(1+M93))) | CV93: =MAX(0,-CP93) | CW93: =MIN(CV93,MAX(0,CM93)) | CX93: =IF(BY93>0,MAX(0,1-BZ93/BY93),0) | CY93: =CQ93*CX93 | CZ93: =BY93*(1+M93-$B$19)-CQ93+(CV93-CW93) | DA93: =BZ93-(CQ93-CY93)+(CV93-CW93) | DB93: =CB93*(1+M93)-CD93-CS93-CK93+Z93+AB93 | DC93: =CC93*(1+M93)-CE93-CT93-CL93+AA93+AC93 | DD93: =CF93*(1+M93)-CU93+CW93 | DE93: =CD93+CK93+CS93 | DF93: =CA93*household!$B$15*$B$20*(1+tax_tables!$B$17) | DG93: =X93+BS93+BU93+BW93+DE93+DF93+CA93*household!$B$15*(1-$B$20)+(CY93+BO93)*household!$B$15*tax_tables!$B$18+(BP93+BM93+AK93)*household!$B$15-Z93 | DH93: =CE93+CL93+CT93 | DI93: =CA93*(1-household!$B$15)*$B$20*(1+tax_tables!$B$17) | DJ93: =Y93+BT93+BV93+BX93+DH93+DI93+CA93*(1-household!$B$15)*(1-$B$20)+(CY93+BO93)*(1-household!$B$15)*tax_tables!$B$18+(BP93+BM93+AK93)*(1-household!$B$15)-AA93 | DK93: =IF((DG93>=DJ93),MIN(0.5*(BW93+IF(B93>=65,DE93,0)),MAX(0,(DG93-DJ93)/2)),MIN(0.5*(BX93+IF(C93>=65,DH93,0)),MAX(0,(DJ93-DG93)/2))) | DL93: =DG93+IF((DG93>=DJ93),-DK93,DK93) | DM93: =BW93+IF(B93>=65,DE93,0)+IF((DG93>=DJ93),-DK93,DK93) | DN93: =MIN(BU93,tax_tables!$B$22*MAX(0,DL93-tax_tables!$B$21*P93)) | DO93: =MAX(0,DL93-DN93) | DP93: =DJ93+IF((DG93>=DJ93),DK93,-DK93) | DQ93: =BX93+IF(C93>=65,DH93,0)+IF((DG93>=DJ93),DK93,-DK93) | DR93: =MIN(BV93,tax_tables!$B$22*MAX(0,DP93-tax_tables!$B$21*P93)) | DS93: =MAX(0,DP93-DR93) | DT93: =BJ93-BD93 | DU93: =(tax_tables!$B$6-(tax_tables!$B$6-tax_tables!$B$7)*MIN(1,MAX(0,(DL93-tax_tables!$B$8*P93)/((tax_tables!$B$9-tax_tables!$B$8)*P93))))*P93+(B93>=65)*MAX(0,tax_tables!$B$10*P93-tax_tables!$B$12*MAX(0,DL93-tax_tables!$B$11*P93))+MIN(tax_tables!$B$13,DM93)+MIN(tax_tables!$B$14*P93,X93)+AF93+(DL93<=DP93)*MAX(0,DT93-MIN(0.03*DL93,tax_tables!$B$15*P93)) | DV93: =MAX(0,SUMPRODUCT((DO93>tax_tables!$E$5:$E$16*P93)*(DO93-tax_tables!$E$5:$E$16*P93)*tax_tables!$G$5:$G$16)-tax_tables!$B$5*DU93-tax_tables!$B$16*DF93) | DW93: =tax_tables!$B$35*Q93+(B93>=65)*MAX(0,tax_tables!$B$36*Q93-tax_tables!$B$12*MAX(0,DL93-tax_tables!$B$37*Q93))+MIN(tax_tables!$B$38,DM93)+AF93+(DL93<=DP93)*MAX(0,DT93-MIN(0.03*DL93,tax_tables!$B$39*Q93)) | DX93: =MAX(0,SUMPRODUCT((DO93>tax_tables!$I$5:$I$16*Q93)*(DO93-tax_tables!$I$5:$I$16*Q93)*tax_tables!$K$5:$K$16)-tax_tables!$B$34*DW93-tax_tables!$B$40*DF93-MAX(0,tax_tables!$B$41*Q93-tax_tables!$B$43*MAX(0,DL93-tax_tables!$B$42*Q93))) | DY93: =(tax_tables!$B$6-(tax_tables!$B$6-tax_tables!$B$7)*MIN(1,MAX(0,(DP93-tax_tables!$B$8*P93)/((tax_tables!$B$9-tax_tables!$B$8)*P93))))*P93+(C93>=65)*MAX(0,tax_tables!$B$10*P93-tax_tables!$B$12*MAX(0,DP93-tax_tables!$B$11*P93))+MIN(tax_tables!$B$13,DQ93)+MIN(tax_tables!$B$14*P93,Y93)+AG93+(DL93>DP93)*MAX(0,DT93-MIN(0.03*DP93,tax_tables!$B$15*P93)) | DZ93: =MAX(0,SUMPRODUCT((DS93>tax_tables!$E$5:$E$16*P93)*(DS93-tax_tables!$E$5:$E$16*P93)*tax_tables!$G$5:$G$16)-tax_tables!$B$5*DY93-tax_tables!$B$16*DI93) | EA93: =tax_tables!$B$35*Q93+(C93>=65)*MAX(0,tax_tables!$B$36*Q93-tax_tables!$B$12*MAX(0,DP93-tax_tables!$B$37*Q93))+MIN(tax_tables!$B$38,DQ93)+AG93+(DL93>DP93)*MAX(0,DT93-MIN(0.03*DP93,tax_tables!$B$39*Q93)) | EB93: =MAX(0,SUMPRODUCT((DS93>tax_tables!$I$5:$I$16*Q93)*(DS93-tax_tables!$I$5:$I$16*Q93)*tax_tables!$K$5:$K$16)-tax_tables!$B$34*EA93-tax_tables!$B$40*DI93-MAX(0,tax_tables!$B$41*Q93-tax_tables!$B$43*MAX(0,DP93-tax_tables!$B$42*Q93))) | EC93: =DV93+DZ93+DX93+EB93+DN93+DR93 | ED93: =CZ93+DB93+DC93+DD93 | EE93: =ED93+BQ93-AR93+BR93
... A123: =A122+1 | B123: =A123-household!$B$6 | C123: =A123-household!$B$9 | D123: =AU123+AV123+AW123+AX123+BB123+BJ123+AM123 | E123: =CN123+AI123+AH123 | F123: =BS123+BT123+BU123+BV123 | G123: =CQ123+CR123+CU123+CD123+CE123+CA123-CV123+CJ123+CW123 | H123: =IF(BY123+CB123+CC123+CF123<=0,"",G123/(BY123+CB123+CC123+CF123)) | I123: =ED123/O123 | J123: =EE123/O123 | K123: =MAX(0,CP123-CQ123-CR123-CU123) | M123: =IF(L123="",$B$18,L123) | O123: =(1+$B$17)^(A123-household!$B$4+1) | P123: =(1+$B$17)^(A123-tax_tables!$B$4) | Q123: =(1+$B$17)^(A123-tax_tables!$B$4-MAX(0,MIN(A123,tax_tables!$B$45)-tax_tables!$B$44+1)) | R123: =(1+$B$21)^(A123-household!$B$4+1) | S123: =(1+$B$22)^(A123-household!$B$4+1) | T123: =(1+$B$23)^(A123-household!$B$4+1) | U123: =IF(A123<$B$5,1,0) | V123: =IF(A123<$B$6,1,0) | W123: =IF(U123+V123>0,1,0) | X123: =U123*$B$7*O123+SUMPRODUCT(($B$72:$B$77=A123)*($D$72:$D$77="Wages: person 1")*$C$72:$C$77)*O123 | Y123: =V123*$B$8*O123+SUMPRODUCT(($B$72:$B$77=A123)*($D$72:$D$77="Wages: person 2")*$C$72:$C$77)*O123 | Z123: =U123*$B$9*O123 | AA123: =V123*$B$10*O123 | AB123: =U123*$B$11*O123 | AC123: =V123*$B$12*O123 | AD123: =X123+Y123 | AE123: =AD123-Z123-AA123 | AF123: =tax_tables!$B$25*MAX(0,MIN(X123,tax_tables!$B$27*P123)-tax_tables!$B$26)+tax_tables!$B$28*MAX(0,MIN(X123,tax_tables!$B$29*P123)-tax_tables!$B$27*P123)+tax_tables!$B$30*MIN(X123,tax_tables!$B$31*P123) | AG123: =tax_tables!$B$25*MAX(0,MIN(Y123,tax_tables!$B$27*P123)-tax_tables!$B$26)+tax_tables!$B$28*MAX(0,MIN(Y123,tax_tables!$B$29*P123)-tax_tables!$B$27*P123)+tax_tables!$B$30*MIN(Y123,tax_tables!$B$31*P123) | AH123: =AF123+AG123 | AI123: =$B$13*AE123 | AJ123: =AD123-Z123-AA123-AH123-AI123 | AK123: =SUMPRODUCT(($B$72:$B$77=A123)*($D$72:$D$77="Other taxable income")*$C$72:$C$77)*O123 | AL123: =SUMPRODUCT(($B$72:$B$77=A123)*($D$72:$D$77="Tax-free money in")*$C$72:$C$77)*O123 | AM123: =SUMPRODUCT(($B$72:$B$77=A123)*($D$72:$D$77="Expense")*$C$72:$C$77)*O123 | AN123: =IF(OR($B$64="",A123<$B$64),1,0) | AO123: =AR122 | AP123: =AN123*AO123*properties!$J$2 | AQ123: =AN123*MIN(properties!$K$2,AO123+AP123) | AR123: =AN123*(AO123+AP123-AQ123) | AS123: =AN123*properties!$G$2*O123 | AT123: =(1-AN123)*$E$64*O123 | AU123: =AQ123+AS123+AT123 | AV123: =SUMIF(budget!$A$2:$A$300,"household",budget!$F$2:$F$300)*O123*IF(N123="",1,N123) | AW123: =SUMPRODUCT((other_budget!$C$2:$C$30<=A123)*(other_budget!$D$2:$D$30>=A123)*other_budget!$B$2:$B$30)*O123 | AX123: =SUMPRODUCT((kids_budget!$D$2:$D$40<=A123)*(kids_budget!$E$2:$E$40>=A123)*(kids_budget!$G$2:$G$40<>"college_funds")*kids_budget!$C$2:$C$40*((kids_budget!$F$2:$F$40="college")*S123+(kids_budget!$F$2:$F$40<>"college")*O123)) | AY123: =SUMPRODUCT((kids_budget!$D$2:$D$40<=A123)*(kids_budget!$E$2:$E$40>=A123)*(kids_budget!$G$2:$G$40="college_funds")*kids_budget!$C$2:$C$40*((kids_budget!$F$2:$F$40="college")*S123+(kids_budget!$F$2:$F$40<>"college")*O123)) | AZ123: =BC122 | BA123: =MIN(AY123,AZ123*(1+M123)) | BB123: =AY123-BA123 | BC123: =AZ123*(1+M123)-BA123 | BD123: =W123*healthcare!$B$2*R123 | BE123: =(1-W123)*2 | BF123: =BE123*healthcare!$B$3*12*R123 | BG123: =BE123*healthcare!$B$4*R123 | BH123: =AND(B123>=$B$44,B123<$B$44+$B$45)*1+AND(C123>=$B$46,C123<$B$46+$B$47)*1 | BI123: =BH123*$B$48*T123 | BJ123: =BD123+BF123+BG123+BI123 | BK123: =SUMPRODUCT((1-($B$65:$B$68>0)*(A123>=$B$65:$B$68))*(1-(($C$65:$C$68>0)*(A123>=$C$65:$C$68)))*(properties!$L$3:$L$6-properties!$M$3:$M$6))*O123+SUMPRODUCT((1-($B$65:$B$68>0)*(A123>=$B$65:$B$68))*(($C$65:$C$68>0)*(A123>=$C$65:$C$68))*($D$65:$D$68-$E$65:$E$68))*O123 | BL123: =SUMPRODUCT((1-($B$65:$B$68>0)*(A123>=$B$65:$B$68))*properties!$N$3:$N$6*(A123<=properties!$O$3:$O$6)) | BM123: =MAX(0,BK123-BL123) | BN123: =SUMPRODUCT(($B$64:$B$68=A123)*$G$64:$G$68) | BO123: =SUMPRODUCT(($B$64:$B$68=A123)*$H$64:$H$68) | BP123: =SUMPRODUCT(($B$64:$B$68=A123)*$I$64:$I$68) | BQ123: =AN123*properties!$C$2*(1+properties!$D$2)^(A123-household!$B$4+1) | BR123: =SUMPRODUCT((1-($B$65:$B$68>0)*(A123>=$B$65:$B$68))*properties!$C$3:$C$6*(1+properties!$D$3:$D$6)^(A123-household!$B$4+1)) | BS123: =IF(A123>=household!$B$6+$B$26,household!$B$11*12*$B$30*O123,0) | BT123: =IF(A123>=household!$B$9+$B$27,household!$B$12*12*$B$31*O123,0) | BU123: =IF(A123>=household!$B$6+$B$28,tax_tables!$B$19*12*P123*MIN(1,household!$B$13/40)*$B$32*(1+tax_tables!$B$20*(B123>=75)),0) | BV123: =IF(A123>=household!$B$9+$B$29,tax_tables!$B$19*12*P123*MIN(1,household!$B$14/40)*$B$33*(1+tax_tables!$B$20*(C123>=75)),0) | BW123: =IF(AND($B$36<>0,A123>=household!$B$6+$B$37),$B$36*(1+$B$17)^(MAX(household!$B$6+$B$37,household!$B$4-1)-household!$B$4+1)*(1+$B$40*$B$17)^(A123-MAX(household!$B$6+$B$37,household!$B$4-1)),0) | BX123: =IF(AND($B$38<>0,A123>=household!$B$9+$B$39),$B$38*(1+$B$17)^(MAX(household!$B$9+$B$39,household!$B$4-1)-household!$B$4+1)*(1+$B$40*$B$17)^(A123-MAX(household!$B$9+$B$39,household!$B$4-1)),0) | BY123: =CZ122 | BZ123: =DA122 | CA123: =$B$19*BY123 | CB123: =DB122 | CC123: =DC122 | CD123: =IF(B123>=tax_tables!$B$46,MAX(0,CB123)*INDEX(tax_tables!$N$5:$N$54,MATCH(MIN(B123-1,120),tax_tables!$M$5:$M$54,0)),0) | CE123: =IF(C123>=tax_tables!$B$46,MAX(0,CC123)*INDEX(tax_tables!$N$5:$N$54,MATCH(MIN(C123-1,120),tax_tables!$M$5:$M$54,0)),0) | CF123: =DD122 | CG123: =IF(OR($B$52="",$B$53=""),0,IF(AND(A123>=$B$52,A123<=$B$53),$B$51*O123,0)) | CH123: =MAX(0,CB123*(1+M123)-CD123) | CI123: =MAX(0,CC123*(1+M123)-CE123) | CJ123: =MIN(CG123,CH123+CI123) | CK123: =IF(CH123+CI123>1,CJ123*CH123/(CH123+CI123),0) | CL123: =CJ123-CK123 | CM123: =CM122-CW122+CU122+tax_tables!$B$32*P123*2 | CN123: =EC122-AI122 | CO123: =AJ123+F123+BW123+BX123+BK123+CA123+CD123+CE123+BN123+AK123+AL123+CJ123 | CP123: =D123+CN123-CO123 | CQ123: =MAX(0,MIN(CP123,BY123*(1+M123-$B$19))) | CR123: =MAX(0,MIN(CP123-CQ123,(CH123-CK123)+(CI123-CL123))) | CS123: =IF((CH123-CK123)+(CI123-CL123)>1,CR123*(CH123-CK123)/((CH123-CK123)+(CI123-CL123)),0) | CT123: =CR123-CS123 | CU123: =MAX(0,MIN(CP123-CQ123-CR123,CF123*(1+M123))) | CV123: =MAX(0,-CP123) | CW123: =MIN(CV123,MAX(0,CM123)) | CX123: =IF(BY123>0,MAX(0,1-BZ123/BY123),0) | CY123: =CQ123*CX123 | CZ123: =BY123*(1+M123-$B$19)-CQ123+(CV123-CW123) | DA123: =BZ123-(CQ123-CY123)+(CV123-CW123) | DB123: =CB123*(1+M123)-CD123-CS123-CK123+Z123+AB123 | DC123: =CC123*(1+M123)-CE123-CT123-CL123+AA123+AC123 | DD123: =CF123*(1+M123)-CU123+CW123 | DE123: =CD123+CK123+CS123 | DF123: =CA123*household!$B$15*$B$20*(1+tax_tables!$B$17) | DG123: =X123+BS123+BU123+BW123+DE123+DF123+CA123*household!$B$15*(1-$B$20)+(CY123+BO123)*household!$B$15*tax_tables!$B$18+(BP123+BM123+AK123)*household!$B$15-Z123 | DH123: =CE123+CL123+CT123 | DI123: =CA123*(1-household!$B$15)*$B$20*(1+tax_tables!$B$17) | DJ123: =Y123+BT123+BV123+BX123+DH123+DI123+CA123*(1-household!$B$15)*(1-$B$20)+(CY123+BO123)*(1-household!$B$15)*tax_tables!$B$18+(BP123+BM123+AK123)*(1-household!$B$15)-AA123 | DK123: =IF((DG123>=DJ123),MIN(0.5*(BW123+IF(B123>=65,DE123,0)),MAX(0,(DG123-DJ123)/2)),MIN(0.5*(BX123+IF(C123>=65,DH123,0)),MAX(0,(DJ123-DG123)/2))) | DL123: =DG123+IF((DG123>=DJ123),-DK123,DK123) | DM123: =BW123+IF(B123>=65,DE123,0)+IF((DG123>=DJ123),-DK123,DK123) | DN123: =MIN(BU123,tax_tables!$B$22*MAX(0,DL123-tax_tables!$B$21*P123)) | DO123: =MAX(0,DL123-DN123) | DP123: =DJ123+IF((DG123>=DJ123),DK123,-DK123) | DQ123: =BX123+IF(C123>=65,DH123,0)+IF((DG123>=DJ123),DK123,-DK123) | DR123: =MIN(BV123,tax_tables!$B$22*MAX(0,DP123-tax_tables!$B$21*P123)) | DS123: =MAX(0,DP123-DR123) | DT123: =BJ123-BD123 | DU123: =(tax_tables!$B$6-(tax_tables!$B$6-tax_tables!$B$7)*MIN(1,MAX(0,(DL123-tax_tables!$B$8*P123)/((tax_tables!$B$9-tax_tables!$B$8)*P123))))*P123+(B123>=65)*MAX(0,tax_tables!$B$10*P123-tax_tables!$B$12*MAX(0,DL123-tax_tables!$B$11*P123))+MIN(tax_tables!$B$13,DM123)+MIN(tax_tables!$B$14*P123,X123)+AF123+(DL123<=DP123)*MAX(0,DT123-MIN(0.03*DL123,tax_tables!$B$15*P123)) | DV123: =MAX(0,SUMPRODUCT((DO123>tax_tables!$E$5:$E$16*P123)*(DO123-tax_tables!$E$5:$E$16*P123)*tax_tables!$G$5:$G$16)-tax_tables!$B$5*DU123-tax_tables!$B$16*DF123) | DW123: =tax_tables!$B$35*Q123+(B123>=65)*MAX(0,tax_tables!$B$36*Q123-tax_tables!$B$12*MAX(0,DL123-tax_tables!$B$37*Q123))+MIN(tax_tables!$B$38,DM123)+AF123+(DL123<=DP123)*MAX(0,DT123-MIN(0.03*DL123,tax_tables!$B$39*Q123)) | DX123: =MAX(0,SUMPRODUCT((DO123>tax_tables!$I$5:$I$16*Q123)*(DO123-tax_tables!$I$5:$I$16*Q123)*tax_tables!$K$5:$K$16)-tax_tables!$B$34*DW123-tax_tables!$B$40*DF123-MAX(0,tax_tables!$B$41*Q123-tax_tables!$B$43*MAX(0,DL123-tax_tables!$B$42*Q123))) | DY123: =(tax_tables!$B$6-(tax_tables!$B$6-tax_tables!$B$7)*MIN(1,MAX(0,(DP123-tax_tables!$B$8*P123)/((tax_tables!$B$9-tax_tables!$B$8)*P123))))*P123+(C123>=65)*MAX(0,tax_tables!$B$10*P123-tax_tables!$B$12*MAX(0,DP123-tax_tables!$B$11*P123))+MIN(tax_tables!$B$13,DQ123)+MIN(tax_tables!$B$14*P123,Y123)+AG123+(DL123>DP123)*MAX(0,DT123-MIN(0.03*DP123,tax_tables!$B$15*P123)) | DZ123: =MAX(0,SUMPRODUCT((DS123>tax_tables!$E$5:$E$16*P123)*(DS123-tax_tables!$E$5:$E$16*P123)*tax_tables!$G$5:$G$16)-tax_tables!$B$5*DY123-tax_tables!$B$16*DI123) | EA123: =tax_tables!$B$35*Q123+(C123>=65)*MAX(0,tax_tables!$B$36*Q123-tax_tables!$B$12*MAX(0,DP123-tax_tables!$B$37*Q123))+MIN(tax_tables!$B$38,DQ123)+AG123+(DL123>DP123)*MAX(0,DT123-MIN(0.03*DP123,tax_tables!$B$39*Q123)) | EB123: =MAX(0,SUMPRODUCT((DS123>tax_tables!$I$5:$I$16*Q123)*(DS123-tax_tables!$I$5:$I$16*Q123)*tax_tables!$K$5:$K$16)-tax_tables!$B$34*EA123-tax_tables!$B$40*DI123-MAX(0,tax_tables!$B$41*Q123-tax_tables!$B$43*MAX(0,DP123-tax_tables!$B$42*Q123))) | EC123: =DV123+DZ123+DX123+EB123+DN123+DR123 | ED123: =CZ123+DB123+DC123+DD123 | EE123: =ED123+BQ123-AR123+BR123

Sheet household
A1: key | B1: value | C1: notes
A2: country | B2: CA | C2: US = United States, CA = Canada. Fixed when the workbook is built
A3: region | B3: British Columbia | C3: State or province (its tax brackets are on the tax_tables tab)
A4: start_year | B4: 2027 | C4: First year the model covers. Balances on the assets tab are as of 1 January of it; 'today's dollars' are the year before
A5: p1_name | B5: Sam | C5: Person 1
A6: p1_born | B6: 1967 | C6: Birth year
A7: p1_sex | B7: M | C7: M or F: which column of the life table the Monte Carlo uses for person 1
A8: p2_name | B8: Taylor | C8: Person 2
A9: p2_born | B9: 1969 | C9: Birth year
A10: p2_sex | B10: F | C10: M or F for person 2
A11: p1_cpp_at_65 | B11: 1320 | C11: Person 1's CPP at 65, per month, today's $ - from My Service Canada Account
A12: p2_cpp_at_65 | B12: 1040 | C12: Person 2's CPP at 65
A13: p1_oas_years | B13: 40 | C13: Person 1's years in Canada after 18 (40 = full OAS)
A14: p2_oas_years | B14: 34 | C14: Person 2's years in Canada after 18
A15: joint_share_p1 | B15: 0.5 | C15: Share of joint investment and rental income taxed to person 1 (usually 50%)
A16: tfsa_room | B16: 42000 | C16: Unused TFSA room for the two of you on 1 January of the first year (incl. that year's new room)
A18: Kids
A19: name | B19: born | C19: (not used) | D19: notes
A20: Morgan | B20: 2007 | D20: At UBC
A21: Jamie | B21: 2010 | D21: Starts university in 2028
A28: Kids' costs are on the kids_budget tab (one line per kid and cost).

Sheet budget
A1: model_line | B1: expense_group | C1: category | D1: subcategory | E1: annual_actual | F1: retirement_budget | G1: source_period | H1: n_transactions | I1: notes | K1: Household living budget used by the model | L1: =SUMIF($A$2:$A$300,"household",$F$2:$F$300)
A2: household | B2: Essential | C2: Groceries | D2: General | E2: 17200 | F2: 17200 | G2: example | H2: 230 | K2: All lines, 12-month actual | L2: =SUM($E$2:$E$300)
A3: household | B3: Essential | C3: Utilities | D3: Electric, gas, water | E3: 2600 | F3: 2600 | G3: example | H3: 12
A4: household | B4: Essential | C4: Utilities | D4: Phone & internet | E4: 2900 | F4: 2900 | G4: example | H4: 24 | K4: model_line: 'household' lines are summed and grow with inflation. Other lines (housing, healthcare, taxes, kids) are modeled on their own tabs and shown here only for reference.
A5: household | B5: Essential | C5: Insurance | D5: General | E5: 3800 | F5: 3800 | G5: example | H5: 4 | K5: Edit column F (retirement_budget) to test a different budget; column E is what you actually spent.
A6: household | B6: Essential | C6: Transportation | D6: Gas & parking | E6: 4200 | F6: 4200 | G6: example | H6: 120
A7: household | B7: Essential | C7: Transportation | D7: Car maintenance | E7: 1600 | F7: 1600 | G7: example | H7: 4
A8: household | B8: Essential | C8: Personal Care | D8: General | E8: 1900 | F8: 1900 | G8: example | H8: 28
A9: household | B9: Discretionary | C9: Dining | D9: Restaurants & takeout | E9: 8900 | F9: 8900 | G9: example | H9: 170
A10: household | B10: Discretionary | C10: Travel | D10: Flights, hotels, rentals | E10: 13000 | F10: 15000 | G10: example | H10: 32 | I10: More travel once retired
A11: household | B11: Discretionary | C11: Shopping | D11: General | E11: 9400 | F11: 9000 | G11: example | H11: 210
A12: household | B12: Discretionary | C12: Entertainment | D12: General | E12: 2800 | F12: 2800 | G12: example | H12: 40
A13: household | B13: Discretionary | C13: Subscriptions | D13: Streaming & software | E13: 1100 | F13: 1100 | G13: example | H13: 44
A14: household | B14: Discretionary | C14: Gifts & Donations | D14: General | E14: 4200 | F14: 4200 | G14: example | H14: 20
A15: household | B15: Discretionary | C15: Home | D15: Household goods | E15: 2600 | F15: 2600 | G15: example | H15: 40
A16: household | B16: Discretionary | C16: Recreation | D16: Gym, sports | E16: 3500 | F16: 3500 | G16: example | H16: 12
A17: housing | B17: Housing | C17: Housing | D17: Mortgage | E17: 36400 | G17: example | H17: 26 | I17: Modeled from the properties tab
A18: housing | B18: Housing | C18: Housing | D18: Property tax, strata, insurance | E18: 11800 | G18: example | H18: 16 | I18: Modeled from the properties tab (carrying_costs)
A19: healthcare | B19: Healthcare | C19: Healthcare | D19: Dental, drugs, physio | E19: 2900 | G19: example | H19: 30 | I19: Modeled on the healthcare tab
A20: kids | B20: Kids | C20: Kids | D20: Support | E20: 14400 | G20: example | H20: 40 | I20: Modeled on the kids_budget tab

Sheet kids_budget
A1: kid | B1: item | C1: annual_amount_today | D1: start_year | E1: end_year | F1: inflation | G1: paid_from | H1: notes
A2: Morgan | B2: UBC tuition + books | C2: 9500 | D2: 2027 | E2: 2029 | F2: college | G2: college_funds | H2: RESP pays first
A3: Morgan | B3: Living at home - extra costs | C3: 6000 | D3: 2027 | E3: 2029 | F3: general | G3: parents
A4: Morgan | B4: Help after graduating (rent share) | C4: 12000 | D4: 2030 | E4: 2032 | F4: general | G4: parents | H4: Vancouver rents
A5: Jamie | B5: University tuition + residence (out of town) | C5: 24000 | D5: 2028 | E5: 2031 | F5: college | G5: college_funds
A6: Jamie | B6: Spending money | C6: 4800 | D6: 2028 | E6: 2031 | F6: general | G6: parents
A7: Jamie | B7: Help after graduating | C7: 9000 | D7: 2032 | E7: 2033 | F7: general | G7: parents
A8: Jamie | B8: Master's degree | C8: 18000 | D8: 2034 | E8: 2035 | F8: college | G8: parents
A42: One line per kid and cost, per year in today's dollars, for the years start_year-end_year. inflation: 'college' lines rise with college cost growth, 'general' with inflation. paid_from: 'college_funds' lines are paid by the RESPs first and only the shortfall comes from you; 'parents' lines come straight from you. Add rows above row 41.

Sheet other_budget
A1: item | B1: annual_amount_today | C1: start_year | D1: end_year | E1: notes
A2: Home maintenance and renovations | B2: 10000 | C2: 2027 | D2: 2060
A3: Car replacement | B3: 7000 | C3: 2027 | D3: 2055
A4: Cabin trips / cottage share | B4: 3000 | C4: 2027 | D4: 2045
A32: Big irregular costs averaged per year (renovations, cars, gifts), in today's dollars, for the years start_year-end_year. Add rows above row 31.

Sheet properties
A1: property | B1: type | C1: value_now | D1: appreciation | E1: selling_cost_pct | F1: cost_basis | G1: carrying_costs | H1: property_tax | I1: mortgage_balance | J1: mortgage_rate | K1: mortgage_payment | L1: rent | M1: cash_costs | N1: depreciation | O1: depreciation_end_year | P1: accum_depreciation | Q1: notes
A2: House (East Vancouver) | B2: primary | C2: 1850000 | D2: 0.03 | E2: 0.04 | F2: 780000 | G2: 11800 | H2: 6300 | I2: 340000 | J2: 0.0449 | K2: 36400 | Q2: Principal residence: the gain on sale isn't taxed. Carrying costs: property tax $6,300, insurance $3,000, utilities/other $2,500
A3: Condo rental (Burnaby) | B3: rental | C3: 720000 | D3: 0.025 | E3: 0.045 | F3: 540000 | L3: 32400 | M3: 11800 | N3: 9500 | O3: 2045 | P3: 48000 | Q3: Bought 2019 for $540,000. Cash costs: strata $4,600, property tax $2,400, insurance $900, repairs $1,400, vacancy tax/other $2,500. CCA claimed yearly
A9: Row 2 is your home (principal residence); rows 3-6 are other properties (rentals, a cottage). Sell / rent decisions are made on each Model tab. Amounts are today's dollars.
A10: value_now: market value; appreciation: growth per year. carrying_costs: property tax + condo/HOA/strata fees + insurance + utilities you want counted as housing (for the home; if you rent, put the rent here and leave value_now blank). property_tax: the part that's property tax (not used in Canada).
A11: mortgage_*: the home's mortgage on 1 January of the first year (balance, interest rate, payments per year). Other properties are assumed mortgage-free: include any loan payments in cash_costs.
A12: Other properties: rent and cash_costs per year; depreciation (capital cost allowance) claimed per year until depreciation_end_year, and accum_depreciation already claimed. cost_basis is what you paid plus improvements.

Sheet healthcare
A1: key | B1: value | C1: unit | D1: notes | E1: source
A2: employer_plan_cost | B2: 1500 | C2: $/year | D2: Your share of the group benefits plan + out-of-pocket while working | E2: Benefits statement
A3: private_plan_monthly | B3: 160 | C3: $/month | D3: Extended health + dental for one retired adult (e.g. PacificBlue Cross, Manulife FlexCare) | E3: Insurer quotes
A4: oop_per_person | B4: 1800 | C4: $/year | D4: Drugs above PharmaCare, dental, vision, physio not covered
A5: medical_inflation | B5: 0.045 | C5: per year
A6: ltc_annual_cost | B6: 95000 | C6: $/year | D6: Private assisted living / private-pay care in Metro Vancouver. Publicly subsidized long-term care costs up to 80% of after-tax income instead | E6: BC Seniors Advocate
A7: ltc_inflation | B7: 0.04 | C7: per year

Sheet assets
A1: account | B1: bucket | C1: value | D1: as_of | E1: cost_basis | F1: notes | H1: bucket | I1: total | J1: cost basis | K1: what goes in it
A2: Joint non-registered (ETFs) | B2: non_registered | C2: 420000 | D2: 2027-01-01 | E2: 290000 | F2: Adjusted cost base from the broker | H2: non_registered | I2: =SUMIF($B$2:$B$150,"non_registered",$C$2:$C$150) | J2: =SUMIF($B$2:$B$150,"non_registered",$E$2:$E$150) | K2: Non-registered investment accounts, bank and savings cash
A3: High-interest savings | B3: non_registered | C3: 35000 | D3: 2027-01-01 | F3: cash: cost basis = value | H3: rrsp_p1 | I3: =SUMIF($B$2:$B$150,"rrsp_p1",$C$2:$C$150) | K3: Person 1's RRSP, RRIF, LIRA, defined-contribution pension
A4: Chequing | B4: non_registered | C4: 12000 | D4: 2027-01-01 | H4: rrsp_p2 | I4: =SUMIF($B$2:$B$150,"rrsp_p2",$C$2:$C$150) | K4: Person 2's RRSP/RRIF/LIRA
A5: Sam RRSP | B5: rrsp_p1 | C5: 760000 | D5: 2027-01-01 | H5: tfsa | I5: =SUMIF($B$2:$B$150,"tfsa",$C$2:$C$150) | K5: TFSAs (either person)
A6: Sam DC pension (LIRA on leaving) | B6: rrsp_p1 | C6: 180000 | D6: 2027-01-01 | H6: resp | I6: =SUMIF($B$2:$B$150,"resp",$C$2:$C$150) | K6: RESPs (the kids' education money; not counted as yours)
A7: Taylor RRSP | B7: rrsp_p2 | C7: 410000 | D7: 2027-01-01 | H7: not_modeled | I7: =SUMIF($B$2:$B$150,"not_modeled",$C$2:$C$150) | K7: Anything the model should ignore (cars, collectibles, a business)
A8: Sam TFSA | B8: tfsa | C8: 118000 | D8: 2027-01-01
A9: Taylor TFSA | B9: tfsa | C9: 96000 | D9: 2027-01-01 | H9: One row per account, balance as of 1 January of the first year. cost_basis matters only for taxable accounts (blank = same as value, e.g. cash).
A10: Family RESP | B10: resp | C10: 88000 | D10: 2027-01-01
A11: Car | B11: not_modeled | C11: 25000 | D11: 2027-01-01

Sheet tax_tables
A1: Tax law used by the model (each spouse files separately; pension income is split). Yellow cells can be edited; indexed amounts grow with inflation after TAX_YEAR.
A2: Sources: CRA 2026 indexation (canada.ca, tax rates and payroll deduction tables); BC Budget 2026 (lowest rate 5.6%, indexing paused 2027-2030); ESDC CPP/OAS amounts (Jan 2026). Update each January.
A3: name | B3: value | C3: notes | E3: Federal brackets | I3: Provincial brackets: British Columbia | M3: RRIF minimum withdrawal (age on 1 January)
A4: TAX_YEAR | B4: 2026 | C4: Year the amounts on this tab are for; indexed amounts grow with inflation after it | E4: over | F4: rate | G4: step | I4: over | J4: rate | K4: step | M4: age | N4: minimum
A5: FED_CREDIT_RATE | B5: 0.14 | C5: Federal non-refundable credits are worth this rate (lowest bracket, 2026+) | E5: 0 | F5: 0.14 | G5: =IF(F5="",0,F5-0) | I5: 0 | J5: 0.056 | K5: =IF(J5="",0,J5-0) | M5: 71 | N5: 0.0528
A6: FED_BPA_MAX | B6: 16452 | C6: Federal basic personal amount (full) | E6: 58523 | F6: 0.205 | G6: =IF(F6="",0,F6-F5) | I6: 50363 | J6: 0.077 | K6: =IF(J6="",0,J6-J5) | M6: 72 | N6: 0.054
A7: FED_BPA_MIN | B7: 14829 | C7: ... reduced to this at high income | E7: 117045 | F7: 0.26 | G7: =IF(F7="",0,F7-F6) | I7: 100728 | J7: 0.105 | K7: =IF(J7="",0,J7-J6) | M7: 73 | N7: 0.0553
A8: FED_BPA_PHASE_START | B8: 181440 | C8: ... reduction starts at this net income | E8: 181440 | F8: 0.29 | G8: =IF(F8="",0,F8-F7) | I8: 115648 | J8: 0.1229 | K8: =IF(J8="",0,J8-J7) | M8: 74 | N8: 0.0567
A9: FED_BPA_PHASE_END | B9: 258482 | C9: ... and is complete here | E9: 258482 | F9: 0.33 | G9: =IF(F9="",0,F9-F8) | I9: 140430 | J9: 0.147 | K9: =IF(J9="",0,J9-J8) | M9: 75 | N9: 0.0582
A10: FED_AGE_AMOUNT | B10: 9208 | C10: Age amount (65+) | G10: =IF(F10="",0,F10-F9) | I10: 190405 | J10: 0.168 | K10: =IF(J10="",0,J10-J9) | M10: 76 | N10: 0.0598
A11: FED_AGE_THRESHOLD | B11: 46432 | C11: ... reduced by 15% of net income above this | G11: =IF(F11="",0,F11-F10) | I11: 265545 | J11: 0.205 | K11: =IF(J11="",0,J11-J10) | M11: 77 | N11: 0.0617
A12: AGE_REDUCTION_RATE | B12: 0.15 | G12: =IF(F12="",0,F12-F11) | K12: =IF(J12="",0,J12-J11) | M12: 78 | N12: 0.0636
A13: FED_PENSION_AMOUNT | B13: 2000 | C13: Pension income amount (not indexed) | G13: =IF(F13="",0,F13-F12) | K13: =IF(J13="",0,J13-J12) | M13: 79 | N13: 0.0658
A14: FED_EMPLOYMENT_AMOUNT | B14: 1501 | C14: Canada employment amount | G14: =IF(F14="",0,F14-F13) | K14: =IF(J14="",0,J14-J13) | M14: 80 | N14: 0.0682
A15: FED_MEDICAL_THRESHOLD | B15: 2891 | C15: Medical expenses above the lesser of 3% of net income and this | G15: =IF(F15="",0,F15-F14) | K15: =IF(J15="",0,J15-J14) | M15: 81 | N15: 0.0708
A16: FED_ELIGIBLE_DTC | B16: 0.150198 | C16: Federal dividend tax credit, eligible dividends (share of grossed-up amount) | G16: =IF(F16="",0,F16-F15) | K16: =IF(J16="",0,J16-J15) | M16: 82 | N16: 0.0738
A17: ELIGIBLE_GROSSUP | B17: 0.38 | C17: Eligible dividend gross-up | M17: 83 | N17: 0.0771
A18: CG_INCLUSION | B18: 0.5 | C18: Share of capital gains that is taxable | M18: 84 | N18: 0.0808
A19: OAS_MONTHLY | B19: 742.31 | C19: Full OAS pension at 65-74, per month (Jan 2026) | M19: 85 | N19: 0.0851
A20: OAS_75_BOOST | B20: 0.1 | C20: OAS increase from age 75 | M20: 86 | N20: 0.0899
A21: OAS_CLAWBACK_THRESHOLD | B21: 95323 | C21: OAS recovery tax starts at this net income | M21: 87 | N21: 0.0955
A22: OAS_CLAWBACK_RATE | B22: 0.15 | M22: 88 | N22: 0.1021
A23: CPP_MAX_MONTHLY | B23: 1507.65 | C23: Maximum CPP retirement pension at 65 (2026); caps survivor + own pension | M23: 89 | N23: 0.1099
A24: CPP_SURVIVOR_SHARE | B24: 0.6 | C24: Survivor pension (65+) as a share of the deceased's pension | M24: 90 | N24: 0.1192
A25: CPP_RATE | B25: 0.0595 | C25: Employee CPP contribution rate (base + first additional) | M25: 91 | N25: 0.1306
A26: CPP_EXEMPTION | B26: 3500 | C26: Basic exemption (not indexed) | M26: 92 | N26: 0.1449
A27: YMPE | B27: 74600 | C27: Year's maximum pensionable earnings | M27: 93 | N27: 0.1634
A28: CPP2_RATE | B28: 0.04 | C28: Second additional CPP rate | M28: 94 | N28: 0.1879
A29: YAMPE | B29: 85000 | C29: Year's additional maximum pensionable earnings | M29: 95 | N29: 0.2
A30: EI_RATE | B30: 0.0163 | C30: Employee EI premium rate | M30: 96 | N30: 0.2
A31: EI_MAX_INSURABLE | B31: 68900 | M31: 97 | N31: 0.2
A32: TFSA_LIMIT | B32: 7000 | C32: New TFSA room per person per year | M32: 98 | N32: 0.2
A33: PROV_NAME | B33: British Columbia | C33: Province used for provincial tax (edit the brackets and amounts to change it) | M33: 99 | N33: 0.2
A34: PROV_CREDIT_RATE | B34: 0.056 | C34: Provincial credits are worth this rate (BC lowest rate, 5.6% from 2026) | M34: 100 | N34: 0.2
A35: PROV_BPA | B35: 13216 | C35: Provincial basic personal amount | M35: 101 | N35: 0.2
A36: PROV_AGE_AMOUNT | B36: 5927 | C36: Provincial age amount (65+) | M36: 102 | N36: 0.2
A37: PROV_AGE_THRESHOLD | B37: 44119 | C37: ... reduced by 15% of net income above this | M37: 103 | N37: 0.2
A38: PROV_PENSION_AMOUNT | B38: 1000 | C38: Provincial pension income amount (not indexed) | M38: 104 | N38: 0.2
A39: PROV_MEDICAL_THRESHOLD | B39: 2748 | C39: Provincial medical expense threshold | M39: 105 | N39: 0.2
A40: PROV_ELIGIBLE_DTC | B40: 0.12 | C40: Provincial dividend tax credit, eligible dividends | M40: 106 | N40: 0.2
A41: PROV_REDUCTION_MAX | B41: 690 | C41: BC tax reduction (low income) | M41: 107 | N41: 0.2
A42: PROV_REDUCTION_THRESHOLD | B42: 25570 | C42: ... reduced by the rate below above this net income | M42: 108 | N42: 0.2
A43: PROV_REDUCTION_RATE | B43: 0.0356 | M43: 109 | N43: 0.2
A44: PROV_INDEX_PAUSE_FROM | B44: 2027 | C44: BC isn't indexing its brackets and amounts from this year ... | M44: 110 | N44: 0.2
A45: PROV_INDEX_PAUSE_TO | B45: 2030 | C45: ... through this year (BC Budget 2026); indexing resumes after | M45: 111 | N45: 0.2
A46: RRIF_START_AGE | B46: 72 | C46: Minimum RRIF withdrawals start the year you turn this (RRSP must convert by the end of 71) | M46: 112 | N46: 0.2
M47: 113 | N47: 0.2
M48: 114 | N48: 0.2
M49: 115 | N49: 0.2
M50: 116 | N50: 0.2
M51: 117 | N51: 0.2
M52: 118 | N52: 0.2
M53: 119 | N53: 0.2
M54: 120 | N54: 0.2

Sheet historical_returns
A1: year | B1: stocks | C1: bonds | D1: bills | E1: inflation | G1: US history: S&P 500 total return, 10-year Treasury, 3-month T-bill, CPI inflation. Source: Aswath Damodaran, NYU Stern (histretSP.xls, January 2026). Add a row each January, or replace the columns with another country's series (keep the headers).
A2: 1928 | B2: 0.438112 | C2: 0.008355 | D2: 0.0308 | E2: -0.011561
A3: 1929 | B3: -0.082979 | C3: 0.042038 | D3: 0.0316 | E3: 0.005848
A4: 1930 | B4: -0.251236 | C4: 0.045409 | D4: 0.0455 | E4: -0.063953
A5: 1931 | B5: -0.438375 | C5: -0.025589 | D5: 0.0231 | E5: -0.093168
A6: 1932 | B6: -0.086424 | C6: 0.087903 | D6: 0.0107 | E6: -0.10274
A7: 1933 | B7: 0.499822 | C7: 0.018553 | D7: 0.0096 | E7: 0.007634
A8: 1934 | B8: -0.011886 | C8: 0.079634 | D8: 0.002783 | E8: 0.015152
A9: 1935 | B9: 0.467404 | C9: 0.04472 | D9: 0.001675 | E9: 0.029851
A10: 1936 | B10: 0.319434 | C10: 0.050179 | D10: 0.001725 | E10: 0.014493
A11: 1937 | B11: -0.353367 | C11: 0.013791 | D11: 0.002758 | E11: 0.028571
A12: 1938 | B12: 0.292827 | C12: 0.042132 | D12: 0.00065 | E12: -0.027778
A13: 1939 | B13: -0.010976 | C13: 0.044123 | D13: 0.000458 | E13: 0
... A99: 2025 | B99: 0.177237 | C99: 0.077955 | D99: 0.0421 | E99: 0.027351

Sheet life_table
A1: age | B1: male_death_probability | C1: female_death_probability | E1: Probability of dying within a year at each age. US Social Security period life table for 2023 (as used in the 2026 Trustees Report). The Monte Carlo shifts it by the extra years of life expectancy set on the monte_carlo tab.
A2: 0 | B2: 0.006015 | C2: 0.005125
A3: 1 | B3: 0.000479 | C3: 0.000392
A4: 2 | B4: 0.00032 | C4: 0.000229
A5: 3 | B5: 0.000249 | C5: 0.000188
A6: 4 | B6: 0.000194 | C6: 0.000155
A7: 5 | B7: 0.000159 | C7: 0.000133
A8: 6 | B8: 0.000137 | C8: 0.000115
A9: 7 | B9: 0.000125 | C9: 0.000105
A10: 8 | B10: 0.00012 | C10: 0.0001
A11: 9 | B11: 0.00012 | C11: 9.8e-05
A12: 10 | B12: 0.000125 | C12: 0.000101
A13: 11 | B13: 0.00014 | C13: 0.000111
... A121: 119 | B121: 0.926604 | C121: 0.926604

Sheet monte_carlo
A1: Monte Carlo: every scenario replayed through history
A2: Each run replaces the Model tab's flat return and inflation with a stretch of real history (historical_returns tab) and draws lifetimes from the life_table tab. Change the yellow cells, then run the Monte Carlo (see README). Results are written below, in today's dollars.
A4: SETTINGS
A5: Stocks | B5: 0.6 | C5: Share of investments in stocks (historical_returns 'stocks' column)
A6: Bonds | B6: 0.4 | C6: Share in bonds ('bonds' column)
A7: Cash | B7: 0 | C7: Share in cash ('bills' column); the three should add to 100%
A8: Random runs per scenario | B8: 1000 | C8: 0 = historical starting years only
A9: Block length for random runs (years) | B9: 10 | C9: Random runs stitch together blocks of this many consecutive years of history
A10: Random seed | B10: 1 | C10: Change it to draw a different set of random runs
A11: Scenarios to run | C11: Comma-separated Model tab names; blank = every Model tab
A12: Sam: extra years of life expectancy | B12: 3 | C12: Years added to the life table's average. Healthier, higher-income people live longer (often +3 to +6). More years is the cautious direction
A13: Taylor: extra years of life expectancy | B13: 3 | C13: Same for person 2
A14: Survivor spending | B14: 0.7 | C14: After the first death, household and other spending as a share of the couple's
A15: Lifetimes drawn per historical start | B15: 20 | C15: Each historical start is run with this many random pairs of lifetimes
