Workbook

Sheet README
A1: Retirement plan
A2: A year-by-year retirement model for a couple, with a Monte Carlo test against history. See the project README for how to use it with Claude.
A4: Tabs
A5: Model - ...: a scenario. Yellow cells are its inputs (when you stop working, pensions, property sales, one-off events). Duplicate the tab to try another scenario.
A6: household: names, birth years, Social Security benefits, kids.
A7: budget: 12 months of spending by category (the statement pipeline fills it). The retirement_budget column is what the model spends.
A8: kids_budget: one line per kid and cost (support, college, help after college), each with its own years and amount.
A9: other_budget: renovations, cars and other big irregular costs, per year.
A10: properties: your home and any other properties.
A11: healthcare: marketplace, Medicare and long-term care costs.
A12: assets: every account, its balance and which bucket it feeds.
A13: tax_tables: the tax law the model uses (federal + your state). Edit to change state/province or update the law.
... A24: Not financial advice. Tax rules are simplified; check important decisions with a professional.

Sheet Model - Example
A1: Retirement model - Example
A2: Yellow cells are this scenario's inputs. To try another scenario: right-click this tab > Duplicate, rename it 'Model - <name>', change its yellow cells. Shared facts (budgets, properties, accounts, healthcare, tax law) are on the other tabs. Don't insert or delete rows on this tab.
A4: WORK | E4: RESULTS (today's dollars)
A5: =household!$B$5&"'s first year without a paycheck" | B5: 2030 | C5: The year after the last working year | E5: ="Net worth when "&household!$B$5&" is 70" | G5: =IFERROR(INDEX($J$92:$J$135,MATCH(household!$B$6+70,$A$92:$A$135,0)),"")
A6: =household!$B$8&"'s first year without a paycheck" | B6: 2029 | E6: ... at 80 | G6: =IFERROR(INDEX($J$92:$J$135,MATCH(household!$B$6+80,$A$92:$A$135,0)),"")
A7: =household!$B$5&"'s pay per year while working (today's $)" | B7: 190000 | C7: Salary + bonus + stock vesting | E7: ... at 85 | G7: =IFERROR(INDEX($J$92:$J$135,MATCH(household!$B$6+85,$A$92:$A$135,0)),"")
A8: =household!$B$8&"'s pay per year while working" | B8: 98000 | E8: ... at 90 | G8: =IFERROR(INDEX($J$92:$J$135,MATCH(household!$B$6+90,$A$92:$A$135,0)),"")
A9: =household!$B$5&"'s 401(k)/403(b) contributions (pre-tax)" | B9: 31000 | C9: While working | E9: ... at 95 | G9: =IFERROR(INDEX($J$92:$J$135,MATCH(household!$B$6+95,$A$92:$A$135,0)),"")
A10: =household!$B$8&"'s 401(k)/403(b) contributions (pre-tax)" | B10: 24500 | E10: ="Investments when "&household!$B$5&" is 90" | G10: =IFERROR(MAX(0,INDEX($I$92:$I$135,MATCH(household!$B$6+90,$A$92:$A$135,0))),"")
A11: ="Employer match / pension contributions for "&household!$B$5 | B11: 9500 | E11: First year investments can't cover costs | G11: =IF(COUNTIF($K$92:$K$135,">1")=0,"never",SUMPRODUCT(MIN($A$92:$A$135+($K$92:$K$135<=1)*10000)))
A12: ="Employer match / pension contributions for "&household!$B$8 | B12: 4900 | E12: First year's living costs | G12: =INDEX($D$92:$D$135,1)
A13: HSA contributions (while either works) | B13: 9550 | C13: Family limit + catch-up | E13: First year's withdrawal rate | G13: =INDEX($H$92:$H$135,1)
A14: Income tax withheld from pay | B14: 0.22 | C14: Share of taxable pay; the difference is settled next April | E14: Lifetime income tax (today's $) | G14: =SUMPRODUCT($EB$92:$EB$135/$O$92:$O$135)
A15: Tax owed for last year, paid in April of the first year | B15: 4000 | C15: Negative = a refund
A17: ECONOMY
A18: Inflation | B18: 0.03 | C18: Living costs, pay, pensions, tax brackets
A19: Investment return (per year, before inflation) | B19: 0.055 | C19: Override any year in the yellow 'Return override' column below
A20: Dividend yield on taxable accounts | B20: 0.015 | C20: Paid out as cash each year
A21: Healthcare cost growth | B21: =healthcare!$B$10 | C21: From the healthcare tab
A22: College cost growth | B22: 0.04
A23: Long-term care cost growth | B23: =healthcare!$B$12 | C23: From the healthcare tab
A25: SOCIAL SECURITY
A26: =household!$B$5&" starts Social Security at age" | B26: 68 | C26: 62-70
A27: =household!$B$8&" starts Social Security at age" | B27: 67 | C27: 62-70. A spouse can get up to half the other's benefit once both claim
A28: Benefit reduction for stopping work early | B28: 0.02 | C28: SSA statements assume you work until claiming; zero-earning years lower the average (often 1-5%)
A29: Across-the-board benefit cut | B29: 0.19 | C29: If Congress doesn't act, the trust fund pays ~81% from about 2034
A30: Cut starts in | B30: 2034 | C30: Set the cut to 0% to assume Congress fixes it
A31: =household!$B$5&"'s claim year" | B31: =household!$B$6+$B$26
A32: =household!$B$8&"'s claim year" | B32: =household!$B$9+$B$27
A33: =household!$B$5&"'s benefit vs full retirement age" | B33: =IF(ROUND(($B$26-tax_tables!$B$24)*12,0)>=0,1+0.08/12*MIN(ROUND(($B$26-tax_tables!$B$24)*12,0),36),1-5/900*MIN(-ROUND(($B$26-tax_tables!$B$24)*12,0),36)-5/1200*MAX(0,-ROUND(($B$26-tax_tables!$B$24)*12,0)-36)) | C33: Early claims are reduced, later ones get 8%/yr
A34: =household!$B$8&"'s benefit vs full retirement age" | B34: =IF(ROUND(($B$27-tax_tables!$B$24)*12,0)>=0,1+0.08/12*MIN(ROUND(($B$27-tax_tables!$B$24)*12,0),36),1-5/900*MIN(-ROUND(($B$27-tax_tables!$B$24)*12,0),36)-5/1200*MAX(0,-ROUND(($B$27-tax_tables!$B$24)*12,0)-36))
A35: =household!$B$5&"'s spousal benefit factor" | B35: =IF(ROUND(($B$26-tax_tables!$B$24)*12,0)>=0,1,1-25/3600*MIN(-ROUND(($B$26-tax_tables!$B$24)*12,0),36)-5/1200*MAX(0,-ROUND(($B$26-tax_tables!$B$24)*12,0)-36)) | C35: Spousal benefits don't grow after full retirement age
A36: =household!$B$8&"'s spousal benefit factor" | B36: =IF(ROUND(($B$27-tax_tables!$B$24)*12,0)>=0,1,1-25/3600*MIN(-ROUND(($B$27-tax_tables!$B$24)*12,0),36)-5/1200*MAX(0,-ROUND(($B$27-tax_tables!$B$24)*12,0)-36))
A38: WHERE YOU LIVE (STATE TAX)
A39: Year you move to another state | C39: Blank = stay. The state brackets are on the tax_tables tab
A40: The new state's income tax rate | B40: 0 | C40: Flat rate on income except Social Security; 0% for FL, TX, TN, NV, WA...
A42: WORKPLACE PENSIONS
A43: =household!$B$5&"'s defined-benefit pension per year (today's $)" | B43: 0 | C43: 0 = none. Your pension statement's estimate
A44: ... starts at age | B44: 65
A45: =household!$B$8&"'s defined-benefit pension per year (today's $)" | B45: 26000
A46: ... starts at age | B46: 62
A47: Pension increases, as a share of inflation | B47: 0.5 | C47: 0% = fixed dollar amount, 100% = fully indexed
A48: Share that continues to the survivor | B48: 0.5 | C48: Joint-and-survivor option; used in the Monte Carlo's lifetime runs
A50: HEALTHCARE AND LONG-TERM CARE
A51: =household!$B$5&" needs long-term care from age" | B51: 88 | C51: Paid from savings (HSA first)
A52: ... for this many years | B52: 3 | C52: Averages: men ~2 years, women ~3.5
A53: =household!$B$8&" needs long-term care from age" | B53: 84 | C53: Overlapping years double the cost
A54: ... for this many years | B54: 2
A55: Long-term care cost per person-year (today's $) | B55: =healthcare!$B$11 | C55: From the healthcare tab
A57: TAX MOVES
A58: Roth conversion per year (today's $) | B58: 60000 | C58: Moves pre-tax money to the Roth; taxed as income that year
A59: ... from year | B59: 2031 | C59: Blank = no conversions
A60: ... through year | B60: 2035
A61: Charitable giving per year (today's $) | B61: 3000 | C61: Deductible if you itemize; the spending itself belongs in the budget
A63: STARTING POINT (1 January of the first year) - from the assets tab; type over to freeze
A64: Taxable investments + cash | B64: =SUMIF(assets!$B$2:$B$150,"taxable",assets!$C$2:$C$150)
A65: ... their cost basis | B65: =assets!$J$2
A66: =household!$B$5&"'s pre-tax accounts" | B66: =SUMIF(assets!$B$2:$B$150,"pretax_p1",assets!$C$2:$C$150)
A67: =household!$B$8&"'s pre-tax accounts" | B67: =SUMIF(assets!$B$2:$B$150,"pretax_p2",assets!$C$2:$C$150)
A68: Roth accounts | B68: =SUMIF(assets!$B$2:$B$150,"roth",assets!$C$2:$C$150)
A69: HSAs | B69: =SUMIF(assets!$B$2:$B$150,"hsa",assets!$C$2:$C$150)
A70: 529s / college funds | B70: =SUMIF(assets!$B$2:$B$150,"college_529",assets!$C$2:$C$150)
A71: =household!$B$5&"'s required withdrawals start at" | B71: =IF(household!$B$6<1951,72,IF(household!$B$6<1960,73,75)) | C71: 73 if born 1951-59, 75 if born 1960 or later
A72: =household!$B$8&"'s required withdrawals start at" | B72: =IF(household!$B$9<1951,72,IF(household!$B$9<1960,73,75))
A74: Property | B74: Sell in year | C74: Change use from year | D74: New rent / yr (today's $) | E74: New costs / yr (today's $) | F74: Sale price | G74: Net proceeds | H74: Taxable gain | I74: Recapture
A75: =IF(properties!$A$2="","",properties!$A$2) | B75: 2040 | E75: 36000 | F75: =IF($B75="",0,properties!$C$2*(1+properties!$D$2)^($B75-household!$B$4+1)) | G75: =IF($B75="",0,F75*(1-properties!$E$2)-IFERROR(INDEX($AM$92:$AM$135,MATCH($B75,$A$92:$A$135,0)),0)) | H75: =IF($B75="",0,MAX(0,F75*(1-properties!$E$2)-properties!$F$2-tax_tables!$B$20)) | I75: 0
A76: =IF(properties!$A$3="","",properties!$A$3) | B76: 2045 | F76: =IF($B76="",0,properties!$C$3*(1+properties!$D$3)^($B76-household!$B$4+1)) | G76: =IF($B76="",0,F76*(1-properties!$E$3)) | H76: =IF($B76="",0,MAX(0,G76-(properties!$F$3-(properties!$P$3+properties!$N$3*MAX(0,MIN($B76,properties!$O$3)-household!$B$4+1))))) | I76: =IF($B76="",0,MIN(H76,(properties!$P$3+properties!$N$3*MAX(0,MIN($B76,properties!$O$3)-household!$B$4+1))))
A77: =IF(properties!$A$4="","",properties!$A$4) | F77: =IF($B77="",0,properties!$C$4*(1+properties!$D$4)^($B77-household!$B$4+1)) | G77: =IF($B77="",0,F77*(1-properties!$E$4)) | H77: =IF($B77="",0,MAX(0,G77-(properties!$F$4-(properties!$P$4+properties!$N$4*MAX(0,MIN($B77,properties!$O$4)-household!$B$4+1))))) | I77: =IF($B77="",0,MIN(H77,(properties!$P$4+properties!$N$4*MAX(0,MIN($B77,properties!$O$4)-household!$B$4+1))))
A78: =IF(properties!$A$5="","",properties!$A$5) | F78: =IF($B78="",0,properties!$C$5*(1+properties!$D$5)^($B78-household!$B$4+1)) | G78: =IF($B78="",0,F78*(1-properties!$E$5)) | H78: =IF($B78="",0,MAX(0,G78-(properties!$F$5-(properties!$P$5+properties!$N$5*MAX(0,MIN($B78,properties!$O$5)-household!$B$4+1))))) | I78: =IF($B78="",0,MIN(H78,(properties!$P$5+properties!$N$5*MAX(0,MIN($B78,properties!$O$5)-household!$B$4+1))))
A79: =IF(properties!$A$6="","",properties!$A$6) | F79: =IF($B79="",0,properties!$C$6*(1+properties!$D$6)^($B79-household!$B$4+1)) | G79: =IF($B79="",0,F79*(1-properties!$E$6)) | H79: =IF($B79="",0,MAX(0,G79-(properties!$F$6-(properties!$P$6+properties!$N$6*MAX(0,MIN($B79,properties!$O$6)-household!$B$4+1))))) | I79: =IF($B79="",0,MIN(H79,(properties!$P$6+properties!$N$6*MAX(0,MIN($B79,properties!$O$6)-household!$B$4+1))))
A80: Home: 'New costs' = what housing costs per year after you sell it (rent, or a new place's carrying costs; if you buy one, its price goes in one-off Expenses below and its value isn't counted in net worth). Other properties: 'Change use' switches to the new rent/costs from that year (e.g. move into the cottage: rent 0, costs = its upkeep). Sale price is a formula; type over it to use your own estimate.
A82: One-off money in or out | B82: Year | C82: Amount (today's $) | D82: Type
A83: Moving costs when selling the house | B83: 2040 | C83: 15000 | D83: Expense | F83: Severance, an inheritance, a wedding, a new car, buying a smaller home. Wages get payroll tax; 'Other taxable income' is taxed as ordinary income; 'Tax-free money in' isn't taxed; 'Expense' is spent that year.
A84: Inheritance from Jordan's parents | B84: 2036 | C84: 150000 | D84: Tax-free money in
A90: SUMMARY | L90: ASSUMPTIONS BY YEAR | T90: WORK | AL90: HOUSING | AT90: LIVING | BB90: HEALTHCARE | BQ90: PROPERTIES | BY90: SOCIAL SECURITY | CA90: PENSIONS | CC90: INVESTMENTS | DH90: INCOME TAX | EC90: TOTALS
A91: Year | B91: =household!$B$5&"'s age" | C91: =household!$B$8&"'s age" | D91: Living costs (all spending except income tax) | E91: Income + payroll tax paid this year | F91: Social Security | G91: Taken out of investments (net) | H91: Withdrawal rate | I91: Investments at year end (today's $) | J91: Net worth at year end (today's $) | K91: Shortfall (costs your accounts couldn't cover) | L91: Return override (blank = default) | M91: Return used | N91: Household spending multiplier (blank = 100%) | O91: Price level vs today | P91: Tax-law index | Q91: Healthcare price level | R91: College price level | S91: Long-term care price level | T91: =household!$B$5&" working?" | U91: =household!$B$8&" working?" | V91: Either working? | W91: =household!$B$5&"'s pay" | X91: =household!$B$8&"'s pay" | Y91: =household!$B$5&"'s retirement contributions" | Z91: =household!$B$8&"'s retirement contributions" | AA91: ="Employer contributions for "&household!$B$5 | AB91: ="Employer contributions for "&household!$B$8 | AC91: HSA contributions | AD91: Total pay | AE91: Taxable pay | AF91: Social Security + Medicare payroll tax | AG91: Income tax withheld from pay | AH91: Take-home pay | AI91: One-off: other taxable income | AJ91: One-off: tax-free money in | AK91: One-off: expenses | AL91: Own your home? | AM91: Mortgage balance, start | AN91: Mortgage interest | AO91: Mortgage payments | AP91: Mortgage balance, end | AQ91: Home carrying costs | AR91: Housing after selling your home | AS91: Housing total | AT91: Household living (budget tab) | AU91: Renovations, cars, other (other_budget tab) | AV91: Kids: costs you pay | AW91: Kids: costs paid from college funds | AX91: College funds, start | AY91: Paid by college funds | AZ91: College costs paid by you | BA91: College funds, end | BB91: Employer health plan (while working) | BC91: Adults buying their own insurance | BD91: Kids on your plan | BE91: Marketplace premiums | BF91: Marketplace out-of-pocket | BG91: People on Medicare | BH91: Medicare B + D + Medigap premiums | BI91: Medicare out-of-pocket | BJ91: Medicare income surcharge (IRMAA) | BK91: People in long-term care | BL91: Long-term care | BM91: Healthcare total | BN91: HSA, start | BO91: Paid from HSA | BP91: HSA, end | BQ91: Property income after costs | BR91: Depreciation | BS91: Taxable property income | BT91: Property sale proceeds | BU91: Taxable gain on sales | BV91: Depreciation recapture | BW91: Home value, end | BX91: Other property values, end | BY91: =household!$B$5&"'s Social Security" | BZ91: =household!$B$8&"'s Social Security" | CA91: =household!$B$5&"'s workplace pension" | CB91: =household!$B$8&"'s workplace pension" | CC91: Taxable, start | CD91: Cost basis, start | CE91: Dividends | CF91: =household!$B$5&" pre-tax, start" | CG91: =household!$B$8&" pre-tax, start" | CH91: =household!$B$5&"'s required withdrawal" | CI91: =household!$B$8&"'s required withdrawal" | CJ91: Roth, start | CK91: Roth conversion planned | CL91: =household!$B$5&" pre-tax available" | CM91: =household!$B$8&" pre-tax available" | CN91: Last year's income tax still owed | CO91: Cash coming in | CP91: Still needed (+) or surplus (-) | CQ91: Sold from taxable | CR91: Withdrawn from pre-tax | CS91: ="... from "&household!$B$5&"'s" | CT91: ="... from "&household!$B$8&"'s" | CU91: Withdrawn from Roth | CV91: Extra from HSA (last resort) | CW91: Surplus reinvested | CX91: Roth conversion | CY91: ="... from "&household!$B$5&"'s" | CZ91: ="... from "&household!$B$8&"'s" | DA91: Gain share of sales | DB91: Capital gains realized | DC91: Taxable, end | DD91: Cost basis, end | DE91: =household!$B$5&" pre-tax, end" | DF91: =household!$B$8&" pre-tax, end" | DG91: Roth, end | DH91: Ordinary income | DI91: Dividends + capital gains | DJ91: Taxable Social Security | DK91: Adjusted gross income | DL91: People 65+ | DM91: Standard deduction | DN91: Senior deduction | DO91: SALT cap | DP91: Medical deduction | DQ91: Itemized deductions | DR91: Deduction used | DS91: Taxable ordinary income | DT91: Taxable gains + dividends | DU91: Federal income tax | DV91: Moved to another state? | DW91: State retirement-income exclusion | DX91: State taxable income | DY91: State income tax | DZ91: Local income tax | EA91: New state's income tax | EB91: Income tax for the year | EC91: Investments, end | ED91: Net worth, end
A92: =household!$B$4+0 | B92: =A92-household!$B$6 | C92: =A92-household!$B$9 | D92: =AS92+AT92+AU92+AV92+AZ92+BM92+AK92 | E92: =CN92+AG92+AF92 | F92: =BY92+BZ92 | G92: =CQ92+CR92+CU92+CH92+CI92+CE92-CW92+CV92+BO92 | H92: =IF(CC92+CF92+CG92+CJ92+BN92<=0,"",G92/(CC92+CF92+CG92+CJ92+BN92)) | I92: =EC92/O92 | J92: =ED92/O92 | K92: =MAX(0,CP92-CQ92-CR92-CU92-CV92) | M92: =IF(L92="",$B$19,L92) | O92: =(1+$B$18)^(A92-household!$B$4+1) | P92: =(1+$B$18)^(A92-tax_tables!$B$4) | Q92: =(1+$B$21)^(A92-household!$B$4+1) | R92: =(1+$B$22)^(A92-household!$B$4+1) | S92: =(1+$B$23)^(A92-household!$B$4+1) | T92: =IF(A92<$B$5,1,0) | U92: =IF(A92<$B$6,1,0) | V92: =IF(T92+U92>0,1,0) | W92: =T92*$B$7*O92+SUMPRODUCT(($B$83:$B$88=A92)*($D$83:$D$88="Wages: person 1")*$C$83:$C$88)*O92 | X92: =U92*$B$8*O92+SUMPRODUCT(($B$83:$B$88=A92)*($D$83:$D$88="Wages: person 2")*$C$83:$C$88)*O92 | Y92: =T92*$B$9*O92 | Z92: =U92*$B$10*O92 | AA92: =T92*$B$11*O92 | AB92: =U92*$B$12*O92 | AC92: =V92*$B$13*O92 | AD92: =W92+X92 | AE92: =AD92-Y92-Z92-AC92 | AF92: =0.062*MIN(W92,tax_tables!$B$21*P92)+0.062*MIN(X92,tax_tables!$B$21*P92)+0.0145*AD92+0.009*MAX(0,AD92-tax_tables!$B$22) | AG92: =$B$14*AE92 | AH92: =AD92-Y92-Z92-AC92-AF92-AG92 | AI92: =SUMPRODUCT(($B$83:$B$88=A92)*($D$83:$D$88="Other taxable income")*$C$83:$C$88)*O92 | AJ92: =SUMPRODUCT(($B$83:$B$88=A92)*($D$83:$D$88="Tax-free money in")*$C$83:$C$88)*O92 | AK92: =SUMPRODUCT(($B$83:$B$88=A92)*($D$83:$D$88="Expense")*$C$83:$C$88)*O92 | AL92: =IF(OR($B$75="",A92<$B$75),1,0) | AM92: =properties!$I$2 | AN92: =AL92*AM92*properties!$J$2 | AO92: =AL92*MIN(properties!$K$2,AM92+AN92) | AP92: =AL92*(AM92+AN92-AO92) | AQ92: =AL92*properties!$G$2*O92 | AR92: =(1-AL92)*$E$75*O92 | AS92: =AO92+AQ92+AR92 | AT92: =SUMIF(budget!$A$2:$A$300,"household",budget!$F$2:$F$300)*O92*IF(N92="",1,N92) | AU92: =SUMPRODUCT((other_budget!$C$2:$C$30<=A92)*(other_budget!$D$2:$D$30>=A92)*other_budget!$B$2:$B$30)*O92 | AV92: =SUMPRODUCT((kids_budget!$D$2:$D$40<=A92)*(kids_budget!$E$2:$E$40>=A92)*(kids_budget!$G$2:$G$40<>"college_funds")*kids_budget!$C$2:$C$40*((kids_budget!$F$2:$F$40="college")*R92+(kids_budget!$F$2:$F$40<>"college")*O92)) | AW92: =SUMPRODUCT((kids_budget!$D$2:$D$40<=A92)*(kids_budget!$E$2:$E$40>=A92)*(kids_budget!$G$2:$G$40="college_funds")*kids_budget!$C$2:$C$40*((kids_budget!$F$2:$F$40="college")*R92+(kids_budget!$F$2:$F$40<>"college")*O92)) | AX92: =$B$70 | AY92: =MIN(AW92,AX92*(1+M92)) | AZ92: =AW92-AY92 | BA92: =AX92*(1+M92)-AY92 | BB92: =V92*healthcare!$B$5*Q92 | BC92: =(1-V92)*((B92<65)+(C92<65)) | BD92: =COUNTIF(household!$C$16:$C$23,">="&A92) | BE92: =(BC92*healthcare!$B$2+IF(BC92>0,BD92,0)*healthcare!$B$3)*12*Q92 | BF92: =IF(BC92>0,(BC92+BD92)*healthcare!$B$4*Q92,0) | BG92: =(B92>=65)+(C92>=65) | BH92: =BG92*(healthcare!$B$6+healthcare!$B$7+healthcare!$B$8)*12*Q92 | BI92: =BG92*healthcare!$B$9*Q92 | BJ92: =0 | BK92: =AND(B92>=$B$51,B92<$B$51+$B$52)*1+AND(C92>=$B$53,C92<$B$53+$B$54)*1 | BL92: =BK92*$B$55*S92 | BM92: =BB92+BE92+BF92+BH92+BI92+BJ92+BL92 | BN92: =$B$69 | BO92: =IF(V92=1,0,MIN(BN92*(1+M92),BF92+BG92*(healthcare!$B$6+healthcare!$B$7)*12*Q92+BI92+BJ92+BL92)) | BP92: =BN92*(1+M92)-BO92+AC92-CV92 | BQ92: =SUMPRODUCT((1-($B$76:$B$79>0)*(A92>=$B$76:$B$79))*(1-(($C$76:$C$79>0)*(A92>=$C$76:$C$79)))*(properties!$L$3:$L$6-properties!$M$3:$M$6))*O92+SUMPRODUCT((1-($B$76:$B$79>0)*(A92>=$B$76:$B$79))*(($C$76:$C$79>0)*(A92>=$C$76:$C$79))*($D$76:$D$79-$E$76:$E$79))*O92 | BR92: =SUMPRODUCT((1-($B$76:$B$79>0)*(A92>=$B$76:$B$79))*properties!$N$3:$N$6*(A92<=properties!$O$3:$O$6)) | BS92: =MAX(0,BQ92-BR92) | BT92: =SUMPRODUCT(($B$75:$B$79=A92)*$G$75:$G$79) | BU92: =SUMPRODUCT(($B$75:$B$79=A92)*$H$75:$H$79) | BV92: =SUMPRODUCT(($B$75:$B$79=A92)*$I$75:$I$79) | BW92: =AL92*properties!$C$2*(1+properties!$D$2)^(A92-household!$B$4+1) | BX92: =SUMPRODUCT((1-($B$76:$B$79>0)*(A92>=$B$76:$B$79))*properties!$C$3:$C$6*(1+properties!$D$3:$D$6)^(A92-household!$B$4+1)) | BY92: =IF(A92>=$B$31,IF(A92>=$B$32,MAX(household!$B$11*12*(1-$B$28)*O92*IF(A92>=$B$30,1-$B$29,1)*$B$33,0.5*household!$B$12*12*(1-$B$28)*O92*IF(A92>=$B$30,1-$B$29,1)*$B$35),household!$B$11*12*(1-$B$28)*O92*IF(A92>=$B$30,1-$B$29,1)*$B$33),0) | BZ92: =IF(A92>=$B$32,IF(A92>=$B$31,MAX(household!$B$12*12*(1-$B$28)*O92*IF(A92>=$B$30,1-$B$29,1)*$B$34,0.5*household!$B$11*12*(1-$B$28)*O92*IF(A92>=$B$30,1-$B$29,1)*$B$36),household!$B$12*12*(1-$B$28)*O92*IF(A92>=$B$30,1-$B$29,1)*$B$34),0) | CA92: =IF(AND($B$43<>0,A92>=household!$B$6+$B$44),$B$43*(1+$B$18)^(MAX(household!$B$6+$B$44,household!$B$4-1)-household!$B$4+1)*(1+$B$47*$B$18)^(A92-MAX(household!$B$6+$B$44,household!$B$4-1)),0) | CB92: =IF(AND($B$45<>0,A92>=household!$B$9+$B$46),$B$45*(1+$B$18)^(MAX(household!$B$9+$B$46,household!$B$4-1)-household!$B$4+1)*(1+$B$47*$B$18)^(A92-MAX(household!$B$9+$B$46,household!$B$4-1)),0) | CC92: =$B$64 | CD92: =$B$65 | CE92: =$B$20*CC92 | CF92: =$B$66 | CG92: =$B$67 | CH92: =IF(B92>=$B$71,MAX(0,CF92)/INDEX(tax_tables!$Z$5:$Z$53,MATCH(B92,tax_tables!$Y$5:$Y$53,0)),0) | CI92: =IF(C92>=$B$72,MAX(0,CG92)/INDEX(tax_tables!$Z$5:$Z$53,MATCH(C92,tax_tables!$Y$5:$Y$53,0)),0) | CJ92: =$B$68 | CK92: =IF(OR($B$59="",$B$60=""),0,IF(AND(A92>=$B$59,A92<=$B$60),$B$58*O92,0)) | CL92: =MAX(0,CF92*(1+M92)-CH92) | CM92: =MAX(0,CG92*(1+M92)-CI92) | CN92: =$B$15 | CO92: =AH92+F92+CA92+CB92+BQ92+CE92+CH92+CI92+BT92+AI92+AJ92+BO92 | CP92: =D92+CN92-CO92 | CQ92: =MAX(0,MIN(CP92,CC92*(1+M92-$B$20))) | CR92: =MAX(0,MIN(CP92-CQ92,CL92+CM92)) | CS92: =IF(CL92+CM92>1,CR92*CL92/(CL92+CM92),0) | CT92: =CR92-CS92 | CU92: =MAX(0,MIN(CP92-CQ92-CR92,CJ92*(1+M92))) | CV92: =MAX(0,MIN(CP92-CQ92-CR92-CU92,BN92*(1+M92)-BO92+AC92)) | CW92: =MAX(0,-CP92) | CX92: =MIN(CK92,CL92-CS92+CM92-CT92) | CY92: =IF(CL92-CS92+CM92-CT92>1,CX92*(CL92-CS92)/(CL92-CS92+CM92-CT92),0) | CZ92: =CX92-CY92 | DA92: =IF(CC92>0,MAX(0,1-CD92/CC92),0) | DB92: =CQ92*DA92 | DC92: =CC92*(1+M92-$B$20)-CQ92+CW92 | DD92: =CD92-(CQ92-DB92)+CW92 | DE92: =CF92*(1+M92)-CH92-CS92-CY92+Y92+AA92 | DF92: =CG92*(1+M92)-CI92-CT92-CZ92+Z92+AB92 | DG92: =CJ92*(1+M92)-CU92+CX92 | DH92: =AE92+CR92+CH92+CI92+CX92+CV92+BS92+AI92+CA92+CB92 | DI92: =CE92+DB92+BU92 | DJ92: =IF((DH92+DI92+0.5*F92)<=tax_tables!$B$14,0,IF((DH92+DI92+0.5*F92)<=tax_tables!$B$15,MIN(0.5*F92,0.5*((DH92+DI92+0.5*F92)-tax_tables!$B$14)),MIN(0.85*F92,0.85*((DH92+DI92+0.5*F92)-tax_tables!$B$15)+MIN(0.5*F92,tax_tables!$B$15-tax_tables!$B$14)))) | DK92: =DH92+DI92+DJ92 | DL92: =(B92>=65)+(C92>=65) | DM92: =(tax_tables!$B$5+tax_tables!$B$6*DL92)*P92 | DN92: =IF(AND(A92>=tax_tables!$B$8,A92<=tax_tables!$B$9),DL92*MAX(0,tax_tables!$B$7-tax_tables!$B$11*MAX(0,DK92-tax_tables!$B$10)),0) | DO92: =IFERROR(MAX(tax_tables!$B$16,INDEX(tax_tables!$W$5:$W$8,MATCH(A92,tax_tables!$V$5:$V$8,0))-tax_tables!$B$18*MAX(0,DK92-tax_tables!$B$17*1.01^(A92-tax_tables!$B$4))),tax_tables!$B$16) | DP92: =MAX(0,BM92-BB92-tax_tables!$B$23*DK92) | DQ92: =AN92+MIN(DO92,0+AL92*properties!$H$2*O92)+DP92+$B$61*O92 | DR92: =MAX(DM92,DQ92) | DS92: =MAX(0,DH92+DJ92-DR92-DN92) | DT92: =MAX(0,DI92-MAX(0,DR92+DN92-DH92-DJ92)) | DU92: =SUMPRODUCT((DS92>tax_tables!$E$5:$E$16*P92)*(DS92-tax_tables!$E$5:$E$16*P92)*tax_tables!$G$5:$G$16)+SUMPRODUCT(((DS92+DT92)>tax_tables!$I$5:$I$16*P92)*((DS92+DT92)-tax_tables!$I$5:$I$16*P92)*tax_tables!$K$5:$K$16)-SUMPRODUCT((DS92>tax_tables!$I$5:$I$16*P92)*(DS92-tax_tables!$I$5:$I$16*P92)*tax_tables!$K$5:$K$16)+tax_tables!$B$19*BV92+tax_tables!$B$12*MIN(CE92+DB92+BS92+BU92,MAX(0,DK92-tax_tables!$B$13)) | DV92: =IF($B$39="",0,IF(A92>=$B$39,1,0)) | DW92: =IF(B92+0.5>=tax_tables!$B$30,MIN(CS92+CH92+CY92+CA92,tax_tables!$B$29),0)+IF(C92+0.5>=tax_tables!$B$30,MIN(CT92+CI92+CZ92+CB92,tax_tables!$B$29),0) | DX92: =MAX(0,DK92-tax_tables!$B$28*DJ92-DW92-tax_tables!$B$26*IF(tax_tables!$B$27=1,P92,1)) | DY92: =(1-DV92)*SUMPRODUCT((DX92>tax_tables!$M$5:$M$16*IF(tax_tables!$B$27=1,P92,1))*(DX92-tax_tables!$M$5:$M$16*IF(tax_tables!$B$27=1,P92,1))*tax_tables!$O$5:$O$16) | DZ92: =(1-DV92)*tax_tables!$B$31*DX92 | EA92: =DV92*$B$40*MAX(0,DK92-DJ92) | EB92: =DU92+DY92+DZ92+EA92 | EC92: =DC92+DE92+DF92+DG92+BP92 | ED92: =EC92+BW92-AP92+BX92
A93: =A92+1 | B93: =A93-household!$B$6 | C93: =A93-household!$B$9 | D93: =AS93+AT93+AU93+AV93+AZ93+BM93+AK93 | E93: =CN93+AG93+AF93 | F93: =BY93+BZ93 | G93: =CQ93+CR93+CU93+CH93+CI93+CE93-CW93+CV93+BO93 | H93: =IF(CC93+CF93+CG93+CJ93+BN93<=0,"",G93/(CC93+CF93+CG93+CJ93+BN93)) | I93: =EC93/O93 | J93: =ED93/O93 | K93: =MAX(0,CP93-CQ93-CR93-CU93-CV93) | M93: =IF(L93="",$B$19,L93) | O93: =(1+$B$18)^(A93-household!$B$4+1) | P93: =(1+$B$18)^(A93-tax_tables!$B$4) | Q93: =(1+$B$21)^(A93-household!$B$4+1) | R93: =(1+$B$22)^(A93-household!$B$4+1) | S93: =(1+$B$23)^(A93-household!$B$4+1) | T93: =IF(A93<$B$5,1,0) | U93: =IF(A93<$B$6,1,0) | V93: =IF(T93+U93>0,1,0) | W93: =T93*$B$7*O93+SUMPRODUCT(($B$83:$B$88=A93)*($D$83:$D$88="Wages: person 1")*$C$83:$C$88)*O93 | X93: =U93*$B$8*O93+SUMPRODUCT(($B$83:$B$88=A93)*($D$83:$D$88="Wages: person 2")*$C$83:$C$88)*O93 | Y93: =T93*$B$9*O93 | Z93: =U93*$B$10*O93 | AA93: =T93*$B$11*O93 | AB93: =U93*$B$12*O93 | AC93: =V93*$B$13*O93 | AD93: =W93+X93 | AE93: =AD93-Y93-Z93-AC93 | AF93: =0.062*MIN(W93,tax_tables!$B$21*P93)+0.062*MIN(X93,tax_tables!$B$21*P93)+0.0145*AD93+0.009*MAX(0,AD93-tax_tables!$B$22) | AG93: =$B$14*AE93 | AH93: =AD93-Y93-Z93-AC93-AF93-AG93 | AI93: =SUMPRODUCT(($B$83:$B$88=A93)*($D$83:$D$88="Other taxable income")*$C$83:$C$88)*O93 | AJ93: =SUMPRODUCT(($B$83:$B$88=A93)*($D$83:$D$88="Tax-free money in")*$C$83:$C$88)*O93 | AK93: =SUMPRODUCT(($B$83:$B$88=A93)*($D$83:$D$88="Expense")*$C$83:$C$88)*O93 | AL93: =IF(OR($B$75="",A93<$B$75),1,0) | AM93: =AP92 | AN93: =AL93*AM93*properties!$J$2 | AO93: =AL93*MIN(properties!$K$2,AM93+AN93) | AP93: =AL93*(AM93+AN93-AO93) | AQ93: =AL93*properties!$G$2*O93 | AR93: =(1-AL93)*$E$75*O93 | AS93: =AO93+AQ93+AR93 | AT93: =SUMIF(budget!$A$2:$A$300,"household",budget!$F$2:$F$300)*O93*IF(N93="",1,N93) | AU93: =SUMPRODUCT((other_budget!$C$2:$C$30<=A93)*(other_budget!$D$2:$D$30>=A93)*other_budget!$B$2:$B$30)*O93 | AV93: =SUMPRODUCT((kids_budget!$D$2:$D$40<=A93)*(kids_budget!$E$2:$E$40>=A93)*(kids_budget!$G$2:$G$40<>"college_funds")*kids_budget!$C$2:$C$40*((kids_budget!$F$2:$F$40="college")*R93+(kids_budget!$F$2:$F$40<>"college")*O93)) | AW93: =SUMPRODUCT((kids_budget!$D$2:$D$40<=A93)*(kids_budget!$E$2:$E$40>=A93)*(kids_budget!$G$2:$G$40="college_funds")*kids_budget!$C$2:$C$40*((kids_budget!$F$2:$F$40="college")*R93+(kids_budget!$F$2:$F$40<>"college")*O93)) | AX93: =BA92 | AY93: =MIN(AW93,AX93*(1+M93)) | AZ93: =AW93-AY93 | BA93: =AX93*(1+M93)-AY93 | BB93: =V93*healthcare!$B$5*Q93 | BC93: =(1-V93)*((B93<65)+(C93<65)) | BD93: =COUNTIF(household!$C$16:$C$23,">="&A93) | BE93: =(BC93*healthcare!$B$2+IF(BC93>0,BD93,0)*healthcare!$B$3)*12*Q93 | BF93: =IF(BC93>0,(BC93+BD93)*healthcare!$B$4*Q93,0) | BG93: =(B93>=65)+(C93>=65) | BH93: =BG93*(healthcare!$B$6+healthcare!$B$7+healthcare!$B$8)*12*Q93 | BI93: =BG93*healthcare!$B$9*Q93 | BJ93: =0 | BK93: =AND(B93>=$B$51,B93<$B$51+$B$52)*1+AND(C93>=$B$53,C93<$B$53+$B$54)*1 | BL93: =BK93*$B$55*S93 | BM93: =BB93+BE93+BF93+BH93+BI93+BJ93+BL93 | BN93: =BP92 | BO93: =IF(V93=1,0,MIN(BN93*(1+M93),BF93+BG93*(healthcare!$B$6+healthcare!$B$7)*12*Q93+BI93+BJ93+BL93)) | BP93: =BN93*(1+M93)-BO93+AC93-CV93 | BQ93: =SUMPRODUCT((1-($B$76:$B$79>0)*(A93>=$B$76:$B$79))*(1-(($C$76:$C$79>0)*(A93>=$C$76:$C$79)))*(properties!$L$3:$L$6-properties!$M$3:$M$6))*O93+SUMPRODUCT((1-($B$76:$B$79>0)*(A93>=$B$76:$B$79))*(($C$76:$C$79>0)*(A93>=$C$76:$C$79))*($D$76:$D$79-$E$76:$E$79))*O93 | BR93: =SUMPRODUCT((1-($B$76:$B$79>0)*(A93>=$B$76:$B$79))*properties!$N$3:$N$6*(A93<=properties!$O$3:$O$6)) | BS93: =MAX(0,BQ93-BR93) | BT93: =SUMPRODUCT(($B$75:$B$79=A93)*$G$75:$G$79) | BU93: =SUMPRODUCT(($B$75:$B$79=A93)*$H$75:$H$79) | BV93: =SUMPRODUCT(($B$75:$B$79=A93)*$I$75:$I$79) | BW93: =AL93*properties!$C$2*(1+properties!$D$2)^(A93-household!$B$4+1) | BX93: =SUMPRODUCT((1-($B$76:$B$79>0)*(A93>=$B$76:$B$79))*properties!$C$3:$C$6*(1+properties!$D$3:$D$6)^(A93-household!$B$4+1)) | BY93: =IF(A93>=$B$31,IF(A93>=$B$32,MAX(household!$B$11*12*(1-$B$28)*O93*IF(A93>=$B$30,1-$B$29,1)*$B$33,0.5*household!$B$12*12*(1-$B$28)*O93*IF(A93>=$B$30,1-$B$29,1)*$B$35),household!$B$11*12*(1-$B$28)*O93*IF(A93>=$B$30,1-$B$29,1)*$B$33),0) | BZ93: =IF(A93>=$B$32,IF(A93>=$B$31,MAX(household!$B$12*12*(1-$B$28)*O93*IF(A93>=$B$30,1-$B$29,1)*$B$34,0.5*household!$B$11*12*(1-$B$28)*O93*IF(A93>=$B$30,1-$B$29,1)*$B$36),household!$B$12*12*(1-$B$28)*O93*IF(A93>=$B$30,1-$B$29,1)*$B$34),0) | CA93: =IF(AND($B$43<>0,A93>=household!$B$6+$B$44),$B$43*(1+$B$18)^(MAX(household!$B$6+$B$44,household!$B$4-1)-household!$B$4+1)*(1+$B$47*$B$18)^(A93-MAX(household!$B$6+$B$44,household!$B$4-1)),0) | CB93: =IF(AND($B$45<>0,A93>=household!$B$9+$B$46),$B$45*(1+$B$18)^(MAX(household!$B$9+$B$46,household!$B$4-1)-household!$B$4+1)*(1+$B$47*$B$18)^(A93-MAX(household!$B$9+$B$46,household!$B$4-1)),0) | CC93: =DC92 | CD93: =DD92 | CE93: =$B$20*CC93 | CF93: =DE92 | CG93: =DF92 | CH93: =IF(B93>=$B$71,MAX(0,CF93)/INDEX(tax_tables!$Z$5:$Z$53,MATCH(B93,tax_tables!$Y$5:$Y$53,0)),0) | CI93: =IF(C93>=$B$72,MAX(0,CG93)/INDEX(tax_tables!$Z$5:$Z$53,MATCH(C93,tax_tables!$Y$5:$Y$53,0)),0) | CJ93: =DG92 | CK93: =IF(OR($B$59="",$B$60=""),0,IF(AND(A93>=$B$59,A93<=$B$60),$B$58*O93,0)) | CL93: =MAX(0,CF93*(1+M93)-CH93) | CM93: =MAX(0,CG93*(1+M93)-CI93) | CN93: =EB92-AG92 | CO93: =AH93+F93+CA93+CB93+BQ93+CE93+CH93+CI93+BT93+AI93+AJ93+BO93 | CP93: =D93+CN93-CO93 | CQ93: =MAX(0,MIN(CP93,CC93*(1+M93-$B$20))) | CR93: =MAX(0,MIN(CP93-CQ93,CL93+CM93)) | CS93: =IF(CL93+CM93>1,CR93*CL93/(CL93+CM93),0) | CT93: =CR93-CS93 | CU93: =MAX(0,MIN(CP93-CQ93-CR93,CJ93*(1+M93))) | CV93: =MAX(0,MIN(CP93-CQ93-CR93-CU93,BN93*(1+M93)-BO93+AC93)) | CW93: =MAX(0,-CP93) | CX93: =MIN(CK93,CL93-CS93+CM93-CT93) | CY93: =IF(CL93-CS93+CM93-CT93>1,CX93*(CL93-CS93)/(CL93-CS93+CM93-CT93),0) | CZ93: =CX93-CY93 | DA93: =IF(CC93>0,MAX(0,1-CD93/CC93),0) | DB93: =CQ93*DA93 | DC93: =CC93*(1+M93-$B$20)-CQ93+CW93 | DD93: =CD93-(CQ93-DB93)+CW93 | DE93: =CF93*(1+M93)-CH93-CS93-CY93+Y93+AA93 | DF93: =CG93*(1+M93)-CI93-CT93-CZ93+Z93+AB93 | DG93: =CJ93*(1+M93)-CU93+CX93 | DH93: =AE93+CR93+CH93+CI93+CX93+CV93+BS93+AI93+CA93+CB93 | DI93: =CE93+DB93+BU93 | DJ93: =IF((DH93+DI93+0.5*F93)<=tax_tables!$B$14,0,IF((DH93+DI93+0.5*F93)<=tax_tables!$B$15,MIN(0.5*F93,0.5*((DH93+DI93+0.5*F93)-tax_tables!$B$14)),MIN(0.85*F93,0.85*((DH93+DI93+0.5*F93)-tax_tables!$B$15)+MIN(0.5*F93,tax_tables!$B$15-tax_tables!$B$14)))) | DK93: =DH93+DI93+DJ93 | DL93: =(B93>=65)+(C93>=65) | DM93: =(tax_tables!$B$5+tax_tables!$B$6*DL93)*P93 | DN93: =IF(AND(A93>=tax_tables!$B$8,A93<=tax_tables!$B$9),DL93*MAX(0,tax_tables!$B$7-tax_tables!$B$11*MAX(0,DK93-tax_tables!$B$10)),0) | DO93: =IFERROR(MAX(tax_tables!$B$16,INDEX(tax_tables!$W$5:$W$8,MATCH(A93,tax_tables!$V$5:$V$8,0))-tax_tables!$B$18*MAX(0,DK93-tax_tables!$B$17*1.01^(A93-tax_tables!$B$4))),tax_tables!$B$16) | DP93: =MAX(0,BM93-BB93-tax_tables!$B$23*DK93) | DQ93: =AN93+MIN(DO93,DY92+DZ92+EA92+AL93*properties!$H$2*O93)+DP93+$B$61*O93 | DR93: =MAX(DM93,DQ93) | DS93: =MAX(0,DH93+DJ93-DR93-DN93) | DT93: =MAX(0,DI93-MAX(0,DR93+DN93-DH93-DJ93)) | DU93: =SUMPRODUCT((DS93>tax_tables!$E$5:$E$16*P93)*(DS93-tax_tables!$E$5:$E$16*P93)*tax_tables!$G$5:$G$16)+SUMPRODUCT(((DS93+DT93)>tax_tables!$I$5:$I$16*P93)*((DS93+DT93)-tax_tables!$I$5:$I$16*P93)*tax_tables!$K$5:$K$16)-SUMPRODUCT((DS93>tax_tables!$I$5:$I$16*P93)*(DS93-tax_tables!$I$5:$I$16*P93)*tax_tables!$K$5:$K$16)+tax_tables!$B$19*BV93+tax_tables!$B$12*MIN(CE93+DB93+BS93+BU93,MAX(0,DK93-tax_tables!$B$13)) | DV93: =IF($B$39="",0,IF(A93>=$B$39,1,0)) | DW93: =IF(B93+0.5>=tax_tables!$B$30,MIN(CS93+CH93+CY93+CA93,tax_tables!$B$29),0)+IF(C93+0.5>=tax_tables!$B$30,MIN(CT93+CI93+CZ93+CB93,tax_tables!$B$29),0) | DX93: =MAX(0,DK93-tax_tables!$B$28*DJ93-DW93-tax_tables!$B$26*IF(tax_tables!$B$27=1,P93,1)) | DY93: =(1-DV93)*SUMPRODUCT((DX93>tax_tables!$M$5:$M$16*IF(tax_tables!$B$27=1,P93,1))*(DX93-tax_tables!$M$5:$M$16*IF(tax_tables!$B$27=1,P93,1))*tax_tables!$O$5:$O$16) | DZ93: =(1-DV93)*tax_tables!$B$31*DX93 | EA93: =DV93*$B$40*MAX(0,DK93-DJ93) | EB93: =DU93+DY93+DZ93+EA93 | EC93: =DC93+DE93+DF93+DG93+BP93 | ED93: =EC93+BW93-AP93+BX93
A94: =A93+1 | B94: =A94-household!$B$6 | C94: =A94-household!$B$9 | D94: =AS94+AT94+AU94+AV94+AZ94+BM94+AK94 | E94: =CN94+AG94+AF94 | F94: =BY94+BZ94 | G94: =CQ94+CR94+CU94+CH94+CI94+CE94-CW94+CV94+BO94 | H94: =IF(CC94+CF94+CG94+CJ94+BN94<=0,"",G94/(CC94+CF94+CG94+CJ94+BN94)) | I94: =EC94/O94 | J94: =ED94/O94 | K94: =MAX(0,CP94-CQ94-CR94-CU94-CV94) | M94: =IF(L94="",$B$19,L94) | O94: =(1+$B$18)^(A94-household!$B$4+1) | P94: =(1+$B$18)^(A94-tax_tables!$B$4) | Q94: =(1+$B$21)^(A94-household!$B$4+1) | R94: =(1+$B$22)^(A94-household!$B$4+1) | S94: =(1+$B$23)^(A94-household!$B$4+1) | T94: =IF(A94<$B$5,1,0) | U94: =IF(A94<$B$6,1,0) | V94: =IF(T94+U94>0,1,0) | W94: =T94*$B$7*O94+SUMPRODUCT(($B$83:$B$88=A94)*($D$83:$D$88="Wages: person 1")*$C$83:$C$88)*O94 | X94: =U94*$B$8*O94+SUMPRODUCT(($B$83:$B$88=A94)*($D$83:$D$88="Wages: person 2")*$C$83:$C$88)*O94 | Y94: =T94*$B$9*O94 | Z94: =U94*$B$10*O94 | AA94: =T94*$B$11*O94 | AB94: =U94*$B$12*O94 | AC94: =V94*$B$13*O94 | AD94: =W94+X94 | AE94: =AD94-Y94-Z94-AC94 | AF94: =0.062*MIN(W94,tax_tables!$B$21*P94)+0.062*MIN(X94,tax_tables!$B$21*P94)+0.0145*AD94+0.009*MAX(0,AD94-tax_tables!$B$22) | AG94: =$B$14*AE94 | AH94: =AD94-Y94-Z94-AC94-AF94-AG94 | AI94: =SUMPRODUCT(($B$83:$B$88=A94)*($D$83:$D$88="Other taxable income")*$C$83:$C$88)*O94 | AJ94: =SUMPRODUCT(($B$83:$B$88=A94)*($D$83:$D$88="Tax-free money in")*$C$83:$C$88)*O94 | AK94: =SUMPRODUCT(($B$83:$B$88=A94)*($D$83:$D$88="Expense")*$C$83:$C$88)*O94 | AL94: =IF(OR($B$75="",A94<$B$75),1,0) | AM94: =AP93 | AN94: =AL94*AM94*properties!$J$2 | AO94: =AL94*MIN(properties!$K$2,AM94+AN94) | AP94: =AL94*(AM94+AN94-AO94) | AQ94: =AL94*properties!$G$2*O94 | AR94: =(1-AL94)*$E$75*O94 | AS94: =AO94+AQ94+AR94 | AT94: =SUMIF(budget!$A$2:$A$300,"household",budget!$F$2:$F$300)*O94*IF(N94="",1,N94) | AU94: =SUMPRODUCT((other_budget!$C$2:$C$30<=A94)*(other_budget!$D$2:$D$30>=A94)*other_budget!$B$2:$B$30)*O94 | AV94: =SUMPRODUCT((kids_budget!$D$2:$D$40<=A94)*(kids_budget!$E$2:$E$40>=A94)*(kids_budget!$G$2:$G$40<>"college_funds")*kids_budget!$C$2:$C$40*((kids_budget!$F$2:$F$40="college")*R94+(kids_budget!$F$2:$F$40<>"college")*O94)) | AW94: =SUMPRODUCT((kids_budget!$D$2:$D$40<=A94)*(kids_budget!$E$2:$E$40>=A94)*(kids_budget!$G$2:$G$40="college_funds")*kids_budget!$C$2:$C$40*((kids_budget!$F$2:$F$40="college")*R94+(kids_budget!$F$2:$F$40<>"college")*O94)) | AX94: =BA93 | AY94: =MIN(AW94,AX94*(1+M94)) | AZ94: =AW94-AY94 | BA94: =AX94*(1+M94)-AY94 | BB94: =V94*healthcare!$B$5*Q94 | BC94: =(1-V94)*((B94<65)+(C94<65)) | BD94: =COUNTIF(household!$C$16:$C$23,">="&A94) | BE94: =(BC94*healthcare!$B$2+IF(BC94>0,BD94,0)*healthcare!$B$3)*12*Q94 | BF94: =IF(BC94>0,(BC94+BD94)*healthcare!$B$4*Q94,0) | BG94: =(B94>=65)+(C94>=65) | BH94: =BG94*(healthcare!$B$6+healthcare!$B$7+healthcare!$B$8)*12*Q94 | BI94: =BG94*healthcare!$B$9*Q94 | BJ94: =BG94*12*O94*SUMPRODUCT((DK92>tax_tables!$Q$5:$Q$9*P94)*tax_tables!$T$5:$T$9) | BK94: =AND(B94>=$B$51,B94<$B$51+$B$52)*1+AND(C94>=$B$53,C94<$B$53+$B$54)*1 | BL94: =BK94*$B$55*S94 | BM94: =BB94+BE94+BF94+BH94+BI94+BJ94+BL94 | BN94: =BP93 | BO94: =IF(V94=1,0,MIN(BN94*(1+M94),BF94+BG94*(healthcare!$B$6+healthcare!$B$7)*12*Q94+BI94+BJ94+BL94)) | BP94: =BN94*(1+M94)-BO94+AC94-CV94 | BQ94: =SUMPRODUCT((1-($B$76:$B$79>0)*(A94>=$B$76:$B$79))*(1-(($C$76:$C$79>0)*(A94>=$C$76:$C$79)))*(properties!$L$3:$L$6-properties!$M$3:$M$6))*O94+SUMPRODUCT((1-($B$76:$B$79>0)*(A94>=$B$76:$B$79))*(($C$76:$C$79>0)*(A94>=$C$76:$C$79))*($D$76:$D$79-$E$76:$E$79))*O94 | BR94: =SUMPRODUCT((1-($B$76:$B$79>0)*(A94>=$B$76:$B$79))*properties!$N$3:$N$6*(A94<=properties!$O$3:$O$6)) | BS94: =MAX(0,BQ94-BR94) | BT94: =SUMPRODUCT(($B$75:$B$79=A94)*$G$75:$G$79) | BU94: =SUMPRODUCT(($B$75:$B$79=A94)*$H$75:$H$79) | BV94: =SUMPRODUCT(($B$75:$B$79=A94)*$I$75:$I$79) | BW94: =AL94*properties!$C$2*(1+properties!$D$2)^(A94-household!$B$4+1) | BX94: =SUMPRODUCT((1-($B$76:$B$79>0)*(A94>=$B$76:$B$79))*properties!$C$3:$C$6*(1+properties!$D$3:$D$6)^(A94-household!$B$4+1)) | BY94: =IF(A94>=$B$31,IF(A94>=$B$32,MAX(household!$B$11*12*(1-$B$28)*O94*IF(A94>=$B$30,1-$B$29,1)*$B$33,0.5*household!$B$12*12*(1-$B$28)*O94*IF(A94>=$B$30,1-$B$29,1)*$B$35),household!$B$11*12*(1-$B$28)*O94*IF(A94>=$B$30,1-$B$29,1)*$B$33),0) | BZ94: =IF(A94>=$B$32,IF(A94>=$B$31,MAX(household!$B$12*12*(1-$B$28)*O94*IF(A94>=$B$30,1-$B$29,1)*$B$34,0.5*household!$B$11*12*(1-$B$28)*O94*IF(A94>=$B$30,1-$B$29,1)*$B$36),household!$B$12*12*(1-$B$28)*O94*IF(A94>=$B$30,1-$B$29,1)*$B$34),0) | CA94: =IF(AND($B$43<>0,A94>=household!$B$6+$B$44),$B$43*(1+$B$18)^(MAX(household!$B$6+$B$44,household!$B$4-1)-household!$B$4+1)*(1+$B$47*$B$18)^(A94-MAX(household!$B$6+$B$44,household!$B$4-1)),0) | CB94: =IF(AND($B$45<>0,A94>=household!$B$9+$B$46),$B$45*(1+$B$18)^(MAX(household!$B$9+$B$46,household!$B$4-1)-household!$B$4+1)*(1+$B$47*$B$18)^(A94-MAX(household!$B$9+$B$46,household!$B$4-1)),0) | CC94: =DC93 | CD94: =DD93 | CE94: =$B$20*CC94 | CF94: =DE93 | CG94: =DF93 | CH94: =IF(B94>=$B$71,MAX(0,CF94)/INDEX(tax_tables!$Z$5:$Z$53,MATCH(B94,tax_tables!$Y$5:$Y$53,0)),0) | CI94: =IF(C94>=$B$72,MAX(0,CG94)/INDEX(tax_tables!$Z$5:$Z$53,MATCH(C94,tax_tables!$Y$5:$Y$53,0)),0) | CJ94: =DG93 | CK94: =IF(OR($B$59="",$B$60=""),0,IF(AND(A94>=$B$59,A94<=$B$60),$B$58*O94,0)) | CL94: =MAX(0,CF94*(1+M94)-CH94) | CM94: =MAX(0,CG94*(1+M94)-CI94) | CN94: =EB93-AG93 | CO94: =AH94+F94+CA94+CB94+BQ94+CE94+CH94+CI94+BT94+AI94+AJ94+BO94 | CP94: =D94+CN94-CO94 | CQ94: =MAX(0,MIN(CP94,CC94*(1+M94-$B$20))) | CR94: =MAX(0,MIN(CP94-CQ94,CL94+CM94)) | CS94: =IF(CL94+CM94>1,CR94*CL94/(CL94+CM94),0) | CT94: =CR94-CS94 | CU94: =MAX(0,MIN(CP94-CQ94-CR94,CJ94*(1+M94))) | CV94: =MAX(0,MIN(CP94-CQ94-CR94-CU94,BN94*(1+M94)-BO94+AC94)) | CW94: =MAX(0,-CP94) | CX94: =MIN(CK94,CL94-CS94+CM94-CT94) | CY94: =IF(CL94-CS94+CM94-CT94>1,CX94*(CL94-CS94)/(CL94-CS94+CM94-CT94),0) | CZ94: =CX94-CY94 | DA94: =IF(CC94>0,MAX(0,1-CD94/CC94),0) | DB94: =CQ94*DA94 | DC94: =CC94*(1+M94-$B$20)-CQ94+CW94 | DD94: =CD94-(CQ94-DB94)+CW94 | DE94: =CF94*(1+M94)-CH94-CS94-CY94+Y94+AA94 | DF94: =CG94*(1+M94)-CI94-CT94-CZ94+Z94+AB94 | DG94: =CJ94*(1+M94)-CU94+CX94 | DH94: =AE94+CR94+CH94+CI94+CX94+CV94+BS94+AI94+CA94+CB94 | DI94: =CE94+DB94+BU94 | DJ94: =IF((DH94+DI94+0.5*F94)<=tax_tables!$B$14,0,IF((DH94+DI94+0.5*F94)<=tax_tables!$B$15,MIN(0.5*F94,0.5*((DH94+DI94+0.5*F94)-tax_tables!$B$14)),MIN(0.85*F94,0.85*((DH94+DI94+0.5*F94)-tax_tables!$B$15)+MIN(0.5*F94,tax_tables!$B$15-tax_tables!$B$14)))) | DK94: =DH94+DI94+DJ94 | DL94: =(B94>=65)+(C94>=65) | DM94: =(tax_tables!$B$5+tax_tables!$B$6*DL94)*P94 | DN94: =IF(AND(A94>=tax_tables!$B$8,A94<=tax_tables!$B$9),DL94*MAX(0,tax_tables!$B$7-tax_tables!$B$11*MAX(0,DK94-tax_tables!$B$10)),0) | DO94: =IFERROR(MAX(tax_tables!$B$16,INDEX(tax_tables!$W$5:$W$8,MATCH(A94,tax_tables!$V$5:$V$8,0))-tax_tables!$B$18*MAX(0,DK94-tax_tables!$B$17*1.01^(A94-tax_tables!$B$4))),tax_tables!$B$16) | DP94: =MAX(0,BM94-BB94-tax_tables!$B$23*DK94) | DQ94: =AN94+MIN(DO94,DY93+DZ93+EA93+AL94*properties!$H$2*O94)+DP94+$B$61*O94 | DR94: =MAX(DM94,DQ94) | DS94: =MAX(0,DH94+DJ94-DR94-DN94) | DT94: =MAX(0,DI94-MAX(0,DR94+DN94-DH94-DJ94)) | DU94: =SUMPRODUCT((DS94>tax_tables!$E$5:$E$16*P94)*(DS94-tax_tables!$E$5:$E$16*P94)*tax_tables!$G$5:$G$16)+SUMPRODUCT(((DS94+DT94)>tax_tables!$I$5:$I$16*P94)*((DS94+DT94)-tax_tables!$I$5:$I$16*P94)*tax_tables!$K$5:$K$16)-SUMPRODUCT((DS94>tax_tables!$I$5:$I$16*P94)*(DS94-tax_tables!$I$5:$I$16*P94)*tax_tables!$K$5:$K$16)+tax_tables!$B$19*BV94+tax_tables!$B$12*MIN(CE94+DB94+BS94+BU94,MAX(0,DK94-tax_tables!$B$13)) | DV94: =IF($B$39="",0,IF(A94>=$B$39,1,0)) | DW94: =IF(B94+0.5>=tax_tables!$B$30,MIN(CS94+CH94+CY94+CA94,tax_tables!$B$29),0)+IF(C94+0.5>=tax_tables!$B$30,MIN(CT94+CI94+CZ94+CB94,tax_tables!$B$29),0) | DX94: =MAX(0,DK94-tax_tables!$B$28*DJ94-DW94-tax_tables!$B$26*IF(tax_tables!$B$27=1,P94,1)) | DY94: =(1-DV94)*SUMPRODUCT((DX94>tax_tables!$M$5:$M$16*IF(tax_tables!$B$27=1,P94,1))*(DX94-tax_tables!$M$5:$M$16*IF(tax_tables!$B$27=1,P94,1))*tax_tables!$O$5:$O$16) | DZ94: =(1-DV94)*tax_tables!$B$31*DX94 | EA94: =DV94*$B$40*MAX(0,DK94-DJ94) | EB94: =DU94+DY94+DZ94+EA94 | EC94: =DC94+DE94+DF94+DG94+BP94 | ED94: =EC94+BW94-AP94+BX94
A95: =A94+1 | B95: =A95-household!$B$6 | C95: =A95-household!$B$9 | D95: =AS95+AT95+AU95+AV95+AZ95+BM95+AK95 | E95: =CN95+AG95+AF95 | F95: =BY95+BZ95 | G95: =CQ95+CR95+CU95+CH95+CI95+CE95-CW95+CV95+BO95 | H95: =IF(CC95+CF95+CG95+CJ95+BN95<=0,"",G95/(CC95+CF95+CG95+CJ95+BN95)) | I95: =EC95/O95 | J95: =ED95/O95 | K95: =MAX(0,CP95-CQ95-CR95-CU95-CV95) | M95: =IF(L95="",$B$19,L95) | O95: =(1+$B$18)^(A95-household!$B$4+1) | P95: =(1+$B$18)^(A95-tax_tables!$B$4) | Q95: =(1+$B$21)^(A95-household!$B$4+1) | R95: =(1+$B$22)^(A95-household!$B$4+1) | S95: =(1+$B$23)^(A95-household!$B$4+1) | T95: =IF(A95<$B$5,1,0) | U95: =IF(A95<$B$6,1,0) | V95: =IF(T95+U95>0,1,0) | W95: =T95*$B$7*O95+SUMPRODUCT(($B$83:$B$88=A95)*($D$83:$D$88="Wages: person 1")*$C$83:$C$88)*O95 | X95: =U95*$B$8*O95+SUMPRODUCT(($B$83:$B$88=A95)*($D$83:$D$88="Wages: person 2")*$C$83:$C$88)*O95 | Y95: =T95*$B$9*O95 | Z95: =U95*$B$10*O95 | AA95: =T95*$B$11*O95 | AB95: =U95*$B$12*O95 | AC95: =V95*$B$13*O95 | AD95: =W95+X95 | AE95: =AD95-Y95-Z95-AC95 | AF95: =0.062*MIN(W95,tax_tables!$B$21*P95)+0.062*MIN(X95,tax_tables!$B$21*P95)+0.0145*AD95+0.009*MAX(0,AD95-tax_tables!$B$22) | AG95: =$B$14*AE95 | AH95: =AD95-Y95-Z95-AC95-AF95-AG95 | AI95: =SUMPRODUCT(($B$83:$B$88=A95)*($D$83:$D$88="Other taxable income")*$C$83:$C$88)*O95 | AJ95: =SUMPRODUCT(($B$83:$B$88=A95)*($D$83:$D$88="Tax-free money in")*$C$83:$C$88)*O95 | AK95: =SUMPRODUCT(($B$83:$B$88=A95)*($D$83:$D$88="Expense")*$C$83:$C$88)*O95 | AL95: =IF(OR($B$75="",A95<$B$75),1,0) | AM95: =AP94 | AN95: =AL95*AM95*properties!$J$2 | AO95: =AL95*MIN(properties!$K$2,AM95+AN95) | AP95: =AL95*(AM95+AN95-AO95) | AQ95: =AL95*properties!$G$2*O95 | AR95: =(1-AL95)*$E$75*O95 | AS95: =AO95+AQ95+AR95 | AT95: =SUMIF(budget!$A$2:$A$300,"household",budget!$F$2:$F$300)*O95*IF(N95="",1,N95) | AU95: =SUMPRODUCT((other_budget!$C$2:$C$30<=A95)*(other_budget!$D$2:$D$30>=A95)*other_budget!$B$2:$B$30)*O95 | AV95: =SUMPRODUCT((kids_budget!$D$2:$D$40<=A95)*(kids_budget!$E$2:$E$40>=A95)*(kids_budget!$G$2:$G$40<>"college_funds")*kids_budget!$C$2:$C$40*((kids_budget!$F$2:$F$40="college")*R95+(kids_budget!$F$2:$F$40<>"college")*O95)) | AW95: =SUMPRODUCT((kids_budget!$D$2:$D$40<=A95)*(kids_budget!$E$2:$E$40>=A95)*(kids_budget!$G$2:$G$40="college_funds")*kids_budget!$C$2:$C$40*((kids_budget!$F$2:$F$40="college")*R95+(kids_budget!$F$2:$F$40<>"college")*O95)) | AX95: =BA94 | AY95: =MIN(AW95,AX95*(1+M95)) | AZ95: =AW95-AY95 | BA95: =AX95*(1+M95)-AY95 | BB95: =V95*healthcare!$B$5*Q95 | BC95: =(1-V95)*((B95<65)+(C95<65)) | BD95: =COUNTIF(household!$C$16:$C$23,">="&A95) | BE95: =(BC95*healthcare!$B$2+IF(BC95>0,BD95,0)*healthcare!$B$3)*12*Q95 | BF95: =IF(BC95>0,(BC95+BD95)*healthcare!$B$4*Q95,0) | BG95: =(B95>=65)+(C95>=65) | BH95: =BG95*(healthcare!$B$6+healthcare!$B$7+healthcare!$B$8)*12*Q95 | BI95: =BG95*healthcare!$B$9*Q95 | BJ95: =BG95*12*O95*SUMPRODUCT((DK93>tax_tables!$Q$5:$Q$9*P95)*tax_tables!$T$5:$T$9) | BK95: =AND(B95>=$B$51,B95<$B$51+$B$52)*1+AND(C95>=$B$53,C95<$B$53+$B$54)*1 | BL95: =BK95*$B$55*S95 | BM95: =BB95+BE95+BF95+BH95+BI95+BJ95+BL95 | BN95: =BP94 | BO95: =IF(V95=1,0,MIN(BN95*(1+M95),BF95+BG95*(healthcare!$B$6+healthcare!$B$7)*12*Q95+BI95+BJ95+BL95)) | BP95: =BN95*(1+M95)-BO95+AC95-CV95 | BQ95: =SUMPRODUCT((1-($B$76:$B$79>0)*(A95>=$B$76:$B$79))*(1-(($C$76:$C$79>0)*(A95>=$C$76:$C$79)))*(properties!$L$3:$L$6-properties!$M$3:$M$6))*O95+SUMPRODUCT((1-($B$76:$B$79>0)*(A95>=$B$76:$B$79))*(($C$76:$C$79>0)*(A95>=$C$76:$C$79))*($D$76:$D$79-$E$76:$E$79))*O95 | BR95: =SUMPRODUCT((1-($B$76:$B$79>0)*(A95>=$B$76:$B$79))*properties!$N$3:$N$6*(A95<=properties!$O$3:$O$6)) | BS95: =MAX(0,BQ95-BR95) | BT95: =SUMPRODUCT(($B$75:$B$79=A95)*$G$75:$G$79) | BU95: =SUMPRODUCT(($B$75:$B$79=A95)*$H$75:$H$79) | BV95: =SUMPRODUCT(($B$75:$B$79=A95)*$I$75:$I$79) | BW95: =AL95*properties!$C$2*(1+properties!$D$2)^(A95-household!$B$4+1) | BX95: =SUMPRODUCT((1-($B$76:$B$79>0)*(A95>=$B$76:$B$79))*properties!$C$3:$C$6*(1+properties!$D$3:$D$6)^(A95-household!$B$4+1)) | BY95: =IF(A95>=$B$31,IF(A95>=$B$32,MAX(household!$B$11*12*(1-$B$28)*O95*IF(A95>=$B$30,1-$B$29,1)*$B$33,0.5*household!$B$12*12*(1-$B$28)*O95*IF(A95>=$B$30,1-$B$29,1)*$B$35),household!$B$11*12*(1-$B$28)*O95*IF(A95>=$B$30,1-$B$29,1)*$B$33),0) | BZ95: =IF(A95>=$B$32,IF(A95>=$B$31,MAX(household!$B$12*12*(1-$B$28)*O95*IF(A95>=$B$30,1-$B$29,1)*$B$34,0.5*household!$B$11*12*(1-$B$28)*O95*IF(A95>=$B$30,1-$B$29,1)*$B$36),household!$B$12*12*(1-$B$28)*O95*IF(A95>=$B$30,1-$B$29,1)*$B$34),0) | CA95: =IF(AND($B$43<>0,A95>=household!$B$6+$B$44),$B$43*(1+$B$18)^(MAX(household!$B$6+$B$44,household!$B$4-1)-household!$B$4+1)*(1+$B$47*$B$18)^(A95-MAX(household!$B$6+$B$44,household!$B$4-1)),0) | CB95: =IF(AND($B$45<>0,A95>=household!$B$9+$B$46),$B$45*(1+$B$18)^(MAX(household!$B$9+$B$46,household!$B$4-1)-household!$B$4+1)*(1+$B$47*$B$18)^(A95-MAX(household!$B$9+$B$46,household!$B$4-1)),0) | CC95: =DC94 | CD95: =DD94 | CE95: =$B$20*CC95 | CF95: =DE94 | CG95: =DF94 | CH95: =IF(B95>=$B$71,MAX(0,CF95)/INDEX(tax_tables!$Z$5:$Z$53,MATCH(B95,tax_tables!$Y$5:$Y$53,0)),0) | CI95: =IF(C95>=$B$72,MAX(0,CG95)/INDEX(tax_tables!$Z$5:$Z$53,MATCH(C95,tax_tables!$Y$5:$Y$53,0)),0) | CJ95: =DG94 | CK95: =IF(OR($B$59="",$B$60=""),0,IF(AND(A95>=$B$59,A95<=$B$60),$B$58*O95,0)) | CL95: =MAX(0,CF95*(1+M95)-CH95) | CM95: =MAX(0,CG95*(1+M95)-CI95) | CN95: =EB94-AG94 | CO95: =AH95+F95+CA95+CB95+BQ95+CE95+CH95+CI95+BT95+AI95+AJ95+BO95 | CP95: =D95+CN95-CO95 | CQ95: =MAX(0,MIN(CP95,CC95*(1+M95-$B$20))) | CR95: =MAX(0,MIN(CP95-CQ95,CL95+CM95)) | CS95: =IF(CL95+CM95>1,CR95*CL95/(CL95+CM95),0) | CT95: =CR95-CS95 | CU95: =MAX(0,MIN(CP95-CQ95-CR95,CJ95*(1+M95))) | CV95: =MAX(0,MIN(CP95-CQ95-CR95-CU95,BN95*(1+M95)-BO95+AC95)) | CW95: =MAX(0,-CP95) | CX95: =MIN(CK95,CL95-CS95+CM95-CT95) | CY95: =IF(CL95-CS95+CM95-CT95>1,CX95*(CL95-CS95)/(CL95-CS95+CM95-CT95),0) | CZ95: =CX95-CY95 | DA95: =IF(CC95>0,MAX(0,1-CD95/CC95),0) | DB95: =CQ95*DA95 | DC95: =CC95*(1+M95-$B$20)-CQ95+CW95 | DD95: =CD95-(CQ95-DB95)+CW95 | DE95: =CF95*(1+M95)-CH95-CS95-CY95+Y95+AA95 | DF95: =CG95*(1+M95)-CI95-CT95-CZ95+Z95+AB95 | DG95: =CJ95*(1+M95)-CU95+CX95 | DH95: =AE95+CR95+CH95+CI95+CX95+CV95+BS95+AI95+CA95+CB95 | DI95: =CE95+DB95+BU95 | DJ95: =IF((DH95+DI95+0.5*F95)<=tax_tables!$B$14,0,IF((DH95+DI95+0.5*F95)<=tax_tables!$B$15,MIN(0.5*F95,0.5*((DH95+DI95+0.5*F95)-tax_tables!$B$14)),MIN(0.85*F95,0.85*((DH95+DI95+0.5*F95)-tax_tables!$B$15)+MIN(0.5*F95,tax_tables!$B$15-tax_tables!$B$14)))) | DK95: =DH95+DI95+DJ95 | DL95: =(B95>=65)+(C95>=65) | DM95: =(tax_tables!$B$5+tax_tables!$B$6*DL95)*P95 | DN95: =IF(AND(A95>=tax_tables!$B$8,A95<=tax_tables!$B$9),DL95*MAX(0,tax_tables!$B$7-tax_tables!$B$11*MAX(0,DK95-tax_tables!$B$10)),0) | DO95: =IFERROR(MAX(tax_tables!$B$16,INDEX(tax_tables!$W$5:$W$8,MATCH(A95,tax_tables!$V$5:$V$8,0))-tax_tables!$B$18*MAX(0,DK95-tax_tables!$B$17*1.01^(A95-tax_tables!$B$4))),tax_tables!$B$16) | DP95: =MAX(0,BM95-BB95-tax_tables!$B$23*DK95) | DQ95: =AN95+MIN(DO95,DY94+DZ94+EA94+AL95*properties!$H$2*O95)+DP95+$B$61*O95 | DR95: =MAX(DM95,DQ95) | DS95: =MAX(0,DH95+DJ95-DR95-DN95) | DT95: =MAX(0,DI95-MAX(0,DR95+DN95-DH95-DJ95)) | DU95: =SUMPRODUCT((DS95>tax_tables!$E$5:$E$16*P95)*(DS95-tax_tables!$E$5:$E$16*P95)*tax_tables!$G$5:$G$16)+SUMPRODUCT(((DS95+DT95)>tax_tables!$I$5:$I$16*P95)*((DS95+DT95)-tax_tables!$I$5:$I$16*P95)*tax_tables!$K$5:$K$16)-SUMPRODUCT((DS95>tax_tables!$I$5:$I$16*P95)*(DS95-tax_tables!$I$5:$I$16*P95)*tax_tables!$K$5:$K$16)+tax_tables!$B$19*BV95+tax_tables!$B$12*MIN(CE95+DB95+BS95+BU95,MAX(0,DK95-tax_tables!$B$13)) | DV95: =IF($B$39="",0,IF(A95>=$B$39,1,0)) | DW95: =IF(B95+0.5>=tax_tables!$B$30,MIN(CS95+CH95+CY95+CA95,tax_tables!$B$29),0)+IF(C95+0.5>=tax_tables!$B$30,MIN(CT95+CI95+CZ95+CB95,tax_tables!$B$29),0) | DX95: =MAX(0,DK95-tax_tables!$B$28*DJ95-DW95-tax_tables!$B$26*IF(tax_tables!$B$27=1,P95,1)) | DY95: =(1-DV95)*SUMPRODUCT((DX95>tax_tables!$M$5:$M$16*IF(tax_tables!$B$27=1,P95,1))*(DX95-tax_tables!$M$5:$M$16*IF(tax_tables!$B$27=1,P95,1))*tax_tables!$O$5:$O$16) | DZ95: =(1-DV95)*tax_tables!$B$31*DX95 | EA95: =DV95*$B$40*MAX(0,DK95-DJ95) | EB95: =DU95+DY95+DZ95+EA95 | EC95: =DC95+DE95+DF95+DG95+BP95 | ED95: =EC95+BW95-AP95+BX95
A96: =A95+1 | B96: =A96-household!$B$6 | C96: =A96-household!$B$9 | D96: =AS96+AT96+AU96+AV96+AZ96+BM96+AK96 | E96: =CN96+AG96+AF96 | F96: =BY96+BZ96 | G96: =CQ96+CR96+CU96+CH96+CI96+CE96-CW96+CV96+BO96 | H96: =IF(CC96+CF96+CG96+CJ96+BN96<=0,"",G96/(CC96+CF96+CG96+CJ96+BN96)) | I96: =EC96/O96 | J96: =ED96/O96 | K96: =MAX(0,CP96-CQ96-CR96-CU96-CV96) | M96: =IF(L96="",$B$19,L96) | O96: =(1+$B$18)^(A96-household!$B$4+1) | P96: =(1+$B$18)^(A96-tax_tables!$B$4) | Q96: =(1+$B$21)^(A96-household!$B$4+1) | R96: =(1+$B$22)^(A96-household!$B$4+1) | S96: =(1+$B$23)^(A96-household!$B$4+1) | T96: =IF(A96<$B$5,1,0) | U96: =IF(A96<$B$6,1,0) | V96: =IF(T96+U96>0,1,0) | W96: =T96*$B$7*O96+SUMPRODUCT(($B$83:$B$88=A96)*($D$83:$D$88="Wages: person 1")*$C$83:$C$88)*O96 | X96: =U96*$B$8*O96+SUMPRODUCT(($B$83:$B$88=A96)*($D$83:$D$88="Wages: person 2")*$C$83:$C$88)*O96 | Y96: =T96*$B$9*O96 | Z96: =U96*$B$10*O96 | AA96: =T96*$B$11*O96 | AB96: =U96*$B$12*O96 | AC96: =V96*$B$13*O96 | AD96: =W96+X96 | AE96: =AD96-Y96-Z96-AC96 | AF96: =0.062*MIN(W96,tax_tables!$B$21*P96)+0.062*MIN(X96,tax_tables!$B$21*P96)+0.0145*AD96+0.009*MAX(0,AD96-tax_tables!$B$22) | AG96: =$B$14*AE96 | AH96: =AD96-Y96-Z96-AC96-AF96-AG96 | AI96: =SUMPRODUCT(($B$83:$B$88=A96)*($D$83:$D$88="Other taxable income")*$C$83:$C$88)*O96 | AJ96: =SUMPRODUCT(($B$83:$B$88=A96)*($D$83:$D$88="Tax-free money in")*$C$83:$C$88)*O96 | AK96: =SUMPRODUCT(($B$83:$B$88=A96)*($D$83:$D$88="Expense")*$C$83:$C$88)*O96 | AL96: =IF(OR($B$75="",A96<$B$75),1,0) | AM96: =AP95 | AN96: =AL96*AM96*properties!$J$2 | AO96: =AL96*MIN(properties!$K$2,AM96+AN96) | AP96: =AL96*(AM96+AN96-AO96) | AQ96: =AL96*properties!$G$2*O96 | AR96: =(1-AL96)*$E$75*O96 | AS96: =AO96+AQ96+AR96 | AT96: =SUMIF(budget!$A$2:$A$300,"household",budget!$F$2:$F$300)*O96*IF(N96="",1,N96) | AU96: =SUMPRODUCT((other_budget!$C$2:$C$30<=A96)*(other_budget!$D$2:$D$30>=A96)*other_budget!$B$2:$B$30)*O96 | AV96: =SUMPRODUCT((kids_budget!$D$2:$D$40<=A96)*(kids_budget!$E$2:$E$40>=A96)*(kids_budget!$G$2:$G$40<>"college_funds")*kids_budget!$C$2:$C$40*((kids_budget!$F$2:$F$40="college")*R96+(kids_budget!$F$2:$F$40<>"college")*O96)) | AW96: =SUMPRODUCT((kids_budget!$D$2:$D$40<=A96)*(kids_budget!$E$2:$E$40>=A96)*(kids_budget!$G$2:$G$40="college_funds")*kids_budget!$C$2:$C$40*((kids_budget!$F$2:$F$40="college")*R96+(kids_budget!$F$2:$F$40<>"college")*O96)) | AX96: =BA95 | AY96: =MIN(AW96,AX96*(1+M96)) | AZ96: =AW96-AY96 | BA96: =AX96*(1+M96)-AY96 | BB96: =V96*healthcare!$B$5*Q96 | BC96: =(1-V96)*((B96<65)+(C96<65)) | BD96: =COUNTIF(household!$C$16:$C$23,">="&A96) | BE96: =(BC96*healthcare!$B$2+IF(BC96>0,BD96,0)*healthcare!$B$3)*12*Q96 | BF96: =IF(BC96>0,(BC96+BD96)*healthcare!$B$4*Q96,0) | BG96: =(B96>=65)+(C96>=65) | BH96: =BG96*(healthcare!$B$6+healthcare!$B$7+healthcare!$B$8)*12*Q96 | BI96: =BG96*healthcare!$B$9*Q96 | BJ96: =BG96*12*O96*SUMPRODUCT((DK94>tax_tables!$Q$5:$Q$9*P96)*tax_tables!$T$5:$T$9) | BK96: =AND(B96>=$B$51,B96<$B$51+$B$52)*1+AND(C96>=$B$53,C96<$B$53+$B$54)*1 | BL96: =BK96*$B$55*S96 | BM96: =BB96+BE96+BF96+BH96+BI96+BJ96+BL96 | BN96: =BP95 | BO96: =IF(V96=1,0,MIN(BN96*(1+M96),BF96+BG96*(healthcare!$B$6+healthcare!$B$7)*12*Q96+BI96+BJ96+BL96)) | BP96: =BN96*(1+M96)-BO96+AC96-CV96 | BQ96: =SUMPRODUCT((1-($B$76:$B$79>0)*(A96>=$B$76:$B$79))*(1-(($C$76:$C$79>0)*(A96>=$C$76:$C$79)))*(properties!$L$3:$L$6-properties!$M$3:$M$6))*O96+SUMPRODUCT((1-($B$76:$B$79>0)*(A96>=$B$76:$B$79))*(($C$76:$C$79>0)*(A96>=$C$76:$C$79))*($D$76:$D$79-$E$76:$E$79))*O96 | BR96: =SUMPRODUCT((1-($B$76:$B$79>0)*(A96>=$B$76:$B$79))*properties!$N$3:$N$6*(A96<=properties!$O$3:$O$6)) | BS96: =MAX(0,BQ96-BR96) | BT96: =SUMPRODUCT(($B$75:$B$79=A96)*$G$75:$G$79) | BU96: =SUMPRODUCT(($B$75:$B$79=A96)*$H$75:$H$79) | BV96: =SUMPRODUCT(($B$75:$B$79=A96)*$I$75:$I$79) | BW96: =AL96*properties!$C$2*(1+properties!$D$2)^(A96-household!$B$4+1) | BX96: =SUMPRODUCT((1-($B$76:$B$79>0)*(A96>=$B$76:$B$79))*properties!$C$3:$C$6*(1+properties!$D$3:$D$6)^(A96-household!$B$4+1)) | BY96: =IF(A96>=$B$31,IF(A96>=$B$32,MAX(household!$B$11*12*(1-$B$28)*O96*IF(A96>=$B$30,1-$B$29,1)*$B$33,0.5*household!$B$12*12*(1-$B$28)*O96*IF(A96>=$B$30,1-$B$29,1)*$B$35),household!$B$11*12*(1-$B$28)*O96*IF(A96>=$B$30,1-$B$29,1)*$B$33),0) | BZ96: =IF(A96>=$B$32,IF(A96>=$B$31,MAX(household!$B$12*12*(1-$B$28)*O96*IF(A96>=$B$30,1-$B$29,1)*$B$34,0.5*household!$B$11*12*(1-$B$28)*O96*IF(A96>=$B$30,1-$B$29,1)*$B$36),household!$B$12*12*(1-$B$28)*O96*IF(A96>=$B$30,1-$B$29,1)*$B$34),0) | CA96: =IF(AND($B$43<>0,A96>=household!$B$6+$B$44),$B$43*(1+$B$18)^(MAX(household!$B$6+$B$44,household!$B$4-1)-household!$B$4+1)*(1+$B$47*$B$18)^(A96-MAX(household!$B$6+$B$44,household!$B$4-1)),0) | CB96: =IF(AND($B$45<>0,A96>=household!$B$9+$B$46),$B$45*(1+$B$18)^(MAX(household!$B$9+$B$46,household!$B$4-1)-household!$B$4+1)*(1+$B$47*$B$18)^(A96-MAX(household!$B$9+$B$46,household!$B$4-1)),0) | CC96: =DC95 | CD96: =DD95 | CE96: =$B$20*CC96 | CF96: =DE95 | CG96: =DF95 | CH96: =IF(B96>=$B$71,MAX(0,CF96)/INDEX(tax_tables!$Z$5:$Z$53,MATCH(B96,tax_tables!$Y$5:$Y$53,0)),0) | CI96: =IF(C96>=$B$72,MAX(0,CG96)/INDEX(tax_tables!$Z$5:$Z$53,MATCH(C96,tax_tables!$Y$5:$Y$53,0)),0) | CJ96: =DG95 | CK96: =IF(OR($B$59="",$B$60=""),0,IF(AND(A96>=$B$59,A96<=$B$60),$B$58*O96,0)) | CL96: =MAX(0,CF96*(1+M96)-CH96) | CM96: =MAX(0,CG96*(1+M96)-CI96) | CN96: =EB95-AG95 | CO96: =AH96+F96+CA96+CB96+BQ96+CE96+CH96+CI96+BT96+AI96+AJ96+BO96 | CP96: =D96+CN96-CO96 | CQ96: =MAX(0,MIN(CP96,CC96*(1+M96-$B$20))) | CR96: =MAX(0,MIN(CP96-CQ96,CL96+CM96)) | CS96: =IF(CL96+CM96>1,CR96*CL96/(CL96+CM96),0) | CT96: =CR96-CS96 | CU96: =MAX(0,MIN(CP96-CQ96-CR96,CJ96*(1+M96))) | CV96: =MAX(0,MIN(CP96-CQ96-CR96-CU96,BN96*(1+M96)-BO96+AC96)) | CW96: =MAX(0,-CP96) | CX96: =MIN(CK96,CL96-CS96+CM96-CT96) | CY96: =IF(CL96-CS96+CM96-CT96>1,CX96*(CL96-CS96)/(CL96-CS96+CM96-CT96),0) | CZ96: =CX96-CY96 | DA96: =IF(CC96>0,MAX(0,1-CD96/CC96),0) | DB96: =CQ96*DA96 | DC96: =CC96*(1+M96-$B$20)-CQ96+CW96 | DD96: =CD96-(CQ96-DB96)+CW96 | DE96: =CF96*(1+M96)-CH96-CS96-CY96+Y96+AA96 | DF96: =CG96*(1+M96)-CI96-CT96-CZ96+Z96+AB96 | DG96: =CJ96*(1+M96)-CU96+CX96 | DH96: =AE96+CR96+CH96+CI96+CX96+CV96+BS96+AI96+CA96+CB96 | DI96: =CE96+DB96+BU96 | DJ96: =IF((DH96+DI96+0.5*F96)<=tax_tables!$B$14,0,IF((DH96+DI96+0.5*F96)<=tax_tables!$B$15,MIN(0.5*F96,0.5*((DH96+DI96+0.5*F96)-tax_tables!$B$14)),MIN(0.85*F96,0.85*((DH96+DI96+0.5*F96)-tax_tables!$B$15)+MIN(0.5*F96,tax_tables!$B$15-tax_tables!$B$14)))) | DK96: =DH96+DI96+DJ96 | DL96: =(B96>=65)+(C96>=65) | DM96: =(tax_tables!$B$5+tax_tables!$B$6*DL96)*P96 | DN96: =IF(AND(A96>=tax_tables!$B$8,A96<=tax_tables!$B$9),DL96*MAX(0,tax_tables!$B$7-tax_tables!$B$11*MAX(0,DK96-tax_tables!$B$10)),0) | DO96: =IFERROR(MAX(tax_tables!$B$16,INDEX(tax_tables!$W$5:$W$8,MATCH(A96,tax_tables!$V$5:$V$8,0))-tax_tables!$B$18*MAX(0,DK96-tax_tables!$B$17*1.01^(A96-tax_tables!$B$4))),tax_tables!$B$16) | DP96: =MAX(0,BM96-BB96-tax_tables!$B$23*DK96) | DQ96: =AN96+MIN(DO96,DY95+DZ95+EA95+AL96*properties!$H$2*O96)+DP96+$B$61*O96 | DR96: =MAX(DM96,DQ96) | DS96: =MAX(0,DH96+DJ96-DR96-DN96) | DT96: =MAX(0,DI96-MAX(0,DR96+DN96-DH96-DJ96)) | DU96: =SUMPRODUCT((DS96>tax_tables!$E$5:$E$16*P96)*(DS96-tax_tables!$E$5:$E$16*P96)*tax_tables!$G$5:$G$16)+SUMPRODUCT(((DS96+DT96)>tax_tables!$I$5:$I$16*P96)*((DS96+DT96)-tax_tables!$I$5:$I$16*P96)*tax_tables!$K$5:$K$16)-SUMPRODUCT((DS96>tax_tables!$I$5:$I$16*P96)*(DS96-tax_tables!$I$5:$I$16*P96)*tax_tables!$K$5:$K$16)+tax_tables!$B$19*BV96+tax_tables!$B$12*MIN(CE96+DB96+BS96+BU96,MAX(0,DK96-tax_tables!$B$13)) | DV96: =IF($B$39="",0,IF(A96>=$B$39,1,0)) | DW96: =IF(B96+0.5>=tax_tables!$B$30,MIN(CS96+CH96+CY96+CA96,tax_tables!$B$29),0)+IF(C96+0.5>=tax_tables!$B$30,MIN(CT96+CI96+CZ96+CB96,tax_tables!$B$29),0) | DX96: =MAX(0,DK96-tax_tables!$B$28*DJ96-DW96-tax_tables!$B$26*IF(tax_tables!$B$27=1,P96,1)) | DY96: =(1-DV96)*SUMPRODUCT((DX96>tax_tables!$M$5:$M$16*IF(tax_tables!$B$27=1,P96,1))*(DX96-tax_tables!$M$5:$M$16*IF(tax_tables!$B$27=1,P96,1))*tax_tables!$O$5:$O$16) | DZ96: =(1-DV96)*tax_tables!$B$31*DX96 | EA96: =DV96*$B$40*MAX(0,DK96-DJ96) | EB96: =DU96+DY96+DZ96+EA96 | EC96: =DC96+DE96+DF96+DG96+BP96 | ED96: =EC96+BW96-AP96+BX96
A97: =A96+1 | B97: =A97-household!$B$6 | C97: =A97-household!$B$9 | D97: =AS97+AT97+AU97+AV97+AZ97+BM97+AK97 | E97: =CN97+AG97+AF97 | F97: =BY97+BZ97 | G97: =CQ97+CR97+CU97+CH97+CI97+CE97-CW97+CV97+BO97 | H97: =IF(CC97+CF97+CG97+CJ97+BN97<=0,"",G97/(CC97+CF97+CG97+CJ97+BN97)) | I97: =EC97/O97 | J97: =ED97/O97 | K97: =MAX(0,CP97-CQ97-CR97-CU97-CV97) | M97: =IF(L97="",$B$19,L97) | O97: =(1+$B$18)^(A97-household!$B$4+1) | P97: =(1+$B$18)^(A97-tax_tables!$B$4) | Q97: =(1+$B$21)^(A97-household!$B$4+1) | R97: =(1+$B$22)^(A97-household!$B$4+1) | S97: =(1+$B$23)^(A97-household!$B$4+1) | T97: =IF(A97<$B$5,1,0) | U97: =IF(A97<$B$6,1,0) | V97: =IF(T97+U97>0,1,0) | W97: =T97*$B$7*O97+SUMPRODUCT(($B$83:$B$88=A97)*($D$83:$D$88="Wages: person 1")*$C$83:$C$88)*O97 | X97: =U97*$B$8*O97+SUMPRODUCT(($B$83:$B$88=A97)*($D$83:$D$88="Wages: person 2")*$C$83:$C$88)*O97 | Y97: =T97*$B$9*O97 | Z97: =U97*$B$10*O97 | AA97: =T97*$B$11*O97 | AB97: =U97*$B$12*O97 | AC97: =V97*$B$13*O97 | AD97: =W97+X97 | AE97: =AD97-Y97-Z97-AC97 | AF97: =0.062*MIN(W97,tax_tables!$B$21*P97)+0.062*MIN(X97,tax_tables!$B$21*P97)+0.0145*AD97+0.009*MAX(0,AD97-tax_tables!$B$22) | AG97: =$B$14*AE97 | AH97: =AD97-Y97-Z97-AC97-AF97-AG97 | AI97: =SUMPRODUCT(($B$83:$B$88=A97)*($D$83:$D$88="Other taxable income")*$C$83:$C$88)*O97 | AJ97: =SUMPRODUCT(($B$83:$B$88=A97)*($D$83:$D$88="Tax-free money in")*$C$83:$C$88)*O97 | AK97: =SUMPRODUCT(($B$83:$B$88=A97)*($D$83:$D$88="Expense")*$C$83:$C$88)*O97 | AL97: =IF(OR($B$75="",A97<$B$75),1,0) | AM97: =AP96 | AN97: =AL97*AM97*properties!$J$2 | AO97: =AL97*MIN(properties!$K$2,AM97+AN97) | AP97: =AL97*(AM97+AN97-AO97) | AQ97: =AL97*properties!$G$2*O97 | AR97: =(1-AL97)*$E$75*O97 | AS97: =AO97+AQ97+AR97 | AT97: =SUMIF(budget!$A$2:$A$300,"household",budget!$F$2:$F$300)*O97*IF(N97="",1,N97) | AU97: =SUMPRODUCT((other_budget!$C$2:$C$30<=A97)*(other_budget!$D$2:$D$30>=A97)*other_budget!$B$2:$B$30)*O97 | AV97: =SUMPRODUCT((kids_budget!$D$2:$D$40<=A97)*(kids_budget!$E$2:$E$40>=A97)*(kids_budget!$G$2:$G$40<>"college_funds")*kids_budget!$C$2:$C$40*((kids_budget!$F$2:$F$40="college")*R97+(kids_budget!$F$2:$F$40<>"college")*O97)) | AW97: =SUMPRODUCT((kids_budget!$D$2:$D$40<=A97)*(kids_budget!$E$2:$E$40>=A97)*(kids_budget!$G$2:$G$40="college_funds")*kids_budget!$C$2:$C$40*((kids_budget!$F$2:$F$40="college")*R97+(kids_budget!$F$2:$F$40<>"college")*O97)) | AX97: =BA96 | AY97: =MIN(AW97,AX97*(1+M97)) | AZ97: =AW97-AY97 | BA97: =AX97*(1+M97)-AY97 | BB97: =V97*healthcare!$B$5*Q97 | BC97: =(1-V97)*((B97<65)+(C97<65)) | BD97: =COUNTIF(household!$C$16:$C$23,">="&A97) | BE97: =(BC97*healthcare!$B$2+IF(BC97>0,BD97,0)*healthcare!$B$3)*12*Q97 | BF97: =IF(BC97>0,(BC97+BD97)*healthcare!$B$4*Q97,0) | BG97: =(B97>=65)+(C97>=65) | BH97: =BG97*(healthcare!$B$6+healthcare!$B$7+healthcare!$B$8)*12*Q97 | BI97: =BG97*healthcare!$B$9*Q97 | BJ97: =BG97*12*O97*SUMPRODUCT((DK95>tax_tables!$Q$5:$Q$9*P97)*tax_tables!$T$5:$T$9) | BK97: =AND(B97>=$B$51,B97<$B$51+$B$52)*1+AND(C97>=$B$53,C97<$B$53+$B$54)*1 | BL97: =BK97*$B$55*S97 | BM97: =BB97+BE97+BF97+BH97+BI97+BJ97+BL97 | BN97: =BP96 | BO97: =IF(V97=1,0,MIN(BN97*(1+M97),BF97+BG97*(healthcare!$B$6+healthcare!$B$7)*12*Q97+BI97+BJ97+BL97)) | BP97: =BN97*(1+M97)-BO97+AC97-CV97 | BQ97: =SUMPRODUCT((1-($B$76:$B$79>0)*(A97>=$B$76:$B$79))*(1-(($C$76:$C$79>0)*(A97>=$C$76:$C$79)))*(properties!$L$3:$L$6-properties!$M$3:$M$6))*O97+SUMPRODUCT((1-($B$76:$B$79>0)*(A97>=$B$76:$B$79))*(($C$76:$C$79>0)*(A97>=$C$76:$C$79))*($D$76:$D$79-$E$76:$E$79))*O97 | BR97: =SUMPRODUCT((1-($B$76:$B$79>0)*(A97>=$B$76:$B$79))*properties!$N$3:$N$6*(A97<=properties!$O$3:$O$6)) | BS97: =MAX(0,BQ97-BR97) | BT97: =SUMPRODUCT(($B$75:$B$79=A97)*$G$75:$G$79) | BU97: =SUMPRODUCT(($B$75:$B$79=A97)*$H$75:$H$79) | BV97: =SUMPRODUCT(($B$75:$B$79=A97)*$I$75:$I$79) | BW97: =AL97*properties!$C$2*(1+properties!$D$2)^(A97-household!$B$4+1) | BX97: =SUMPRODUCT((1-($B$76:$B$79>0)*(A97>=$B$76:$B$79))*properties!$C$3:$C$6*(1+properties!$D$3:$D$6)^(A97-household!$B$4+1)) | BY97: =IF(A97>=$B$31,IF(A97>=$B$32,MAX(household!$B$11*12*(1-$B$28)*O97*IF(A97>=$B$30,1-$B$29,1)*$B$33,0.5*household!$B$12*12*(1-$B$28)*O97*IF(A97>=$B$30,1-$B$29,1)*$B$35),household!$B$11*12*(1-$B$28)*O97*IF(A97>=$B$30,1-$B$29,1)*$B$33),0) | BZ97: =IF(A97>=$B$32,IF(A97>=$B$31,MAX(household!$B$12*12*(1-$B$28)*O97*IF(A97>=$B$30,1-$B$29,1)*$B$34,0.5*household!$B$11*12*(1-$B$28)*O97*IF(A97>=$B$30,1-$B$29,1)*$B$36),household!$B$12*12*(1-$B$28)*O97*IF(A97>=$B$30,1-$B$29,1)*$B$34),0) | CA97: =IF(AND($B$43<>0,A97>=household!$B$6+$B$44),$B$43*(1+$B$18)^(MAX(household!$B$6+$B$44,household!$B$4-1)-household!$B$4+1)*(1+$B$47*$B$18)^(A97-MAX(household!$B$6+$B$44,household!$B$4-1)),0) | CB97: =IF(AND($B$45<>0,A97>=household!$B$9+$B$46),$B$45*(1+$B$18)^(MAX(household!$B$9+$B$46,household!$B$4-1)-household!$B$4+1)*(1+$B$47*$B$18)^(A97-MAX(household!$B$9+$B$46,household!$B$4-1)),0) | CC97: =DC96 | CD97: =DD96 | CE97: =$B$20*CC97 | CF97: =DE96 | CG97: =DF96 | CH97: =IF(B97>=$B$71,MAX(0,CF97)/INDEX(tax_tables!$Z$5:$Z$53,MATCH(B97,tax_tables!$Y$5:$Y$53,0)),0) | CI97: =IF(C97>=$B$72,MAX(0,CG97)/INDEX(tax_tables!$Z$5:$Z$53,MATCH(C97,tax_tables!$Y$5:$Y$53,0)),0) | CJ97: =DG96 | CK97: =IF(OR($B$59="",$B$60=""),0,IF(AND(A97>=$B$59,A97<=$B$60),$B$58*O97,0)) | CL97: =MAX(0,CF97*(1+M97)-CH97) | CM97: =MAX(0,CG97*(1+M97)-CI97) | CN97: =EB96-AG96 | CO97: =AH97+F97+CA97+CB97+BQ97+CE97+CH97+CI97+BT97+AI97+AJ97+BO97 | CP97: =D97+CN97-CO97 | CQ97: =MAX(0,MIN(CP97,CC97*(1+M97-$B$20))) | CR97: =MAX(0,MIN(CP97-CQ97,CL97+CM97)) | CS97: =IF(CL97+CM97>1,CR97*CL97/(CL97+CM97),0) | CT97: =CR97-CS97 | CU97: =MAX(0,MIN(CP97-CQ97-CR97,CJ97*(1+M97))) | CV97: =MAX(0,MIN(CP97-CQ97-CR97-CU97,BN97*(1+M97)-BO97+AC97)) | CW97: =MAX(0,-CP97) | CX97: =MIN(CK97,CL97-CS97+CM97-CT97) | CY97: =IF(CL97-CS97+CM97-CT97>1,CX97*(CL97-CS97)/(CL97-CS97+CM97-CT97),0) | CZ97: =CX97-CY97 | DA97: =IF(CC97>0,MAX(0,1-CD97/CC97),0) | DB97: =CQ97*DA97 | DC97: =CC97*(1+M97-$B$20)-CQ97+CW97 | DD97: =CD97-(CQ97-DB97)+CW97 | DE97: =CF97*(1+M97)-CH97-CS97-CY97+Y97+AA97 | DF97: =CG97*(1+M97)-CI97-CT97-CZ97+Z97+AB97 | DG97: =CJ97*(1+M97)-CU97+CX97 | DH97: =AE97+CR97+CH97+CI97+CX97+CV97+BS97+AI97+CA97+CB97 | DI97: =CE97+DB97+BU97 | DJ97: =IF((DH97+DI97+0.5*F97)<=tax_tables!$B$14,0,IF((DH97+DI97+0.5*F97)<=tax_tables!$B$15,MIN(0.5*F97,0.5*((DH97+DI97+0.5*F97)-tax_tables!$B$14)),MIN(0.85*F97,0.85*((DH97+DI97+0.5*F97)-tax_tables!$B$15)+MIN(0.5*F97,tax_tables!$B$15-tax_tables!$B$14)))) | DK97: =DH97+DI97+DJ97 | DL97: =(B97>=65)+(C97>=65) | DM97: =(tax_tables!$B$5+tax_tables!$B$6*DL97)*P97 | DN97: =IF(AND(A97>=tax_tables!$B$8,A97<=tax_tables!$B$9),DL97*MAX(0,tax_tables!$B$7-tax_tables!$B$11*MAX(0,DK97-tax_tables!$B$10)),0) | DO97: =IFERROR(MAX(tax_tables!$B$16,INDEX(tax_tables!$W$5:$W$8,MATCH(A97,tax_tables!$V$5:$V$8,0))-tax_tables!$B$18*MAX(0,DK97-tax_tables!$B$17*1.01^(A97-tax_tables!$B$4))),tax_tables!$B$16) | DP97: =MAX(0,BM97-BB97-tax_tables!$B$23*DK97) | DQ97: =AN97+MIN(DO97,DY96+DZ96+EA96+AL97*properties!$H$2*O97)+DP97+$B$61*O97 | DR97: =MAX(DM97,DQ97) | DS97: =MAX(0,DH97+DJ97-DR97-DN97) | DT97: =MAX(0,DI97-MAX(0,DR97+DN97-DH97-DJ97)) | DU97: =SUMPRODUCT((DS97>tax_tables!$E$5:$E$16*P97)*(DS97-tax_tables!$E$5:$E$16*P97)*tax_tables!$G$5:$G$16)+SUMPRODUCT(((DS97+DT97)>tax_tables!$I$5:$I$16*P97)*((DS97+DT97)-tax_tables!$I$5:$I$16*P97)*tax_tables!$K$5:$K$16)-SUMPRODUCT((DS97>tax_tables!$I$5:$I$16*P97)*(DS97-tax_tables!$I$5:$I$16*P97)*tax_tables!$K$5:$K$16)+tax_tables!$B$19*BV97+tax_tables!$B$12*MIN(CE97+DB97+BS97+BU97,MAX(0,DK97-tax_tables!$B$13)) | DV97: =IF($B$39="",0,IF(A97>=$B$39,1,0)) | DW97: =IF(B97+0.5>=tax_tables!$B$30,MIN(CS97+CH97+CY97+CA97,tax_tables!$B$29),0)+IF(C97+0.5>=tax_tables!$B$30,MIN(CT97+CI97+CZ97+CB97,tax_tables!$B$29),0) | DX97: =MAX(0,DK97-tax_tables!$B$28*DJ97-DW97-tax_tables!$B$26*IF(tax_tables!$B$27=1,P97,1)) | DY97: =(1-DV97)*SUMPRODUCT((DX97>tax_tables!$M$5:$M$16*IF(tax_tables!$B$27=1,P97,1))*(DX97-tax_tables!$M$5:$M$16*IF(tax_tables!$B$27=1,P97,1))*tax_tables!$O$5:$O$16) | DZ97: =(1-DV97)*tax_tables!$B$31*DX97 | EA97: =DV97*$B$40*MAX(0,DK97-DJ97) | EB97: =DU97+DY97+DZ97+EA97 | EC97: =DC97+DE97+DF97+DG97+BP97 | ED97: =EC97+BW97-AP97+BX97
A98: =A97+1 | B98: =A98-household!$B$6 | C98: =A98-household!$B$9 | D98: =AS98+AT98+AU98+AV98+AZ98+BM98+AK98 | E98: =CN98+AG98+AF98 | F98: =BY98+BZ98 | G98: =CQ98+CR98+CU98+CH98+CI98+CE98-CW98+CV98+BO98 | H98: =IF(CC98+CF98+CG98+CJ98+BN98<=0,"",G98/(CC98+CF98+CG98+CJ98+BN98)) | I98: =EC98/O98 | J98: =ED98/O98 | K98: =MAX(0,CP98-CQ98-CR98-CU98-CV98) | M98: =IF(L98="",$B$19,L98) | O98: =(1+$B$18)^(A98-household!$B$4+1) | P98: =(1+$B$18)^(A98-tax_tables!$B$4) | Q98: =(1+$B$21)^(A98-household!$B$4+1) | R98: =(1+$B$22)^(A98-household!$B$4+1) | S98: =(1+$B$23)^(A98-household!$B$4+1) | T98: =IF(A98<$B$5,1,0) | U98: =IF(A98<$B$6,1,0) | V98: =IF(T98+U98>0,1,0) | W98: =T98*$B$7*O98+SUMPRODUCT(($B$83:$B$88=A98)*($D$83:$D$88="Wages: person 1")*$C$83:$C$88)*O98 | X98: =U98*$B$8*O98+SUMPRODUCT(($B$83:$B$88=A98)*($D$83:$D$88="Wages: person 2")*$C$83:$C$88)*O98 | Y98: =T98*$B$9*O98 | Z98: =U98*$B$10*O98 | AA98: =T98*$B$11*O98 | AB98: =U98*$B$12*O98 | AC98: =V98*$B$13*O98 | AD98: =W98+X98 | AE98: =AD98-Y98-Z98-AC98 | AF98: =0.062*MIN(W98,tax_tables!$B$21*P98)+0.062*MIN(X98,tax_tables!$B$21*P98)+0.0145*AD98+0.009*MAX(0,AD98-tax_tables!$B$22) | AG98: =$B$14*AE98 | AH98: =AD98-Y98-Z98-AC98-AF98-AG98 | AI98: =SUMPRODUCT(($B$83:$B$88=A98)*($D$83:$D$88="Other taxable income")*$C$83:$C$88)*O98 | AJ98: =SUMPRODUCT(($B$83:$B$88=A98)*($D$83:$D$88="Tax-free money in")*$C$83:$C$88)*O98 | AK98: =SUMPRODUCT(($B$83:$B$88=A98)*($D$83:$D$88="Expense")*$C$83:$C$88)*O98 | AL98: =IF(OR($B$75="",A98<$B$75),1,0) | AM98: =AP97 | AN98: =AL98*AM98*properties!$J$2 | AO98: =AL98*MIN(properties!$K$2,AM98+AN98) | AP98: =AL98*(AM98+AN98-AO98) | AQ98: =AL98*properties!$G$2*O98 | AR98: =(1-AL98)*$E$75*O98 | AS98: =AO98+AQ98+AR98 | AT98: =SUMIF(budget!$A$2:$A$300,"household",budget!$F$2:$F$300)*O98*IF(N98="",1,N98) | AU98: =SUMPRODUCT((other_budget!$C$2:$C$30<=A98)*(other_budget!$D$2:$D$30>=A98)*other_budget!$B$2:$B$30)*O98 | AV98: =SUMPRODUCT((kids_budget!$D$2:$D$40<=A98)*(kids_budget!$E$2:$E$40>=A98)*(kids_budget!$G$2:$G$40<>"college_funds")*kids_budget!$C$2:$C$40*((kids_budget!$F$2:$F$40="college")*R98+(kids_budget!$F$2:$F$40<>"college")*O98)) | AW98: =SUMPRODUCT((kids_budget!$D$2:$D$40<=A98)*(kids_budget!$E$2:$E$40>=A98)*(kids_budget!$G$2:$G$40="college_funds")*kids_budget!$C$2:$C$40*((kids_budget!$F$2:$F$40="college")*R98+(kids_budget!$F$2:$F$40<>"college")*O98)) | AX98: =BA97 | AY98: =MIN(AW98,AX98*(1+M98)) | AZ98: =AW98-AY98 | BA98: =AX98*(1+M98)-AY98 | BB98: =V98*healthcare!$B$5*Q98 | BC98: =(1-V98)*((B98<65)+(C98<65)) | BD98: =COUNTIF(household!$C$16:$C$23,">="&A98) | BE98: =(BC98*healthcare!$B$2+IF(BC98>0,BD98,0)*healthcare!$B$3)*12*Q98 | BF98: =IF(BC98>0,(BC98+BD98)*healthcare!$B$4*Q98,0) | BG98: =(B98>=65)+(C98>=65) | BH98: =BG98*(healthcare!$B$6+healthcare!$B$7+healthcare!$B$8)*12*Q98 | BI98: =BG98*healthcare!$B$9*Q98 | BJ98: =BG98*12*O98*SUMPRODUCT((DK96>tax_tables!$Q$5:$Q$9*P98)*tax_tables!$T$5:$T$9) | BK98: =AND(B98>=$B$51,B98<$B$51+$B$52)*1+AND(C98>=$B$53,C98<$B$53+$B$54)*1 | BL98: =BK98*$B$55*S98 | BM98: =BB98+BE98+BF98+BH98+BI98+BJ98+BL98 | BN98: =BP97 | BO98: =IF(V98=1,0,MIN(BN98*(1+M98),BF98+BG98*(healthcare!$B$6+healthcare!$B$7)*12*Q98+BI98+BJ98+BL98)) | BP98: =BN98*(1+M98)-BO98+AC98-CV98 | BQ98: =SUMPRODUCT((1-($B$76:$B$79>0)*(A98>=$B$76:$B$79))*(1-(($C$76:$C$79>0)*(A98>=$C$76:$C$79)))*(properties!$L$3:$L$6-properties!$M$3:$M$6))*O98+SUMPRODUCT((1-($B$76:$B$79>0)*(A98>=$B$76:$B$79))*(($C$76:$C$79>0)*(A98>=$C$76:$C$79))*($D$76:$D$79-$E$76:$E$79))*O98 | BR98: =SUMPRODUCT((1-($B$76:$B$79>0)*(A98>=$B$76:$B$79))*properties!$N$3:$N$6*(A98<=properties!$O$3:$O$6)) | BS98: =MAX(0,BQ98-BR98) | BT98: =SUMPRODUCT(($B$75:$B$79=A98)*$G$75:$G$79) | BU98: =SUMPRODUCT(($B$75:$B$79=A98)*$H$75:$H$79) | BV98: =SUMPRODUCT(($B$75:$B$79=A98)*$I$75:$I$79) | BW98: =AL98*properties!$C$2*(1+properties!$D$2)^(A98-household!$B$4+1) | BX98: =SUMPRODUCT((1-($B$76:$B$79>0)*(A98>=$B$76:$B$79))*properties!$C$3:$C$6*(1+properties!$D$3:$D$6)^(A98-household!$B$4+1)) | BY98: =IF(A98>=$B$31,IF(A98>=$B$32,MAX(household!$B$11*12*(1-$B$28)*O98*IF(A98>=$B$30,1-$B$29,1)*$B$33,0.5*household!$B$12*12*(1-$B$28)*O98*IF(A98>=$B$30,1-$B$29,1)*$B$35),household!$B$11*12*(1-$B$28)*O98*IF(A98>=$B$30,1-$B$29,1)*$B$33),0) | BZ98: =IF(A98>=$B$32,IF(A98>=$B$31,MAX(household!$B$12*12*(1-$B$28)*O98*IF(A98>=$B$30,1-$B$29,1)*$B$34,0.5*household!$B$11*12*(1-$B$28)*O98*IF(A98>=$B$30,1-$B$29,1)*$B$36),household!$B$12*12*(1-$B$28)*O98*IF(A98>=$B$30,1-$B$29,1)*$B$34),0) | CA98: =IF(AND($B$43<>0,A98>=household!$B$6+$B$44),$B$43*(1+$B$18)^(MAX(household!$B$6+$B$44,household!$B$4-1)-household!$B$4+1)*(1+$B$47*$B$18)^(A98-MAX(household!$B$6+$B$44,household!$B$4-1)),0) | CB98: =IF(AND($B$45<>0,A98>=household!$B$9+$B$46),$B$45*(1+$B$18)^(MAX(household!$B$9+$B$46,household!$B$4-1)-household!$B$4+1)*(1+$B$47*$B$18)^(A98-MAX(household!$B$9+$B$46,household!$B$4-1)),0) | CC98: =DC97 | CD98: =DD97 | CE98: =$B$20*CC98 | CF98: =DE97 | CG98: =DF97 | CH98: =IF(B98>=$B$71,MAX(0,CF98)/INDEX(tax_tables!$Z$5:$Z$53,MATCH(B98,tax_tables!$Y$5:$Y$53,0)),0) | CI98: =IF(C98>=$B$72,MAX(0,CG98)/INDEX(tax_tables!$Z$5:$Z$53,MATCH(C98,tax_tables!$Y$5:$Y$53,0)),0) | CJ98: =DG97 | CK98: =IF(OR($B$59="",$B$60=""),0,IF(AND(A98>=$B$59,A98<=$B$60),$B$58*O98,0)) | CL98: =MAX(0,CF98*(1+M98)-CH98) | CM98: =MAX(0,CG98*(1+M98)-CI98) | CN98: =EB97-AG97 | CO98: =AH98+F98+CA98+CB98+BQ98+CE98+CH98+CI98+BT98+AI98+AJ98+BO98 | CP98: =D98+CN98-CO98 | CQ98: =MAX(0,MIN(CP98,CC98*(1+M98-$B$20))) | CR98: =MAX(0,MIN(CP98-CQ98,CL98+CM98)) | CS98: =IF(CL98+CM98>1,CR98*CL98/(CL98+CM98),0) | CT98: =CR98-CS98 | CU98: =MAX(0,MIN(CP98-CQ98-CR98,CJ98*(1+M98))) | CV98: =MAX(0,MIN(CP98-CQ98-CR98-CU98,BN98*(1+M98)-BO98+AC98)) | CW98: =MAX(0,-CP98) | CX98: =MIN(CK98,CL98-CS98+CM98-CT98) | CY98: =IF(CL98-CS98+CM98-CT98>1,CX98*(CL98-CS98)/(CL98-CS98+CM98-CT98),0) | CZ98: =CX98-CY98 | DA98: =IF(CC98>0,MAX(0,1-CD98/CC98),0) | DB98: =CQ98*DA98 | DC98: =CC98*(1+M98-$B$20)-CQ98+CW98 | DD98: =CD98-(CQ98-DB98)+CW98 | DE98: =CF98*(1+M98)-CH98-CS98-CY98+Y98+AA98 | DF98: =CG98*(1+M98)-CI98-CT98-CZ98+Z98+AB98 | DG98: =CJ98*(1+M98)-CU98+CX98 | DH98: =AE98+CR98+CH98+CI98+CX98+CV98+BS98+AI98+CA98+CB98 | DI98: =CE98+DB98+BU98 | DJ98: =IF((DH98+DI98+0.5*F98)<=tax_tables!$B$14,0,IF((DH98+DI98+0.5*F98)<=tax_tables!$B$15,MIN(0.5*F98,0.5*((DH98+DI98+0.5*F98)-tax_tables!$B$14)),MIN(0.85*F98,0.85*((DH98+DI98+0.5*F98)-tax_tables!$B$15)+MIN(0.5*F98,tax_tables!$B$15-tax_tables!$B$14)))) | DK98: =DH98+DI98+DJ98 | DL98: =(B98>=65)+(C98>=65) | DM98: =(tax_tables!$B$5+tax_tables!$B$6*DL98)*P98 | DN98: =IF(AND(A98>=tax_tables!$B$8,A98<=tax_tables!$B$9),DL98*MAX(0,tax_tables!$B$7-tax_tables!$B$11*MAX(0,DK98-tax_tables!$B$10)),0) | DO98: =IFERROR(MAX(tax_tables!$B$16,INDEX(tax_tables!$W$5:$W$8,MATCH(A98,tax_tables!$V$5:$V$8,0))-tax_tables!$B$18*MAX(0,DK98-tax_tables!$B$17*1.01^(A98-tax_tables!$B$4))),tax_tables!$B$16) | DP98: =MAX(0,BM98-BB98-tax_tables!$B$23*DK98) | DQ98: =AN98+MIN(DO98,DY97+DZ97+EA97+AL98*properties!$H$2*O98)+DP98+$B$61*O98 | DR98: =MAX(DM98,DQ98) | DS98: =MAX(0,DH98+DJ98-DR98-DN98) | DT98: =MAX(0,DI98-MAX(0,DR98+DN98-DH98-DJ98)) | DU98: =SUMPRODUCT((DS98>tax_tables!$E$5:$E$16*P98)*(DS98-tax_tables!$E$5:$E$16*P98)*tax_tables!$G$5:$G$16)+SUMPRODUCT(((DS98+DT98)>tax_tables!$I$5:$I$16*P98)*((DS98+DT98)-tax_tables!$I$5:$I$16*P98)*tax_tables!$K$5:$K$16)-SUMPRODUCT((DS98>tax_tables!$I$5:$I$16*P98)*(DS98-tax_tables!$I$5:$I$16*P98)*tax_tables!$K$5:$K$16)+tax_tables!$B$19*BV98+tax_tables!$B$12*MIN(CE98+DB98+BS98+BU98,MAX(0,DK98-tax_tables!$B$13)) | DV98: =IF($B$39="",0,IF(A98>=$B$39,1,0)) | DW98: =IF(B98+0.5>=tax_tables!$B$30,MIN(CS98+CH98+CY98+CA98,tax_tables!$B$29),0)+IF(C98+0.5>=tax_tables!$B$30,MIN(CT98+CI98+CZ98+CB98,tax_tables!$B$29),0) | DX98: =MAX(0,DK98-tax_tables!$B$28*DJ98-DW98-tax_tables!$B$26*IF(tax_tables!$B$27=1,P98,1)) | DY98: =(1-DV98)*SUMPRODUCT((DX98>tax_tables!$M$5:$M$16*IF(tax_tables!$B$27=1,P98,1))*(DX98-tax_tables!$M$5:$M$16*IF(tax_tables!$B$27=1,P98,1))*tax_tables!$O$5:$O$16) | DZ98: =(1-DV98)*tax_tables!$B$31*DX98 | EA98: =DV98*$B$40*MAX(0,DK98-DJ98) | EB98: =DU98+DY98+DZ98+EA98 | EC98: =DC98+DE98+DF98+DG98+BP98 | ED98: =EC98+BW98-AP98+BX98
A99: =A98+1 | B99: =A99-household!$B$6 | C99: =A99-household!$B$9 | D99: =AS99+AT99+AU99+AV99+AZ99+BM99+AK99 | E99: =CN99+AG99+AF99 | F99: =BY99+BZ99 | G99: =CQ99+CR99+CU99+CH99+CI99+CE99-CW99+CV99+BO99 | H99: =IF(CC99+CF99+CG99+CJ99+BN99<=0,"",G99/(CC99+CF99+CG99+CJ99+BN99)) | I99: =EC99/O99 | J99: =ED99/O99 | K99: =MAX(0,CP99-CQ99-CR99-CU99-CV99) | M99: =IF(L99="",$B$19,L99) | O99: =(1+$B$18)^(A99-household!$B$4+1) | P99: =(1+$B$18)^(A99-tax_tables!$B$4) | Q99: =(1+$B$21)^(A99-household!$B$4+1) | R99: =(1+$B$22)^(A99-household!$B$4+1) | S99: =(1+$B$23)^(A99-household!$B$4+1) | T99: =IF(A99<$B$5,1,0) | U99: =IF(A99<$B$6,1,0) | V99: =IF(T99+U99>0,1,0) | W99: =T99*$B$7*O99+SUMPRODUCT(($B$83:$B$88=A99)*($D$83:$D$88="Wages: person 1")*$C$83:$C$88)*O99 | X99: =U99*$B$8*O99+SUMPRODUCT(($B$83:$B$88=A99)*($D$83:$D$88="Wages: person 2")*$C$83:$C$88)*O99 | Y99: =T99*$B$9*O99 | Z99: =U99*$B$10*O99 | AA99: =T99*$B$11*O99 | AB99: =U99*$B$12*O99 | AC99: =V99*$B$13*O99 | AD99: =W99+X99 | AE99: =AD99-Y99-Z99-AC99 | AF99: =0.062*MIN(W99,tax_tables!$B$21*P99)+0.062*MIN(X99,tax_tables!$B$21*P99)+0.0145*AD99+0.009*MAX(0,AD99-tax_tables!$B$22) | AG99: =$B$14*AE99 | AH99: =AD99-Y99-Z99-AC99-AF99-AG99 | AI99: =SUMPRODUCT(($B$83:$B$88=A99)*($D$83:$D$88="Other taxable income")*$C$83:$C$88)*O99 | AJ99: =SUMPRODUCT(($B$83:$B$88=A99)*($D$83:$D$88="Tax-free money in")*$C$83:$C$88)*O99 | AK99: =SUMPRODUCT(($B$83:$B$88=A99)*($D$83:$D$88="Expense")*$C$83:$C$88)*O99 | AL99: =IF(OR($B$75="",A99<$B$75),1,0) | AM99: =AP98 | AN99: =AL99*AM99*properties!$J$2 | AO99: =AL99*MIN(properties!$K$2,AM99+AN99) | AP99: =AL99*(AM99+AN99-AO99) | AQ99: =AL99*properties!$G$2*O99 | AR99: =(1-AL99)*$E$75*O99 | AS99: =AO99+AQ99+AR99 | AT99: =SUMIF(budget!$A$2:$A$300,"household",budget!$F$2:$F$300)*O99*IF(N99="",1,N99) | AU99: =SUMPRODUCT((other_budget!$C$2:$C$30<=A99)*(other_budget!$D$2:$D$30>=A99)*other_budget!$B$2:$B$30)*O99 | AV99: =SUMPRODUCT((kids_budget!$D$2:$D$40<=A99)*(kids_budget!$E$2:$E$40>=A99)*(kids_budget!$G$2:$G$40<>"college_funds")*kids_budget!$C$2:$C$40*((kids_budget!$F$2:$F$40="college")*R99+(kids_budget!$F$2:$F$40<>"college")*O99)) | AW99: =SUMPRODUCT((kids_budget!$D$2:$D$40<=A99)*(kids_budget!$E$2:$E$40>=A99)*(kids_budget!$G$2:$G$40="college_funds")*kids_budget!$C$2:$C$40*((kids_budget!$F$2:$F$40="college")*R99+(kids_budget!$F$2:$F$40<>"college")*O99)) | AX99: =BA98 | AY99: =MIN(AW99,AX99*(1+M99)) | AZ99: =AW99-AY99 | BA99: =AX99*(1+M99)-AY99 | BB99: =V99*healthcare!$B$5*Q99 | BC99: =(1-V99)*((B99<65)+(C99<65)) | BD99: =COUNTIF(household!$C$16:$C$23,">="&A99) | BE99: =(BC99*healthcare!$B$2+IF(BC99>0,BD99,0)*healthcare!$B$3)*12*Q99 | BF99: =IF(BC99>0,(BC99+BD99)*healthcare!$B$4*Q99,0) | BG99: =(B99>=65)+(C99>=65) | BH99: =BG99*(healthcare!$B$6+healthcare!$B$7+healthcare!$B$8)*12*Q99 | BI99: =BG99*healthcare!$B$9*Q99 | BJ99: =BG99*12*O99*SUMPRODUCT((DK97>tax_tables!$Q$5:$Q$9*P99)*tax_tables!$T$5:$T$9) | BK99: =AND(B99>=$B$51,B99<$B$51+$B$52)*1+AND(C99>=$B$53,C99<$B$53+$B$54)*1 | BL99: =BK99*$B$55*S99 | BM99: =BB99+BE99+BF99+BH99+BI99+BJ99+BL99 | BN99: =BP98 | BO99: =IF(V99=1,0,MIN(BN99*(1+M99),BF99+BG99*(healthcare!$B$6+healthcare!$B$7)*12*Q99+BI99+BJ99+BL99)) | BP99: =BN99*(1+M99)-BO99+AC99-CV99 | BQ99: =SUMPRODUCT((1-($B$76:$B$79>0)*(A99>=$B$76:$B$79))*(1-(($C$76:$C$79>0)*(A99>=$C$76:$C$79)))*(properties!$L$3:$L$6-properties!$M$3:$M$6))*O99+SUMPRODUCT((1-($B$76:$B$79>0)*(A99>=$B$76:$B$79))*(($C$76:$C$79>0)*(A99>=$C$76:$C$79))*($D$76:$D$79-$E$76:$E$79))*O99 | BR99: =SUMPRODUCT((1-($B$76:$B$79>0)*(A99>=$B$76:$B$79))*properties!$N$3:$N$6*(A99<=properties!$O$3:$O$6)) | BS99: =MAX(0,BQ99-BR99) | BT99: =SUMPRODUCT(($B$75:$B$79=A99)*$G$75:$G$79) | BU99: =SUMPRODUCT(($B$75:$B$79=A99)*$H$75:$H$79) | BV99: =SUMPRODUCT(($B$75:$B$79=A99)*$I$75:$I$79) | BW99: =AL99*properties!$C$2*(1+properties!$D$2)^(A99-household!$B$4+1) | BX99: =SUMPRODUCT((1-($B$76:$B$79>0)*(A99>=$B$76:$B$79))*properties!$C$3:$C$6*(1+properties!$D$3:$D$6)^(A99-household!$B$4+1)) | BY99: =IF(A99>=$B$31,IF(A99>=$B$32,MAX(household!$B$11*12*(1-$B$28)*O99*IF(A99>=$B$30,1-$B$29,1)*$B$33,0.5*household!$B$12*12*(1-$B$28)*O99*IF(A99>=$B$30,1-$B$29,1)*$B$35),household!$B$11*12*(1-$B$28)*O99*IF(A99>=$B$30,1-$B$29,1)*$B$33),0) | BZ99: =IF(A99>=$B$32,IF(A99>=$B$31,MAX(household!$B$12*12*(1-$B$28)*O99*IF(A99>=$B$30,1-$B$29,1)*$B$34,0.5*household!$B$11*12*(1-$B$28)*O99*IF(A99>=$B$30,1-$B$29,1)*$B$36),household!$B$12*12*(1-$B$28)*O99*IF(A99>=$B$30,1-$B$29,1)*$B$34),0) | CA99: =IF(AND($B$43<>0,A99>=household!$B$6+$B$44),$B$43*(1+$B$18)^(MAX(household!$B$6+$B$44,household!$B$4-1)-household!$B$4+1)*(1+$B$47*$B$18)^(A99-MAX(household!$B$6+$B$44,household!$B$4-1)),0) | CB99: =IF(AND($B$45<>0,A99>=household!$B$9+$B$46),$B$45*(1+$B$18)^(MAX(household!$B$9+$B$46,household!$B$4-1)-household!$B$4+1)*(1+$B$47*$B$18)^(A99-MAX(household!$B$9+$B$46,household!$B$4-1)),0) | CC99: =DC98 | CD99: =DD98 | CE99: =$B$20*CC99 | CF99: =DE98 | CG99: =DF98 | CH99: =IF(B99>=$B$71,MAX(0,CF99)/INDEX(tax_tables!$Z$5:$Z$53,MATCH(B99,tax_tables!$Y$5:$Y$53,0)),0) | CI99: =IF(C99>=$B$72,MAX(0,CG99)/INDEX(tax_tables!$Z$5:$Z$53,MATCH(C99,tax_tables!$Y$5:$Y$53,0)),0) | CJ99: =DG98 | CK99: =IF(OR($B$59="",$B$60=""),0,IF(AND(A99>=$B$59,A99<=$B$60),$B$58*O99,0)) | CL99: =MAX(0,CF99*(1+M99)-CH99) | CM99: =MAX(0,CG99*(1+M99)-CI99) | CN99: =EB98-AG98 | CO99: =AH99+F99+CA99+CB99+BQ99+CE99+CH99+CI99+BT99+AI99+AJ99+BO99 | CP99: =D99+CN99-CO99 | CQ99: =MAX(0,MIN(CP99,CC99*(1+M99-$B$20))) | CR99: =MAX(0,MIN(CP99-CQ99,CL99+CM99)) | CS99: =IF(CL99+CM99>1,CR99*CL99/(CL99+CM99),0) | CT99: =CR99-CS99 | CU99: =MAX(0,MIN(CP99-CQ99-CR99,CJ99*(1+M99))) | CV99: =MAX(0,MIN(CP99-CQ99-CR99-CU99,BN99*(1+M99)-BO99+AC99)) | CW99: =MAX(0,-CP99) | CX99: =MIN(CK99,CL99-CS99+CM99-CT99) | CY99: =IF(CL99-CS99+CM99-CT99>1,CX99*(CL99-CS99)/(CL99-CS99+CM99-CT99),0) | CZ99: =CX99-CY99 | DA99: =IF(CC99>0,MAX(0,1-CD99/CC99),0) | DB99: =CQ99*DA99 | DC99: =CC99*(1+M99-$B$20)-CQ99+CW99 | DD99: =CD99-(CQ99-DB99)+CW99 | DE99: =CF99*(1+M99)-CH99-CS99-CY99+Y99+AA99 | DF99: =CG99*(1+M99)-CI99-CT99-CZ99+Z99+AB99 | DG99: =CJ99*(1+M99)-CU99+CX99 | DH99: =AE99+CR99+CH99+CI99+CX99+CV99+BS99+AI99+CA99+CB99 | DI99: =CE99+DB99+BU99 | DJ99: =IF((DH99+DI99+0.5*F99)<=tax_tables!$B$14,0,IF((DH99+DI99+0.5*F99)<=tax_tables!$B$15,MIN(0.5*F99,0.5*((DH99+DI99+0.5*F99)-tax_tables!$B$14)),MIN(0.85*F99,0.85*((DH99+DI99+0.5*F99)-tax_tables!$B$15)+MIN(0.5*F99,tax_tables!$B$15-tax_tables!$B$14)))) | DK99: =DH99+DI99+DJ99 | DL99: =(B99>=65)+(C99>=65) | DM99: =(tax_tables!$B$5+tax_tables!$B$6*DL99)*P99 | DN99: =IF(AND(A99>=tax_tables!$B$8,A99<=tax_tables!$B$9),DL99*MAX(0,tax_tables!$B$7-tax_tables!$B$11*MAX(0,DK99-tax_tables!$B$10)),0) | DO99: =IFERROR(MAX(tax_tables!$B$16,INDEX(tax_tables!$W$5:$W$8,MATCH(A99,tax_tables!$V$5:$V$8,0))-tax_tables!$B$18*MAX(0,DK99-tax_tables!$B$17*1.01^(A99-tax_tables!$B$4))),tax_tables!$B$16) | DP99: =MAX(0,BM99-BB99-tax_tables!$B$23*DK99) | DQ99: =AN99+MIN(DO99,DY98+DZ98+EA98+AL99*properties!$H$2*O99)+DP99+$B$61*O99 | DR99: =MAX(DM99,DQ99) | DS99: =MAX(0,DH99+DJ99-DR99-DN99) | DT99: =MAX(0,DI99-MAX(0,DR99+DN99-DH99-DJ99)) | DU99: =SUMPRODUCT((DS99>tax_tables!$E$5:$E$16*P99)*(DS99-tax_tables!$E$5:$E$16*P99)*tax_tables!$G$5:$G$16)+SUMPRODUCT(((DS99+DT99)>tax_tables!$I$5:$I$16*P99)*((DS99+DT99)-tax_tables!$I$5:$I$16*P99)*tax_tables!$K$5:$K$16)-SUMPRODUCT((DS99>tax_tables!$I$5:$I$16*P99)*(DS99-tax_tables!$I$5:$I$16*P99)*tax_tables!$K$5:$K$16)+tax_tables!$B$19*BV99+tax_tables!$B$12*MIN(CE99+DB99+BS99+BU99,MAX(0,DK99-tax_tables!$B$13)) | DV99: =IF($B$39="",0,IF(A99>=$B$39,1,0)) | DW99: =IF(B99+0.5>=tax_tables!$B$30,MIN(CS99+CH99+CY99+CA99,tax_tables!$B$29),0)+IF(C99+0.5>=tax_tables!$B$30,MIN(CT99+CI99+CZ99+CB99,tax_tables!$B$29),0) | DX99: =MAX(0,DK99-tax_tables!$B$28*DJ99-DW99-tax_tables!$B$26*IF(tax_tables!$B$27=1,P99,1)) | DY99: =(1-DV99)*SUMPRODUCT((DX99>tax_tables!$M$5:$M$16*IF(tax_tables!$B$27=1,P99,1))*(DX99-tax_tables!$M$5:$M$16*IF(tax_tables!$B$27=1,P99,1))*tax_tables!$O$5:$O$16) | DZ99: =(1-DV99)*tax_tables!$B$31*DX99 | EA99: =DV99*$B$40*MAX(0,DK99-DJ99) | EB99: =DU99+DY99+DZ99+EA99 | EC99: =DC99+DE99+DF99+DG99+BP99 | ED99: =EC99+BW99-AP99+BX99
A100: =A99+1 | B100: =A100-household!$B$6 | C100: =A100-household!$B$9 | D100: =AS100+AT100+AU100+AV100+AZ100+BM100+AK100 | E100: =CN100+AG100+AF100 | F100: =BY100+BZ100 | G100: =CQ100+CR100+CU100+CH100+CI100+CE100-CW100+CV100+BO100 | H100: =IF(CC100+CF100+CG100+CJ100+BN100<=0,"",G100/(CC100+CF100+CG100+CJ100+BN100)) | I100: =EC100/O100 | J100: =ED100/O100 | K100: =MAX(0,CP100-CQ100-CR100-CU100-CV100) | M100: =IF(L100="",$B$19,L100) | O100: =(1+$B$18)^(A100-household!$B$4+1) | P100: =(1+$B$18)^(A100-tax_tables!$B$4) | Q100: =(1+$B$21)^(A100-household!$B$4+1) | R100: =(1+$B$22)^(A100-household!$B$4+1) | S100: =(1+$B$23)^(A100-household!$B$4+1) | T100: =IF(A100<$B$5,1,0) | U100: =IF(A100<$B$6,1,0) | V100: =IF(T100+U100>0,1,0) | W100: =T100*$B$7*O100+SUMPRODUCT(($B$83:$B$88=A100)*($D$83:$D$88="Wages: person 1")*$C$83:$C$88)*O100 | X100: =U100*$B$8*O100+SUMPRODUCT(($B$83:$B$88=A100)*($D$83:$D$88="Wages: person 2")*$C$83:$C$88)*O100 | Y100: =T100*$B$9*O100 | Z100: =U100*$B$10*O100 | AA100: =T100*$B$11*O100 | AB100: =U100*$B$12*O100 | AC100: =V100*$B$13*O100 | AD100: =W100+X100 | AE100: =AD100-Y100-Z100-AC100 | AF100: =0.062*MIN(W100,tax_tables!$B$21*P100)+0.062*MIN(X100,tax_tables!$B$21*P100)+0.0145*AD100+0.009*MAX(0,AD100-tax_tables!$B$22) | AG100: =$B$14*AE100 | AH100: =AD100-Y100-Z100-AC100-AF100-AG100 | AI100: =SUMPRODUCT(($B$83:$B$88=A100)*($D$83:$D$88="Other taxable income")*$C$83:$C$88)*O100 | AJ100: =SUMPRODUCT(($B$83:$B$88=A100)*($D$83:$D$88="Tax-free money in")*$C$83:$C$88)*O100 | AK100: =SUMPRODUCT(($B$83:$B$88=A100)*($D$83:$D$88="Expense")*$C$83:$C$88)*O100 | AL100: =IF(OR($B$75="",A100<$B$75),1,0) | AM100: =AP99 | AN100: =AL100*AM100*properties!$J$2 | AO100: =AL100*MIN(properties!$K$2,AM100+AN100) | AP100: =AL100*(AM100+AN100-AO100) | AQ100: =AL100*properties!$G$2*O100 | AR100: =(1-AL100)*$E$75*O100 | AS100: =AO100+AQ100+AR100 | AT100: =SUMIF(budget!$A$2:$A$300,"household",budget!$F$2:$F$300)*O100*IF(N100="",1,N100) | AU100: =SUMPRODUCT((other_budget!$C$2:$C$30<=A100)*(other_budget!$D$2:$D$30>=A100)*other_budget!$B$2:$B$30)*O100 | AV100: =SUMPRODUCT((kids_budget!$D$2:$D$40<=A100)*(kids_budget!$E$2:$E$40>=A100)*(kids_budget!$G$2:$G$40<>"college_funds")*kids_budget!$C$2:$C$40*((kids_budget!$F$2:$F$40="college")*R100+(kids_budget!$F$2:$F$40<>"college")*O100)) | AW100: =SUMPRODUCT((kids_budget!$D$2:$D$40<=A100)*(kids_budget!$E$2:$E$40>=A100)*(kids_budget!$G$2:$G$40="college_funds")*kids_budget!$C$2:$C$40*((kids_budget!$F$2:$F$40="college")*R100+(kids_budget!$F$2:$F$40<>"college")*O100)) | AX100: =BA99 | AY100: =MIN(AW100,AX100*(1+M100)) | AZ100: =AW100-AY100 | BA100: =AX100*(1+M100)-AY100 | BB100: =V100*healthcare!$B$5*Q100 | BC100: =(1-V100)*((B100<65)+(C100<65)) | BD100: =COUNTIF(household!$C$16:$C$23,">="&A100) | BE100: =(BC100*healthcare!$B$2+IF(BC100>0,BD100,0)*healthcare!$B$3)*12*Q100 | BF100: =IF(BC100>0,(BC100+BD100)*healthcare!$B$4*Q100,0) | BG100: =(B100>=65)+(C100>=65) | BH100: =BG100*(healthcare!$B$6+healthcare!$B$7+healthcare!$B$8)*12*Q100 | BI100: =BG100*healthcare!$B$9*Q100 | BJ100: =BG100*12*O100*SUMPRODUCT((DK98>tax_tables!$Q$5:$Q$9*P100)*tax_tables!$T$5:$T$9) | BK100: =AND(B100>=$B$51,B100<$B$51+$B$52)*1+AND(C100>=$B$53,C100<$B$53+$B$54)*1 | BL100: =BK100*$B$55*S100 | BM100: =BB100+BE100+BF100+BH100+BI100+BJ100+BL100 | BN100: =BP99 | BO100: =IF(V100=1,0,MIN(BN100*(1+M100),BF100+BG100*(healthcare!$B$6+healthcare!$B$7)*12*Q100+BI100+BJ100+BL100)) | BP100: =BN100*(1+M100)-BO100+AC100-CV100 | BQ100: =SUMPRODUCT((1-($B$76:$B$79>0)*(A100>=$B$76:$B$79))*(1-(($C$76:$C$79>0)*(A100>=$C$76:$C$79)))*(properties!$L$3:$L$6-properties!$M$3:$M$6))*O100+SUMPRODUCT((1-($B$76:$B$79>0)*(A100>=$B$76:$B$79))*(($C$76:$C$79>0)*(A100>=$C$76:$C$79))*($D$76:$D$79-$E$76:$E$79))*O100 | BR100: =SUMPRODUCT((1-($B$76:$B$79>0)*(A100>=$B$76:$B$79))*properties!$N$3:$N$6*(A100<=properties!$O$3:$O$6)) | BS100: =MAX(0,BQ100-BR100) | BT100: =SUMPRODUCT(($B$75:$B$79=A100)*$G$75:$G$79) | BU100: =SUMPRODUCT(($B$75:$B$79=A100)*$H$75:$H$79) | BV100: =SUMPRODUCT(($B$75:$B$79=A100)*$I$75:$I$79) | BW100: =AL100*properties!$C$2*(1+properties!$D$2)^(A100-household!$B$4+1) | BX100: =SUMPRODUCT((1-($B$76:$B$79>0)*(A100>=$B$76:$B$79))*properties!$C$3:$C$6*(1+properties!$D$3:$D$6)^(A100-household!$B$4+1)) | BY100: =IF(A100>=$B$31,IF(A100>=$B$32,MAX(household!$B$11*12*(1-$B$28)*O100*IF(A100>=$B$30,1-$B$29,1)*$B$33,0.5*household!$B$12*12*(1-$B$28)*O100*IF(A100>=$B$30,1-$B$29,1)*$B$35),household!$B$11*12*(1-$B$28)*O100*IF(A100>=$B$30,1-$B$29,1)*$B$33),0) | BZ100: =IF(A100>=$B$32,IF(A100>=$B$31,MAX(household!$B$12*12*(1-$B$28)*O100*IF(A100>=$B$30,1-$B$29,1)*$B$34,0.5*household!$B$11*12*(1-$B$28)*O100*IF(A100>=$B$30,1-$B$29,1)*$B$36),household!$B$12*12*(1-$B$28)*O100*IF(A100>=$B$30,1-$B$29,1)*$B$34),0) | CA100: =IF(AND($B$43<>0,A100>=household!$B$6+$B$44),$B$43*(1+$B$18)^(MAX(household!$B$6+$B$44,household!$B$4-1)-household!$B$4+1)*(1+$B$47*$B$18)^(A100-MAX(household!$B$6+$B$44,household!$B$4-1)),0) | CB100: =IF(AND($B$45<>0,A100>=household!$B$9+$B$46),$B$45*(1+$B$18)^(MAX(household!$B$9+$B$46,household!$B$4-1)-household!$B$4+1)*(1+$B$47*$B$18)^(A100-MAX(household!$B$9+$B$46,household!$B$4-1)),0) | CC100: =DC99 | CD100: =DD99 | CE100: =$B$20*CC100 | CF100: =DE99 | CG100: =DF99 | CH100: =IF(B100>=$B$71,MAX(0,CF100)/INDEX(tax_tables!$Z$5:$Z$53,MATCH(B100,tax_tables!$Y$5:$Y$53,0)),0) | CI100: =IF(C100>=$B$72,MAX(0,CG100)/INDEX(tax_tables!$Z$5:$Z$53,MATCH(C100,tax_tables!$Y$5:$Y$53,0)),0) | CJ100: =DG99 | CK100: =IF(OR($B$59="",$B$60=""),0,IF(AND(A100>=$B$59,A100<=$B$60),$B$58*O100,0)) | CL100: =MAX(0,CF100*(1+M100)-CH100) | CM100: =MAX(0,CG100*(1+M100)-CI100) | CN100: =EB99-AG99 | CO100: =AH100+F100+CA100+CB100+BQ100+CE100+CH100+CI100+BT100+AI100+AJ100+BO100 | CP100: =D100+CN100-CO100 | CQ100: =MAX(0,MIN(CP100,CC100*(1+M100-$B$20))) | CR100: =MAX(0,MIN(CP100-CQ100,CL100+CM100)) | CS100: =IF(CL100+CM100>1,CR100*CL100/(CL100+CM100),0) | CT100: =CR100-CS100 | CU100: =MAX(0,MIN(CP100-CQ100-CR100,CJ100*(1+M100))) | CV100: =MAX(0,MIN(CP100-CQ100-CR100-CU100,BN100*(1+M100)-BO100+AC100)) | CW100: =MAX(0,-CP100) | CX100: =MIN(CK100,CL100-CS100+CM100-CT100) | CY100: =IF(CL100-CS100+CM100-CT100>1,CX100*(CL100-CS100)/(CL100-CS100+CM100-CT100),0) | CZ100: =CX100-CY100 | DA100: =IF(CC100>0,MAX(0,1-CD100/CC100),0) | DB100: =CQ100*DA100 | DC100: =CC100*(1+M100-$B$20)-CQ100+CW100 | DD100: =CD100-(CQ100-DB100)+CW100 | DE100: =CF100*(1+M100)-CH100-CS100-CY100+Y100+AA100 | DF100: =CG100*(1+M100)-CI100-CT100-CZ100+Z100+AB100 | DG100: =CJ100*(1+M100)-CU100+CX100 | DH100: =AE100+CR100+CH100+CI100+CX100+CV100+BS100+AI100+CA100+CB100 | DI100: =CE100+DB100+BU100 | DJ100: =IF((DH100+DI100+0.5*F100)<=tax_tables!$B$14,0,IF((DH100+DI100+0.5*F100)<=tax_tables!$B$15,MIN(0.5*F100,0.5*((DH100+DI100+0.5*F100)-tax_tables!$B$14)),MIN(0.85*F100,0.85*((DH100+DI100+0.5*F100)-tax_tables!$B$15)+MIN(0.5*F100,tax_tables!$B$15-tax_tables!$B$14)))) | DK100: =DH100+DI100+DJ100 | DL100: =(B100>=65)+(C100>=65) | DM100: =(tax_tables!$B$5+tax_tables!$B$6*DL100)*P100 | DN100: =IF(AND(A100>=tax_tables!$B$8,A100<=tax_tables!$B$9),DL100*MAX(0,tax_tables!$B$7-tax_tables!$B$11*MAX(0,DK100-tax_tables!$B$10)),0) | DO100: =IFERROR(MAX(tax_tables!$B$16,INDEX(tax_tables!$W$5:$W$8,MATCH(A100,tax_tables!$V$5:$V$8,0))-tax_tables!$B$18*MAX(0,DK100-tax_tables!$B$17*1.01^(A100-tax_tables!$B$4))),tax_tables!$B$16) | DP100: =MAX(0,BM100-BB100-tax_tables!$B$23*DK100) | DQ100: =AN100+MIN(DO100,DY99+DZ99+EA99+AL100*properties!$H$2*O100)+DP100+$B$61*O100 | DR100: =MAX(DM100,DQ100) | DS100: =MAX(0,DH100+DJ100-DR100-DN100) | DT100: =MAX(0,DI100-MAX(0,DR100+DN100-DH100-DJ100)) | DU100: =SUMPRODUCT((DS100>tax_tables!$E$5:$E$16*P100)*(DS100-tax_tables!$E$5:$E$16*P100)*tax_tables!$G$5:$G$16)+SUMPRODUCT(((DS100+DT100)>tax_tables!$I$5:$I$16*P100)*((DS100+DT100)-tax_tables!$I$5:$I$16*P100)*tax_tables!$K$5:$K$16)-SUMPRODUCT((DS100>tax_tables!$I$5:$I$16*P100)*(DS100-tax_tables!$I$5:$I$16*P100)*tax_tables!$K$5:$K$16)+tax_tables!$B$19*BV100+tax_tables!$B$12*MIN(CE100+DB100+BS100+BU100,MAX(0,DK100-tax_tables!$B$13)) | DV100: =IF($B$39="",0,IF(A100>=$B$39,1,0)) | DW100: =IF(B100+0.5>=tax_tables!$B$30,MIN(CS100+CH100+CY100+CA100,tax_tables!$B$29),0)+IF(C100+0.5>=tax_tables!$B$30,MIN(CT100+CI100+CZ100+CB100,tax_tables!$B$29),0) | DX100: =MAX(0,DK100-tax_tables!$B$28*DJ100-DW100-tax_tables!$B$26*IF(tax_tables!$B$27=1,P100,1)) | DY100: =(1-DV100)*SUMPRODUCT((DX100>tax_tables!$M$5:$M$16*IF(tax_tables!$B$27=1,P100,1))*(DX100-tax_tables!$M$5:$M$16*IF(tax_tables!$B$27=1,P100,1))*tax_tables!$O$5:$O$16) | DZ100: =(1-DV100)*tax_tables!$B$31*DX100 | EA100: =DV100*$B$40*MAX(0,DK100-DJ100) | EB100: =DU100+DY100+DZ100+EA100 | EC100: =DC100+DE100+DF100+DG100+BP100 | ED100: =EC100+BW100-AP100+BX100
A101: =A100+1 | B101: =A101-household!$B$6 | C101: =A101-household!$B$9 | D101: =AS101+AT101+AU101+AV101+AZ101+BM101+AK101 | E101: =CN101+AG101+AF101 | F101: =BY101+BZ101 | G101: =CQ101+CR101+CU101+CH101+CI101+CE101-CW101+CV101+BO101 | H101: =IF(CC101+CF101+CG101+CJ101+BN101<=0,"",G101/(CC101+CF101+CG101+CJ101+BN101)) | I101: =EC101/O101 | J101: =ED101/O101 | K101: =MAX(0,CP101-CQ101-CR101-CU101-CV101) | M101: =IF(L101="",$B$19,L101) | O101: =(1+$B$18)^(A101-household!$B$4+1) | P101: =(1+$B$18)^(A101-tax_tables!$B$4) | Q101: =(1+$B$21)^(A101-household!$B$4+1) | R101: =(1+$B$22)^(A101-household!$B$4+1) | S101: =(1+$B$23)^(A101-household!$B$4+1) | T101: =IF(A101<$B$5,1,0) | U101: =IF(A101<$B$6,1,0) | V101: =IF(T101+U101>0,1,0) | W101: =T101*$B$7*O101+SUMPRODUCT(($B$83:$B$88=A101)*($D$83:$D$88="Wages: person 1")*$C$83:$C$88)*O101 | X101: =U101*$B$8*O101+SUMPRODUCT(($B$83:$B$88=A101)*($D$83:$D$88="Wages: person 2")*$C$83:$C$88)*O101 | Y101: =T101*$B$9*O101 | Z101: =U101*$B$10*O101 | AA101: =T101*$B$11*O101 | AB101: =U101*$B$12*O101 | AC101: =V101*$B$13*O101 | AD101: =W101+X101 | AE101: =AD101-Y101-Z101-AC101 | AF101: =0.062*MIN(W101,tax_tables!$B$21*P101)+0.062*MIN(X101,tax_tables!$B$21*P101)+0.0145*AD101+0.009*MAX(0,AD101-tax_tables!$B$22) | AG101: =$B$14*AE101 | AH101: =AD101-Y101-Z101-AC101-AF101-AG101 | AI101: =SUMPRODUCT(($B$83:$B$88=A101)*($D$83:$D$88="Other taxable income")*$C$83:$C$88)*O101 | AJ101: =SUMPRODUCT(($B$83:$B$88=A101)*($D$83:$D$88="Tax-free money in")*$C$83:$C$88)*O101 | AK101: =SUMPRODUCT(($B$83:$B$88=A101)*($D$83:$D$88="Expense")*$C$83:$C$88)*O101 | AL101: =IF(OR($B$75="",A101<$B$75),1,0) | AM101: =AP100 | AN101: =AL101*AM101*properties!$J$2 | AO101: =AL101*MIN(properties!$K$2,AM101+AN101) | AP101: =AL101*(AM101+AN101-AO101) | AQ101: =AL101*properties!$G$2*O101 | AR101: =(1-AL101)*$E$75*O101 | AS101: =AO101+AQ101+AR101 | AT101: =SUMIF(budget!$A$2:$A$300,"household",budget!$F$2:$F$300)*O101*IF(N101="",1,N101) | AU101: =SUMPRODUCT((other_budget!$C$2:$C$30<=A101)*(other_budget!$D$2:$D$30>=A101)*other_budget!$B$2:$B$30)*O101 | AV101: =SUMPRODUCT((kids_budget!$D$2:$D$40<=A101)*(kids_budget!$E$2:$E$40>=A101)*(kids_budget!$G$2:$G$40<>"college_funds")*kids_budget!$C$2:$C$40*((kids_budget!$F$2:$F$40="college")*R101+(kids_budget!$F$2:$F$40<>"college")*O101)) | AW101: =SUMPRODUCT((kids_budget!$D$2:$D$40<=A101)*(kids_budget!$E$2:$E$40>=A101)*(kids_budget!$G$2:$G$40="college_funds")*kids_budget!$C$2:$C$40*((kids_budget!$F$2:$F$40="college")*R101+(kids_budget!$F$2:$F$40<>"college")*O101)) | AX101: =BA100 | AY101: =MIN(AW101,AX101*(1+M101)) | AZ101: =AW101-AY101 | BA101: =AX101*(1+M101)-AY101 | BB101: =V101*healthcare!$B$5*Q101 | BC101: =(1-V101)*((B101<65)+(C101<65)) | BD101: =COUNTIF(household!$C$16:$C$23,">="&A101) | BE101: =(BC101*healthcare!$B$2+IF(BC101>0,BD101,0)*healthcare!$B$3)*12*Q101 | BF101: =IF(BC101>0,(BC101+BD101)*healthcare!$B$4*Q101,0) | BG101: =(B101>=65)+(C101>=65) | BH101: =BG101*(healthcare!$B$6+healthcare!$B$7+healthcare!$B$8)*12*Q101 | BI101: =BG101*healthcare!$B$9*Q101 | BJ101: =BG101*12*O101*SUMPRODUCT((DK99>tax_tables!$Q$5:$Q$9*P101)*tax_tables!$T$5:$T$9) | BK101: =AND(B101>=$B$51,B101<$B$51+$B$52)*1+AND(C101>=$B$53,C101<$B$53+$B$54)*1 | BL101: =BK101*$B$55*S101 | BM101: =BB101+BE101+BF101+BH101+BI101+BJ101+BL101 | BN101: =BP100 | BO101: =IF(V101=1,0,MIN(BN101*(1+M101),BF101+BG101*(healthcare!$B$6+healthcare!$B$7)*12*Q101+BI101+BJ101+BL101)) | BP101: =BN101*(1+M101)-BO101+AC101-CV101 | BQ101: =SUMPRODUCT((1-($B$76:$B$79>0)*(A101>=$B$76:$B$79))*(1-(($C$76:$C$79>0)*(A101>=$C$76:$C$79)))*(properties!$L$3:$L$6-properties!$M$3:$M$6))*O101+SUMPRODUCT((1-($B$76:$B$79>0)*(A101>=$B$76:$B$79))*(($C$76:$C$79>0)*(A101>=$C$76:$C$79))*($D$76:$D$79-$E$76:$E$79))*O101 | BR101: =SUMPRODUCT((1-($B$76:$B$79>0)*(A101>=$B$76:$B$79))*properties!$N$3:$N$6*(A101<=properties!$O$3:$O$6)) | BS101: =MAX(0,BQ101-BR101) | BT101: =SUMPRODUCT(($B$75:$B$79=A101)*$G$75:$G$79) | BU101: =SUMPRODUCT(($B$75:$B$79=A101)*$H$75:$H$79) | BV101: =SUMPRODUCT(($B$75:$B$79=A101)*$I$75:$I$79) | BW101: =AL101*properties!$C$2*(1+properties!$D$2)^(A101-household!$B$4+1) | BX101: =SUMPRODUCT((1-($B$76:$B$79>0)*(A101>=$B$76:$B$79))*properties!$C$3:$C$6*(1+properties!$D$3:$D$6)^(A101-household!$B$4+1)) | BY101: =IF(A101>=$B$31,IF(A101>=$B$32,MAX(household!$B$11*12*(1-$B$28)*O101*IF(A101>=$B$30,1-$B$29,1)*$B$33,0.5*household!$B$12*12*(1-$B$28)*O101*IF(A101>=$B$30,1-$B$29,1)*$B$35),household!$B$11*12*(1-$B$28)*O101*IF(A101>=$B$30,1-$B$29,1)*$B$33),0) | BZ101: =IF(A101>=$B$32,IF(A101>=$B$31,MAX(household!$B$12*12*(1-$B$28)*O101*IF(A101>=$B$30,1-$B$29,1)*$B$34,0.5*household!$B$11*12*(1-$B$28)*O101*IF(A101>=$B$30,1-$B$29,1)*$B$36),household!$B$12*12*(1-$B$28)*O101*IF(A101>=$B$30,1-$B$29,1)*$B$34),0) | CA101: =IF(AND($B$43<>0,A101>=household!$B$6+$B$44),$B$43*(1+$B$18)^(MAX(household!$B$6+$B$44,household!$B$4-1)-household!$B$4+1)*(1+$B$47*$B$18)^(A101-MAX(household!$B$6+$B$44,household!$B$4-1)),0) | CB101: =IF(AND($B$45<>0,A101>=household!$B$9+$B$46),$B$45*(1+$B$18)^(MAX(household!$B$9+$B$46,household!$B$4-1)-household!$B$4+1)*(1+$B$47*$B$18)^(A101-MAX(household!$B$9+$B$46,household!$B$4-1)),0) | CC101: =DC100 | CD101: =DD100 | CE101: =$B$20*CC101 | CF101: =DE100 | CG101: =DF100 | CH101: =IF(B101>=$B$71,MAX(0,CF101)/INDEX(tax_tables!$Z$5:$Z$53,MATCH(B101,tax_tables!$Y$5:$Y$53,0)),0) | CI101: =IF(C101>=$B$72,MAX(0,CG101)/INDEX(tax_tables!$Z$5:$Z$53,MATCH(C101,tax_tables!$Y$5:$Y$53,0)),0) | CJ101: =DG100 | CK101: =IF(OR($B$59="",$B$60=""),0,IF(AND(A101>=$B$59,A101<=$B$60),$B$58*O101,0)) | CL101: =MAX(0,CF101*(1+M101)-CH101) | CM101: =MAX(0,CG101*(1+M101)-CI101) | CN101: =EB100-AG100 | CO101: =AH101+F101+CA101+CB101+BQ101+CE101+CH101+CI101+BT101+AI101+AJ101+BO101 | CP101: =D101+CN101-CO101 | CQ101: =MAX(0,MIN(CP101,CC101*(1+M101-$B$20))) | CR101: =MAX(0,MIN(CP101-CQ101,CL101+CM101)) | CS101: =IF(CL101+CM101>1,CR101*CL101/(CL101+CM101),0) | CT101: =CR101-CS101 | CU101: =MAX(0,MIN(CP101-CQ101-CR101,CJ101*(1+M101))) | CV101: =MAX(0,MIN(CP101-CQ101-CR101-CU101,BN101*(1+M101)-BO101+AC101)) | CW101: =MAX(0,-CP101) | CX101: =MIN(CK101,CL101-CS101+CM101-CT101) | CY101: =IF(CL101-CS101+CM101-CT101>1,CX101*(CL101-CS101)/(CL101-CS101+CM101-CT101),0) | CZ101: =CX101-CY101 | DA101: =IF(CC101>0,MAX(0,1-CD101/CC101),0) | DB101: =CQ101*DA101 | DC101: =CC101*(1+M101-$B$20)-CQ101+CW101 | DD101: =CD101-(CQ101-DB101)+CW101 | DE101: =CF101*(1+M101)-CH101-CS101-CY101+Y101+AA101 | DF101: =CG101*(1+M101)-CI101-CT101-CZ101+Z101+AB101 | DG101: =CJ101*(1+M101)-CU101+CX101 | DH101: =AE101+CR101+CH101+CI101+CX101+CV101+BS101+AI101+CA101+CB101 | DI101: =CE101+DB101+BU101 | DJ101: =IF((DH101+DI101+0.5*F101)<=tax_tables!$B$14,0,IF((DH101+DI101+0.5*F101)<=tax_tables!$B$15,MIN(0.5*F101,0.5*((DH101+DI101+0.5*F101)-tax_tables!$B$14)),MIN(0.85*F101,0.85*((DH101+DI101+0.5*F101)-tax_tables!$B$15)+MIN(0.5*F101,tax_tables!$B$15-tax_tables!$B$14)))) | DK101: =DH101+DI101+DJ101 | DL101: =(B101>=65)+(C101>=65) | DM101: =(tax_tables!$B$5+tax_tables!$B$6*DL101)*P101 | DN101: =IF(AND(A101>=tax_tables!$B$8,A101<=tax_tables!$B$9),DL101*MAX(0,tax_tables!$B$7-tax_tables!$B$11*MAX(0,DK101-tax_tables!$B$10)),0) | DO101: =IFERROR(MAX(tax_tables!$B$16,INDEX(tax_tables!$W$5:$W$8,MATCH(A101,tax_tables!$V$5:$V$8,0))-tax_tables!$B$18*MAX(0,DK101-tax_tables!$B$17*1.01^(A101-tax_tables!$B$4))),tax_tables!$B$16) | DP101: =MAX(0,BM101-BB101-tax_tables!$B$23*DK101) | DQ101: =AN101+MIN(DO101,DY100+DZ100+EA100+AL101*properties!$H$2*O101)+DP101+$B$61*O101 | DR101: =MAX(DM101,DQ101) | DS101: =MAX(0,DH101+DJ101-DR101-DN101) | DT101: =MAX(0,DI101-MAX(0,DR101+DN101-DH101-DJ101)) | DU101: =SUMPRODUCT((DS101>tax_tables!$E$5:$E$16*P101)*(DS101-tax_tables!$E$5:$E$16*P101)*tax_tables!$G$5:$G$16)+SUMPRODUCT(((DS101+DT101)>tax_tables!$I$5:$I$16*P101)*((DS101+DT101)-tax_tables!$I$5:$I$16*P101)*tax_tables!$K$5:$K$16)-SUMPRODUCT((DS101>tax_tables!$I$5:$I$16*P101)*(DS101-tax_tables!$I$5:$I$16*P101)*tax_tables!$K$5:$K$16)+tax_tables!$B$19*BV101+tax_tables!$B$12*MIN(CE101+DB101+BS101+BU101,MAX(0,DK101-tax_tables!$B$13)) | DV101: =IF($B$39="",0,IF(A101>=$B$39,1,0)) | DW101: =IF(B101+0.5>=tax_tables!$B$30,MIN(CS101+CH101+CY101+CA101,tax_tables!$B$29),0)+IF(C101+0.5>=tax_tables!$B$30,MIN(CT101+CI101+CZ101+CB101,tax_tables!$B$29),0) | DX101: =MAX(0,DK101-tax_tables!$B$28*DJ101-DW101-tax_tables!$B$26*IF(tax_tables!$B$27=1,P101,1)) | DY101: =(1-DV101)*SUMPRODUCT((DX101>tax_tables!$M$5:$M$16*IF(tax_tables!$B$27=1,P101,1))*(DX101-tax_tables!$M$5:$M$16*IF(tax_tables!$B$27=1,P101,1))*tax_tables!$O$5:$O$16) | DZ101: =(1-DV101)*tax_tables!$B$31*DX101 | EA101: =DV101*$B$40*MAX(0,DK101-DJ101) | EB101: =DU101+DY101+DZ101+EA101 | EC101: =DC101+DE101+DF101+DG101+BP101 | ED101: =EC101+BW101-AP101+BX101
A102: =A101+1 | B102: =A102-household!$B$6 | C102: =A102-household!$B$9 | D102: =AS102+AT102+AU102+AV102+AZ102+BM102+AK102 | E102: =CN102+AG102+AF102 | F102: =BY102+BZ102 | G102: =CQ102+CR102+CU102+CH102+CI102+CE102-CW102+CV102+BO102 | H102: =IF(CC102+CF102+CG102+CJ102+BN102<=0,"",G102/(CC102+CF102+CG102+CJ102+BN102)) | I102: =EC102/O102 | J102: =ED102/O102 | K102: =MAX(0,CP102-CQ102-CR102-CU102-CV102) | M102: =IF(L102="",$B$19,L102) | O102: =(1+$B$18)^(A102-household!$B$4+1) | P102: =(1+$B$18)^(A102-tax_tables!$B$4) | Q102: =(1+$B$21)^(A102-household!$B$4+1) | R102: =(1+$B$22)^(A102-household!$B$4+1) | S102: =(1+$B$23)^(A102-household!$B$4+1) | T102: =IF(A102<$B$5,1,0) | U102: =IF(A102<$B$6,1,0) | V102: =IF(T102+U102>0,1,0) | W102: =T102*$B$7*O102+SUMPRODUCT(($B$83:$B$88=A102)*($D$83:$D$88="Wages: person 1")*$C$83:$C$88)*O102 | X102: =U102*$B$8*O102+SUMPRODUCT(($B$83:$B$88=A102)*($D$83:$D$88="Wages: person 2")*$C$83:$C$88)*O102 | Y102: =T102*$B$9*O102 | Z102: =U102*$B$10*O102 | AA102: =T102*$B$11*O102 | AB102: =U102*$B$12*O102 | AC102: =V102*$B$13*O102 | AD102: =W102+X102 | AE102: =AD102-Y102-Z102-AC102 | AF102: =0.062*MIN(W102,tax_tables!$B$21*P102)+0.062*MIN(X102,tax_tables!$B$21*P102)+0.0145*AD102+0.009*MAX(0,AD102-tax_tables!$B$22) | AG102: =$B$14*AE102 | AH102: =AD102-Y102-Z102-AC102-AF102-AG102 | AI102: =SUMPRODUCT(($B$83:$B$88=A102)*($D$83:$D$88="Other taxable income")*$C$83:$C$88)*O102 | AJ102: =SUMPRODUCT(($B$83:$B$88=A102)*($D$83:$D$88="Tax-free money in")*$C$83:$C$88)*O102 | AK102: =SUMPRODUCT(($B$83:$B$88=A102)*($D$83:$D$88="Expense")*$C$83:$C$88)*O102 | AL102: =IF(OR($B$75="",A102<$B$75),1,0) | AM102: =AP101 | AN102: =AL102*AM102*properties!$J$2 | AO102: =AL102*MIN(properties!$K$2,AM102+AN102) | AP102: =AL102*(AM102+AN102-AO102) | AQ102: =AL102*properties!$G$2*O102 | AR102: =(1-AL102)*$E$75*O102 | AS102: =AO102+AQ102+AR102 | AT102: =SUMIF(budget!$A$2:$A$300,"household",budget!$F$2:$F$300)*O102*IF(N102="",1,N102) | AU102: =SUMPRODUCT((other_budget!$C$2:$C$30<=A102)*(other_budget!$D$2:$D$30>=A102)*other_budget!$B$2:$B$30)*O102 | AV102: =SUMPRODUCT((kids_budget!$D$2:$D$40<=A102)*(kids_budget!$E$2:$E$40>=A102)*(kids_budget!$G$2:$G$40<>"college_funds")*kids_budget!$C$2:$C$40*((kids_budget!$F$2:$F$40="college")*R102+(kids_budget!$F$2:$F$40<>"college")*O102)) | AW102: =SUMPRODUCT((kids_budget!$D$2:$D$40<=A102)*(kids_budget!$E$2:$E$40>=A102)*(kids_budget!$G$2:$G$40="college_funds")*kids_budget!$C$2:$C$40*((kids_budget!$F$2:$F$40="college")*R102+(kids_budget!$F$2:$F$40<>"college")*O102)) | AX102: =BA101 | AY102: =MIN(AW102,AX102*(1+M102)) | AZ102: =AW102-AY102 | BA102: =AX102*(1+M102)-AY102 | BB102: =V102*healthcare!$B$5*Q102 | BC102: =(1-V102)*((B102<65)+(C102<65)) | BD102: =COUNTIF(household!$C$16:$C$23,">="&A102) | BE102: =(BC102*healthcare!$B$2+IF(BC102>0,BD102,0)*healthcare!$B$3)*12*Q102 | BF102: =IF(BC102>0,(BC102+BD102)*healthcare!$B$4*Q102,0) | BG102: =(B102>=65)+(C102>=65) | BH102: =BG102*(healthcare!$B$6+healthcare!$B$7+healthcare!$B$8)*12*Q102 | BI102: =BG102*healthcare!$B$9*Q102 | BJ102: =BG102*12*O102*SUMPRODUCT((DK100>tax_tables!$Q$5:$Q$9*P102)*tax_tables!$T$5:$T$9) | BK102: =AND(B102>=$B$51,B102<$B$51+$B$52)*1+AND(C102>=$B$53,C102<$B$53+$B$54)*1 | BL102: =BK102*$B$55*S102 | BM102: =BB102+BE102+BF102+BH102+BI102+BJ102+BL102 | BN102: =BP101 | BO102: =IF(V102=1,0,MIN(BN102*(1+M102),BF102+BG102*(healthcare!$B$6+healthcare!$B$7)*12*Q102+BI102+BJ102+BL102)) | BP102: =BN102*(1+M102)-BO102+AC102-CV102 | BQ102: =SUMPRODUCT((1-($B$76:$B$79>0)*(A102>=$B$76:$B$79))*(1-(($C$76:$C$79>0)*(A102>=$C$76:$C$79)))*(properties!$L$3:$L$6-properties!$M$3:$M$6))*O102+SUMPRODUCT((1-($B$76:$B$79>0)*(A102>=$B$76:$B$79))*(($C$76:$C$79>0)*(A102>=$C$76:$C$79))*($D$76:$D$79-$E$76:$E$79))*O102 | BR102: =SUMPRODUCT((1-($B$76:$B$79>0)*(A102>=$B$76:$B$79))*properties!$N$3:$N$6*(A102<=properties!$O$3:$O$6)) | BS102: =MAX(0,BQ102-BR102) | BT102: =SUMPRODUCT(($B$75:$B$79=A102)*$G$75:$G$79) | BU102: =SUMPRODUCT(($B$75:$B$79=A102)*$H$75:$H$79) | BV102: =SUMPRODUCT(($B$75:$B$79=A102)*$I$75:$I$79) | BW102: =AL102*properties!$C$2*(1+properties!$D$2)^(A102-household!$B$4+1) | BX102: =SUMPRODUCT((1-($B$76:$B$79>0)*(A102>=$B$76:$B$79))*properties!$C$3:$C$6*(1+properties!$D$3:$D$6)^(A102-household!$B$4+1)) | BY102: =IF(A102>=$B$31,IF(A102>=$B$32,MAX(household!$B$11*12*(1-$B$28)*O102*IF(A102>=$B$30,1-$B$29,1)*$B$33,0.5*household!$B$12*12*(1-$B$28)*O102*IF(A102>=$B$30,1-$B$29,1)*$B$35),household!$B$11*12*(1-$B$28)*O102*IF(A102>=$B$30,1-$B$29,1)*$B$33),0) | BZ102: =IF(A102>=$B$32,IF(A102>=$B$31,MAX(household!$B$12*12*(1-$B$28)*O102*IF(A102>=$B$30,1-$B$29,1)*$B$34,0.5*household!$B$11*12*(1-$B$28)*O102*IF(A102>=$B$30,1-$B$29,1)*$B$36),household!$B$12*12*(1-$B$28)*O102*IF(A102>=$B$30,1-$B$29,1)*$B$34),0) | CA102: =IF(AND($B$43<>0,A102>=household!$B$6+$B$44),$B$43*(1+$B$18)^(MAX(household!$B$6+$B$44,household!$B$4-1)-household!$B$4+1)*(1+$B$47*$B$18)^(A102-MAX(household!$B$6+$B$44,household!$B$4-1)),0) | CB102: =IF(AND($B$45<>0,A102>=household!$B$9+$B$46),$B$45*(1+$B$18)^(MAX(household!$B$9+$B$46,household!$B$4-1)-household!$B$4+1)*(1+$B$47*$B$18)^(A102-MAX(household!$B$9+$B$46,household!$B$4-1)),0) | CC102: =DC101 | CD102: =DD101 | CE102: =$B$20*CC102 | CF102: =DE101 | CG102: =DF101 | CH102: =IF(B102>=$B$71,MAX(0,CF102)/INDEX(tax_tables!$Z$5:$Z$53,MATCH(B102,tax_tables!$Y$5:$Y$53,0)),0) | CI102: =IF(C102>=$B$72,MAX(0,CG102)/INDEX(tax_tables!$Z$5:$Z$53,MATCH(C102,tax_tables!$Y$5:$Y$53,0)),0) | CJ102: =DG101 | CK102: =IF(OR($B$59="",$B$60=""),0,IF(AND(A102>=$B$59,A102<=$B$60),$B$58*O102,0)) | CL102: =MAX(0,CF102*(1+M102)-CH102) | CM102: =MAX(0,CG102*(1+M102)-CI102) | CN102: =EB101-AG101 | CO102: =AH102+F102+CA102+CB102+BQ102+CE102+CH102+CI102+BT102+AI102+AJ102+BO102 | CP102: =D102+CN102-CO102 | CQ102: =MAX(0,MIN(CP102,CC102*(1+M102-$B$20))) | CR102: =MAX(0,MIN(CP102-CQ102,CL102+CM102)) | CS102: =IF(CL102+CM102>1,CR102*CL102/(CL102+CM102),0) | CT102: =CR102-CS102 | CU102: =MAX(0,MIN(CP102-CQ102-CR102,CJ102*(1+M102))) | CV102: =MAX(0,MIN(CP102-CQ102-CR102-CU102,BN102*(1+M102)-BO102+AC102)) | CW102: =MAX(0,-CP102) | CX102: =MIN(CK102,CL102-CS102+CM102-CT102) | CY102: =IF(CL102-CS102+CM102-CT102>1,CX102*(CL102-CS102)/(CL102-CS102+CM102-CT102),0) | CZ102: =CX102-CY102 | DA102: =IF(CC102>0,MAX(0,1-CD102/CC102),0) | DB102: =CQ102*DA102 | DC102: =CC102*(1+M102-$B$20)-CQ102+CW102 | DD102: =CD102-(CQ102-DB102)+CW102 | DE102: =CF102*(1+M102)-CH102-CS102-CY102+Y102+AA102 | DF102: =CG102*(1+M102)-CI102-CT102-CZ102+Z102+AB102 | DG102: =CJ102*(1+M102)-CU102+CX102 | DH102: =AE102+CR102+CH102+CI102+CX102+CV102+BS102+AI102+CA102+CB102 | DI102: =CE102+DB102+BU102 | DJ102: =IF((DH102+DI102+0.5*F102)<=tax_tables!$B$14,0,IF((DH102+DI102+0.5*F102)<=tax_tables!$B$15,MIN(0.5*F102,0.5*((DH102+DI102+0.5*F102)-tax_tables!$B$14)),MIN(0.85*F102,0.85*((DH102+DI102+0.5*F102)-tax_tables!$B$15)+MIN(0.5*F102,tax_tables!$B$15-tax_tables!$B$14)))) | DK102: =DH102+DI102+DJ102 | DL102: =(B102>=65)+(C102>=65) | DM102: =(tax_tables!$B$5+tax_tables!$B$6*DL102)*P102 | DN102: =IF(AND(A102>=tax_tables!$B$8,A102<=tax_tables!$B$9),DL102*MAX(0,tax_tables!$B$7-tax_tables!$B$11*MAX(0,DK102-tax_tables!$B$10)),0) | DO102: =IFERROR(MAX(tax_tables!$B$16,INDEX(tax_tables!$W$5:$W$8,MATCH(A102,tax_tables!$V$5:$V$8,0))-tax_tables!$B$18*MAX(0,DK102-tax_tables!$B$17*1.01^(A102-tax_tables!$B$4))),tax_tables!$B$16) | DP102: =MAX(0,BM102-BB102-tax_tables!$B$23*DK102) | DQ102: =AN102+MIN(DO102,DY101+DZ101+EA101+AL102*properties!$H$2*O102)+DP102+$B$61*O102 | DR102: =MAX(DM102,DQ102) | DS102: =MAX(0,DH102+DJ102-DR102-DN102) | DT102: =MAX(0,DI102-MAX(0,DR102+DN102-DH102-DJ102)) | DU102: =SUMPRODUCT((DS102>tax_tables!$E$5:$E$16*P102)*(DS102-tax_tables!$E$5:$E$16*P102)*tax_tables!$G$5:$G$16)+SUMPRODUCT(((DS102+DT102)>tax_tables!$I$5:$I$16*P102)*((DS102+DT102)-tax_tables!$I$5:$I$16*P102)*tax_tables!$K$5:$K$16)-SUMPRODUCT((DS102>tax_tables!$I$5:$I$16*P102)*(DS102-tax_tables!$I$5:$I$16*P102)*tax_tables!$K$5:$K$16)+tax_tables!$B$19*BV102+tax_tables!$B$12*MIN(CE102+DB102+BS102+BU102,MAX(0,DK102-tax_tables!$B$13)) | DV102: =IF($B$39="",0,IF(A102>=$B$39,1,0)) | DW102: =IF(B102+0.5>=tax_tables!$B$30,MIN(CS102+CH102+CY102+CA102,tax_tables!$B$29),0)+IF(C102+0.5>=tax_tables!$B$30,MIN(CT102+CI102+CZ102+CB102,tax_tables!$B$29),0) | DX102: =MAX(0,DK102-tax_tables!$B$28*DJ102-DW102-tax_tables!$B$26*IF(tax_tables!$B$27=1,P102,1)) | DY102: =(1-DV102)*SUMPRODUCT((DX102>tax_tables!$M$5:$M$16*IF(tax_tables!$B$27=1,P102,1))*(DX102-tax_tables!$M$5:$M$16*IF(tax_tables!$B$27=1,P102,1))*tax_tables!$O$5:$O$16) | DZ102: =(1-DV102)*tax_tables!$B$31*DX102 | EA102: =DV102*$B$40*MAX(0,DK102-DJ102) | EB102: =DU102+DY102+DZ102+EA102 | EC102: =DC102+DE102+DF102+DG102+BP102 | ED102: =EC102+BW102-AP102+BX102
A103: =A102+1 | B103: =A103-household!$B$6 | C103: =A103-household!$B$9 | D103: =AS103+AT103+AU103+AV103+AZ103+BM103+AK103 | E103: =CN103+AG103+AF103 | F103: =BY103+BZ103 | G103: =CQ103+CR103+CU103+CH103+CI103+CE103-CW103+CV103+BO103 | H103: =IF(CC103+CF103+CG103+CJ103+BN103<=0,"",G103/(CC103+CF103+CG103+CJ103+BN103)) | I103: =EC103/O103 | J103: =ED103/O103 | K103: =MAX(0,CP103-CQ103-CR103-CU103-CV103) | M103: =IF(L103="",$B$19,L103) | O103: =(1+$B$18)^(A103-household!$B$4+1) | P103: =(1+$B$18)^(A103-tax_tables!$B$4) | Q103: =(1+$B$21)^(A103-household!$B$4+1) | R103: =(1+$B$22)^(A103-household!$B$4+1) | S103: =(1+$B$23)^(A103-household!$B$4+1) | T103: =IF(A103<$B$5,1,0) | U103: =IF(A103<$B$6,1,0) | V103: =IF(T103+U103>0,1,0) | W103: =T103*$B$7*O103+SUMPRODUCT(($B$83:$B$88=A103)*($D$83:$D$88="Wages: person 1")*$C$83:$C$88)*O103 | X103: =U103*$B$8*O103+SUMPRODUCT(($B$83:$B$88=A103)*($D$83:$D$88="Wages: person 2")*$C$83:$C$88)*O103 | Y103: =T103*$B$9*O103 | Z103: =U103*$B$10*O103 | AA103: =T103*$B$11*O103 | AB103: =U103*$B$12*O103 | AC103: =V103*$B$13*O103 | AD103: =W103+X103 | AE103: =AD103-Y103-Z103-AC103 | AF103: =0.062*MIN(W103,tax_tables!$B$21*P103)+0.062*MIN(X103,tax_tables!$B$21*P103)+0.0145*AD103+0.009*MAX(0,AD103-tax_tables!$B$22) | AG103: =$B$14*AE103 | AH103: =AD103-Y103-Z103-AC103-AF103-AG103 | AI103: =SUMPRODUCT(($B$83:$B$88=A103)*($D$83:$D$88="Other taxable income")*$C$83:$C$88)*O103 | AJ103: =SUMPRODUCT(($B$83:$B$88=A103)*($D$83:$D$88="Tax-free money in")*$C$83:$C$88)*O103 | AK103: =SUMPRODUCT(($B$83:$B$88=A103)*($D$83:$D$88="Expense")*$C$83:$C$88)*O103 | AL103: =IF(OR($B$75="",A103<$B$75),1,0) | AM103: =AP102 | AN103: =AL103*AM103*properties!$J$2 | AO103: =AL103*MIN(properties!$K$2,AM103+AN103) | AP103: =AL103*(AM103+AN103-AO103) | AQ103: =AL103*properties!$G$2*O103 | AR103: =(1-AL103)*$E$75*O103 | AS103: =AO103+AQ103+AR103 | AT103: =SUMIF(budget!$A$2:$A$300,"household",budget!$F$2:$F$300)*O103*IF(N103="",1,N103) | AU103: =SUMPRODUCT((other_budget!$C$2:$C$30<=A103)*(other_budget!$D$2:$D$30>=A103)*other_budget!$B$2:$B$30)*O103 | AV103: =SUMPRODUCT((kids_budget!$D$2:$D$40<=A103)*(kids_budget!$E$2:$E$40>=A103)*(kids_budget!$G$2:$G$40<>"college_funds")*kids_budget!$C$2:$C$40*((kids_budget!$F$2:$F$40="college")*R103+(kids_budget!$F$2:$F$40<>"college")*O103)) | AW103: =SUMPRODUCT((kids_budget!$D$2:$D$40<=A103)*(kids_budget!$E$2:$E$40>=A103)*(kids_budget!$G$2:$G$40="college_funds")*kids_budget!$C$2:$C$40*((kids_budget!$F$2:$F$40="college")*R103+(kids_budget!$F$2:$F$40<>"college")*O103)) | AX103: =BA102 | AY103: =MIN(AW103,AX103*(1+M103)) | AZ103: =AW103-AY103 | BA103: =AX103*(1+M103)-AY103 | BB103: =V103*healthcare!$B$5*Q103 | BC103: =(1-V103)*((B103<65)+(C103<65)) | BD103: =COUNTIF(household!$C$16:$C$23,">="&A103) | BE103: =(BC103*healthcare!$B$2+IF(BC103>0,BD103,0)*healthcare!$B$3)*12*Q103 | BF103: =IF(BC103>0,(BC103+BD103)*healthcare!$B$4*Q103,0) | BG103: =(B103>=65)+(C103>=65) | BH103: =BG103*(healthcare!$B$6+healthcare!$B$7+healthcare!$B$8)*12*Q103 | BI103: =BG103*healthcare!$B$9*Q103 | BJ103: =BG103*12*O103*SUMPRODUCT((DK101>tax_tables!$Q$5:$Q$9*P103)*tax_tables!$T$5:$T$9) | BK103: =AND(B103>=$B$51,B103<$B$51+$B$52)*1+AND(C103>=$B$53,C103<$B$53+$B$54)*1 | BL103: =BK103*$B$55*S103 | BM103: =BB103+BE103+BF103+BH103+BI103+BJ103+BL103 | BN103: =BP102 | BO103: =IF(V103=1,0,MIN(BN103*(1+M103),BF103+BG103*(healthcare!$B$6+healthcare!$B$7)*12*Q103+BI103+BJ103+BL103)) | BP103: =BN103*(1+M103)-BO103+AC103-CV103 | BQ103: =SUMPRODUCT((1-($B$76:$B$79>0)*(A103>=$B$76:$B$79))*(1-(($C$76:$C$79>0)*(A103>=$C$76:$C$79)))*(properties!$L$3:$L$6-properties!$M$3:$M$6))*O103+SUMPRODUCT((1-($B$76:$B$79>0)*(A103>=$B$76:$B$79))*(($C$76:$C$79>0)*(A103>=$C$76:$C$79))*($D$76:$D$79-$E$76:$E$79))*O103 | BR103: =SUMPRODUCT((1-($B$76:$B$79>0)*(A103>=$B$76:$B$79))*properties!$N$3:$N$6*(A103<=properties!$O$3:$O$6)) | BS103: =MAX(0,BQ103-BR103) | BT103: =SUMPRODUCT(($B$75:$B$79=A103)*$G$75:$G$79) | BU103: =SUMPRODUCT(($B$75:$B$79=A103)*$H$75:$H$79) | BV103: =SUMPRODUCT(($B$75:$B$79=A103)*$I$75:$I$79) | BW103: =AL103*properties!$C$2*(1+properties!$D$2)^(A103-household!$B$4+1) | BX103: =SUMPRODUCT((1-($B$76:$B$79>0)*(A103>=$B$76:$B$79))*properties!$C$3:$C$6*(1+properties!$D$3:$D$6)^(A103-household!$B$4+1)) | BY103: =IF(A103>=$B$31,IF(A103>=$B$32,MAX(household!$B$11*12*(1-$B$28)*O103*IF(A103>=$B$30,1-$B$29,1)*$B$33,0.5*household!$B$12*12*(1-$B$28)*O103*IF(A103>=$B$30,1-$B$29,1)*$B$35),household!$B$11*12*(1-$B$28)*O103*IF(A103>=$B$30,1-$B$29,1)*$B$33),0) | BZ103: =IF(A103>=$B$32,IF(A103>=$B$31,MAX(household!$B$12*12*(1-$B$28)*O103*IF(A103>=$B$30,1-$B$29,1)*$B$34,0.5*household!$B$11*12*(1-$B$28)*O103*IF(A103>=$B$30,1-$B$29,1)*$B$36),household!$B$12*12*(1-$B$28)*O103*IF(A103>=$B$30,1-$B$29,1)*$B$34),0) | CA103: =IF(AND($B$43<>0,A103>=household!$B$6+$B$44),$B$43*(1+$B$18)^(MAX(household!$B$6+$B$44,household!$B$4-1)-household!$B$4+1)*(1+$B$47*$B$18)^(A103-MAX(household!$B$6+$B$44,household!$B$4-1)),0) | CB103: =IF(AND($B$45<>0,A103>=household!$B$9+$B$46),$B$45*(1+$B$18)^(MAX(household!$B$9+$B$46,household!$B$4-1)-household!$B$4+1)*(1+$B$47*$B$18)^(A103-MAX(household!$B$9+$B$46,household!$B$4-1)),0) | CC103: =DC102 | CD103: =DD102 | CE103: =$B$20*CC103 | CF103: =DE102 | CG103: =DF102 | CH103: =IF(B103>=$B$71,MAX(0,CF103)/INDEX(tax_tables!$Z$5:$Z$53,MATCH(B103,tax_tables!$Y$5:$Y$53,0)),0) | CI103: =IF(C103>=$B$72,MAX(0,CG103)/INDEX(tax_tables!$Z$5:$Z$53,MATCH(C103,tax_tables!$Y$5:$Y$53,0)),0) | CJ103: =DG102 | CK103: =IF(OR($B$59="",$B$60=""),0,IF(AND(A103>=$B$59,A103<=$B$60),$B$58*O103,0)) | CL103: =MAX(0,CF103*(1+M103)-CH103) | CM103: =MAX(0,CG103*(1+M103)-CI103) | CN103: =EB102-AG102 | CO103: =AH103+F103+CA103+CB103+BQ103+CE103+CH103+CI103+BT103+AI103+AJ103+BO103 | CP103: =D103+CN103-CO103 | CQ103: =MAX(0,MIN(CP103,CC103*(1+M103-$B$20))) | CR103: =MAX(0,MIN(CP103-CQ103,CL103+CM103)) | CS103: =IF(CL103+CM103>1,CR103*CL103/(CL103+CM103),0) | CT103: =CR103-CS103 | CU103: =MAX(0,MIN(CP103-CQ103-CR103,CJ103*(1+M103))) | CV103: =MAX(0,MIN(CP103-CQ103-CR103-CU103,BN103*(1+M103)-BO103+AC103)) | CW103: =MAX(0,-CP103) | CX103: =MIN(CK103,CL103-CS103+CM103-CT103) | CY103: =IF(CL103-CS103+CM103-CT103>1,CX103*(CL103-CS103)/(CL103-CS103+CM103-CT103),0) | CZ103: =CX103-CY103 | DA103: =IF(CC103>0,MAX(0,1-CD103/CC103),0) | DB103: =CQ103*DA103 | DC103: =CC103*(1+M103-$B$20)-CQ103+CW103 | DD103: =CD103-(CQ103-DB103)+CW103 | DE103: =CF103*(1+M103)-CH103-CS103-CY103+Y103+AA103 | DF103: =CG103*(1+M103)-CI103-CT103-CZ103+Z103+AB103 | DG103: =CJ103*(1+M103)-CU103+CX103 | DH103: =AE103+CR103+CH103+CI103+CX103+CV103+BS103+AI103+CA103+CB103 | DI103: =CE103+DB103+BU103 | DJ103: =IF((DH103+DI103+0.5*F103)<=tax_tables!$B$14,0,IF((DH103+DI103+0.5*F103)<=tax_tables!$B$15,MIN(0.5*F103,0.5*((DH103+DI103+0.5*F103)-tax_tables!$B$14)),MIN(0.85*F103,0.85*((DH103+DI103+0.5*F103)-tax_tables!$B$15)+MIN(0.5*F103,tax_tables!$B$15-tax_tables!$B$14)))) | DK103: =DH103+DI103+DJ103 | DL103: =(B103>=65)+(C103>=65) | DM103: =(tax_tables!$B$5+tax_tables!$B$6*DL103)*P103 | DN103: =IF(AND(A103>=tax_tables!$B$8,A103<=tax_tables!$B$9),DL103*MAX(0,tax_tables!$B$7-tax_tables!$B$11*MAX(0,DK103-tax_tables!$B$10)),0) | DO103: =IFERROR(MAX(tax_tables!$B$16,INDEX(tax_tables!$W$5:$W$8,MATCH(A103,tax_tables!$V$5:$V$8,0))-tax_tables!$B$18*MAX(0,DK103-tax_tables!$B$17*1.01^(A103-tax_tables!$B$4))),tax_tables!$B$16) | DP103: =MAX(0,BM103-BB103-tax_tables!$B$23*DK103) | DQ103: =AN103+MIN(DO103,DY102+DZ102+EA102+AL103*properties!$H$2*O103)+DP103+$B$61*O103 | DR103: =MAX(DM103,DQ103) | DS103: =MAX(0,DH103+DJ103-DR103-DN103) | DT103: =MAX(0,DI103-MAX(0,DR103+DN103-DH103-DJ103)) | DU103: =SUMPRODUCT((DS103>tax_tables!$E$5:$E$16*P103)*(DS103-tax_tables!$E$5:$E$16*P103)*tax_tables!$G$5:$G$16)+SUMPRODUCT(((DS103+DT103)>tax_tables!$I$5:$I$16*P103)*((DS103+DT103)-tax_tables!$I$5:$I$16*P103)*tax_tables!$K$5:$K$16)-SUMPRODUCT((DS103>tax_tables!$I$5:$I$16*P103)*(DS103-tax_tables!$I$5:$I$16*P103)*tax_tables!$K$5:$K$16)+tax_tables!$B$19*BV103+tax_tables!$B$12*MIN(CE103+DB103+BS103+BU103,MAX(0,DK103-tax_tables!$B$13)) | DV103: =IF($B$39="",0,IF(A103>=$B$39,1,0)) | DW103: =IF(B103+0.5>=tax_tables!$B$30,MIN(CS103+CH103+CY103+CA103,tax_tables!$B$29),0)+IF(C103+0.5>=tax_tables!$B$30,MIN(CT103+CI103+CZ103+CB103,tax_tables!$B$29),0) | DX103: =MAX(0,DK103-tax_tables!$B$28*DJ103-DW103-tax_tables!$B$26*IF(tax_tables!$B$27=1,P103,1)) | DY103: =(1-DV103)*SUMPRODUCT((DX103>tax_tables!$M$5:$M$16*IF(tax_tables!$B$27=1,P103,1))*(DX103-tax_tables!$M$5:$M$16*IF(tax_tables!$B$27=1,P103,1))*tax_tables!$O$5:$O$16) | DZ103: =(1-DV103)*tax_tables!$B$31*DX103 | EA103: =DV103*$B$40*MAX(0,DK103-DJ103) | EB103: =DU103+DY103+DZ103+EA103 | EC103: =DC103+DE103+DF103+DG103+BP103 | ED103: =EC103+BW103-AP103+BX103
A104: =A103+1 | B104: =A104-household!$B$6 | C104: =A104-household!$B$9 | D104: =AS104+AT104+AU104+AV104+AZ104+BM104+AK104 | E104: =CN104+AG104+AF104 | F104: =BY104+BZ104 | G104: =CQ104+CR104+CU104+CH104+CI104+CE104-CW104+CV104+BO104 | H104: =IF(CC104+CF104+CG104+CJ104+BN104<=0,"",G104/(CC104+CF104+CG104+CJ104+BN104)) | I104: =EC104/O104 | J104: =ED104/O104 | K104: =MAX(0,CP104-CQ104-CR104-CU104-CV104) | M104: =IF(L104="",$B$19,L104) | O104: =(1+$B$18)^(A104-household!$B$4+1) | P104: =(1+$B$18)^(A104-tax_tables!$B$4) | Q104: =(1+$B$21)^(A104-household!$B$4+1) | R104: =(1+$B$22)^(A104-household!$B$4+1) | S104: =(1+$B$23)^(A104-household!$B$4+1) | T104: =IF(A104<$B$5,1,0) | U104: =IF(A104<$B$6,1,0) | V104: =IF(T104+U104>0,1,0) | W104: =T104*$B$7*O104+SUMPRODUCT(($B$83:$B$88=A104)*($D$83:$D$88="Wages: person 1")*$C$83:$C$88)*O104 | X104: =U104*$B$8*O104+SUMPRODUCT(($B$83:$B$88=A104)*($D$83:$D$88="Wages: person 2")*$C$83:$C$88)*O104 | Y104: =T104*$B$9*O104 | Z104: =U104*$B$10*O104 | AA104: =T104*$B$11*O104 | AB104: =U104*$B$12*O104 | AC104: =V104*$B$13*O104 | AD104: =W104+X104 | AE104: =AD104-Y104-Z104-AC104 | AF104: =0.062*MIN(W104,tax_tables!$B$21*P104)+0.062*MIN(X104,tax_tables!$B$21*P104)+0.0145*AD104+0.009*MAX(0,AD104-tax_tables!$B$22) | AG104: =$B$14*AE104 | AH104: =AD104-Y104-Z104-AC104-AF104-AG104 | AI104: =SUMPRODUCT(($B$83:$B$88=A104)*($D$83:$D$88="Other taxable income")*$C$83:$C$88)*O104 | AJ104: =SUMPRODUCT(($B$83:$B$88=A104)*($D$83:$D$88="Tax-free money in")*$C$83:$C$88)*O104 | AK104: =SUMPRODUCT(($B$83:$B$88=A104)*($D$83:$D$88="Expense")*$C$83:$C$88)*O104 | AL104: =IF(OR($B$75="",A104<$B$75),1,0) | AM104: =AP103 | AN104: =AL104*AM104*properties!$J$2 | AO104: =AL104*MIN(properties!$K$2,AM104+AN104) | AP104: =AL104*(AM104+AN104-AO104) | AQ104: =AL104*properties!$G$2*O104 | AR104: =(1-AL104)*$E$75*O104 | AS104: =AO104+AQ104+AR104 | AT104: =SUMIF(budget!$A$2:$A$300,"household",budget!$F$2:$F$300)*O104*IF(N104="",1,N104) | AU104: =SUMPRODUCT((other_budget!$C$2:$C$30<=A104)*(other_budget!$D$2:$D$30>=A104)*other_budget!$B$2:$B$30)*O104 | AV104: =SUMPRODUCT((kids_budget!$D$2:$D$40<=A104)*(kids_budget!$E$2:$E$40>=A104)*(kids_budget!$G$2:$G$40<>"college_funds")*kids_budget!$C$2:$C$40*((kids_budget!$F$2:$F$40="college")*R104+(kids_budget!$F$2:$F$40<>"college")*O104)) | AW104: =SUMPRODUCT((kids_budget!$D$2:$D$40<=A104)*(kids_budget!$E$2:$E$40>=A104)*(kids_budget!$G$2:$G$40="college_funds")*kids_budget!$C$2:$C$40*((kids_budget!$F$2:$F$40="college")*R104+(kids_budget!$F$2:$F$40<>"college")*O104)) | AX104: =BA103 | AY104: =MIN(AW104,AX104*(1+M104)) | AZ104: =AW104-AY104 | BA104: =AX104*(1+M104)-AY104 | BB104: =V104*healthcare!$B$5*Q104 | BC104: =(1-V104)*((B104<65)+(C104<65)) | BD104: =COUNTIF(household!$C$16:$C$23,">="&A104) | BE104: =(BC104*healthcare!$B$2+IF(BC104>0,BD104,0)*healthcare!$B$3)*12*Q104 | BF104: =IF(BC104>0,(BC104+BD104)*healthcare!$B$4*Q104,0) | BG104: =(B104>=65)+(C104>=65) | BH104: =BG104*(healthcare!$B$6+healthcare!$B$7+healthcare!$B$8)*12*Q104 | BI104: =BG104*healthcare!$B$9*Q104 | BJ104: =BG104*12*O104*SUMPRODUCT((DK102>tax_tables!$Q$5:$Q$9*P104)*tax_tables!$T$5:$T$9) | BK104: =AND(B104>=$B$51,B104<$B$51+$B$52)*1+AND(C104>=$B$53,C104<$B$53+$B$54)*1 | BL104: =BK104*$B$55*S104 | BM104: =BB104+BE104+BF104+BH104+BI104+BJ104+BL104 | BN104: =BP103 | BO104: =IF(V104=1,0,MIN(BN104*(1+M104),BF104+BG104*(healthcare!$B$6+healthcare!$B$7)*12*Q104+BI104+BJ104+BL104)) | BP104: =BN104*(1+M104)-BO104+AC104-CV104 | BQ104: =SUMPRODUCT((1-($B$76:$B$79>0)*(A104>=$B$76:$B$79))*(1-(($C$76:$C$79>0)*(A104>=$C$76:$C$79)))*(properties!$L$3:$L$6-properties!$M$3:$M$6))*O104+SUMPRODUCT((1-($B$76:$B$79>0)*(A104>=$B$76:$B$79))*(($C$76:$C$79>0)*(A104>=$C$76:$C$79))*($D$76:$D$79-$E$76:$E$79))*O104 | BR104: =SUMPRODUCT((1-($B$76:$B$79>0)*(A104>=$B$76:$B$79))*properties!$N$3:$N$6*(A104<=properties!$O$3:$O$6)) | BS104: =MAX(0,BQ104-BR104) | BT104: =SUMPRODUCT(($B$75:$B$79=A104)*$G$75:$G$79) | BU104: =SUMPRODUCT(($B$75:$B$79=A104)*$H$75:$H$79) | BV104: =SUMPRODUCT(($B$75:$B$79=A104)*$I$75:$I$79) | BW104: =AL104*properties!$C$2*(1+properties!$D$2)^(A104-household!$B$4+1) | BX104: =SUMPRODUCT((1-($B$76:$B$79>0)*(A104>=$B$76:$B$79))*properties!$C$3:$C$6*(1+properties!$D$3:$D$6)^(A104-household!$B$4+1)) | BY104: =IF(A104>=$B$31,IF(A104>=$B$32,MAX(household!$B$11*12*(1-$B$28)*O104*IF(A104>=$B$30,1-$B$29,1)*$B$33,0.5*household!$B$12*12*(1-$B$28)*O104*IF(A104>=$B$30,1-$B$29,1)*$B$35),household!$B$11*12*(1-$B$28)*O104*IF(A104>=$B$30,1-$B$29,1)*$B$33),0) | BZ104: =IF(A104>=$B$32,IF(A104>=$B$31,MAX(household!$B$12*12*(1-$B$28)*O104*IF(A104>=$B$30,1-$B$29,1)*$B$34,0.5*household!$B$11*12*(1-$B$28)*O104*IF(A104>=$B$30,1-$B$29,1)*$B$36),household!$B$12*12*(1-$B$28)*O104*IF(A104>=$B$30,1-$B$29,1)*$B$34),0) | CA104: =IF(AND($B$43<>0,A104>=household!$B$6+$B$44),$B$43*(1+$B$18)^(MAX(household!$B$6+$B$44,household!$B$4-1)-household!$B$4+1)*(1+$B$47*$B$18)^(A104-MAX(household!$B$6+$B$44,household!$B$4-1)),0) | CB104: =IF(AND($B$45<>0,A104>=household!$B$9+$B$46),$B$45*(1+$B$18)^(MAX(household!$B$9+$B$46,household!$B$4-1)-household!$B$4+1)*(1+$B$47*$B$18)^(A104-MAX(household!$B$9+$B$46,household!$B$4-1)),0) | CC104: =DC103 | CD104: =DD103 | CE104: =$B$20*CC104 | CF104: =DE103 | CG104: =DF103 | CH104: =IF(B104>=$B$71,MAX(0,CF104)/INDEX(tax_tables!$Z$5:$Z$53,MATCH(B104,tax_tables!$Y$5:$Y$53,0)),0) | CI104: =IF(C104>=$B$72,MAX(0,CG104)/INDEX(tax_tables!$Z$5:$Z$53,MATCH(C104,tax_tables!$Y$5:$Y$53,0)),0) | CJ104: =DG103 | CK104: =IF(OR($B$59="",$B$60=""),0,IF(AND(A104>=$B$59,A104<=$B$60),$B$58*O104,0)) | CL104: =MAX(0,CF104*(1+M104)-CH104) | CM104: =MAX(0,CG104*(1+M104)-CI104) | CN104: =EB103-AG103 | CO104: =AH104+F104+CA104+CB104+BQ104+CE104+CH104+CI104+BT104+AI104+AJ104+BO104 | CP104: =D104+CN104-CO104 | CQ104: =MAX(0,MIN(CP104,CC104*(1+M104-$B$20))) | CR104: =MAX(0,MIN(CP104-CQ104,CL104+CM104)) | CS104: =IF(CL104+CM104>1,CR104*CL104/(CL104+CM104),0) | CT104: =CR104-CS104 | CU104: =MAX(0,MIN(CP104-CQ104-CR104,CJ104*(1+M104))) | CV104: =MAX(0,MIN(CP104-CQ104-CR104-CU104,BN104*(1+M104)-BO104+AC104)) | CW104: =MAX(0,-CP104) | CX104: =MIN(CK104,CL104-CS104+CM104-CT104) | CY104: =IF(CL104-CS104+CM104-CT104>1,CX104*(CL104-CS104)/(CL104-CS104+CM104-CT104),0) | CZ104: =CX104-CY104 | DA104: =IF(CC104>0,MAX(0,1-CD104/CC104),0) | DB104: =CQ104*DA104 | DC104: =CC104*(1+M104-$B$20)-CQ104+CW104 | DD104: =CD104-(CQ104-DB104)+CW104 | DE104: =CF104*(1+M104)-CH104-CS104-CY104+Y104+AA104 | DF104: =CG104*(1+M104)-CI104-CT104-CZ104+Z104+AB104 | DG104: =CJ104*(1+M104)-CU104+CX104 | DH104: =AE104+CR104+CH104+CI104+CX104+CV104+BS104+AI104+CA104+CB104 | DI104: =CE104+DB104+BU104 | DJ104: =IF((DH104+DI104+0.5*F104)<=tax_tables!$B$14,0,IF((DH104+DI104+0.5*F104)<=tax_tables!$B$15,MIN(0.5*F104,0.5*((DH104+DI104+0.5*F104)-tax_tables!$B$14)),MIN(0.85*F104,0.85*((DH104+DI104+0.5*F104)-tax_tables!$B$15)+MIN(0.5*F104,tax_tables!$B$15-tax_tables!$B$14)))) | DK104: =DH104+DI104+DJ104 | DL104: =(B104>=65)+(C104>=65) | DM104: =(tax_tables!$B$5+tax_tables!$B$6*DL104)*P104 | DN104: =IF(AND(A104>=tax_tables!$B$8,A104<=tax_tables!$B$9),DL104*MAX(0,tax_tables!$B$7-tax_tables!$B$11*MAX(0,DK104-tax_tables!$B$10)),0) | DO104: =IFERROR(MAX(tax_tables!$B$16,INDEX(tax_tables!$W$5:$W$8,MATCH(A104,tax_tables!$V$5:$V$8,0))-tax_tables!$B$18*MAX(0,DK104-tax_tables!$B$17*1.01^(A104-tax_tables!$B$4))),tax_tables!$B$16) | DP104: =MAX(0,BM104-BB104-tax_tables!$B$23*DK104) | DQ104: =AN104+MIN(DO104,DY103+DZ103+EA103+AL104*properties!$H$2*O104)+DP104+$B$61*O104 | DR104: =MAX(DM104,DQ104) | DS104: =MAX(0,DH104+DJ104-DR104-DN104) | DT104: =MAX(0,DI104-MAX(0,DR104+DN104-DH104-DJ104)) | DU104: =SUMPRODUCT((DS104>tax_tables!$E$5:$E$16*P104)*(DS104-tax_tables!$E$5:$E$16*P104)*tax_tables!$G$5:$G$16)+SUMPRODUCT(((DS104+DT104)>tax_tables!$I$5:$I$16*P104)*((DS104+DT104)-tax_tables!$I$5:$I$16*P104)*tax_tables!$K$5:$K$16)-SUMPRODUCT((DS104>tax_tables!$I$5:$I$16*P104)*(DS104-tax_tables!$I$5:$I$16*P104)*tax_tables!$K$5:$K$16)+tax_tables!$B$19*BV104+tax_tables!$B$12*MIN(CE104+DB104+BS104+BU104,MAX(0,DK104-tax_tables!$B$13)) | DV104: =IF($B$39="",0,IF(A104>=$B$39,1,0)) | DW104: =IF(B104+0.5>=tax_tables!$B$30,MIN(CS104+CH104+CY104+CA104,tax_tables!$B$29),0)+IF(C104+0.5>=tax_tables!$B$30,MIN(CT104+CI104+CZ104+CB104,tax_tables!$B$29),0) | DX104: =MAX(0,DK104-tax_tables!$B$28*DJ104-DW104-tax_tables!$B$26*IF(tax_tables!$B$27=1,P104,1)) | DY104: =(1-DV104)*SUMPRODUCT((DX104>tax_tables!$M$5:$M$16*IF(tax_tables!$B$27=1,P104,1))*(DX104-tax_tables!$M$5:$M$16*IF(tax_tables!$B$27=1,P104,1))*tax_tables!$O$5:$O$16) | DZ104: =(1-DV104)*tax_tables!$B$31*DX104 | EA104: =DV104*$B$40*MAX(0,DK104-DJ104) | EB104: =DU104+DY104+DZ104+EA104 | EC104: =DC104+DE104+DF104+DG104+BP104 | ED104: =EC104+BW104-AP104+BX104
A105: =A104+1 | B105: =A105-household!$B$6 | C105: =A105-household!$B$9 | D105: =AS105+AT105+AU105+AV105+AZ105+BM105+AK105 | E105: =CN105+AG105+AF105 | F105: =BY105+BZ105 | G105: =CQ105+CR105+CU105+CH105+CI105+CE105-CW105+CV105+BO105 | H105: =IF(CC105+CF105+CG105+CJ105+BN105<=0,"",G105/(CC105+CF105+CG105+CJ105+BN105)) | I105: =EC105/O105 | J105: =ED105/O105 | K105: =MAX(0,CP105-CQ105-CR105-CU105-CV105) | M105: =IF(L105="",$B$19,L105) | O105: =(1+$B$18)^(A105-household!$B$4+1) | P105: =(1+$B$18)^(A105-tax_tables!$B$4) | Q105: =(1+$B$21)^(A105-household!$B$4+1) | R105: =(1+$B$22)^(A105-household!$B$4+1) | S105: =(1+$B$23)^(A105-household!$B$4+1) | T105: =IF(A105<$B$5,1,0) | U105: =IF(A105<$B$6,1,0) | V105: =IF(T105+U105>0,1,0) | W105: =T105*$B$7*O105+SUMPRODUCT(($B$83:$B$88=A105)*($D$83:$D$88="Wages: person 1")*$C$83:$C$88)*O105 | X105: =U105*$B$8*O105+SUMPRODUCT(($B$83:$B$88=A105)*($D$83:$D$88="Wages: person 2")*$C$83:$C$88)*O105 | Y105: =T105*$B$9*O105 | Z105: =U105*$B$10*O105 | AA105: =T105*$B$11*O105 | AB105: =U105*$B$12*O105 | AC105: =V105*$B$13*O105 | AD105: =W105+X105 | AE105: =AD105-Y105-Z105-AC105 | AF105: =0.062*MIN(W105,tax_tables!$B$21*P105)+0.062*MIN(X105,tax_tables!$B$21*P105)+0.0145*AD105+0.009*MAX(0,AD105-tax_tables!$B$22) | AG105: =$B$14*AE105 | AH105: =AD105-Y105-Z105-AC105-AF105-AG105 | AI105: =SUMPRODUCT(($B$83:$B$88=A105)*($D$83:$D$88="Other taxable income")*$C$83:$C$88)*O105 | AJ105: =SUMPRODUCT(($B$83:$B$88=A105)*($D$83:$D$88="Tax-free money in")*$C$83:$C$88)*O105 | AK105: =SUMPRODUCT(($B$83:$B$88=A105)*($D$83:$D$88="Expense")*$C$83:$C$88)*O105 | AL105: =IF(OR($B$75="",A105<$B$75),1,0) | AM105: =AP104 | AN105: =AL105*AM105*properties!$J$2 | AO105: =AL105*MIN(properties!$K$2,AM105+AN105) | AP105: =AL105*(AM105+AN105-AO105) | AQ105: =AL105*properties!$G$2*O105 | AR105: =(1-AL105)*$E$75*O105 | AS105: =AO105+AQ105+AR105 | AT105: =SUMIF(budget!$A$2:$A$300,"household",budget!$F$2:$F$300)*O105*IF(N105="",1,N105) | AU105: =SUMPRODUCT((other_budget!$C$2:$C$30<=A105)*(other_budget!$D$2:$D$30>=A105)*other_budget!$B$2:$B$30)*O105 | AV105: =SUMPRODUCT((kids_budget!$D$2:$D$40<=A105)*(kids_budget!$E$2:$E$40>=A105)*(kids_budget!$G$2:$G$40<>"college_funds")*kids_budget!$C$2:$C$40*((kids_budget!$F$2:$F$40="college")*R105+(kids_budget!$F$2:$F$40<>"college")*O105)) | AW105: =SUMPRODUCT((kids_budget!$D$2:$D$40<=A105)*(kids_budget!$E$2:$E$40>=A105)*(kids_budget!$G$2:$G$40="college_funds")*kids_budget!$C$2:$C$40*((kids_budget!$F$2:$F$40="college")*R105+(kids_budget!$F$2:$F$40<>"college")*O105)) | AX105: =BA104 | AY105: =MIN(AW105,AX105*(1+M105)) | AZ105: =AW105-AY105 | BA105: =AX105*(1+M105)-AY105 | BB105: =V105*healthcare!$B$5*Q105 | BC105: =(1-V105)*((B105<65)+(C105<65)) | BD105: =COUNTIF(household!$C$16:$C$23,">="&A105) | BE105: =(BC105*healthcare!$B$2+IF(BC105>0,BD105,0)*healthcare!$B$3)*12*Q105 | BF105: =IF(BC105>0,(BC105+BD105)*healthcare!$B$4*Q105,0) | BG105: =(B105>=65)+(C105>=65) | BH105: =BG105*(healthcare!$B$6+healthcare!$B$7+healthcare!$B$8)*12*Q105 | BI105: =BG105*healthcare!$B$9*Q105 | BJ105: =BG105*12*O105*SUMPRODUCT((DK103>tax_tables!$Q$5:$Q$9*P105)*tax_tables!$T$5:$T$9) | BK105: =AND(B105>=$B$51,B105<$B$51+$B$52)*1+AND(C105>=$B$53,C105<$B$53+$B$54)*1 | BL105: =BK105*$B$55*S105 | BM105: =BB105+BE105+BF105+BH105+BI105+BJ105+BL105 | BN105: =BP104 | BO105: =IF(V105=1,0,MIN(BN105*(1+M105),BF105+BG105*(healthcare!$B$6+healthcare!$B$7)*12*Q105+BI105+BJ105+BL105)) | BP105: =BN105*(1+M105)-BO105+AC105-CV105 | BQ105: =SUMPRODUCT((1-($B$76:$B$79>0)*(A105>=$B$76:$B$79))*(1-(($C$76:$C$79>0)*(A105>=$C$76:$C$79)))*(properties!$L$3:$L$6-properties!$M$3:$M$6))*O105+SUMPRODUCT((1-($B$76:$B$79>0)*(A105>=$B$76:$B$79))*(($C$76:$C$79>0)*(A105>=$C$76:$C$79))*($D$76:$D$79-$E$76:$E$79))*O105 | BR105: =SUMPRODUCT((1-($B$76:$B$79>0)*(A105>=$B$76:$B$79))*properties!$N$3:$N$6*(A105<=properties!$O$3:$O$6)) | BS105: =MAX(0,BQ105-BR105) | BT105: =SUMPRODUCT(($B$75:$B$79=A105)*$G$75:$G$79) | BU105: =SUMPRODUCT(($B$75:$B$79=A105)*$H$75:$H$79) | BV105: =SUMPRODUCT(($B$75:$B$79=A105)*$I$75:$I$79) | BW105: =AL105*properties!$C$2*(1+properties!$D$2)^(A105-household!$B$4+1) | BX105: =SUMPRODUCT((1-($B$76:$B$79>0)*(A105>=$B$76:$B$79))*properties!$C$3:$C$6*(1+properties!$D$3:$D$6)^(A105-household!$B$4+1)) | BY105: =IF(A105>=$B$31,IF(A105>=$B$32,MAX(household!$B$11*12*(1-$B$28)*O105*IF(A105>=$B$30,1-$B$29,1)*$B$33,0.5*household!$B$12*12*(1-$B$28)*O105*IF(A105>=$B$30,1-$B$29,1)*$B$35),household!$B$11*12*(1-$B$28)*O105*IF(A105>=$B$30,1-$B$29,1)*$B$33),0) | BZ105: =IF(A105>=$B$32,IF(A105>=$B$31,MAX(household!$B$12*12*(1-$B$28)*O105*IF(A105>=$B$30,1-$B$29,1)*$B$34,0.5*household!$B$11*12*(1-$B$28)*O105*IF(A105>=$B$30,1-$B$29,1)*$B$36),household!$B$12*12*(1-$B$28)*O105*IF(A105>=$B$30,1-$B$29,1)*$B$34),0) | CA105: =IF(AND($B$43<>0,A105>=household!$B$6+$B$44),$B$43*(1+$B$18)^(MAX(household!$B$6+$B$44,household!$B$4-1)-household!$B$4+1)*(1+$B$47*$B$18)^(A105-MAX(household!$B$6+$B$44,household!$B$4-1)),0) | CB105: =IF(AND($B$45<>0,A105>=household!$B$9+$B$46),$B$45*(1+$B$18)^(MAX(household!$B$9+$B$46,household!$B$4-1)-household!$B$4+1)*(1+$B$47*$B$18)^(A105-MAX(household!$B$9+$B$46,household!$B$4-1)),0) | CC105: =DC104 | CD105: =DD104 | CE105: =$B$20*CC105 | CF105: =DE104 | CG105: =DF104 | CH105: =IF(B105>=$B$71,MAX(0,CF105)/INDEX(tax_tables!$Z$5:$Z$53,MATCH(B105,tax_tables!$Y$5:$Y$53,0)),0) | CI105: =IF(C105>=$B$72,MAX(0,CG105)/INDEX(tax_tables!$Z$5:$Z$53,MATCH(C105,tax_tables!$Y$5:$Y$53,0)),0) | CJ105: =DG104 | CK105: =IF(OR($B$59="",$B$60=""),0,IF(AND(A105>=$B$59,A105<=$B$60),$B$58*O105,0)) | CL105: =MAX(0,CF105*(1+M105)-CH105) | CM105: =MAX(0,CG105*(1+M105)-CI105) | CN105: =EB104-AG104 | CO105: =AH105+F105+CA105+CB105+BQ105+CE105+CH105+CI105+BT105+AI105+AJ105+BO105 | CP105: =D105+CN105-CO105 | CQ105: =MAX(0,MIN(CP105,CC105*(1+M105-$B$20))) | CR105: =MAX(0,MIN(CP105-CQ105,CL105+CM105)) | CS105: =IF(CL105+CM105>1,CR105*CL105/(CL105+CM105),0) | CT105: =CR105-CS105 | CU105: =MAX(0,MIN(CP105-CQ105-CR105,CJ105*(1+M105))) | CV105: =MAX(0,MIN(CP105-CQ105-CR105-CU105,BN105*(1+M105)-BO105+AC105)) | CW105: =MAX(0,-CP105) | CX105: =MIN(CK105,CL105-CS105+CM105-CT105) | CY105: =IF(CL105-CS105+CM105-CT105>1,CX105*(CL105-CS105)/(CL105-CS105+CM105-CT105),0) | CZ105: =CX105-CY105 | DA105: =IF(CC105>0,MAX(0,1-CD105/CC105),0) | DB105: =CQ105*DA105 | DC105: =CC105*(1+M105-$B$20)-CQ105+CW105 | DD105: =CD105-(CQ105-DB105)+CW105 | DE105: =CF105*(1+M105)-CH105-CS105-CY105+Y105+AA105 | DF105: =CG105*(1+M105)-CI105-CT105-CZ105+Z105+AB105 | DG105: =CJ105*(1+M105)-CU105+CX105 | DH105: =AE105+CR105+CH105+CI105+CX105+CV105+BS105+AI105+CA105+CB105 | DI105: =CE105+DB105+BU105 | DJ105: =IF((DH105+DI105+0.5*F105)<=tax_tables!$B$14,0,IF((DH105+DI105+0.5*F105)<=tax_tables!$B$15,MIN(0.5*F105,0.5*((DH105+DI105+0.5*F105)-tax_tables!$B$14)),MIN(0.85*F105,0.85*((DH105+DI105+0.5*F105)-tax_tables!$B$15)+MIN(0.5*F105,tax_tables!$B$15-tax_tables!$B$14)))) | DK105: =DH105+DI105+DJ105 | DL105: =(B105>=65)+(C105>=65) | DM105: =(tax_tables!$B$5+tax_tables!$B$6*DL105)*P105 | DN105: =IF(AND(A105>=tax_tables!$B$8,A105<=tax_tables!$B$9),DL105*MAX(0,tax_tables!$B$7-tax_tables!$B$11*MAX(0,DK105-tax_tables!$B$10)),0) | DO105: =IFERROR(MAX(tax_tables!$B$16,INDEX(tax_tables!$W$5:$W$8,MATCH(A105,tax_tables!$V$5:$V$8,0))-tax_tables!$B$18*MAX(0,DK105-tax_tables!$B$17*1.01^(A105-tax_tables!$B$4))),tax_tables!$B$16) | DP105: =MAX(0,BM105-BB105-tax_tables!$B$23*DK105) | DQ105: =AN105+MIN(DO105,DY104+DZ104+EA104+AL105*properties!$H$2*O105)+DP105+$B$61*O105 | DR105: =MAX(DM105,DQ105) | DS105: =MAX(0,DH105+DJ105-DR105-DN105) | DT105: =MAX(0,DI105-MAX(0,DR105+DN105-DH105-DJ105)) | DU105: =SUMPRODUCT((DS105>tax_tables!$E$5:$E$16*P105)*(DS105-tax_tables!$E$5:$E$16*P105)*tax_tables!$G$5:$G$16)+SUMPRODUCT(((DS105+DT105)>tax_tables!$I$5:$I$16*P105)*((DS105+DT105)-tax_tables!$I$5:$I$16*P105)*tax_tables!$K$5:$K$16)-SUMPRODUCT((DS105>tax_tables!$I$5:$I$16*P105)*(DS105-tax_tables!$I$5:$I$16*P105)*tax_tables!$K$5:$K$16)+tax_tables!$B$19*BV105+tax_tables!$B$12*MIN(CE105+DB105+BS105+BU105,MAX(0,DK105-tax_tables!$B$13)) | DV105: =IF($B$39="",0,IF(A105>=$B$39,1,0)) | DW105: =IF(B105+0.5>=tax_tables!$B$30,MIN(CS105+CH105+CY105+CA105,tax_tables!$B$29),0)+IF(C105+0.5>=tax_tables!$B$30,MIN(CT105+CI105+CZ105+CB105,tax_tables!$B$29),0) | DX105: =MAX(0,DK105-tax_tables!$B$28*DJ105-DW105-tax_tables!$B$26*IF(tax_tables!$B$27=1,P105,1)) | DY105: =(1-DV105)*SUMPRODUCT((DX105>tax_tables!$M$5:$M$16*IF(tax_tables!$B$27=1,P105,1))*(DX105-tax_tables!$M$5:$M$16*IF(tax_tables!$B$27=1,P105,1))*tax_tables!$O$5:$O$16) | DZ105: =(1-DV105)*tax_tables!$B$31*DX105 | EA105: =DV105*$B$40*MAX(0,DK105-DJ105) | EB105: =DU105+DY105+DZ105+EA105 | EC105: =DC105+DE105+DF105+DG105+BP105 | ED105: =EC105+BW105-AP105+BX105
... A135: =A134+1 | B135: =A135-household!$B$6 | C135: =A135-household!$B$9 | D135: =AS135+AT135+AU135+AV135+AZ135+BM135+AK135 | E135: =CN135+AG135+AF135 | F135: =BY135+BZ135 | G135: =CQ135+CR135+CU135+CH135+CI135+CE135-CW135+CV135+BO135 | H135: =IF(CC135+CF135+CG135+CJ135+BN135<=0,"",G135/(CC135+CF135+CG135+CJ135+BN135)) | I135: =EC135/O135 | J135: =ED135/O135 | K135: =MAX(0,CP135-CQ135-CR135-CU135-CV135) | M135: =IF(L135="",$B$19,L135) | O135: =(1+$B$18)^(A135-household!$B$4+1) | P135: =(1+$B$18)^(A135-tax_tables!$B$4) | Q135: =(1+$B$21)^(A135-household!$B$4+1) | R135: =(1+$B$22)^(A135-household!$B$4+1) | S135: =(1+$B$23)^(A135-household!$B$4+1) | T135: =IF(A135<$B$5,1,0) | U135: =IF(A135<$B$6,1,0) | V135: =IF(T135+U135>0,1,0) | W135: =T135*$B$7*O135+SUMPRODUCT(($B$83:$B$88=A135)*($D$83:$D$88="Wages: person 1")*$C$83:$C$88)*O135 | X135: =U135*$B$8*O135+SUMPRODUCT(($B$83:$B$88=A135)*($D$83:$D$88="Wages: person 2")*$C$83:$C$88)*O135 | Y135: =T135*$B$9*O135 | Z135: =U135*$B$10*O135 | AA135: =T135*$B$11*O135 | AB135: =U135*$B$12*O135 | AC135: =V135*$B$13*O135 | AD135: =W135+X135 | AE135: =AD135-Y135-Z135-AC135 | AF135: =0.062*MIN(W135,tax_tables!$B$21*P135)+0.062*MIN(X135,tax_tables!$B$21*P135)+0.0145*AD135+0.009*MAX(0,AD135-tax_tables!$B$22) | AG135: =$B$14*AE135 | AH135: =AD135-Y135-Z135-AC135-AF135-AG135 | AI135: =SUMPRODUCT(($B$83:$B$88=A135)*($D$83:$D$88="Other taxable income")*$C$83:$C$88)*O135 | AJ135: =SUMPRODUCT(($B$83:$B$88=A135)*($D$83:$D$88="Tax-free money in")*$C$83:$C$88)*O135 | AK135: =SUMPRODUCT(($B$83:$B$88=A135)*($D$83:$D$88="Expense")*$C$83:$C$88)*O135 | AL135: =IF(OR($B$75="",A135<$B$75),1,0) | AM135: =AP134 | AN135: =AL135*AM135*properties!$J$2 | AO135: =AL135*MIN(properties!$K$2,AM135+AN135) | AP135: =AL135*(AM135+AN135-AO135) | AQ135: =AL135*properties!$G$2*O135 | AR135: =(1-AL135)*$E$75*O135 | AS135: =AO135+AQ135+AR135 | AT135: =SUMIF(budget!$A$2:$A$300,"household",budget!$F$2:$F$300)*O135*IF(N135="",1,N135) | AU135: =SUMPRODUCT((other_budget!$C$2:$C$30<=A135)*(other_budget!$D$2:$D$30>=A135)*other_budget!$B$2:$B$30)*O135 | AV135: =SUMPRODUCT((kids_budget!$D$2:$D$40<=A135)*(kids_budget!$E$2:$E$40>=A135)*(kids_budget!$G$2:$G$40<>"college_funds")*kids_budget!$C$2:$C$40*((kids_budget!$F$2:$F$40="college")*R135+(kids_budget!$F$2:$F$40<>"college")*O135)) | AW135: =SUMPRODUCT((kids_budget!$D$2:$D$40<=A135)*(kids_budget!$E$2:$E$40>=A135)*(kids_budget!$G$2:$G$40="college_funds")*kids_budget!$C$2:$C$40*((kids_budget!$F$2:$F$40="college")*R135+(kids_budget!$F$2:$F$40<>"college")*O135)) | AX135: =BA134 | AY135: =MIN(AW135,AX135*(1+M135)) | AZ135: =AW135-AY135 | BA135: =AX135*(1+M135)-AY135 | BB135: =V135*healthcare!$B$5*Q135 | BC135: =(1-V135)*((B135<65)+(C135<65)) | BD135: =COUNTIF(household!$C$16:$C$23,">="&A135) | BE135: =(BC135*healthcare!$B$2+IF(BC135>0,BD135,0)*healthcare!$B$3)*12*Q135 | BF135: =IF(BC135>0,(BC135+BD135)*healthcare!$B$4*Q135,0) | BG135: =(B135>=65)+(C135>=65) | BH135: =BG135*(healthcare!$B$6+healthcare!$B$7+healthcare!$B$8)*12*Q135 | BI135: =BG135*healthcare!$B$9*Q135 | BJ135: =BG135*12*O135*SUMPRODUCT((DK133>tax_tables!$Q$5:$Q$9*P135)*tax_tables!$T$5:$T$9) | BK135: =AND(B135>=$B$51,B135<$B$51+$B$52)*1+AND(C135>=$B$53,C135<$B$53+$B$54)*1 | BL135: =BK135*$B$55*S135 | BM135: =BB135+BE135+BF135+BH135+BI135+BJ135+BL135 | BN135: =BP134 | BO135: =IF(V135=1,0,MIN(BN135*(1+M135),BF135+BG135*(healthcare!$B$6+healthcare!$B$7)*12*Q135+BI135+BJ135+BL135)) | BP135: =BN135*(1+M135)-BO135+AC135-CV135 | BQ135: =SUMPRODUCT((1-($B$76:$B$79>0)*(A135>=$B$76:$B$79))*(1-(($C$76:$C$79>0)*(A135>=$C$76:$C$79)))*(properties!$L$3:$L$6-properties!$M$3:$M$6))*O135+SUMPRODUCT((1-($B$76:$B$79>0)*(A135>=$B$76:$B$79))*(($C$76:$C$79>0)*(A135>=$C$76:$C$79))*($D$76:$D$79-$E$76:$E$79))*O135 | BR135: =SUMPRODUCT((1-($B$76:$B$79>0)*(A135>=$B$76:$B$79))*properties!$N$3:$N$6*(A135<=properties!$O$3:$O$6)) | BS135: =MAX(0,BQ135-BR135) | BT135: =SUMPRODUCT(($B$75:$B$79=A135)*$G$75:$G$79) | BU135: =SUMPRODUCT(($B$75:$B$79=A135)*$H$75:$H$79) | BV135: =SUMPRODUCT(($B$75:$B$79=A135)*$I$75:$I$79) | BW135: =AL135*properties!$C$2*(1+properties!$D$2)^(A135-household!$B$4+1) | BX135: =SUMPRODUCT((1-($B$76:$B$79>0)*(A135>=$B$76:$B$79))*properties!$C$3:$C$6*(1+properties!$D$3:$D$6)^(A135-household!$B$4+1)) | BY135: =IF(A135>=$B$31,IF(A135>=$B$32,MAX(household!$B$11*12*(1-$B$28)*O135*IF(A135>=$B$30,1-$B$29,1)*$B$33,0.5*household!$B$12*12*(1-$B$28)*O135*IF(A135>=$B$30,1-$B$29,1)*$B$35),household!$B$11*12*(1-$B$28)*O135*IF(A135>=$B$30,1-$B$29,1)*$B$33),0) | BZ135: =IF(A135>=$B$32,IF(A135>=$B$31,MAX(household!$B$12*12*(1-$B$28)*O135*IF(A135>=$B$30,1-$B$29,1)*$B$34,0.5*household!$B$11*12*(1-$B$28)*O135*IF(A135>=$B$30,1-$B$29,1)*$B$36),household!$B$12*12*(1-$B$28)*O135*IF(A135>=$B$30,1-$B$29,1)*$B$34),0) | CA135: =IF(AND($B$43<>0,A135>=household!$B$6+$B$44),$B$43*(1+$B$18)^(MAX(household!$B$6+$B$44,household!$B$4-1)-household!$B$4+1)*(1+$B$47*$B$18)^(A135-MAX(household!$B$6+$B$44,household!$B$4-1)),0) | CB135: =IF(AND($B$45<>0,A135>=household!$B$9+$B$46),$B$45*(1+$B$18)^(MAX(household!$B$9+$B$46,household!$B$4-1)-household!$B$4+1)*(1+$B$47*$B$18)^(A135-MAX(household!$B$9+$B$46,household!$B$4-1)),0) | CC135: =DC134 | CD135: =DD134 | CE135: =$B$20*CC135 | CF135: =DE134 | CG135: =DF134 | CH135: =IF(B135>=$B$71,MAX(0,CF135)/INDEX(tax_tables!$Z$5:$Z$53,MATCH(B135,tax_tables!$Y$5:$Y$53,0)),0) | CI135: =IF(C135>=$B$72,MAX(0,CG135)/INDEX(tax_tables!$Z$5:$Z$53,MATCH(C135,tax_tables!$Y$5:$Y$53,0)),0) | CJ135: =DG134 | CK135: =IF(OR($B$59="",$B$60=""),0,IF(AND(A135>=$B$59,A135<=$B$60),$B$58*O135,0)) | CL135: =MAX(0,CF135*(1+M135)-CH135) | CM135: =MAX(0,CG135*(1+M135)-CI135) | CN135: =EB134-AG134 | CO135: =AH135+F135+CA135+CB135+BQ135+CE135+CH135+CI135+BT135+AI135+AJ135+BO135 | CP135: =D135+CN135-CO135 | CQ135: =MAX(0,MIN(CP135,CC135*(1+M135-$B$20))) | CR135: =MAX(0,MIN(CP135-CQ135,CL135+CM135)) | CS135: =IF(CL135+CM135>1,CR135*CL135/(CL135+CM135),0) | CT135: =CR135-CS135 | CU135: =MAX(0,MIN(CP135-CQ135-CR135,CJ135*(1+M135))) | CV135: =MAX(0,MIN(CP135-CQ135-CR135-CU135,BN135*(1+M135)-BO135+AC135)) | CW135: =MAX(0,-CP135) | CX135: =MIN(CK135,CL135-CS135+CM135-CT135) | CY135: =IF(CL135-CS135+CM135-CT135>1,CX135*(CL135-CS135)/(CL135-CS135+CM135-CT135),0) | CZ135: =CX135-CY135 | DA135: =IF(CC135>0,MAX(0,1-CD135/CC135),0) | DB135: =CQ135*DA135 | DC135: =CC135*(1+M135-$B$20)-CQ135+CW135 | DD135: =CD135-(CQ135-DB135)+CW135 | DE135: =CF135*(1+M135)-CH135-CS135-CY135+Y135+AA135 | DF135: =CG135*(1+M135)-CI135-CT135-CZ135+Z135+AB135 | DG135: =CJ135*(1+M135)-CU135+CX135 | DH135: =AE135+CR135+CH135+CI135+CX135+CV135+BS135+AI135+CA135+CB135 | DI135: =CE135+DB135+BU135 | DJ135: =IF((DH135+DI135+0.5*F135)<=tax_tables!$B$14,0,IF((DH135+DI135+0.5*F135)<=tax_tables!$B$15,MIN(0.5*F135,0.5*((DH135+DI135+0.5*F135)-tax_tables!$B$14)),MIN(0.85*F135,0.85*((DH135+DI135+0.5*F135)-tax_tables!$B$15)+MIN(0.5*F135,tax_tables!$B$15-tax_tables!$B$14)))) | DK135: =DH135+DI135+DJ135 | DL135: =(B135>=65)+(C135>=65) | DM135: =(tax_tables!$B$5+tax_tables!$B$6*DL135)*P135 | DN135: =IF(AND(A135>=tax_tables!$B$8,A135<=tax_tables!$B$9),DL135*MAX(0,tax_tables!$B$7-tax_tables!$B$11*MAX(0,DK135-tax_tables!$B$10)),0) | DO135: =IFERROR(MAX(tax_tables!$B$16,INDEX(tax_tables!$W$5:$W$8,MATCH(A135,tax_tables!$V$5:$V$8,0))-tax_tables!$B$18*MAX(0,DK135-tax_tables!$B$17*1.01^(A135-tax_tables!$B$4))),tax_tables!$B$16) | DP135: =MAX(0,BM135-BB135-tax_tables!$B$23*DK135) | DQ135: =AN135+MIN(DO135,DY134+DZ134+EA134+AL135*properties!$H$2*O135)+DP135+$B$61*O135 | DR135: =MAX(DM135,DQ135) | DS135: =MAX(0,DH135+DJ135-DR135-DN135) | DT135: =MAX(0,DI135-MAX(0,DR135+DN135-DH135-DJ135)) | DU135: =SUMPRODUCT((DS135>tax_tables!$E$5:$E$16*P135)*(DS135-tax_tables!$E$5:$E$16*P135)*tax_tables!$G$5:$G$16)+SUMPRODUCT(((DS135+DT135)>tax_tables!$I$5:$I$16*P135)*((DS135+DT135)-tax_tables!$I$5:$I$16*P135)*tax_tables!$K$5:$K$16)-SUMPRODUCT((DS135>tax_tables!$I$5:$I$16*P135)*(DS135-tax_tables!$I$5:$I$16*P135)*tax_tables!$K$5:$K$16)+tax_tables!$B$19*BV135+tax_tables!$B$12*MIN(CE135+DB135+BS135+BU135,MAX(0,DK135-tax_tables!$B$13)) | DV135: =IF($B$39="",0,IF(A135>=$B$39,1,0)) | DW135: =IF(B135+0.5>=tax_tables!$B$30,MIN(CS135+CH135+CY135+CA135,tax_tables!$B$29),0)+IF(C135+0.5>=tax_tables!$B$30,MIN(CT135+CI135+CZ135+CB135,tax_tables!$B$29),0) | DX135: =MAX(0,DK135-tax_tables!$B$28*DJ135-DW135-tax_tables!$B$26*IF(tax_tables!$B$27=1,P135,1)) | DY135: =(1-DV135)*SUMPRODUCT((DX135>tax_tables!$M$5:$M$16*IF(tax_tables!$B$27=1,P135,1))*(DX135-tax_tables!$M$5:$M$16*IF(tax_tables!$B$27=1,P135,1))*tax_tables!$O$5:$O$16) | DZ135: =(1-DV135)*tax_tables!$B$31*DX135 | EA135: =DV135*$B$40*MAX(0,DK135-DJ135) | EB135: =DU135+DY135+DZ135+EA135 | EC135: =DC135+DE135+DF135+DG135+BP135 | ED135: =EC135+BW135-AP135+BX135

Sheet household
A1: key | B1: value | C1: notes
A2: country | B2: US | C2: US = United States, CA = Canada. Fixed when the workbook is built
A3: region | B3: New York | C3: State or province (its tax brackets are on the tax_tables tab)
A4: start_year | B4: 2027 | C4: First year the model covers. Balances on the assets tab are as of 1 January of it; 'today's dollars' are the year before
A5: p1_name | B5: Alex | C5: Person 1
A6: p1_born | B6: 1968 | C6: Birth year
A7: p1_sex | B7: F | C7: M or F: which column of the life table the Monte Carlo uses for person 1
A8: p2_name | B8: Jordan | C8: Person 2
A9: p2_born | B9: 1970 | C9: Birth year
A10: p2_sex | B10: M | C10: M or F for person 2
A11: p1_ss_benefit | B11: 3650 | C11: Person 1's Social Security at full retirement age (67), per month, today's $ - from ssa.gov/myaccount
A12: p2_ss_benefit | B12: 2380 | C12: Person 2's, on their own record
A14: Kids
A15: name | B15: born | C15: on_health_plan_through | D15: notes
A16: Riley | B16: 2006 | C16: 2032 | D16: Stays on the family plan until 26 (or a first job with benefits)
A17: Casey | B17: 2009 | C17: 2035
A24: Kids' costs are on the kids_budget tab (one line per kid and cost). Health-plan years matter once you buy your own coverage.

Sheet budget
A1: model_line | B1: expense_group | C1: category | D1: subcategory | E1: annual_actual | F1: retirement_budget | G1: source_period | H1: n_transactions | I1: notes | K1: Household living budget used by the model | L1: =SUMIF($A$2:$A$300,"household",$F$2:$F$300)
A2: household | B2: Essential | C2: Groceries | D2: General | E2: 15840 | F2: 15840 | G2: example | H2: 212 | K2: All lines, 12-month actual | L2: =SUM($E$2:$E$300)
A3: household | B3: Essential | C3: Utilities | D3: Electric, gas, water | E3: 4320 | F3: 4320 | G3: example | H3: 24
A4: household | B4: Essential | C4: Utilities | D4: Phone & internet | E4: 2760 | F4: 2760 | G4: example | H4: 24 | K4: model_line: 'household' lines are summed and grow with inflation. Other lines (housing, healthcare, taxes, kids) are modeled on their own tabs and shown here only for reference.
A5: household | B5: Essential | C5: Insurance | D5: General | E5: 4150 | F5: 4150 | G5: example | H5: 6 | K5: Edit column F (retirement_budget) to test a different budget; column E is what you actually spent.
A6: household | B6: Essential | C6: Transportation | D6: Gas & parking | E6: 3600 | F6: 3600 | G6: example | H6: 96
A7: household | B7: Essential | C7: Transportation | D7: Car maintenance | E7: 1900 | F7: 1900 | G7: example | H7: 5
A8: household | B8: Essential | C8: Personal Care | D8: General | E8: 2100 | F8: 2100 | G8: example | H8: 30
A9: household | B9: Discretionary | C9: Dining | D9: Restaurants & takeout | E9: 9800 | F9: 9800 | G9: example | H9: 180
A10: household | B10: Discretionary | C10: Travel | D10: Flights, hotels, rentals | E10: 14500 | F10: 16000 | G10: example | H10: 40 | I10: Planning to travel a bit more once retired
A11: household | B11: Discretionary | C11: Shopping | D11: General | E11: 11200 | F11: 10000 | G11: example | H11: 260
A12: household | B12: Discretionary | C12: Entertainment | D12: General | E12: 3400 | F12: 3400 | G12: example | H12: 45
A13: household | B13: Discretionary | C13: Subscriptions | D13: Streaming & software | E13: 1250 | F13: 1250 | G13: example | H13: 48
A14: household | B14: Discretionary | C14: Gifts & Donations | D14: General | E14: 5200 | F14: 5200 | G14: example | H14: 22
A15: household | B15: Discretionary | C15: Home | D15: Household goods | E15: 3100 | F15: 3100 | G15: example | H15: 55
A16: household | B16: Discretionary | C16: Pets | D16: General | E16: 2400 | F16: 2400 | G16: example | H16: 30
A17: household | B17: Discretionary | C17: Cash | D17: Withdrawals | E17: 1800 | F17: 1800 | G17: example | H17: 20
A18: housing | B18: Housing | C18: Housing | D18: Mortgage | E18: 22140 | G18: example | H18: 12 | I18: Modeled from the properties tab (mortgage balance and payment)
A19: housing | B19: Housing | C19: Housing | D19: Property tax & insurance | E19: 13900 | G19: example | H19: 6 | I19: Modeled from the properties tab (carrying_costs)
A20: healthcare | B20: Healthcare | C20: Healthcare | D20: Out-of-pocket | E20: 3800 | G20: example | H20: 40 | I20: Modeled on the healthcare tab
A21: kids | B21: Kids | C21: Kids | D21: Support | E21: 19200 | G21: example | H21: 48 | I21: Modeled on the kids_budget tab
A22: taxes | B22: Taxes | C22: Taxes | D22: Estimated payments | E22: 8000 | G22: example | H22: 4 | I22: Replaced by the model's own tax calculation

Sheet kids_budget
A1: kid | B1: item | C1: annual_amount_today | D1: start_year | E1: end_year | F1: inflation | G1: paid_from | H1: notes
A2: Riley | B2: College (private) - tuition + room and board | C2: 82000 | D2: 2027 | E2: 2028 | F2: college | G2: college_funds | H2: Junior and senior years; 529 pays first
A3: Riley | B3: Spending money in college | C3: 6000 | D3: 2027 | E3: 2028 | F3: general | G3: parents
A4: Riley | B4: Help after college (rent share + phone + insurance) | C4: 14000 | D4: 2029 | E4: 2031 | F4: general | G4: parents | H4: First three years after graduating
A5: Riley | B5: Wedding gift | C5: 30000 | D5: 2033 | E5: 2033 | F5: general | G5: parents | H5: A one-time line: start = end year
A6: Casey | B6: College (state school) - tuition + room and board | C6: 34000 | D6: 2027 | E6: 2031 | F6: college | G6: college_funds | H6: Five-year program
A7: Casey | B7: Spending money in college | C7: 5000 | D7: 2027 | E7: 2031 | F7: general | G7: parents
A8: Casey | B8: Help after college | C8: 20000 | D8: 2032 | E8: 2033 | F8: general | G8: parents | H8: Two years while in grad school
A42: One line per kid and cost, per year in today's dollars, for the years start_year-end_year. inflation: 'college' lines rise with college cost growth, 'general' with inflation. paid_from: 'college_funds' lines are paid by the 529s first and only the shortfall comes from you; 'parents' lines come straight from you. Add rows above row 41.

Sheet other_budget
A1: item | B1: annual_amount_today | C1: start_year | D1: end_year | E1: notes
A2: Home repairs and renovations | B2: 12000 | C2: 2027 | D2: 2060 | E2: About 2% of the home's value a year
A3: Car replacement | B3: 8000 | C3: 2027 | D3: 2055 | E3: A $40k car every five years
A4: Help for aging parents | B4: 6000 | C4: 2027 | D4: 2032
A32: Big irregular costs averaged per year (renovations, cars, gifts), in today's dollars, for the years start_year-end_year. Add rows above row 31.

Sheet properties
A1: property | B1: type | C1: value_now | D1: appreciation | E1: selling_cost_pct | F1: cost_basis | G1: carrying_costs | H1: property_tax | I1: mortgage_balance | J1: mortgage_rate | K1: mortgage_payment | L1: rent | M1: cash_costs | N1: depreciation | O1: depreciation_end_year | P1: accum_depreciation | Q1: notes
A2: Home (Saratoga Springs) | B2: primary | C2: 640000 | D2: 0.03 | E2: 0.07 | F2: 410000 | G2: 15600 | H2: 11200 | I2: 262000 | J2: 0.0325 | K2: 22140 | Q2: Bought 2012 for $380,000 + $30,000 kitchen. Carrying costs: property tax $11,200, insurance $2,400, other $2,000
A3: Condo rental (Albany) | B3: rental | C3: 310000 | D3: 0.025 | E3: 0.07 | F3: 245000 | L3: 25200 | M3: 10400 | N3: 7100 | O3: 2045 | P3: 63900 | Q3: Bought 2018 for $245,000 ($50,000 land). Cash costs: HOA $4,800, tax $3,900, insurance $900, repairs $800
A9: Row 2 is your home (principal residence); rows 3-6 are other properties (rentals, a cottage). Sell / rent decisions are made on each Model tab. Amounts are today's dollars.
A10: value_now: market value; appreciation: growth per year. carrying_costs: property tax + condo/HOA/strata fees + insurance + utilities you want counted as housing (for the home; if you rent, put the rent here and leave value_now blank). property_tax: the part that's property tax (deductible up to the SALT cap).
A11: mortgage_*: the home's mortgage on 1 January of the first year (balance, interest rate, payments per year). Other properties are assumed mortgage-free: include any loan payments in cash_costs.
A12: Other properties: rent and cash_costs per year; depreciation claimed per year until depreciation_end_year, and accum_depreciation already claimed. cost_basis is what you paid plus improvements.

Sheet healthcare
A1: key | B1: value | C1: unit | D1: notes | E1: source
A2: marketplace_adult_monthly | B2: 1150 | C2: $/month | D2: Unsubsidized Silver plan for a ~60-year-old. Check healthcare.gov or your state exchange; prices vary a lot by state and age (NY doesn't rate by age) | E2: healthcare.gov plan finder
A3: marketplace_child_monthly | B3: 450 | C3: $/month | D3: Per child on your plan | E3: healthcare.gov plan finder
A4: marketplace_oop_per_person | B4: 3000 | C4: $/year | D4: Deductibles and copays on a Silver plan
A5: employer_plan_cost | B5: 9000 | C5: $/year | D5: Your share of premiums + out-of-pocket while working (the model uses it while either of you works) | E5: Pay stubs / benefits portal
A6: medicare_part_b_monthly | B6: 202.9 | C6: $/month | D6: 2026 standard Part B premium | E6: CMS
A7: medicare_part_d_monthly | B7: 45 | C7: $/month | D7: Typical Part D plan | E7: medicare.gov plan finder
A8: medigap_monthly | B8: 250 | C8: $/month | D8: Medigap Plan G around 65-70 | E8: medicare.gov plan finder
A9: medicare_oop_per_person | B9: 1500 | C9: $/year | D9: Part B deductible, dental, vision, hearing
A10: medical_inflation | B10: 0.05 | C10: per year | D10: Healthcare costs have grown ~2 points faster than inflation
A11: ltc_annual_cost | B11: 130000 | C11: $/year | D11: Home health aide or assisted living; a nursing home is ~$120-180k in the Northeast | E11: Genworth / CareScout cost of care survey
A12: ltc_inflation | B12: 0.04 | C12: per year

Sheet assets
A1: account | B1: bucket | C1: value | D1: as_of | E1: cost_basis | F1: notes | H1: bucket | I1: total | J1: cost basis | K1: what goes in it
A2: Brokerage (joint) - index funds | B2: taxable | C2: 880000 | D2: 2027-01-01 | E2: 560000 | H2: taxable | I2: =SUMIF($B$2:$B$150,"taxable",$C$2:$C$150) | J2: =SUMIF($B$2:$B$150,"taxable",$E$2:$E$150) | K2: Taxable brokerage accounts, bank and money-market cash
A3: High-yield savings | B3: taxable | C3: 55000 | D3: 2027-01-01 | F3: cash: cost basis = value | H3: pretax_p1 | I3: =SUMIF($B$2:$B$150,"pretax_p1",$C$2:$C$150) | K3: Person 1's 401(k), 403(b), traditional IRA, other pre-tax accounts
A4: Checking | B4: taxable | C4: 15000 | D4: 2027-01-01 | H4: pretax_p2 | I4: =SUMIF($B$2:$B$150,"pretax_p2",$C$2:$C$150) | K4: Person 2's pre-tax accounts
A5: Alex 401(k) | B5: pretax_p1 | C5: 1150000 | D5: 2027-01-01 | H5: roth | I5: =SUMIF($B$2:$B$150,"roth",$C$2:$C$150) | K5: Roth IRAs and Roth 401(k)s (either person)
A6: Alex rollover IRA | B6: pretax_p1 | C6: 210000 | D6: 2027-01-01 | H6: hsa | I6: =SUMIF($B$2:$B$150,"hsa",$C$2:$C$150) | K6: Health savings accounts
A7: Jordan 403(b) | B7: pretax_p2 | C7: 540000 | D7: 2027-01-01 | H7: college_529 | I7: =SUMIF($B$2:$B$150,"college_529",$C$2:$C$150) | K7: 529 plans and other money set aside for the kids' college (not counted as yours)
A8: Alex Roth IRA | B8: roth | C8: 95000 | D8: 2027-01-01 | H8: not_modeled | I8: =SUMIF($B$2:$B$150,"not_modeled",$C$2:$C$150) | K8: Anything the model should ignore (cars, collectibles, a business)
A9: Jordan Roth IRA | B9: roth | C9: 62000 | D9: 2027-01-01
A10: HSA | B10: hsa | C10: 48000 | D10: 2027-01-01 | H10: One row per account, balance as of 1 January of the first year. cost_basis matters only for taxable accounts (blank = same as value, e.g. cash).
A11: Riley 529 | B11: college_529 | C11: 115000 | D11: 2027-01-01
A12: Casey 529 | B12: college_529 | C12: 130000 | D12: 2027-01-01
A13: Cars | B13: not_modeled | C13: 35000 | D13: 2027-01-01 | F13: Not investments

Sheet tax_tables
A1: Tax law used by the model (married filing jointly). Yellow cells can be edited; indexed amounts grow with inflation after TAX_YEAR.
A2: Sources: IRS Rev. Proc. 2025-32 (2026 amounts, One Big Beautiful Bill Act); SSA and CMS 2026 figures; state brackets from the state's tax department. Update each January.
A3: name | B3: value | C3: notes | E3: Federal ordinary brackets (joint) | I3: Federal capital gains / qualified dividends (joint) | M3: State brackets (joint): New York | Q3: Medicare IRMAA (per person per month) | V3: SALT cap by year | Y3: Uniform Lifetime Table (RMDs)
A4: TAX_YEAR | B4: 2026 | C4: Year the amounts on this tab are for; indexed amounts grow with inflation after it | E4: over | F4: rate | G4: step | I4: over | J4: rate | K4: step | M4: over | N4: rate | O4: step | Q4: MAGI over | R4: Part B add-on | S4: Part D add-on | T4: step | V4: year | W4: cap | Y4: age | Z4: factor
A5: FED_STD | B5: 32200 | C5: Standard deduction, married filing jointly | E5: 0 | F5: 0.1 | G5: =IF(F5="",0,F5-0) | I5: 0 | J5: 0 | K5: =IF(J5="",0,J5-0) | M5: 0 | N5: 0.04 | O5: =IF(N5="",0,N5-0) | Q5: 218000 | R5: 81.2 | S5: 14.5 | T5: =R5+S5 | V5: 2026 | W5: 40400 | Y5: 72 | Z5: 27.4
A6: FED_65_ADD | B6: 1650 | C6: Extra standard deduction per spouse 65+ | E6: 24800 | F6: 0.12 | G6: =IF(F6="",0,F6-F5) | I6: 98900 | J6: 0.15 | K6: =IF(J6="",0,J6-J5) | M6: 17150 | N6: 0.045 | O6: =IF(N6="",0,N6-N5) | Q6: 274000 | R6: 202.9 | S6: 37.5 | T6: =R6+S6-R5-S5 | V6: 2027 | W6: 40804 | Y6: 73 | Z6: 26.5
A7: SENIOR_DED | B7: 6000 | C7: OBBBA senior deduction per person 65+ (not indexed) | E7: 100800 | F7: 0.22 | G7: =IF(F7="",0,F7-F6) | I7: 613700 | J7: 0.2 | K7: =IF(J7="",0,J7-J6) | M7: 23600 | N7: 0.0525 | O7: =IF(N7="",0,N7-N6) | Q7: 342000 | R7: 324.6 | S7: 60.4 | T7: =R7+S7-R6-S6 | V7: 2028 | W7: 41212 | Y7: 74 | Z7: 25.5
A8: SENIOR_DED_FROM | B8: 2025 | C8: ... first year | E8: 211400 | F8: 0.24 | G8: =IF(F8="",0,F8-F7) | K8: =IF(J8="",0,J8-J7) | M8: 27900 | N8: 0.055 | O8: =IF(N8="",0,N8-N7) | Q8: 410000 | R8: 446.3 | S8: 83.3 | T8: =R8+S8-R7-S7 | V8: 2029 | W8: 41624 | Y8: 75 | Z8: 24.6
A9: SENIOR_DED_TO | B9: 2028 | C9: ... last year (expires after 2028 under current law) | E9: 403550 | F9: 0.32 | G9: =IF(F9="",0,F9-F8) | K9: =IF(J9="",0,J9-J8) | M9: 161550 | N9: 0.06 | O9: =IF(N9="",0,N9-N8) | Q9: 750000 | R9: 487 | S9: 91 | T9: =R9+S9-R8-S8 | Y9: 76 | Z9: 23.7
A10: SENIOR_PHASEOUT_START | B10: 150000 | C10: ... reduced by 6% of MAGI above this (joint) | E10: 512450 | F10: 0.35 | G10: =IF(F10="",0,F10-F9) | K10: =IF(J10="",0,J10-J9) | M10: 323200 | N10: 0.0685 | O10: =IF(N10="",0,N10-N9) | Y10: 77 | Z10: 22.9
A11: SENIOR_PHASEOUT_RATE | B11: 0.06 | E11: 768700 | F11: 0.37 | G11: =IF(F11="",0,F11-F10) | K11: =IF(J11="",0,J11-J10) | M11: 2155350 | N11: 0.0965 | O11: =IF(N11="",0,N11-N10) | Y11: 78 | Z11: 22
A12: NIIT_RATE | B12: 0.038 | C12: Net investment income tax | G12: =IF(F12="",0,F12-F11) | K12: =IF(J12="",0,J12-J11) | M12: 5000000 | N12: 0.103 | O12: =IF(N12="",0,N12-N11) | Y12: 79 | Z12: 21.1
A13: NIIT_THRESHOLD | B13: 250000 | C13: Not indexed | G13: =IF(F13="",0,F13-F12) | K13: =IF(J13="",0,J13-J12) | M13: 25000000 | N13: 0.109 | O13: =IF(N13="",0,N13-N12) | Y13: 80 | Z13: 20.2
A14: SS_TAXABLE_BASE | B14: 32000 | C14: Social Security taxation thresholds (joint, not indexed) | G14: =IF(F14="",0,F14-F13) | K14: =IF(J14="",0,J14-J13) | O14: =IF(N14="",0,N14-N13) | Y14: 81 | Z14: 19.4
A15: SS_TAXABLE_ADJUSTED_BASE | B15: 44000 | G15: =IF(F15="",0,F15-F14) | K15: =IF(J15="",0,J15-J14) | O15: =IF(N15="",0,N15-N14) | Y15: 82 | Z15: 18.5
A16: SALT_CAP_AFTER | B16: 10000 | C16: SALT cap after the years in the SALT table | G16: =IF(F16="",0,F16-F15) | K16: =IF(J16="",0,J16-J15) | O16: =IF(N16="",0,N16-N15) | Y16: 83 | Z16: 17.7
A17: SALT_PHASEDOWN_START | B17: 505000 | C17: SALT cap phase-down starts at this MAGI (2026; grows 1%/yr through 2029) | Y17: 84 | Z17: 16.8
A18: SALT_PHASEDOWN_RATE | B18: 0.3 | Y18: 85 | Z18: 16
A19: UNRECAPTURED_1250_EXTRA | B19: 0.1 | C19: Depreciation recapture: 25% max rate vs 15% | Y19: 86 | Z19: 15.2
A20: HOME_SALE_EXCLUSION | B20: 500000 | C20: Gain excluded on selling your home (joint) | Y20: 87 | Z20: 14.4
A21: SS_WAGE_BASE | B21: 184500 | C21: Social Security payroll tax wage base | Y21: 88 | Z21: 13.7
A22: ADDITIONAL_MEDICARE_THRESHOLD | B22: 250000 | C22: 0.9% extra Medicare tax above this (joint, not indexed) | Y22: 89 | Z22: 12.9
A23: MEDICAL_FLOOR | B23: 0.075 | C23: Medical expenses deductible above this share of AGI | Y23: 90 | Z23: 12.2
A24: SS_FULL_RETIREMENT_AGE | B24: 67 | C24: Born 1960 or later | Y24: 91 | Z24: 11.5
A25: STATE_NAME | B25: New York | C25: State used for state income tax (edit the brackets below to change it) | Y25: 92 | Z25: 10.8
A26: STATE_STD | B26: 16050 | C26: State standard deduction (joint) | Y26: 93 | Z26: 10.1
A27: STATE_INDEXED | B27: 0 | C27: 1 = state brackets and deduction grow with inflation; 0 = fixed | Y27: 94 | Z27: 9.5
A28: STATE_SS_EXEMPT | B28: 1 | C28: 1 = state doesn't tax Social Security | Y28: 95 | Z28: 8.9
A29: STATE_RET_EXCLUSION | B29: 20000 | C29: Per-person exclusion for IRA/401(k)/pension withdrawals | Y29: 96 | Z29: 8.4
A30: STATE_RET_EXCLUSION_AGE | B30: 59.5 | C30: ... from this age | Y30: 97 | Z30: 7.8
A31: LOCAL_RATE | B31: 0 | C31: Flat city/county income tax on state taxable income (NYC is roughly 0.039) | Y31: 98 | Z31: 7.3
Y32: 99 | Z32: 6.8
Y33: 100 | Z33: 6.4
Y34: 101 | Z34: 6
Y35: 102 | Z35: 5.6
Y36: 103 | Z36: 5.2
Y37: 104 | Z37: 4.9
Y38: 105 | Z38: 4.6
Y39: 106 | Z39: 4.3
Y40: 107 | Z40: 4.1
Y41: 108 | Z41: 3.9
Y42: 109 | Z42: 3.7
Y43: 110 | Z43: 3.5
... Y53: 120 | Z53: 2

Sheet historical_returns
A1: year | B1: stocks | C1: bonds | D1: bills | E1: inflation | G1: US history: S&P 500 total return, 10-year Treasury, 3-month T-bill, CPI inflation. Source: Aswath Damodaran, NYU Stern (histretSP.xls, January 2026). Add a row each January, or replace the columns with another country's series (keep the headers).
A2: 1928 | B2: 0.438112 | C2: 0.008355 | D2: 0.0308 | E2: -0.011561
A3: 1929 | B3: -0.082979 | C3: 0.042038 | D3: 0.0316 | E3: 0.005848
A4: 1930 | B4: -0.251236 | C4: 0.045409 | D4: 0.0455 | E4: -0.063953
A5: 1931 | B5: -0.438375 | C5: -0.025589 | D5: 0.0231 | E5: -0.093168
A6: 1932 | B6: -0.086424 | C6: 0.087903 | D6: 0.0107 | E6: -0.10274
A7: 1933 | B7: 0.499822 | C7: 0.018553 | D7: 0.0096 | E7: 0.007634
A8: 1934 | B8: -0.011886 | C8: 0.079634 | D8: 0.002783 | E8: 0.015152
A9: 1935 | B9: 0.467404 | C9: 0.04472 | D9: 0.001675 | E9: 0.029851
A10: 1936 | B10: 0.319434 | C10: 0.050179 | D10: 0.001725 | E10: 0.014493
A11: 1937 | B11: -0.353367 | C11: 0.013791 | D11: 0.002758 | E11: 0.028571
A12: 1938 | B12: 0.292827 | C12: 0.042132 | D12: 0.00065 | E12: -0.027778
A13: 1939 | B13: -0.010976 | C13: 0.044123 | D13: 0.000458 | E13: 0
... A99: 2025 | B99: 0.177237 | C99: 0.077955 | D99: 0.0421 | E99: 0.027351

Sheet life_table
A1: age | B1: male_death_probability | C1: female_death_probability | E1: Probability of dying within a year at each age. US Social Security period life table for 2023 (as used in the 2026 Trustees Report). The Monte Carlo shifts it by the extra years of life expectancy set on the monte_carlo tab.
A2: 0 | B2: 0.006015 | C2: 0.005125
A3: 1 | B3: 0.000479 | C3: 0.000392
A4: 2 | B4: 0.00032 | C4: 0.000229
A5: 3 | B5: 0.000249 | C5: 0.000188
A6: 4 | B6: 0.000194 | C6: 0.000155
A7: 5 | B7: 0.000159 | C7: 0.000133
A8: 6 | B8: 0.000137 | C8: 0.000115
A9: 7 | B9: 0.000125 | C9: 0.000105
A10: 8 | B10: 0.00012 | C10: 0.0001
A11: 9 | B11: 0.00012 | C11: 9.8e-05
A12: 10 | B12: 0.000125 | C12: 0.000101
A13: 11 | B13: 0.00014 | C13: 0.000111
... A121: 119 | B121: 0.926604 | C121: 0.926604

Sheet monte_carlo
A1: Monte Carlo: every scenario replayed through history
A2: Each run replaces the Model tab's flat return and inflation with a stretch of real history (historical_returns tab) and draws lifetimes from the life_table tab. Change the yellow cells, then run the Monte Carlo (see README). Results are written below, in today's dollars.
A4: SETTINGS
A5: Stocks | B5: 0.6 | C5: Share of investments in stocks (historical_returns 'stocks' column)
A6: Bonds | B6: 0.4 | C6: Share in bonds ('bonds' column)
A7: Cash | B7: 0 | C7: Share in cash ('bills' column); the three should add to 100%
A8: Random runs per scenario | B8: 1000 | C8: 0 = historical starting years only
A9: Block length for random runs (years) | B9: 10 | C9: Random runs stitch together blocks of this many consecutive years of history
A10: Random seed | B10: 1 | C10: Change it to draw a different set of random runs
A11: Scenarios to run | C11: Comma-separated Model tab names; blank = every Model tab
A12: Alex: extra years of life expectancy | B12: 3 | C12: Years added to the life table's average. Healthier, higher-income people live longer (often +3 to +6). More years is the cautious direction
A13: Jordan: extra years of life expectancy | B13: 3 | C13: Same for person 2
A14: Survivor spending | B14: 0.7 | C14: After the first death, household and other spending as a share of the couple's
A15: Lifetimes drawn per historical start | B15: 20 | C15: Each historical start is run with this many random pairs of lifetimes
